Workbook

Sheet 01 Cover & Control
B4: Commercial Brokerage Revenue Forecasting & Pricing Model
B5: Driver-Based Operating Model — Commercial Real Estate Advisory Firm
B8: MODEL METADATA
B9: Company Name | C9: Apex CRE Advisors
B10: Model Version | C10: V1.0
B11: Prepared By | C11: Muhammed Sheikh
B12: Date | C12: 46196
B13: Status | C13: Completed
B14: Forecast Base Date | C14: Q1 2026
B15: Historical Period | C15: 2023A – 2025A
B16: Forecast Period | C16: 2026E – 2030E
B18: SCENARIO CONTROL
B19: Active Scenario | C19: Base | D19: <-- This cell drives all scenario-sensitive assumptions in Tabs 02 & 03
B20: Scenario Status | C20: =IF($C$19="Base","BASE CASE ACTIVE",IF($C$19="Upside","UPSIDE CASE ACTIVE",IF($C$19="Downside","DOWNSIDE CASE ACTIVE","— SELECT SCENARIO —"))) -> BASE CASE ACTIVE
B22: MODEL INTEGRITY STATUS
B23: Check Status | C23: =IF('11 Checks'!$F$9>0,"FAIL",IF('11 Checks'!$H$9>0,"PASS WITH WARNINGS","PASS")) -> PASS WITH WARNINGS
C24: Live status reflects critical failures and advisory warnings from Tab 11. See Tab 11 for detailed audit results.
B26: TOP-LINE SUMMARY MIRROR [ Linked to Tab 08 P&L Annual Summary ]
B27: Metric | C27: Units | D27: 2023A | E27: 2024A | F27: 2025A | G27: 2026E | H27: 2027E | I27: 2028E | J27: 2029E | K27: 2030E
B28: Total GCI | C28: $K | D28: ='08 P&L'!I97 -> 167707.94 | E28: ='08 P&L'!N97 -> 200982.97 | F28: ='08 P&L'!S97 -> 233698.5 | G28: ='08 P&L'!X97 -> 262289.94 | H28: ='08 P&L'!AC97 -> 290016.09 | I28: ='08 P&L'!AH97 -> 313002.15 | J28: ='08 P&L'!AM97 -> 334879.56 | K28: ='08 P&L'!AR97 -> 357566.72
B29: Leasing GCI | C29: $K | D29: ='08 P&L'!I93 -> 66192.187 | E29: ='08 P&L'!N93 -> 83285.798 | F29: ='08 P&L'!S93 -> 98924.839 | G29: ='08 P&L'!X93 -> 113320.1 | H29: ='08 P&L'!AC93 -> 126650.33 | I29: ='08 P&L'!AH93 -> 139067.1 | J29: ='08 P&L'!AM93 -> 150698.85 | K29: ='08 P&L'!AR93 -> 161654.55
B30: Investment Sales GCI | C30: $K | D30: ='08 P&L'!I94 -> 57764.133 | E30: ='08 P&L'!N94 -> 69176.662 | F30: ='08 P&L'!S94 -> 81068.929 | G30: ='08 P&L'!X94 -> 90124.081 | H30: ='08 P&L'!AC94 -> 100119.28 | I30: ='08 P&L'!AH94 -> 107396.6 | J30: ='08 P&L'!AM94 -> 114183.83 | K30: ='08 P&L'!AR94 -> 122278.85
B31: D&E Placement GCI | C31: $K | D31: ='08 P&L'!I95 -> 35579.694 | E31: ='08 P&L'!N95 -> 39222.139 | F31: ='08 P&L'!S95 -> 43427.593 | G31: ='08 P&L'!X95 -> 47713.929 | H31: ='08 P&L'!AC95 -> 51364.625 | I31: ='08 P&L'!AH95 -> 53995.283 | J31: ='08 P&L'!AM95 -> 56867.844 | K31: ='08 P&L'!AR95 -> 59982.955
B32: Advisory Revenue | C32: $K | D32: ='08 P&L'!I96 -> 8171.9308 | E32: ='08 P&L'!N96 -> 9298.372 | F32: ='08 P&L'!S96 -> 10277.143 | G32: ='08 P&L'!X96 -> 11131.838 | H32: ='08 P&L'!AC96 -> 11881.853 | I32: ='08 P&L'!AH96 -> 12543.179 | J32: ='08 P&L'!AM96 -> 13129.029 | K32: ='08 P&L'!AR96 -> 13650.359
B33: Producer Payouts | C33: $K | D33: ='08 P&L'!I99 -> 119159.3 | E33: ='08 P&L'!N99 -> 143107.12 | F33: ='08 P&L'!S99 -> 166770.52 | G33: ='08 P&L'!X99 -> 187460.1 | H33: ='08 P&L'!AC99 -> 207592.42 | I33: ='08 P&L'!AH99 -> 224280.64 | J33: ='08 P&L'!AM99 -> 240183.28 | K33: ='08 P&L'!AR99 -> 256769.99
B34: Company Dollar | C34: $K | D34: ='08 P&L'!I100 -> 48548.64 | E34: ='08 P&L'!N100 -> 57875.854 | F34: ='08 P&L'!S100 -> 66927.982 | G34: ='08 P&L'!X100 -> 74829.84 | H34: ='08 P&L'!AC100 -> 82423.67 | I34: ='08 P&L'!AH100 -> 88721.511 | J34: ='08 P&L'!AM100 -> 94696.284 | K34: ='08 P&L'!AR100 -> 100796.72
B35: Company Dollar Margin % | C35: % | D35: ='08 P&L'!I101 -> 0.28948325 | E35: ='08 P&L'!N101 -> 0.28796397 | F35: ='08 P&L'!S101 -> 0.28638601 | G35: ='08 P&L'!X101 -> 0.28529435 | H35: ='08 P&L'!AC101 -> 0.28420378 | I35: ='08 P&L'!AH101 -> 0.28345336 | J35: ='08 P&L'!AM101 -> 0.28277714 | K35: ='08 P&L'!AR101 -> 0.28189627
B36: Total Operating Expenses | C36: $K | D36: ='08 P&L'!I103 -> 34503.263 | E36: ='08 P&L'!N103 -> 38321.534 | F36: ='08 P&L'!S103 -> 41843.558 | G36: ='08 P&L'!X103 -> 37019.454 | H36: ='08 P&L'!AC103 -> 38999.546 | I36: ='08 P&L'!AH103 -> 40670.438 | J36: ='08 P&L'!AM103 -> 42182.537 | K36: ='08 P&L'!AR103 -> 43616.874
B37: EBITDA | C37: $K | D37: ='08 P&L'!I104 -> 14045.378 | E37: ='08 P&L'!N104 -> 19554.32 | F37: ='08 P&L'!S104 -> 25084.424 | G37: ='08 P&L'!X104 -> 37810.386 | H37: ='08 P&L'!AC104 -> 43424.124 | I37: ='08 P&L'!AH104 -> 48051.073 | J37: ='08 P&L'!AM104 -> 52513.747 | K37: ='08 P&L'!AR104 -> 57179.849
B38: EBITDA Margin on GCI % | C38: % | D38: ='08 P&L'!I105 -> 0.083749029 | E38: ='08 P&L'!N105 -> 0.097293417 | F38: ='08 P&L'!S105 -> 0.10733669 | G38: ='08 P&L'!X105 -> 0.14415492 | H38: ='08 P&L'!AC105 -> 0.14973005 | I38: ='08 P&L'!AH105 -> 0.15351675 | J38: ='08 P&L'!AM105 -> 0.15681383 | K38: ='08 P&L'!AR105 -> 0.15991379
B39: Total EPEs (Firm) | C39: # | D39: ='04 Producer Engine'!I213 -> 107.70544 | E39: ='04 Producer Engine'!N213 -> 131.44912 | F39: ='04 Producer Engine'!S213 -> 151.18987 | G39: ='04 Producer Engine'!X213 -> 167.6685 | H39: ='04 Producer Engine'!AC213 -> 181.48096 | I39: ='04 Producer Engine'!AH213 -> 193.10761 | J39: ='04 Producer Engine'!AM213 -> 202.93647 | K39: ='04 Producer Engine'!AR213 -> 211.28174
B40: Effective Payout Ratio | C40: % | D40: ='08 P&L'!I30 -> 0.71051675 | E40: ='08 P&L'!N30 -> 0.71203603 | F40: ='08 P&L'!S30 -> 0.71361399 | G40: ='08 P&L'!X30 -> 0.71470565 | H40: ='08 P&L'!AC30 -> 0.71579622 | I40: ='08 P&L'!AH30 -> 0.71654664 | J40: ='08 P&L'!AM30 -> 0.71722286 | K40: ='08 P&L'!AR30 -> 0.71810373
B41: Note: Forecast assumes no financing structure and applies a 26.0% illustrative effective tax rate to pre-tax operating income. After-Tax Operating Income (Unlevered) is shown before any interest, financing, or capital-structure effects.
B42: TAB DIRECTORY
B43: Tab # | C43: Tab Name | E43: Type | F43: Purpose (one line)
B44: 01 | C44: Cover & Control | E44: Input / Nav | F44: Model identity, scenario selector, summary mirror, tab directory, color legend.
B45: 02 | C45: Market Assumptions | E45: Input | F45: Exogenous market drivers: IS volume, leasing volume, originations, fee rates, macro context.
B46: 03 | C46: Operational Assumptions | E46: Input | F46: Firm-controlled drivers: headcount plan, productivity, comp structure, opex drivers.
B47: 04 | C47: Producer Engine | E47: Engine | F47: Headcount roll-forward → ramp-adjusted EPEs → book loss GCI drag by line and tier.
B48: 05 | C48: Revenue Engine | E48: Engine | F48: GCI build for Leasing, IS, D&E, and Advisory; revenue bridge; market-share diagnostic.
B49: 06 | C49: Compensation Engine | E49: Engine | F49: Tiered splits → producer payouts → Company Dollar; Advisory & support comp; bonus pool.
B50: 07 | C50: Opex Engine | E50: Engine | F50: Driver-based opex: fixed costs, variable costs, D&A — linked to headcount and deal counts.
B51: 08 | C51: P&L | E51: Output | F51: Brokerage waterfall: GCI → Producer Payouts → Company Dollar → Opex → EBITDA.
B52: 09 | C52: Scenario Analysis | E52: Output | F52: Base / Upside / Downside comparison; key assumption spread; EBITDA bridge by driver.
B53: 10 | C53: Dashboard | E53: Output | F53: Executive visual summary: KPI scorecard, 4 native charts, KPI table — all linked, no calculations.
B54: 11 | C54: Checks | E54: Control | F54: Pass/fail integrity checks: structural, ratio, bridge, and market-share governor flags.
B56: COLOR CONVENTION LEGEND
B57: Sample | C57: Cell Type | E57: Meaning
B58: Input (Blue) | C58: Input (Blue) | E58: Hardcoded input — analyst types value directly. Never referenced across tabs as a live calc.
B59: Calculation (Black) | C59: Calculation (Black) | E59: Formula derived from cells in the same tab. No hardcoded values inside formulas.
B60: Link (Green) | C60: Link (Green) | E60: Hard link pulling data from another tab. Always = 'TabName'!CellRef — no intermediaries.
B61: Error / Fail (Red) | C61: Error / Fail (Red) | E61: Formula error (#REF!, #DIV/0!) or a Checks tab flag returning FAIL. Investigate immediately.
B62: Label (Grey) | C62: Label (Grey) | E62: Section header or structural label. Non-data cell — no values, no formulas, never linked.
B64: MODEL NOTES & LIMITATIONS
B65: Purpose
B66: Portfolio-grade, driver-based operating model for Apex CRE Advisors (fictional). Demonstrates brokerage revenue economics, producer productivity (EPE), Company Dollar logic, driver-based opex, EBITDA forecasting, and scenario analysis.
B67: What This Model Is NOT
B68: Not a DCF. Not a valuation model. Not an M&A model. Does not produce intrinsic value or a transaction price. This is a business forecasting and FP&A planning tool.
B69: Assumptions & Benchmarks
B70: Assumptions are illustrative and benchmarked against public CRE company disclosures (Marcus & Millichap 10-K, CBRE, JLL, Newmark, Colliers) and industry data (MSCI/RCA, MBA Originations Survey, CBRE MarketView). No real company financials used.
B71: Scenario Design
B72: Base / Upside / Downside are internally consistent, correlated-driver scenarios — not single-variable flexes. Downside moves volume, fee rates, attrition, ramp, and pull-through together. Advisory provides a partial countercyclical buffer in all scenarios.
B73: V1 Simplifications (V2 Backlog)
B74: V1 omits: full cash flow / working capital, cohort-level producer tracking, draw recovery schedules, deferred comp, step-fixed office expansion, and two-way sensitivity tables. EPE formula: EPE = Beginning HC + (Hires × Ramp Factor) − Attrition.

Sheet 02 Market Assumptions
A1: 02 | MARKET ASSUMPTIONS — EXOGENOUS DRIVERS
A2: Scenario-sensitive rows use Base / Upside / Downside / Active pattern. Active rows link to Tab 01 C19. | E2: ='01 Cover & Control'!C19 -> Base
B3: Assumption / Row | C3: Units | D3: Source / Notes | E3: 2023A Q1 | F3: 2023A Q2 | G3: 2023A Q3 | H3: 2023A Q4 | I3: 2023A Annual | J3: 2024A Q1 | K3: 2024A Q2 | L3: 2024A Q3 | M3: 2024A Q4 | N3: 2024A Annual | O3: 2025A Q1 | P3: 2025A Q2 | Q3: 2025A Q3 | R3: 2025A Q4 | S3: 2025A Annual | T3: 2026E Q1 | U3: 2026E Q2 | V3: 2026E Q3 | W3: 2026E Q4 | X3: 2026E Annual | Y3: 2027E Q1 | Z3: 2027E Q2 | AA3: 2027E Q3 | AB3: 2027E Q4 | AC3: 2027E Annual | AD3: 2028E Q1 | AE3: 2028E Q2 | AF3: 2028E Q3 | AG3: 2028E Q4 | AH3: 2028E Annual | AI3: 2029E Q1 | AJ3: 2029E Q2 | AK3: 2029E Q3 | AL3: 2029E Q4 | AM3: 2029E Annual | AN3: 2030E Q1 | AO3: 2030E Q2 | AP3: 2030E Q3 | AQ3: 2030E Q4 | AR3: 2030E Annual
A5: SECTION A — MACRO CONTEXT
B7: Real GDP Growth (YoY) — Base | C7: % / yr | D7: BEA GDP Release; Bloomberg consensus forecast | E7: 1.8 | F7: 1.8 | G7: 1.8 | H7: 1.8 | I7: =SUM(E7:H7) -> 7.2 | J7: 2.1 | K7: 2.1 | L7: 2.1 | M7: 2.1 | N7: =SUM(J7:M7) -> 8.4 | O7: 2.4 | P7: 2.4 | Q7: 2.4 | R7: 2.4 | S7: =SUM(O7:R7) -> 9.6 | T7: 2.2 | U7: 2.2 | V7: 2.2 | W7: 2.2 | X7: =SUM(T7:W7) -> 8.8 | Y7: 2 | Z7: 2 | AA7: 2 | AB7: 2 | AC7: =SUM(Y7:AB7) -> 8 | AD7: 2 | AE7: 2 | AF7: 2 | AG7: 2 | AH7: =SUM(AD7:AG7) -> 8 | AI7: 2 | AJ7: 2 | AK7: 2 | AL7: 2 | AM7: =SUM(AI7:AL7) -> 8 | AN7: 2 | AO7: 2 | AP7: 2 | AQ7: 2 | AR7: =SUM(AN7:AQ7) -> 8
B8: Real GDP Growth (YoY) — Upside | E8: 1.8 | F8: 1.8 | G8: 1.8 | H8: 1.8 | I8: =SUM(E8:H8) -> 7.2 | J8: 2.1 | K8: 2.1 | L8: 2.1 | M8: 2.1 | N8: =SUM(J8:M8) -> 8.4 | O8: 2.6 | P8: 2.6 | Q8: 2.6 | R8: 2.6 | S8: =SUM(O8:R8) -> 10.4 | T8: 2.8 | U8: 2.8 | V8: 2.8 | W8: 2.8 | X8: =SUM(T8:W8) -> 11.2 | Y8: 2.7 | Z8: 2.7 | AA8: 2.7 | AB8: 2.7 | AC8: =SUM(Y8:AB8) -> 10.8 | AD8: 2.6 | AE8: 2.6 | AF8: 2.6 | AG8: 2.6 | AH8: =SUM(AD8:AG8) -> 10.4 | AI8: 2.5 | AJ8: 2.5 | AK8: 2.5 | AL8: 2.5 | AM8: =SUM(AI8:AL8) -> 10 | AN8: 2.5 | AO8: 2.5 | AP8: 2.5 | AQ8: 2.5 | AR8: =SUM(AN8:AQ8) -> 10
B9: Real GDP Growth (YoY) — Downside | E9: 1.8 | F9: 1.8 | G9: 1.8 | H9: 1.8 | I9: =SUM(E9:H9) -> 7.2 | J9: 2.1 | K9: 2.1 | L9: 2.1 | M9: 2.1 | N9: =SUM(J9:M9) -> 8.4 | O9: 1.2 | P9: 1.2 | Q9: 1.2 | R9: 1.2 | S9: =SUM(O9:R9) -> 4.8 | T9: 0.4 | U9: 0.4 | V9: 0.4 | W9: 0.4 | X9: =SUM(T9:W9) -> 1.6 | Y9: 0.8 | Z9: 0.8 | AA9: 0.8 | AB9: 0.8 | AC9: =SUM(Y9:AB9) -> 3.2 | AD9: 1.2 | AE9: 1.2 | AF9: 1.2 | AG9: 1.2 | AH9: =SUM(AD9:AG9) -> 4.8 | AI9: 1.5 | AJ9: 1.5 | AK9: 1.5 | AL9: 1.5 | AM9: =SUM(AI9:AL9) -> 6 | AN9: 1.6 | AO9: 1.6 | AP9: 1.6 | AQ9: 1.6 | AR9: =SUM(AN9:AQ9) -> 6.4
B10: Real GDP Growth (YoY) — ★ ACTIVE | E10: =IF('01 Cover & Control'!$C$19="Base",E7,IF('01 Cover & Control'!$C$19="Upside",E8,E9)) -> 1.8 | F10: =IF('01 Cover & Control'!$C$19="Base",F7,IF('01 Cover & Control'!$C$19="Upside",F8,F9)) -> 1.8 | G10: =IF('01 Cover & Control'!$C$19="Base",G7,IF('01 Cover & Control'!$C$19="Upside",G8,G9)) -> 1.8 | H10: =IF('01 Cover & Control'!$C$19="Base",H7,IF('01 Cover & Control'!$C$19="Upside",H8,H9)) -> 1.8 | I10: =SUM(E10:H10) -> 7.2 | J10: =IF('01 Cover & Control'!$C$19="Base",J7,IF('01 Cover & Control'!$C$19="Upside",J8,J9)) -> 2.1 | K10: =IF('01 Cover & Control'!$C$19="Base",K7,IF('01 Cover & Control'!$C$19="Upside",K8,K9)) -> 2.1 | L10: =IF('01 Cover & Control'!$C$19="Base",L7,IF('01 Cover & Control'!$C$19="Upside",L8,L9)) -> 2.1 | M10: =IF('01 Cover & Control'!$C$19="Base",M7,IF('01 Cover & Control'!$C$19="Upside",M8,M9)) -> 2.1 | N10: =SUM(J10:M10) -> 8.4 | O10: =IF('01 Cover & Control'!$C$19="Base",O7,IF('01 Cover & Control'!$C$19="Upside",O8,O9)) -> 2.4 | P10: =IF('01 Cover & Control'!$C$19="Base",P7,IF('01 Cover & Control'!$C$19="Upside",P8,P9)) -> 2.4 | Q10: =IF('01 Cover & Control'!$C$19="Base",Q7,IF('01 Cover & Control'!$C$19="Upside",Q8,Q9)) -> 2.4 | R10: =IF('01 Cover & Control'!$C$19="Base",R7,IF('01 Cover & Control'!$C$19="Upside",R8,R9)) -> 2.4 | S10: =SUM(O10:R10) -> 9.6 | T10: =IF('01 Cover & Control'!$C$19="Base",T7,IF('01 Cover & Control'!$C$19="Upside",T8,T9)) -> 2.2 | U10: =IF('01 Cover & Control'!$C$19="Base",U7,IF('01 Cover & Control'!$C$19="Upside",U8,U9)) -> 2.2 | V10: =IF('01 Cover & Control'!$C$19="Base",V7,IF('01 Cover & Control'!$C$19="Upside",V8,V9)) -> 2.2 | W10: =IF('01 Cover & Control'!$C$19="Base",W7,IF('01 Cover & Control'!$C$19="Upside",W8,W9)) -> 2.2 | X10: =SUM(T10:W10) -> 8.8 | Y10: =IF('01 Cover & Control'!$C$19="Base",Y7,IF('01 Cover & Control'!$C$19="Upside",Y8,Y9)) -> 2 | Z10: =IF('01 Cover & Control'!$C$19="Base",Z7,IF('01 Cover & Control'!$C$19="Upside",Z8,Z9)) -> 2 | AA10: =IF('01 Cover & Control'!$C$19="Base",AA7,IF('01 Cover & Control'!$C$19="Upside",AA8,AA9)) -> 2 | AB10: =IF('01 Cover & Control'!$C$19="Base",AB7,IF('01 Cover & Control'!$C$19="Upside",AB8,AB9)) -> 2 | AC10: =SUM(Y10:AB10) -> 8 | AD10: =IF('01 Cover & Control'!$C$19="Base",AD7,IF('01 Cover & Control'!$C$19="Upside",AD8,AD9)) -> 2 | AE10: =IF('01 Cover & Control'!$C$19="Base",AE7,IF('01 Cover & Control'!$C$19="Upside",AE8,AE9)) -> 2 | AF10: =IF('01 Cover & Control'!$C$19="Base",AF7,IF('01 Cover & Control'!$C$19="Upside",AF8,AF9)) -> 2 | AG10: =IF('01 Cover & Control'!$C$19="Base",AG7,IF('01 Cover & Control'!$C$19="Upside",AG8,AG9)) -> 2 | AH10: =SUM(AD10:AG10) -> 8 | AI10: =IF('01 Cover & Control'!$C$19="Base",AI7,IF('01 Cover & Control'!$C$19="Upside",AI8,AI9)) -> 2 | AJ10: =IF('01 Cover & Control'!$C$19="Base",AJ7,IF('01 Cover & Control'!$C$19="Upside",AJ8,AJ9)) -> 2 | AK10: =IF('01 Cover & Control'!$C$19="Base",AK7,IF('01 Cover & Control'!$C$19="Upside",AK8,AK9)) -> 2 | AL10: =IF('01 Cover & Control'!$C$19="Base",AL7,IF('01 Cover & Control'!$C$19="Upside",AL8,AL9)) -> 2 | AM10: =SUM(AI10:AL10) -> 8 | AN10: =IF('01 Cover & Control'!$C$19="Base",AN7,IF('01 Cover & Control'!$C$19="Upside",AN8,AN9)) -> 2 | AO10: =IF('01 Cover & Control'!$C$19="Base",AO7,IF('01 Cover & Control'!$C$19="Upside",AO8,AO9)) -> 2 | AP10: =IF('01 Cover & Control'!$C$19="Base",AP7,IF('01 Cover & Control'!$C$19="Upside",AP8,AP9)) -> 2 | AQ10: =IF('01 Cover & Control'!$C$19="Base",AQ7,IF('01 Cover & Control'!$C$19="Upside",AQ8,AQ9)) -> 2 | AR10: =SUM(AN10:AQ10) -> 8
B12: 10-Year Treasury Yield — Base | C12: % | D12: Federal Reserve H.15; Bloomberg | E12: 3.9 | F12: 3.9 | G12: 3.9 | H12: 3.9 | I12: =SUM(E12:H12) -> 15.6 | J12: 4.2 | K12: 4.2 | L12: 4.2 | M12: 4.2 | N12: =SUM(J12:M12) -> 16.8 | O12: 4.3 | P12: 4.3 | Q12: 4.3 | R12: 4.3 | S12: =SUM(O12:R12) -> 17.2 | T12: 4 | U12: 4 | V12: 4 | W12: 4 | X12: =SUM(T12:W12) -> 16 | Y12: 3.8 | Z12: 3.8 | AA12: 3.8 | AB12: 3.8 | AC12: =SUM(Y12:AB12) -> 15.2 | AD12: 3.7 | AE12: 3.7 | AF12: 3.7 | AG12: 3.7 | AH12: =SUM(AD12:AG12) -> 14.8 | AI12: 3.7 | AJ12: 3.7 | AK12: 3.7 | AL12: 3.7 | AM12: =SUM(AI12:AL12) -> 14.8 | AN12: 3.7 | AO12: 3.7 | AP12: 3.7 | AQ12: 3.7 | AR12: =SUM(AN12:AQ12) -> 14.8
B13: 10-Year Treasury Yield — Upside | E13: 3.9 | F13: 3.9 | G13: 3.9 | H13: 3.9 | I13: =SUM(E13:H13) -> 15.6 | J13: 4.2 | K13: 4.2 | L13: 4.2 | M13: 4.2 | N13: =SUM(J13:M13) -> 16.8 | O13: 4 | P13: 4 | Q13: 4 | R13: 4 | S13: =SUM(O13:R13) -> 16 | T13: 3.5 | U13: 3.5 | V13: 3.5 | W13: 3.5 | X13: =SUM(T13:W13) -> 14 | Y13: 3.3 | Z13: 3.3 | AA13: 3.3 | AB13: 3.3 | AC13: =SUM(Y13:AB13) -> 13.2 | AD13: 3.2 | AE13: 3.2 | AF13: 3.2 | AG13: 3.2 | AH13: =SUM(AD13:AG13) -> 12.8 | AI13: 3.2 | AJ13: 3.2 | AK13: 3.2 | AL13: 3.2 | AM13: =SUM(AI13:AL13) -> 12.8 | AN13: 3.2 | AO13: 3.2 | AP13: 3.2 | AQ13: 3.2 | AR13: =SUM(AN13:AQ13) -> 12.8
B14: 10-Year Treasury Yield — Downside | E14: 3.9 | F14: 3.9 | G14: 3.9 | H14: 3.9 | I14: =SUM(E14:H14) -> 15.6 | J14: 4.2 | K14: 4.2 | L14: 4.2 | M14: 4.2 | N14: =SUM(J14:M14) -> 16.8 | O14: 4.8 | P14: 4.8 | Q14: 4.8 | R14: 4.8 | S14: =SUM(O14:R14) -> 19.2 | T14: 5 | U14: 5 | V14: 5 | W14: 5 | X14: =SUM(T14:W14) -> 20 | Y14: 4.8 | Z14: 4.8 | AA14: 4.8 | AB14: 4.8 | AC14: =SUM(Y14:AB14) -> 19.2 | AD14: 4.6 | AE14: 4.6 | AF14: 4.6 | AG14: 4.6 | AH14: =SUM(AD14:AG14) -> 18.4 | AI14: 4.5 | AJ14: 4.5 | AK14: 4.5 | AL14: 4.5 | AM14: =SUM(AI14:AL14) -> 18 | AN14: 4.4 | AO14: 4.4 | AP14: 4.4 | AQ14: 4.4 | AR14: =SUM(AN14:AQ14) -> 17.6
B15: 10-Year Treasury Yield — ★ ACTIVE | E15: =IF('01 Cover & Control'!$C$19="Base",E12,IF('01 Cover & Control'!$C$19="Upside",E13,E14)) -> 3.9 | F15: =IF('01 Cover & Control'!$C$19="Base",F12,IF('01 Cover & Control'!$C$19="Upside",F13,F14)) -> 3.9 | G15: =IF('01 Cover & Control'!$C$19="Base",G12,IF('01 Cover & Control'!$C$19="Upside",G13,G14)) -> 3.9 | H15: =IF('01 Cover & Control'!$C$19="Base",H12,IF('01 Cover & Control'!$C$19="Upside",H13,H14)) -> 3.9 | I15: =SUM(E15:H15) -> 15.6 | J15: =IF('01 Cover & Control'!$C$19="Base",J12,IF('01 Cover & Control'!$C$19="Upside",J13,J14)) -> 4.2 | K15: =IF('01 Cover & Control'!$C$19="Base",K12,IF('01 Cover & Control'!$C$19="Upside",K13,K14)) -> 4.2 | L15: =IF('01 Cover & Control'!$C$19="Base",L12,IF('01 Cover & Control'!$C$19="Upside",L13,L14)) -> 4.2 | M15: =IF('01 Cover & Control'!$C$19="Base",M12,IF('01 Cover & Control'!$C$19="Upside",M13,M14)) -> 4.2 | N15: =SUM(J15:M15) -> 16.8 | O15: =IF('01 Cover & Control'!$C$19="Base",O12,IF('01 Cover & Control'!$C$19="Upside",O13,O14)) -> 4.3 | P15: =IF('01 Cover & Control'!$C$19="Base",P12,IF('01 Cover & Control'!$C$19="Upside",P13,P14)) -> 4.3 | Q15: =IF('01 Cover & Control'!$C$19="Base",Q12,IF('01 Cover & Control'!$C$19="Upside",Q13,Q14)) -> 4.3 | R15: =IF('01 Cover & Control'!$C$19="Base",R12,IF('01 Cover & Control'!$C$19="Upside",R13,R14)) -> 4.3 | S15: =SUM(O15:R15) -> 17.2 | T15: =IF('01 Cover & Control'!$C$19="Base",T12,IF('01 Cover & Control'!$C$19="Upside",T13,T14)) -> 4 | U15: =IF('01 Cover & Control'!$C$19="Base",U12,IF('01 Cover & Control'!$C$19="Upside",U13,U14)) -> 4 | V15: =IF('01 Cover & Control'!$C$19="Base",V12,IF('01 Cover & Control'!$C$19="Upside",V13,V14)) -> 4 | W15: =IF('01 Cover & Control'!$C$19="Base",W12,IF('01 Cover & Control'!$C$19="Upside",W13,W14)) -> 4 | X15: =SUM(T15:W15) -> 16 | Y15: =IF('01 Cover & Control'!$C$19="Base",Y12,IF('01 Cover & Control'!$C$19="Upside",Y13,Y14)) -> 3.8 | Z15: =IF('01 Cover & Control'!$C$19="Base",Z12,IF('01 Cover & Control'!$C$19="Upside",Z13,Z14)) -> 3.8 | AA15: =IF('01 Cover & Control'!$C$19="Base",AA12,IF('01 Cover & Control'!$C$19="Upside",AA13,AA14)) -> 3.8 | AB15: =IF('01 Cover & Control'!$C$19="Base",AB12,IF('01 Cover & Control'!$C$19="Upside",AB13,AB14)) -> 3.8 | AC15: =SUM(Y15:AB15) -> 15.2 | AD15: =IF('01 Cover & Control'!$C$19="Base",AD12,IF('01 Cover & Control'!$C$19="Upside",AD13,AD14)) -> 3.7 | AE15: =IF('01 Cover & Control'!$C$19="Base",AE12,IF('01 Cover & Control'!$C$19="Upside",AE13,AE14)) -> 3.7 | AF15: =IF('01 Cover & Control'!$C$19="Base",AF12,IF('01 Cover & Control'!$C$19="Upside",AF13,AF14)) -> 3.7 | AG15: =IF('01 Cover & Control'!$C$19="Base",AG12,IF('01 Cover & Control'!$C$19="Upside",AG13,AG14)) -> 3.7 | AH15: =SUM(AD15:AG15) -> 14.8 | AI15: =IF('01 Cover & Control'!$C$19="Base",AI12,IF('01 Cover & Control'!$C$19="Upside",AI13,AI14)) -> 3.7 | AJ15: =IF('01 Cover & Control'!$C$19="Base",AJ12,IF('01 Cover & Control'!$C$19="Upside",AJ13,AJ14)) -> 3.7 | AK15: =IF('01 Cover & Control'!$C$19="Base",AK12,IF('01 Cover & Control'!$C$19="Upside",AK13,AK14)) -> 3.7 | AL15: =IF('01 Cover & Control'!$C$19="Base",AL12,IF('01 Cover & Control'!$C$19="Upside",AL13,AL14)) -> 3.7 | AM15: =SUM(AI15:AL15) -> 14.8 | AN15: =IF('01 Cover & Control'!$C$19="Base",AN12,IF('01 Cover & Control'!$C$19="Upside",AN13,AN14)) -> 3.7 | AO15: =IF('01 Cover & Control'!$C$19="Base",AO12,IF('01 Cover & Control'!$C$19="Upside",AO13,AO14)) -> 3.7 | AP15: =IF('01 Cover & Control'!$C$19="Base",AP12,IF('01 Cover & Control'!$C$19="Upside",AP13,AP14)) -> 3.7 | AQ15: =IF('01 Cover & Control'!$C$19="Base",AQ12,IF('01 Cover & Control'!$C$19="Upside",AQ13,AQ14)) -> 3.7 | AR15: =SUM(AN15:AQ15) -> 14.8
B17: Note: Lending Availability coded as 1=Tight, 2=Normal, 3=Loose. Used as qualitative context to calibrate Tab 03 deal count and pull-through assumptions.
B18: CRE Lending Availability Index — Base | C18: 1/2/3 | D18: CBRE Senior Loan Officer Survey; Fed Survey of Credit Conditions | E18: 1.5 | F18: 1.5 | G18: 1.5 | H18: 1.5 | I18: =SUM(E18:H18) -> 6 | J18: 1.6 | K18: 1.6 | L18: 1.6 | M18: 1.6 | N18: =SUM(J18:M18) -> 6.4 | O18: 1.8 | P18: 1.8 | Q18: 1.8 | R18: 1.8 | S18: =SUM(O18:R18) -> 7.2 | T18: 2 | U18: 2 | V18: 2 | W18: 2 | X18: =SUM(T18:W18) -> 8 | Y18: 2.1 | Z18: 2.1 | AA18: 2.1 | AB18: 2.1 | AC18: =SUM(Y18:AB18) -> 8.4 | AD18: 2.2 | AE18: 2.2 | AF18: 2.2 | AG18: 2.2 | AH18: =SUM(AD18:AG18) -> 8.8 | AI18: 2.2 | AJ18: 2.2 | AK18: 2.2 | AL18: 2.2 | AM18: =SUM(AI18:AL18) -> 8.8 | AN18: 2.2 | AO18: 2.2 | AP18: 2.2 | AQ18: 2.2 | AR18: =SUM(AN18:AQ18) -> 8.8
B19: CRE Lending Availability Index — Upside | E19: 1.5 | F19: 1.5 | G19: 1.5 | H19: 1.5 | I19: =SUM(E19:H19) -> 6 | J19: 1.6 | K19: 1.6 | L19: 1.6 | M19: 1.6 | N19: =SUM(J19:M19) -> 6.4 | O19: 2 | P19: 2 | Q19: 2 | R19: 2 | S19: =SUM(O19:R19) -> 8 | T19: 2.3 | U19: 2.3 | V19: 2.3 | W19: 2.3 | X19: =SUM(T19:W19) -> 9.2 | Y19: 2.5 | Z19: 2.5 | AA19: 2.5 | AB19: 2.5 | AC19: =SUM(Y19:AB19) -> 10 | AD19: 2.6 | AE19: 2.6 | AF19: 2.6 | AG19: 2.6 | AH19: =SUM(AD19:AG19) -> 10.4 | AI19: 2.7 | AJ19: 2.7 | AK19: 2.7 | AL19: 2.7 | AM19: =SUM(AI19:AL19) -> 10.8 | AN19: 2.7 | AO19: 2.7 | AP19: 2.7 | AQ19: 2.7 | AR19: =SUM(AN19:AQ19) -> 10.8
B20: CRE Lending Availability Index — Downside | E20: 1.5 | F20: 1.5 | G20: 1.5 | H20: 1.5 | I20: =SUM(E20:H20) -> 6 | J20: 1.6 | K20: 1.6 | L20: 1.6 | M20: 1.6 | N20: =SUM(J20:M20) -> 6.4 | O20: 1.4 | P20: 1.4 | Q20: 1.4 | R20: 1.4 | S20: =SUM(O20:R20) -> 5.6 | T20: 1.2 | U20: 1.2 | V20: 1.2 | W20: 1.2 | X20: =SUM(T20:W20) -> 4.8 | Y20: 1.4 | Z20: 1.4 | AA20: 1.4 | AB20: 1.4 | AC20: =SUM(Y20:AB20) -> 5.6 | AD20: 1.6 | AE20: 1.6 | AF20: 1.6 | AG20: 1.6 | AH20: =SUM(AD20:AG20) -> 6.4 | AI20: 1.7 | AJ20: 1.7 | AK20: 1.7 | AL20: 1.7 | AM20: =SUM(AI20:AL20) -> 6.8 | AN20: 1.8 | AO20: 1.8 | AP20: 1.8 | AQ20: 1.8 | AR20: =SUM(AN20:AQ20) -> 7.2
B21: CRE Lending Availability Index — ★ ACTIVE | E21: =IF('01 Cover & Control'!$C$19="Base",E18,IF('01 Cover & Control'!$C$19="Upside",E19,E20)) -> 1.5 | F21: =IF('01 Cover & Control'!$C$19="Base",F18,IF('01 Cover & Control'!$C$19="Upside",F19,F20)) -> 1.5 | G21: =IF('01 Cover & Control'!$C$19="Base",G18,IF('01 Cover & Control'!$C$19="Upside",G19,G20)) -> 1.5 | H21: =IF('01 Cover & Control'!$C$19="Base",H18,IF('01 Cover & Control'!$C$19="Upside",H19,H20)) -> 1.5 | I21: =SUM(E21:H21) -> 6 | J21: =IF('01 Cover & Control'!$C$19="Base",J18,IF('01 Cover & Control'!$C$19="Upside",J19,J20)) -> 1.6 | K21: =IF('01 Cover & Control'!$C$19="Base",K18,IF('01 Cover & Control'!$C$19="Upside",K19,K20)) -> 1.6 | L21: =IF('01 Cover & Control'!$C$19="Base",L18,IF('01 Cover & Control'!$C$19="Upside",L19,L20)) -> 1.6 | M21: =IF('01 Cover & Control'!$C$19="Base",M18,IF('01 Cover & Control'!$C$19="Upside",M19,M20)) -> 1.6 | N21: =SUM(J21:M21) -> 6.4 | O21: =IF('01 Cover & Control'!$C$19="Base",O18,IF('01 Cover & Control'!$C$19="Upside",O19,O20)) -> 1.8 | P21: =IF('01 Cover & Control'!$C$19="Base",P18,IF('01 Cover & Control'!$C$19="Upside",P19,P20)) -> 1.8 | Q21: =IF('01 Cover & Control'!$C$19="Base",Q18,IF('01 Cover & Control'!$C$19="Upside",Q19,Q20)) -> 1.8 | R21: =IF('01 Cover & Control'!$C$19="Base",R18,IF('01 Cover & Control'!$C$19="Upside",R19,R20)) -> 1.8 | S21: =SUM(O21:R21) -> 7.2 | T21: =IF('01 Cover & Control'!$C$19="Base",T18,IF('01 Cover & Control'!$C$19="Upside",T19,T20)) -> 2 | U21: =IF('01 Cover & Control'!$C$19="Base",U18,IF('01 Cover & Control'!$C$19="Upside",U19,U20)) -> 2 | V21: =IF('01 Cover & Control'!$C$19="Base",V18,IF('01 Cover & Control'!$C$19="Upside",V19,V20)) -> 2 | W21: =IF('01 Cover & Control'!$C$19="Base",W18,IF('01 Cover & Control'!$C$19="Upside",W19,W20)) -> 2 | X21: =SUM(T21:W21) -> 8 | Y21: =IF('01 Cover & Control'!$C$19="Base",Y18,IF('01 Cover & Control'!$C$19="Upside",Y19,Y20)) -> 2.1 | Z21: =IF('01 Cover & Control'!$C$19="Base",Z18,IF('01 Cover & Control'!$C$19="Upside",Z19,Z20)) -> 2.1 | AA21: =IF('01 Cover & Control'!$C$19="Base",AA18,IF('01 Cover & Control'!$C$19="Upside",AA19,AA20)) -> 2.1 | AB21: =IF('01 Cover & Control'!$C$19="Base",AB18,IF('01 Cover & Control'!$C$19="Upside",AB19,AB20)) -> 2.1 | AC21: =SUM(Y21:AB21) -> 8.4 | AD21: =IF('01 Cover & Control'!$C$19="Base",AD18,IF('01 Cover & Control'!$C$19="Upside",AD19,AD20)) -> 2.2 | AE21: =IF('01 Cover & Control'!$C$19="Base",AE18,IF('01 Cover & Control'!$C$19="Upside",AE19,AE20)) -> 2.2 | AF21: =IF('01 Cover & Control'!$C$19="Base",AF18,IF('01 Cover & Control'!$C$19="Upside",AF19,AF20)) -> 2.2 | AG21: =IF('01 Cover & Control'!$C$19="Base",AG18,IF('01 Cover & Control'!$C$19="Upside",AG19,AG20)) -> 2.2 | AH21: =SUM(AD21:AG21) -> 8.8 | AI21: =IF('01 Cover & Control'!$C$19="Base",AI18,IF('01 Cover & Control'!$C$19="Upside",AI19,AI20)) -> 2.2 | AJ21: =IF('01 Cover & Control'!$C$19="Base",AJ18,IF('01 Cover & Control'!$C$19="Upside",AJ19,AJ20)) -> 2.2 | AK21: =IF('01 Cover & Control'!$C$19="Base",AK18,IF('01 Cover & Control'!$C$19="Upside",AK19,AK20)) -> 2.2 | AL21: =IF('01 Cover & Control'!$C$19="Base",AL18,IF('01 Cover & Control'!$C$19="Upside",AL19,AL20)) -> 2.2 | AM21: =SUM(AI21:AL21) -> 8.8 | AN21: =IF('01 Cover & Control'!$C$19="Base",AN18,IF('01 Cover & Control'!$C$19="Upside",AN19,AN20)) -> 2.2 | AO21: =IF('01 Cover & Control'!$C$19="Base",AO18,IF('01 Cover & Control'!$C$19="Upside",AO19,AO20)) -> 2.2 | AP21: =IF('01 Cover & Control'!$C$19="Base",AP18,IF('01 Cover & Control'!$C$19="Upside",AP19,AP20)) -> 2.2 | AQ21: =IF('01 Cover & Control'!$C$19="Base",AQ18,IF('01 Cover & Control'!$C$19="Upside",AQ19,AQ20)) -> 2.2 | AR21: =SUM(AN21:AQ21) -> 8.8
B23: Cap Rate — Blended CRE (Market Average) — Base | C23: % | D23: CBRE Cap Rate Survey; NCREIF; RCA/MSCI | E23: 6.2 | F23: 6.2 | G23: 6.2 | H23: 6.2 | I23: =SUM(E23:H23) -> 24.8 | J23: 6.5 | K23: 6.5 | L23: 6.5 | M23: 6.5 | N23: =SUM(J23:M23) -> 26 | O23: 6.4 | P23: 6.4 | Q23: 6.4 | R23: 6.4 | S23: =SUM(O23:R23) -> 25.6 | T23: 6.2 | U23: 6.2 | V23: 6.2 | W23: 6.2 | X23: =SUM(T23:W23) -> 24.8 | Y23: 6.1 | Z23: 6.1 | AA23: 6.1 | AB23: 6.1 | AC23: =SUM(Y23:AB23) -> 24.4 | AD23: 6 | AE23: 6 | AF23: 6 | AG23: 6 | AH23: =SUM(AD23:AG23) -> 24 | AI23: 6 | AJ23: 6 | AK23: 6 | AL23: 6 | AM23: =SUM(AI23:AL23) -> 24 | AN23: 6 | AO23: 6 | AP23: 6 | AQ23: 6 | AR23: =SUM(AN23:AQ23) -> 24
B24: Cap Rate — Blended CRE (Market Average) — Upside | E24: 6.2 | F24: 6.2 | G24: 6.2 | H24: 6.2 | I24: =SUM(E24:H24) -> 24.8 | J24: 6.5 | K24: 6.5 | L24: 6.5 | M24: 6.5 | N24: =SUM(J24:M24) -> 26 | O24: 6.2 | P24: 6.2 | Q24: 6.2 | R24: 6.2 | S24: =SUM(O24:R24) -> 24.8 | T24: 5.9 | U24: 5.9 | V24: 5.9 | W24: 5.9 | X24: =SUM(T24:W24) -> 23.6 | Y24: 5.7 | Z24: 5.7 | AA24: 5.7 | AB24: 5.7 | AC24: =SUM(Y24:AB24) -> 22.8 | AD24: 5.6 | AE24: 5.6 | AF24: 5.6 | AG24: 5.6 | AH24: =SUM(AD24:AG24) -> 22.4 | AI24: 5.5 | AJ24: 5.5 | AK24: 5.5 | AL24: 5.5 | AM24: =SUM(AI24:AL24) -> 22 | AN24: 5.5 | AO24: 5.5 | AP24: 5.5 | AQ24: 5.5 | AR24: =SUM(AN24:AQ24) -> 22
B25: Cap Rate — Blended CRE (Market Average) — Downside | E25: 6.2 | F25: 6.2 | G25: 6.2 | H25: 6.2 | I25: =SUM(E25:H25) -> 24.8 | J25: 6.5 | K25: 6.5 | L25: 6.5 | M25: 6.5 | N25: =SUM(J25:M25) -> 26 | O25: 6.8 | P25: 6.8 | Q25: 6.8 | R25: 6.8 | S25: =SUM(O25:R25) -> 27.2 | T25: 7.1 | U25: 7.1 | V25: 7.1 | W25: 7.1 | X25: =SUM(T25:W25) -> 28.4 | Y25: 7 | Z25: 7 | AA25: 7 | AB25: 7 | AC25: =SUM(Y25:AB25) -> 28 | AD25: 6.9 | AE25: 6.9 | AF25: 6.9 | AG25: 6.9 | AH25: =SUM(AD25:AG25) -> 27.6 | AI25: 6.8 | AJ25: 6.8 | AK25: 6.8 | AL25: 6.8 | AM25: =SUM(AI25:AL25) -> 27.2 | AN25: 6.7 | AO25: 6.7 | AP25: 6.7 | AQ25: 6.7 | AR25: =SUM(AN25:AQ25) -> 26.8
B26: Cap Rate — Blended CRE (Market Average) — ★ ACTIVE | E26: =IF('01 Cover & Control'!$C$19="Base",E23,IF('01 Cover & Control'!$C$19="Upside",E24,E25)) -> 6.2 | F26: =IF('01 Cover & Control'!$C$19="Base",F23,IF('01 Cover & Control'!$C$19="Upside",F24,F25)) -> 6.2 | G26: =IF('01 Cover & Control'!$C$19="Base",G23,IF('01 Cover & Control'!$C$19="Upside",G24,G25)) -> 6.2 | H26: =IF('01 Cover & Control'!$C$19="Base",H23,IF('01 Cover & Control'!$C$19="Upside",H24,H25)) -> 6.2 | I26: =SUM(E26:H26) -> 24.8 | J26: =IF('01 Cover & Control'!$C$19="Base",J23,IF('01 Cover & Control'!$C$19="Upside",J24,J25)) -> 6.5 | K26: =IF('01 Cover & Control'!$C$19="Base",K23,IF('01 Cover & Control'!$C$19="Upside",K24,K25)) -> 6.5 | L26: =IF('01 Cover & Control'!$C$19="Base",L23,IF('01 Cover & Control'!$C$19="Upside",L24,L25)) -> 6.5 | M26: =IF('01 Cover & Control'!$C$19="Base",M23,IF('01 Cover & Control'!$C$19="Upside",M24,M25)) -> 6.5 | N26: =SUM(J26:M26) -> 26 | O26: =IF('01 Cover & Control'!$C$19="Base",O23,IF('01 Cover & Control'!$C$19="Upside",O24,O25)) -> 6.4 | P26: =IF('01 Cover & Control'!$C$19="Base",P23,IF('01 Cover & Control'!$C$19="Upside",P24,P25)) -> 6.4 | Q26: =IF('01 Cover & Control'!$C$19="Base",Q23,IF('01 Cover & Control'!$C$19="Upside",Q24,Q25)) -> 6.4 | R26: =IF('01 Cover & Control'!$C$19="Base",R23,IF('01 Cover & Control'!$C$19="Upside",R24,R25)) -> 6.4 | S26: =SUM(O26:R26) -> 25.6 | T26: =IF('01 Cover & Control'!$C$19="Base",T23,IF('01 Cover & Control'!$C$19="Upside",T24,T25)) -> 6.2 | U26: =IF('01 Cover & Control'!$C$19="Base",U23,IF('01 Cover & Control'!$C$19="Upside",U24,U25)) -> 6.2 | V26: =IF('01 Cover & Control'!$C$19="Base",V23,IF('01 Cover & Control'!$C$19="Upside",V24,V25)) -> 6.2 | W26: =IF('01 Cover & Control'!$C$19="Base",W23,IF('01 Cover & Control'!$C$19="Upside",W24,W25)) -> 6.2 | X26: =SUM(T26:W26) -> 24.8 | Y26: =IF('01 Cover & Control'!$C$19="Base",Y23,IF('01 Cover & Control'!$C$19="Upside",Y24,Y25)) -> 6.1 | Z26: =IF('01 Cover & Control'!$C$19="Base",Z23,IF('01 Cover & Control'!$C$19="Upside",Z24,Z25)) -> 6.1 | AA26: =IF('01 Cover & Control'!$C$19="Base",AA23,IF('01 Cover & Control'!$C$19="Upside",AA24,AA25)) -> 6.1 | AB26: =IF('01 Cover & Control'!$C$19="Base",AB23,IF('01 Cover & Control'!$C$19="Upside",AB24,AB25)) -> 6.1 | AC26: =SUM(Y26:AB26) -> 24.4 | AD26: =IF('01 Cover & Control'!$C$19="Base",AD23,IF('01 Cover & Control'!$C$19="Upside",AD24,AD25)) -> 6 | AE26: =IF('01 Cover & Control'!$C$19="Base",AE23,IF('01 Cover & Control'!$C$19="Upside",AE24,AE25)) -> 6 | AF26: =IF('01 Cover & Control'!$C$19="Base",AF23,IF('01 Cover & Control'!$C$19="Upside",AF24,AF25)) -> 6 | AG26: =IF('01 Cover & Control'!$C$19="Base",AG23,IF('01 Cover & Control'!$C$19="Upside",AG24,AG25)) -> 6 | AH26: =SUM(AD26:AG26) -> 24 | AI26: =IF('01 Cover & Control'!$C$19="Base",AI23,IF('01 Cover & Control'!$C$19="Upside",AI24,AI25)) -> 6 | AJ26: =IF('01 Cover & Control'!$C$19="Base",AJ23,IF('01 Cover & Control'!$C$19="Upside",AJ24,AJ25)) -> 6 | AK26: =IF('01 Cover & Control'!$C$19="Base",AK23,IF('01 Cover & Control'!$C$19="Upside",AK24,AK25)) -> 6 | AL26: =IF('01 Cover & Control'!$C$19="Base",AL23,IF('01 Cover & Control'!$C$19="Upside",AL24,AL25)) -> 6 | AM26: =SUM(AI26:AL26) -> 24 | AN26: =IF('01 Cover & Control'!$C$19="Base",AN23,IF('01 Cover & Control'!$C$19="Upside",AN24,AN25)) -> 6 | AO26: =IF('01 Cover & Control'!$C$19="Base",AO23,IF('01 Cover & Control'!$C$19="Upside",AO24,AO25)) -> 6 | AP26: =IF('01 Cover & Control'!$C$19="Base",AP23,IF('01 Cover & Control'!$C$19="Upside",AP24,AP25)) -> 6 | AQ26: =IF('01 Cover & Control'!$C$19="Base",AQ23,IF('01 Cover & Control'!$C$19="Upside",AQ24,AQ25)) -> 6 | AR26: =SUM(AN26:AQ26) -> 24
B28: Market Rent Growth — National Blended — Base | C28: % / yr | D28: CBRE MarketView; JLL Research; Cushman & Wakefield | E28: 2.5 | F28: 2.5 | G28: 2.5 | H28: 2.5 | I28: =SUM(E28:H28) -> 10 | J28: 2 | K28: 2 | L28: 2 | M28: 2 | N28: =SUM(J28:M28) -> 8 | O28: 2.2 | P28: 2.2 | Q28: 2.2 | R28: 2.2 | S28: =SUM(O28:R28) -> 8.8 | T28: 2.8 | U28: 2.8 | V28: 2.8 | W28: 2.8 | X28: =SUM(T28:W28) -> 11.2 | Y28: 3 | Z28: 3 | AA28: 3 | AB28: 3 | AC28: =SUM(Y28:AB28) -> 12 | AD28: 3 | AE28: 3 | AF28: 3 | AG28: 3 | AH28: =SUM(AD28:AG28) -> 12 | AI28: 3 | AJ28: 3 | AK28: 3 | AL28: 3 | AM28: =SUM(AI28:AL28) -> 12 | AN28: 3 | AO28: 3 | AP28: 3 | AQ28: 3 | AR28: =SUM(AN28:AQ28) -> 12
B29: Market Rent Growth — National Blended — Upside | E29: 2.5 | F29: 2.5 | G29: 2.5 | H29: 2.5 | I29: =SUM(E29:H29) -> 10 | J29: 2 | K29: 2 | L29: 2 | M29: 2 | N29: =SUM(J29:M29) -> 8 | O29: 2.8 | P29: 2.8 | Q29: 2.8 | R29: 2.8 | S29: =SUM(O29:R29) -> 11.2 | T29: 3.6 | U29: 3.6 | V29: 3.6 | W29: 3.6 | X29: =SUM(T29:W29) -> 14.4 | Y29: 3.8 | Z29: 3.8 | AA29: 3.8 | AB29: 3.8 | AC29: =SUM(Y29:AB29) -> 15.2 | AD29: 3.8 | AE29: 3.8 | AF29: 3.8 | AG29: 3.8 | AH29: =SUM(AD29:AG29) -> 15.2 | AI29: 3.7 | AJ29: 3.7 | AK29: 3.7 | AL29: 3.7 | AM29: =SUM(AI29:AL29) -> 14.8 | AN29: 3.6 | AO29: 3.6 | AP29: 3.6 | AQ29: 3.6 | AR29: =SUM(AN29:AQ29) -> 14.4
B30: Market Rent Growth — National Blended — Downside | E30: 2.5 | F30: 2.5 | G30: 2.5 | H30: 2.5 | I30: =SUM(E30:H30) -> 10 | J30: 2 | K30: 2 | L30: 2 | M30: 2 | N30: =SUM(J30:M30) -> 8 | O30: 1 | P30: 1 | Q30: 1 | R30: 1 | S30: =SUM(O30:R30) -> 4 | T30: 0.5 | U30: 0.5 | V30: 0.5 | W30: 0.5 | X30: =SUM(T30:W30) -> 2 | Y30: 1 | Z30: 1 | AA30: 1 | AB30: 1 | AC30: =SUM(Y30:AB30) -> 4 | AD30: 1.5 | AE30: 1.5 | AF30: 1.5 | AG30: 1.5 | AH30: =SUM(AD30:AG30) -> 6 | AI30: 1.8 | AJ30: 1.8 | AK30: 1.8 | AL30: 1.8 | AM30: =SUM(AI30:AL30) -> 7.2 | AN30: 2 | AO30: 2 | AP30: 2 | AQ30: 2 | AR30: =SUM(AN30:AQ30) -> 8
B31: Market Rent Growth — National Blended — ★ ACTIVE | E31: =IF('01 Cover & Control'!$C$19="Base",E28,IF('01 Cover & Control'!$C$19="Upside",E29,E30)) -> 2.5 | F31: =IF('01 Cover & Control'!$C$19="Base",F28,IF('01 Cover & Control'!$C$19="Upside",F29,F30)) -> 2.5 | G31: =IF('01 Cover & Control'!$C$19="Base",G28,IF('01 Cover & Control'!$C$19="Upside",G29,G30)) -> 2.5 | H31: =IF('01 Cover & Control'!$C$19="Base",H28,IF('01 Cover & Control'!$C$19="Upside",H29,H30)) -> 2.5 | I31: =SUM(E31:H31) -> 10 | J31: =IF('01 Cover & Control'!$C$19="Base",J28,IF('01 Cover & Control'!$C$19="Upside",J29,J30)) -> 2 | K31: =IF('01 Cover & Control'!$C$19="Base",K28,IF('01 Cover & Control'!$C$19="Upside",K29,K30)) -> 2 | L31: =IF('01 Cover & Control'!$C$19="Base",L28,IF('01 Cover & Control'!$C$19="Upside",L29,L30)) -> 2 | M31: =IF('01 Cover & Control'!$C$19="Base",M28,IF('01 Cover & Control'!$C$19="Upside",M29,M30)) -> 2 | N31: =SUM(J31:M31) -> 8 | O31: =IF('01 Cover & Control'!$C$19="Base",O28,IF('01 Cover & Control'!$C$19="Upside",O29,O30)) -> 2.2 | P31: =IF('01 Cover & Control'!$C$19="Base",P28,IF('01 Cover & Control'!$C$19="Upside",P29,P30)) -> 2.2 | Q31: =IF('01 Cover & Control'!$C$19="Base",Q28,IF('01 Cover & Control'!$C$19="Upside",Q29,Q30)) -> 2.2 | R31: =IF('01 Cover & Control'!$C$19="Base",R28,IF('01 Cover & Control'!$C$19="Upside",R29,R30)) -> 2.2 | S31: =SUM(O31:R31) -> 8.8 | T31: =IF('01 Cover & Control'!$C$19="Base",T28,IF('01 Cover & Control'!$C$19="Upside",T29,T30)) -> 2.8 | U31: =IF('01 Cover & Control'!$C$19="Base",U28,IF('01 Cover & Control'!$C$19="Upside",U29,U30)) -> 2.8 | V31: =IF('01 Cover & Control'!$C$19="Base",V28,IF('01 Cover & Control'!$C$19="Upside",V29,V30)) -> 2.8 | W31: =IF('01 Cover & Control'!$C$19="Base",W28,IF('01 Cover & Control'!$C$19="Upside",W29,W30)) -> 2.8 | X31: =SUM(T31:W31) -> 11.2 | Y31: =IF('01 Cover & Control'!$C$19="Base",Y28,IF('01 Cover & Control'!$C$19="Upside",Y29,Y30)) -> 3 | Z31: =IF('01 Cover & Control'!$C$19="Base",Z28,IF('01 Cover & Control'!$C$19="Upside",Z29,Z30)) -> 3 | AA31: =IF('01 Cover & Control'!$C$19="Base",AA28,IF('01 Cover & Control'!$C$19="Upside",AA29,AA30)) -> 3 | AB31: =IF('01 Cover & Control'!$C$19="Base",AB28,IF('01 Cover & Control'!$C$19="Upside",AB29,AB30)) -> 3 | AC31: =SUM(Y31:AB31) -> 12 | AD31: =IF('01 Cover & Control'!$C$19="Base",AD28,IF('01 Cover & Control'!$C$19="Upside",AD29,AD30)) -> 3 | AE31: =IF('01 Cover & Control'!$C$19="Base",AE28,IF('01 Cover & Control'!$C$19="Upside",AE29,AE30)) -> 3 | AF31: =IF('01 Cover & Control'!$C$19="Base",AF28,IF('01 Cover & Control'!$C$19="Upside",AF29,AF30)) -> 3 | AG31: =IF('01 Cover & Control'!$C$19="Base",AG28,IF('01 Cover & Control'!$C$19="Upside",AG29,AG30)) -> 3 | AH31: =SUM(AD31:AG31) -> 12 | AI31: =IF('01 Cover & Control'!$C$19="Base",AI28,IF('01 Cover & Control'!$C$19="Upside",AI29,AI30)) -> 3 | AJ31: =IF('01 Cover & Control'!$C$19="Base",AJ28,IF('01 Cover & Control'!$C$19="Upside",AJ29,AJ30)) -> 3 | AK31: =IF('01 Cover & Control'!$C$19="Base",AK28,IF('01 Cover & Control'!$C$19="Upside",AK29,AK30)) -> 3 | AL31: =IF('01 Cover & Control'!$C$19="Base",AL28,IF('01 Cover & Control'!$C$19="Upside",AL29,AL30)) -> 3 | AM31: =SUM(AI31:AL31) -> 12 | AN31: =IF('01 Cover & Control'!$C$19="Base",AN28,IF('01 Cover & Control'!$C$19="Upside",AN29,AN30)) -> 3 | AO31: =IF('01 Cover & Control'!$C$19="Base",AO28,IF('01 Cover & Control'!$C$19="Upside",AO29,AO30)) -> 3 | AP31: =IF('01 Cover & Control'!$C$19="Base",AP28,IF('01 Cover & Control'!$C$19="Upside",AP29,AP30)) -> 3 | AQ31: =IF('01 Cover & Control'!$C$19="Base",AQ28,IF('01 Cover & Control'!$C$19="Upside",AQ29,AQ30)) -> 3 | AR31: =SUM(AN31:AQ31) -> 12
B33: Inflation / CPI (YoY) — Base | C33: % / yr | D33: BLS CPI Release; Federal Reserve PCE | E33: 4.1 | F33: 4.1 | G33: 4.1 | H33: 4.1 | I33: =SUM(E33:H33) -> 16.4 | J33: 3.2 | K33: 3.2 | L33: 3.2 | M33: 3.2 | N33: =SUM(J33:M33) -> 12.8 | O33: 2.6 | P33: 2.6 | Q33: 2.6 | R33: 2.6 | S33: =SUM(O33:R33) -> 10.4 | T33: 2.3 | U33: 2.3 | V33: 2.3 | W33: 2.3 | X33: =SUM(T33:W33) -> 9.2 | Y33: 2.2 | Z33: 2.2 | AA33: 2.2 | AB33: 2.2 | AC33: =SUM(Y33:AB33) -> 8.8 | AD33: 2.1 | AE33: 2.1 | AF33: 2.1 | AG33: 2.1 | AH33: =SUM(AD33:AG33) -> 8.4 | AI33: 2 | AJ33: 2 | AK33: 2 | AL33: 2 | AM33: =SUM(AI33:AL33) -> 8 | AN33: 2 | AO33: 2 | AP33: 2 | AQ33: 2 | AR33: =SUM(AN33:AQ33) -> 8
B34: Inflation / CPI (YoY) — Upside | E34: 4.1 | F34: 4.1 | G34: 4.1 | H34: 4.1 | I34: =SUM(E34:H34) -> 16.4 | J34: 3.2 | K34: 3.2 | L34: 3.2 | M34: 3.2 | N34: =SUM(J34:M34) -> 12.8 | O34: 2.4 | P34: 2.4 | Q34: 2.4 | R34: 2.4 | S34: =SUM(O34:R34) -> 9.6 | T34: 2.1 | U34: 2.1 | V34: 2.1 | W34: 2.1 | X34: =SUM(T34:W34) -> 8.4 | Y34: 2 | Z34: 2 | AA34: 2 | AB34: 2 | AC34: =SUM(Y34:AB34) -> 8 | AD34: 2 | AE34: 2 | AF34: 2 | AG34: 2 | AH34: =SUM(AD34:AG34) -> 8 | AI34: 2 | AJ34: 2 | AK34: 2 | AL34: 2 | AM34: =SUM(AI34:AL34) -> 8 | AN34: 2 | AO34: 2 | AP34: 2 | AQ34: 2 | AR34: =SUM(AN34:AQ34) -> 8
B35: Inflation / CPI (YoY) — Downside | E35: 4.1 | F35: 4.1 | G35: 4.1 | H35: 4.1 | I35: =SUM(E35:H35) -> 16.4 | J35: 3.2 | K35: 3.2 | L35: 3.2 | M35: 3.2 | N35: =SUM(J35:M35) -> 12.8 | O35: 3 | P35: 3 | Q35: 3 | R35: 3 | S35: =SUM(O35:R35) -> 12 | T35: 3.2 | U35: 3.2 | V35: 3.2 | W35: 3.2 | X35: =SUM(T35:W35) -> 12.8 | Y35: 3 | Z35: 3 | AA35: 3 | AB35: 3 | AC35: =SUM(Y35:AB35) -> 12 | AD35: 2.8 | AE35: 2.8 | AF35: 2.8 | AG35: 2.8 | AH35: =SUM(AD35:AG35) -> 11.2 | AI35: 2.6 | AJ35: 2.6 | AK35: 2.6 | AL35: 2.6 | AM35: =SUM(AI35:AL35) -> 10.4 | AN35: 2.5 | AO35: 2.5 | AP35: 2.5 | AQ35: 2.5 | AR35: =SUM(AN35:AQ35) -> 10
B36: Inflation / CPI (YoY) — ★ ACTIVE | E36: =IF('01 Cover & Control'!$C$19="Base",E33,IF('01 Cover & Control'!$C$19="Upside",E34,E35)) -> 4.1 | F36: =IF('01 Cover & Control'!$C$19="Base",F33,IF('01 Cover & Control'!$C$19="Upside",F34,F35)) -> 4.1 | G36: =IF('01 Cover & Control'!$C$19="Base",G33,IF('01 Cover & Control'!$C$19="Upside",G34,G35)) -> 4.1 | H36: =IF('01 Cover & Control'!$C$19="Base",H33,IF('01 Cover & Control'!$C$19="Upside",H34,H35)) -> 4.1 | I36: =SUM(E36:H36) -> 16.4 | J36: =IF('01 Cover & Control'!$C$19="Base",J33,IF('01 Cover & Control'!$C$19="Upside",J34,J35)) -> 3.2 | K36: =IF('01 Cover & Control'!$C$19="Base",K33,IF('01 Cover & Control'!$C$19="Upside",K34,K35)) -> 3.2 | L36: =IF('01 Cover & Control'!$C$19="Base",L33,IF('01 Cover & Control'!$C$19="Upside",L34,L35)) -> 3.2 | M36: =IF('01 Cover & Control'!$C$19="Base",M33,IF('01 Cover & Control'!$C$19="Upside",M34,M35)) -> 3.2 | N36: =SUM(J36:M36) -> 12.8 | O36: =IF('01 Cover & Control'!$C$19="Base",O33,IF('01 Cover & Control'!$C$19="Upside",O34,O35)) -> 2.6 | P36: =IF('01 Cover & Control'!$C$19="Base",P33,IF('01 Cover & Control'!$C$19="Upside",P34,P35)) -> 2.6 | Q36: =IF('01 Cover & Control'!$C$19="Base",Q33,IF('01 Cover & Control'!$C$19="Upside",Q34,Q35)) -> 2.6 | R36: =IF('01 Cover & Control'!$C$19="Base",R33,IF('01 Cover & Control'!$C$19="Upside",R34,R35)) -> 2.6 | S36: =SUM(O36:R36) -> 10.4 | T36: =IF('01 Cover & Control'!$C$19="Base",T33,IF('01 Cover & Control'!$C$19="Upside",T34,T35)) -> 2.3 | U36: =IF('01 Cover & Control'!$C$19="Base",U33,IF('01 Cover & Control'!$C$19="Upside",U34,U35)) -> 2.3 | V36: =IF('01 Cover & Control'!$C$19="Base",V33,IF('01 Cover & Control'!$C$19="Upside",V34,V35)) -> 2.3 | W36: =IF('01 Cover & Control'!$C$19="Base",W33,IF('01 Cover & Control'!$C$19="Upside",W34,W35)) -> 2.3 | X36: =SUM(T36:W36) -> 9.2 | Y36: =IF('01 Cover & Control'!$C$19="Base",Y33,IF('01 Cover & Control'!$C$19="Upside",Y34,Y35)) -> 2.2 | Z36: =IF('01 Cover & Control'!$C$19="Base",Z33,IF('01 Cover & Control'!$C$19="Upside",Z34,Z35)) -> 2.2 | AA36: =IF('01 Cover & Control'!$C$19="Base",AA33,IF('01 Cover & Control'!$C$19="Upside",AA34,AA35)) -> 2.2 | AB36: =IF('01 Cover & Control'!$C$19="Base",AB33,IF('01 Cover & Control'!$C$19="Upside",AB34,AB35)) -> 2.2 | AC36: =SUM(Y36:AB36) -> 8.8 | AD36: =IF('01 Cover & Control'!$C$19="Base",AD33,IF('01 Cover & Control'!$C$19="Upside",AD34,AD35)) -> 2.1 | AE36: =IF('01 Cover & Control'!$C$19="Base",AE33,IF('01 Cover & Control'!$C$19="Upside",AE34,AE35)) -> 2.1 | AF36: =IF('01 Cover & Control'!$C$19="Base",AF33,IF('01 Cover & Control'!$C$19="Upside",AF34,AF35)) -> 2.1 | AG36: =IF('01 Cover & Control'!$C$19="Base",AG33,IF('01 Cover & Control'!$C$19="Upside",AG34,AG35)) -> 2.1 | AH36: =SUM(AD36:AG36) -> 8.4 | AI36: =IF('01 Cover & Control'!$C$19="Base",AI33,IF('01 Cover & Control'!$C$19="Upside",AI34,AI35)) -> 2 | AJ36: =IF('01 Cover & Control'!$C$19="Base",AJ33,IF('01 Cover & Control'!$C$19="Upside",AJ34,AJ35)) -> 2 | AK36: =IF('01 Cover & Control'!$C$19="Base",AK33,IF('01 Cover & Control'!$C$19="Upside",AK34,AK35)) -> 2 | AL36: =IF('01 Cover & Control'!$C$19="Base",AL33,IF('01 Cover & Control'!$C$19="Upside",AL34,AL35)) -> 2 | AM36: =SUM(AI36:AL36) -> 8 | AN36: =IF('01 Cover & Control'!$C$19="Base",AN33,IF('01 Cover & Control'!$C$19="Upside",AN34,AN35)) -> 2 | AO36: =IF('01 Cover & Control'!$C$19="Base",AO33,IF('01 Cover & Control'!$C$19="Upside",AO34,AO35)) -> 2 | AP36: =IF('01 Cover & Control'!$C$19="Base",AP33,IF('01 Cover & Control'!$C$19="Upside",AP34,AP35)) -> 2 | AQ36: =IF('01 Cover & Control'!$C$19="Base",AQ33,IF('01 Cover & Control'!$C$19="Upside",AQ34,AQ35)) -> 2 | AR36: =SUM(AN36:AQ36) -> 8
B38: Wage Growth — National Average (YoY) — Base | C38: % / yr | D38: BLS Employment Cost Index; ADP Workforce Vitality Report | E38: 4.4 | F38: 4.4 | G38: 4.4 | H38: 4.4 | I38: =SUM(E38:H38) -> 17.6 | J38: 4 | K38: 4 | L38: 4 | M38: 4 | N38: =SUM(J38:M38) -> 16 | O38: 3.6 | P38: 3.6 | Q38: 3.6 | R38: 3.6 | S38: =SUM(O38:R38) -> 14.4 | T38: 3.4 | U38: 3.4 | V38: 3.4 | W38: 3.4 | X38: =SUM(T38:W38) -> 13.6 | Y38: 3.3 | Z38: 3.3 | AA38: 3.3 | AB38: 3.3 | AC38: =SUM(Y38:AB38) -> 13.2 | AD38: 3.2 | AE38: 3.2 | AF38: 3.2 | AG38: 3.2 | AH38: =SUM(AD38:AG38) -> 12.8 | AI38: 3.2 | AJ38: 3.2 | AK38: 3.2 | AL38: 3.2 | AM38: =SUM(AI38:AL38) -> 12.8 | AN38: 3.2 | AO38: 3.2 | AP38: 3.2 | AQ38: 3.2 | AR38: =SUM(AN38:AQ38) -> 12.8
B39: Wage Growth — National Average (YoY) — Upside | E39: 4.4 | F39: 4.4 | G39: 4.4 | H39: 4.4 | I39: =SUM(E39:H39) -> 17.6 | J39: 4 | K39: 4 | L39: 4 | M39: 4 | N39: =SUM(J39:M39) -> 16 | O39: 3.8 | P39: 3.8 | Q39: 3.8 | R39: 3.8 | S39: =SUM(O39:R39) -> 15.2 | T39: 3.7 | U39: 3.7 | V39: 3.7 | W39: 3.7 | X39: =SUM(T39:W39) -> 14.8 | Y39: 3.6 | Z39: 3.6 | AA39: 3.6 | AB39: 3.6 | AC39: =SUM(Y39:AB39) -> 14.4 | AD39: 3.5 | AE39: 3.5 | AF39: 3.5 | AG39: 3.5 | AH39: =SUM(AD39:AG39) -> 14 | AI39: 3.4 | AJ39: 3.4 | AK39: 3.4 | AL39: 3.4 | AM39: =SUM(AI39:AL39) -> 13.6 | AN39: 3.4 | AO39: 3.4 | AP39: 3.4 | AQ39: 3.4 | AR39: =SUM(AN39:AQ39) -> 13.6
B40: Wage Growth — National Average (YoY) — Downside | E40: 4.4 | F40: 4.4 | G40: 4.4 | H40: 4.4 | I40: =SUM(E40:H40) -> 17.6 | J40: 4 | K40: 4 | L40: 4 | M40: 4 | N40: =SUM(J40:M40) -> 16 | O40: 3.4 | P40: 3.4 | Q40: 3.4 | R40: 3.4 | S40: =SUM(O40:R40) -> 13.6 | T40: 3.2 | U40: 3.2 | V40: 3.2 | W40: 3.2 | X40: =SUM(T40:W40) -> 12.8 | Y40: 3 | Z40: 3 | AA40: 3 | AB40: 3 | AC40: =SUM(Y40:AB40) -> 12 | AD40: 2.9 | AE40: 2.9 | AF40: 2.9 | AG40: 2.9 | AH40: =SUM(AD40:AG40) -> 11.6 | AI40: 2.8 | AJ40: 2.8 | AK40: 2.8 | AL40: 2.8 | AM40: =SUM(AI40:AL40) -> 11.2 | AN40: 2.8 | AO40: 2.8 | AP40: 2.8 | AQ40: 2.8 | AR40: =SUM(AN40:AQ40) -> 11.2
B41: Wage Growth — National Average (YoY) — ★ ACTIVE | E41: =IF('01 Cover & Control'!$C$19="Base",E38,IF('01 Cover & Control'!$C$19="Upside",E39,E40)) -> 4.4 | F41: =IF('01 Cover & Control'!$C$19="Base",F38,IF('01 Cover & Control'!$C$19="Upside",F39,F40)) -> 4.4 | G41: =IF('01 Cover & Control'!$C$19="Base",G38,IF('01 Cover & Control'!$C$19="Upside",G39,G40)) -> 4.4 | H41: =IF('01 Cover & Control'!$C$19="Base",H38,IF('01 Cover & Control'!$C$19="Upside",H39,H40)) -> 4.4 | I41: =SUM(E41:H41) -> 17.6 | J41: =IF('01 Cover & Control'!$C$19="Base",J38,IF('01 Cover & Control'!$C$19="Upside",J39,J40)) -> 4 | K41: =IF('01 Cover & Control'!$C$19="Base",K38,IF('01 Cover & Control'!$C$19="Upside",K39,K40)) -> 4 | L41: =IF('01 Cover & Control'!$C$19="Base",L38,IF('01 Cover & Control'!$C$19="Upside",L39,L40)) -> 4 | M41: =IF('01 Cover & Control'!$C$19="Base",M38,IF('01 Cover & Control'!$C$19="Upside",M39,M40)) -> 4 | N41: =SUM(J41:M41) -> 16 | O41: =IF('01 Cover & Control'!$C$19="Base",O38,IF('01 Cover & Control'!$C$19="Upside",O39,O40)) -> 3.6 | P41: =IF('01 Cover & Control'!$C$19="Base",P38,IF('01 Cover & Control'!$C$19="Upside",P39,P40)) -> 3.6 | Q41: =IF('01 Cover & Control'!$C$19="Base",Q38,IF('01 Cover & Control'!$C$19="Upside",Q39,Q40)) -> 3.6 | R41: =IF('01 Cover & Control'!$C$19="Base",R38,IF('01 Cover & Control'!$C$19="Upside",R39,R40)) -> 3.6 | S41: =SUM(O41:R41) -> 14.4 | T41: =IF('01 Cover & Control'!$C$19="Base",T38,IF('01 Cover & Control'!$C$19="Upside",T39,T40)) -> 3.4 | U41: =IF('01 Cover & Control'!$C$19="Base",U38,IF('01 Cover & Control'!$C$19="Upside",U39,U40)) -> 3.4 | V41: =IF('01 Cover & Control'!$C$19="Base",V38,IF('01 Cover & Control'!$C$19="Upside",V39,V40)) -> 3.4 | W41: =IF('01 Cover & Control'!$C$19="Base",W38,IF('01 Cover & Control'!$C$19="Upside",W39,W40)) -> 3.4 | X41: =SUM(T41:W41) -> 13.6 | Y41: =IF('01 Cover & Control'!$C$19="Base",Y38,IF('01 Cover & Control'!$C$19="Upside",Y39,Y40)) -> 3.3 | Z41: =IF('01 Cover & Control'!$C$19="Base",Z38,IF('01 Cover & Control'!$C$19="Upside",Z39,Z40)) -> 3.3 | AA41: =IF('01 Cover & Control'!$C$19="Base",AA38,IF('01 Cover & Control'!$C$19="Upside",AA39,AA40)) -> 3.3 | AB41: =IF('01 Cover & Control'!$C$19="Base",AB38,IF('01 Cover & Control'!$C$19="Upside",AB39,AB40)) -> 3.3 | AC41: =SUM(Y41:AB41) -> 13.2 | AD41: =IF('01 Cover & Control'!$C$19="Base",AD38,IF('01 Cover & Control'!$C$19="Upside",AD39,AD40)) -> 3.2 | AE41: =IF('01 Cover & Control'!$C$19="Base",AE38,IF('01 Cover & Control'!$C$19="Upside",AE39,AE40)) -> 3.2 | AF41: =IF('01 Cover & Control'!$C$19="Base",AF38,IF('01 Cover & Control'!$C$19="Upside",AF39,AF40)) -> 3.2 | AG41: =IF('01 Cover & Control'!$C$19="Base",AG38,IF('01 Cover & Control'!$C$19="Upside",AG39,AG40)) -> 3.2 | AH41: =SUM(AD41:AG41) -> 12.8 | AI41: =IF('01 Cover & Control'!$C$19="Base",AI38,IF('01 Cover & Control'!$C$19="Upside",AI39,AI40)) -> 3.2 | AJ41: =IF('01 Cover & Control'!$C$19="Base",AJ38,IF('01 Cover & Control'!$C$19="Upside",AJ39,AJ40)) -> 3.2 | AK41: =IF('01 Cover & Control'!$C$19="Base",AK38,IF('01 Cover & Control'!$C$19="Upside",AK39,AK40)) -> 3.2 | AL41: =IF('01 Cover & Control'!$C$19="Base",AL38,IF('01 Cover & Control'!$C$19="Upside",AL39,AL40)) -> 3.2 | AM41: =SUM(AI41:AL41) -> 12.8 | AN41: =IF('01 Cover & Control'!$C$19="Base",AN38,IF('01 Cover & Control'!$C$19="Upside",AN39,AN40)) -> 3.2 | AO41: =IF('01 Cover & Control'!$C$19="Base",AO38,IF('01 Cover & Control'!$C$19="Upside",AO39,AO40)) -> 3.2 | AP41: =IF('01 Cover & Control'!$C$19="Base",AP38,IF('01 Cover & Control'!$C$19="Upside",AP39,AP40)) -> 3.2 | AQ41: =IF('01 Cover & Control'!$C$19="Base",AQ38,IF('01 Cover & Control'!$C$19="Upside",AQ39,AQ40)) -> 3.2 | AR41: =SUM(AN41:AQ41) -> 12.8
A45: SECTION B — CRE MARKET ACTIVITY
A47: B1 — INVESTMENT SALES MARKET
B49: National IS Transaction Volume — Total Market — Base | C49: $B | D49: MSCI Real Capital Analytics (RCA) Quarterly Capital Trends | E49: 78 | F49: 78 | G49: 78 | H49: 78 | I49: =SUM(E49:H49) -> 312 | J49: 82 | K49: 82 | L49: 82 | M49: 82 | N49: =SUM(J49:M49) -> 328 | O49: 92 | P49: 92 | Q49: 92 | R49: 92 | S49: =SUM(O49:R49) -> 368 | T49: 105 | U49: 105 | V49: 105 | W49: 105 | X49: =SUM(T49:W49) -> 420 | Y49: 112 | Z49: 112 | AA49: 112 | AB49: 112 | AC49: =SUM(Y49:AB49) -> 448 | AD49: 118 | AE49: 118 | AF49: 118 | AG49: 118 | AH49: =SUM(AD49:AG49) -> 472 | AI49: 122 | AJ49: 122 | AK49: 122 | AL49: 122 | AM49: =SUM(AI49:AL49) -> 488 | AN49: 126 | AO49: 126 | AP49: 126 | AQ49: 126 | AR49: =SUM(AN49:AQ49) -> 504
B50: National IS Transaction Volume — Total Market — Upside | E50: 78 | F50: 78 | G50: 78 | H50: 78 | I50: =SUM(E50:H50) -> 312 | J50: 82 | K50: 82 | L50: 82 | M50: 82 | N50: =SUM(J50:M50) -> 328 | O50: 99 | P50: 99 | Q50: 99 | R50: 99 | S50: =SUM(O50:R50) -> 396 | T50: 118 | U50: 118 | V50: 118 | W50: 118 | X50: =SUM(T50:W50) -> 472 | Y50: 126 | Z50: 126 | AA50: 126 | AB50: 126 | AC50: =SUM(Y50:AB50) -> 504 | AD50: 133 | AE50: 133 | AF50: 133 | AG50: 133 | AH50: =SUM(AD50:AG50) -> 532 | AI50: 138 | AJ50: 138 | AK50: 138 | AL50: 138 | AM50: =SUM(AI50:AL50) -> 552 | AN50: 143 | AO50: 143 | AP50: 143 | AQ50: 143 | AR50: =SUM(AN50:AQ50) -> 572
B51: National IS Transaction Volume — Total Market — Downside | E51: 78 | F51: 78 | G51: 78 | H51: 78 | I51: =SUM(E51:H51) -> 312 | J51: 82 | K51: 82 | L51: 82 | M51: 82 | N51: =SUM(J51:M51) -> 328 | O51: 86 | P51: 86 | Q51: 86 | R51: 86 | S51: =SUM(O51:R51) -> 344 | T51: 90 | U51: 90 | V51: 90 | W51: 90 | X51: =SUM(T51:W51) -> 360 | Y51: 96 | Z51: 96 | AA51: 96 | AB51: 96 | AC51: =SUM(Y51:AB51) -> 384 | AD51: 102 | AE51: 102 | AF51: 102 | AG51: 102 | AH51: =SUM(AD51:AG51) -> 408 | AI51: 107 | AJ51: 107 | AK51: 107 | AL51: 107 | AM51: =SUM(AI51:AL51) -> 428 | AN51: 112 | AO51: 112 | AP51: 112 | AQ51: 112 | AR51: =SUM(AN51:AQ51) -> 448
B52: National IS Transaction Volume — Total Market — ★ ACTIVE | E52: =IF('01 Cover & Control'!$C$19="Base",E49,IF('01 Cover & Control'!$C$19="Upside",E50,E51)) -> 78 | F52: =IF('01 Cover & Control'!$C$19="Base",F49,IF('01 Cover & Control'!$C$19="Upside",F50,F51)) -> 78 | G52: =IF('01 Cover & Control'!$C$19="Base",G49,IF('01 Cover & Control'!$C$19="Upside",G50,G51)) -> 78 | H52: =IF('01 Cover & Control'!$C$19="Base",H49,IF('01 Cover & Control'!$C$19="Upside",H50,H51)) -> 78 | I52: =SUM(E52:H52) -> 312 | J52: =IF('01 Cover & Control'!$C$19="Base",J49,IF('01 Cover & Control'!$C$19="Upside",J50,J51)) -> 82 | K52: =IF('01 Cover & Control'!$C$19="Base",K49,IF('01 Cover & Control'!$C$19="Upside",K50,K51)) -> 82 | L52: =IF('01 Cover & Control'!$C$19="Base",L49,IF('01 Cover & Control'!$C$19="Upside",L50,L51)) -> 82 | M52: =IF('01 Cover & Control'!$C$19="Base",M49,IF('01 Cover & Control'!$C$19="Upside",M50,M51)) -> 82 | N52: =SUM(J52:M52) -> 328 | O52: =IF('01 Cover & Control'!$C$19="Base",O49,IF('01 Cover & Control'!$C$19="Upside",O50,O51)) -> 92 | P52: =IF('01 Cover & Control'!$C$19="Base",P49,IF('01 Cover & Control'!$C$19="Upside",P50,P51)) -> 92 | Q52: =IF('01 Cover & Control'!$C$19="Base",Q49,IF('01 Cover & Control'!$C$19="Upside",Q50,Q51)) -> 92 | R52: =IF('01 Cover & Control'!$C$19="Base",R49,IF('01 Cover & Control'!$C$19="Upside",R50,R51)) -> 92 | S52: =SUM(O52:R52) -> 368 | T52: =IF('01 Cover & Control'!$C$19="Base",T49,IF('01 Cover & Control'!$C$19="Upside",T50,T51)) -> 105 | U52: =IF('01 Cover & Control'!$C$19="Base",U49,IF('01 Cover & Control'!$C$19="Upside",U50,U51)) -> 105 | V52: =IF('01 Cover & Control'!$C$19="Base",V49,IF('01 Cover & Control'!$C$19="Upside",V50,V51)) -> 105 | W52: =IF('01 Cover & Control'!$C$19="Base",W49,IF('01 Cover & Control'!$C$19="Upside",W50,W51)) -> 105 | X52: =SUM(T52:W52) -> 420 | Y52: =IF('01 Cover & Control'!$C$19="Base",Y49,IF('01 Cover & Control'!$C$19="Upside",Y50,Y51)) -> 112 | Z52: =IF('01 Cover & Control'!$C$19="Base",Z49,IF('01 Cover & Control'!$C$19="Upside",Z50,Z51)) -> 112 | AA52: =IF('01 Cover & Control'!$C$19="Base",AA49,IF('01 Cover & Control'!$C$19="Upside",AA50,AA51)) -> 112 | AB52: =IF('01 Cover & Control'!$C$19="Base",AB49,IF('01 Cover & Control'!$C$19="Upside",AB50,AB51)) -> 112 | AC52: =SUM(Y52:AB52) -> 448 | AD52: =IF('01 Cover & Control'!$C$19="Base",AD49,IF('01 Cover & Control'!$C$19="Upside",AD50,AD51)) -> 118 | AE52: =IF('01 Cover & Control'!$C$19="Base",AE49,IF('01 Cover & Control'!$C$19="Upside",AE50,AE51)) -> 118 | AF52: =IF('01 Cover & Control'!$C$19="Base",AF49,IF('01 Cover & Control'!$C$19="Upside",AF50,AF51)) -> 118 | AG52: =IF('01 Cover & Control'!$C$19="Base",AG49,IF('01 Cover & Control'!$C$19="Upside",AG50,AG51)) -> 118 | AH52: =SUM(AD52:AG52) -> 472 | AI52: =IF('01 Cover & Control'!$C$19="Base",AI49,IF('01 Cover & Control'!$C$19="Upside",AI50,AI51)) -> 122 | AJ52: =IF('01 Cover & Control'!$C$19="Base",AJ49,IF('01 Cover & Control'!$C$19="Upside",AJ50,AJ51)) -> 122 | AK52: =IF('01 Cover & Control'!$C$19="Base",AK49,IF('01 Cover & Control'!$C$19="Upside",AK50,AK51)) -> 122 | AL52: =IF('01 Cover & Control'!$C$19="Base",AL49,IF('01 Cover & Control'!$C$19="Upside",AL50,AL51)) -> 122 | AM52: =SUM(AI52:AL52) -> 488 | AN52: =IF('01 Cover & Control'!$C$19="Base",AN49,IF('01 Cover & Control'!$C$19="Upside",AN50,AN51)) -> 126 | AO52: =IF('01 Cover & Control'!$C$19="Base",AO49,IF('01 Cover & Control'!$C$19="Upside",AO50,AO51)) -> 126 | AP52: =IF('01 Cover & Control'!$C$19="Base",AP49,IF('01 Cover & Control'!$C$19="Upside",AP50,AP51)) -> 126 | AQ52: =IF('01 Cover & Control'!$C$19="Base",AQ49,IF('01 Cover & Control'!$C$19="Upside",AQ50,AQ51)) -> 126 | AR52: =SUM(AN52:AQ52) -> 504
B54: IS Market Velocity Index (2023 = 100) — Base | C54: Index | D54: MSCI RCA; internal calibration. Reflects deal count velocity vs base year. | E54: 100 | F54: 100 | G54: 100 | H54: 100 | I54: =SUM(E54:H54) -> 400 | J54: 100 | K54: 100 | L54: 100 | M54: 100 | N54: =SUM(J54:M54) -> 400 | O54: 100 | P54: 100 | Q54: 100 | R54: 100 | S54: =SUM(O54:R54) -> 400 | T54: 100 | U54: 100 | V54: 100 | W54: 100 | X54: =SUM(T54:W54) -> 400 | Y54: 100 | Z54: 100 | AA54: 100 | AB54: 100 | AC54: =SUM(Y54:AB54) -> 400 | AD54: 100 | AE54: 100 | AF54: 100 | AG54: 100 | AH54: =SUM(AD54:AG54) -> 400 | AI54: 100 | AJ54: 100 | AK54: 100 | AL54: 100 | AM54: =SUM(AI54:AL54) -> 400 | AN54: 100 | AO54: 100 | AP54: 100 | AQ54: 100 | AR54: =SUM(AN54:AQ54) -> 400
B55: IS Market Velocity Index (2023 = 100) — Upside | E55: 110 | F55: 110 | G55: 110 | H55: 110 | I55: =SUM(E55:H55) -> 440 | J55: 110 | K55: 110 | L55: 110 | M55: 110 | N55: =SUM(J55:M55) -> 440 | O55: 110 | P55: 110 | Q55: 110 | R55: 110 | S55: =SUM(O55:R55) -> 440 | T55: 110 | U55: 110 | V55: 110 | W55: 110 | X55: =SUM(T55:W55) -> 440 | Y55: 110 | Z55: 110 | AA55: 110 | AB55: 110 | AC55: =SUM(Y55:AB55) -> 440 | AD55: 110 | AE55: 110 | AF55: 110 | AG55: 110 | AH55: =SUM(AD55:AG55) -> 440 | AI55: 110 | AJ55: 110 | AK55: 110 | AL55: 110 | AM55: =SUM(AI55:AL55) -> 440 | AN55: 110 | AO55: 110 | AP55: 110 | AQ55: 110 | AR55: =SUM(AN55:AQ55) -> 440
B56: IS Market Velocity Index (2023 = 100) — Downside | E56: 85 | F56: 85 | G56: 85 | H56: 85 | I56: =SUM(E56:H56) -> 340 | J56: 85 | K56: 85 | L56: 85 | M56: 85 | N56: =SUM(J56:M56) -> 340 | O56: 85 | P56: 85 | Q56: 85 | R56: 85 | S56: =SUM(O56:R56) -> 340 | T56: 85 | U56: 85 | V56: 85 | W56: 85 | X56: =SUM(T56:W56) -> 340 | Y56: 85 | Z56: 85 | AA56: 85 | AB56: 85 | AC56: =SUM(Y56:AB56) -> 340 | AD56: 85 | AE56: 85 | AF56: 85 | AG56: 85 | AH56: =SUM(AD56:AG56) -> 340 | AI56: 85 | AJ56: 85 | AK56: 85 | AL56: 85 | AM56: =SUM(AI56:AL56) -> 340 | AN56: 85 | AO56: 85 | AP56: 85 | AQ56: 85 | AR56: =SUM(AN56:AQ56) -> 340
B57: [V2 Ref] IS Market Velocity Index (2023 = 100) — ★ ACTIVE | D57: V2 REFERENCE ONLY: IS transaction velocity not used in V1 revenue model. Reserved for V2 velocity-adjusted GCI forecasting. | E57: =IF('01 Cover & Control'!$C$19="Base",E54,IF('01 Cover & Control'!$C$19="Upside",E55,E56)) -> 100 | F57: =IF('01 Cover & Control'!$C$19="Base",F54,IF('01 Cover & Control'!$C$19="Upside",F55,F56)) -> 100 | G57: =IF('01 Cover & Control'!$C$19="Base",G54,IF('01 Cover & Control'!$C$19="Upside",G55,G56)) -> 100 | H57: =IF('01 Cover & Control'!$C$19="Base",H54,IF('01 Cover & Control'!$C$19="Upside",H55,H56)) -> 100 | I57: =SUM(E57:H57) -> 400 | J57: =IF('01 Cover & Control'!$C$19="Base",J54,IF('01 Cover & Control'!$C$19="Upside",J55,J56)) -> 100 | K57: =IF('01 Cover & Control'!$C$19="Base",K54,IF('01 Cover & Control'!$C$19="Upside",K55,K56)) -> 100 | L57: =IF('01 Cover & Control'!$C$19="Base",L54,IF('01 Cover & Control'!$C$19="Upside",L55,L56)) -> 100 | M57: =IF('01 Cover & Control'!$C$19="Base",M54,IF('01 Cover & Control'!$C$19="Upside",M55,M56)) -> 100 | N57: =SUM(J57:M57) -> 400 | O57: =IF('01 Cover & Control'!$C$19="Base",O54,IF('01 Cover & Control'!$C$19="Upside",O55,O56)) -> 100 | P57: =IF('01 Cover & Control'!$C$19="Base",P54,IF('01 Cover & Control'!$C$19="Upside",P55,P56)) -> 100 | Q57: =IF('01 Cover & Control'!$C$19="Base",Q54,IF('01 Cover & Control'!$C$19="Upside",Q55,Q56)) -> 100 | R57: =IF('01 Cover & Control'!$C$19="Base",R54,IF('01 Cover & Control'!$C$19="Upside",R55,R56)) -> 100 | S57: =SUM(O57:R57) -> 400 | T57: =IF('01 Cover & Control'!$C$19="Base",T54,IF('01 Cover & Control'!$C$19="Upside",T55,T56)) -> 100 | U57: =IF('01 Cover & Control'!$C$19="Base",U54,IF('01 Cover & Control'!$C$19="Upside",U55,U56)) -> 100 | V57: =IF('01 Cover & Control'!$C$19="Base",V54,IF('01 Cover & Control'!$C$19="Upside",V55,V56)) -> 100 | W57: =IF('01 Cover & Control'!$C$19="Base",W54,IF('01 Cover & Control'!$C$19="Upside",W55,W56)) -> 100 | X57: =SUM(T57:W57) -> 400 | Y57: =IF('01 Cover & Control'!$C$19="Base",Y54,IF('01 Cover & Control'!$C$19="Upside",Y55,Y56)) -> 100 | Z57: =IF('01 Cover & Control'!$C$19="Base",Z54,IF('01 Cover & Control'!$C$19="Upside",Z55,Z56)) -> 100 | AA57: =IF('01 Cover & Control'!$C$19="Base",AA54,IF('01 Cover & Control'!$C$19="Upside",AA55,AA56)) -> 100 | AB57: =IF('01 Cover & Control'!$C$19="Base",AB54,IF('01 Cover & Control'!$C$19="Upside",AB55,AB56)) -> 100 | AC57: =SUM(Y57:AB57) -> 400 | AD57: =IF('01 Cover & Control'!$C$19="Base",AD54,IF('01 Cover & Control'!$C$19="Upside",AD55,AD56)) -> 100 | AE57: =IF('01 Cover & Control'!$C$19="Base",AE54,IF('01 Cover & Control'!$C$19="Upside",AE55,AE56)) -> 100 | AF57: =IF('01 Cover & Control'!$C$19="Base",AF54,IF('01 Cover & Control'!$C$19="Upside",AF55,AF56)) -> 100 | AG57: =IF('01 Cover & Control'!$C$19="Base",AG54,IF('01 Cover & Control'!$C$19="Upside",AG55,AG56)) -> 100 | AH57: =SUM(AD57:AG57) -> 400 | AI57: =IF('01 Cover & Control'!$C$19="Base",AI54,IF('01 Cover & Control'!$C$19="Upside",AI55,AI56)) -> 100 | AJ57: =IF('01 Cover & Control'!$C$19="Base",AJ54,IF('01 Cover & Control'!$C$19="Upside",AJ55,AJ56)) -> 100 | AK57: =IF('01 Cover & Control'!$C$19="Base",AK54,IF('01 Cover & Control'!$C$19="Upside",AK55,AK56)) -> 100 | AL57: =IF('01 Cover & Control'!$C$19="Base",AL54,IF('01 Cover & Control'!$C$19="Upside",AL55,AL56)) -> 100 | AM57: =SUM(AI57:AL57) -> 400 | AN57: =IF('01 Cover & Control'!$C$19="Base",AN54,IF('01 Cover & Control'!$C$19="Upside",AN55,AN56)) -> 100 | AO57: =IF('01 Cover & Control'!$C$19="Base",AO54,IF('01 Cover & Control'!$C$19="Upside",AO55,AO56)) -> 100 | AP57: =IF('01 Cover & Control'!$C$19="Base",AP54,IF('01 Cover & Control'!$C$19="Upside",AP55,AP56)) -> 100 | AQ57: =IF('01 Cover & Control'!$C$19="Base",AQ54,IF('01 Cover & Control'!$C$19="Upside",AQ55,AQ56)) -> 100 | AR57: =SUM(AN57:AQ57) -> 400
A59: B2 — IS PROPERTY MIX (static structural inputs — not scenario-keyed)
B61: Property mix shifts slowly. Input annually. Rows must sum to 100% (see CHECK row below).
B62: [V2 Ref] IS Mix — Multifamily | C62: % | D62: V2 REFERENCE ONLY: IS property-type mix not used in V1 (tier maps 1:1 to deal size). Reserved for V2 cross-type analysis. | E62: 0.4 | F62: 0.4 | G62: 0.4 | H62: 0.4 | I62: =SUM(E62:H62) -> 1.6 | J62: 0.4 | K62: 0.4 | L62: 0.4 | M62: 0.4 | N62: =SUM(J62:M62) -> 1.6 | O62: 0.4 | P62: 0.4 | Q62: 0.4 | R62: 0.4 | S62: =SUM(O62:R62) -> 1.6 | T62: 0.4 | U62: 0.4 | V62: 0.4 | W62: 0.4 | X62: =SUM(T62:W62) -> 1.6 | Y62: 0.4 | Z62: 0.4 | AA62: 0.4 | AB62: 0.4 | AC62: =SUM(Y62:AB62) -> 1.6 | AD62: 0.4 | AE62: 0.4 | AF62: 0.4 | AG62: 0.4 | AH62: =SUM(AD62:AG62) -> 1.6 | AI62: 0.4 | AJ62: 0.4 | AK62: 0.4 | AL62: 0.4 | AM62: =SUM(AI62:AL62) -> 1.6 | AN62: 0.4 | AO62: 0.4 | AP62: 0.4 | AQ62: 0.4 | AR62: =SUM(AN62:AQ62) -> 1.6
B63: [V2 Ref] IS Mix — Office & Industrial (Blended) | C63: % | D63: V2 REFERENCE ONLY: same as row 62. | E63: 0.45 | F63: 0.45 | G63: 0.45 | H63: 0.45 | I63: =SUM(E63:H63) -> 1.8 | J63: 0.45 | K63: 0.45 | L63: 0.45 | M63: 0.45 | N63: =SUM(J63:M63) -> 1.8 | O63: 0.45 | P63: 0.45 | Q63: 0.45 | R63: 0.45 | S63: =SUM(O63:R63) -> 1.8 | T63: 0.45 | U63: 0.45 | V63: 0.45 | W63: 0.45 | X63: =SUM(T63:W63) -> 1.8 | Y63: 0.45 | Z63: 0.45 | AA63: 0.45 | AB63: 0.45 | AC63: =SUM(Y63:AB63) -> 1.8 | AD63: 0.45 | AE63: 0.45 | AF63: 0.45 | AG63: 0.45 | AH63: =SUM(AD63:AG63) -> 1.8 | AI63: 0.45 | AJ63: 0.45 | AK63: 0.45 | AL63: 0.45 | AM63: =SUM(AI63:AL63) -> 1.8 | AN63: 0.45 | AO63: 0.45 | AP63: 0.45 | AQ63: 0.45 | AR63: =SUM(AN63:AQ63) -> 1.8
B64: [V2 Ref] IS Mix — Retail & Other | C64: % | D64: V2 REFERENCE ONLY: same as row 62. | E64: 0.15 | F64: 0.15 | G64: 0.15 | H64: 0.15 | I64: =SUM(E64:H64) -> 0.6 | J64: 0.15 | K64: 0.15 | L64: 0.15 | M64: 0.15 | N64: =SUM(J64:M64) -> 0.6 | O64: 0.15 | P64: 0.15 | Q64: 0.15 | R64: 0.15 | S64: =SUM(O64:R64) -> 0.6 | T64: 0.15 | U64: 0.15 | V64: 0.15 | W64: 0.15 | X64: =SUM(T64:W64) -> 0.6 | Y64: 0.15 | Z64: 0.15 | AA64: 0.15 | AB64: 0.15 | AC64: =SUM(Y64:AB64) -> 0.6 | AD64: 0.15 | AE64: 0.15 | AF64: 0.15 | AG64: 0.15 | AH64: =SUM(AD64:AG64) -> 0.6 | AI64: 0.15 | AJ64: 0.15 | AK64: 0.15 | AL64: 0.15 | AM64: =SUM(AI64:AL64) -> 0.6 | AN64: 0.15 | AO64: 0.15 | AP64: 0.15 | AQ64: 0.15 | AR64: =SUM(AN64:AQ64) -> 0.6
B66: ✔ CHECK: IS Property Mix Sums to 100% | D66: Structural check. FAIL = property mix inputs do not total 100%. | E66: — | F66: — | G66: — | H66: — | I66: =IF(ABS(SUM(I62:I64)-1)<0.001,"PASS","WARN — V2 Reference (not used in V1)") -> WARN — V2 Reference (not used in V1) | J66: — | K66: — | L66: — | M66: — | N66: =IF(ABS(SUM(N62:N64)-1)<0.001,"PASS","WARN — V2 Reference (not used in V1)") -> WARN — V2 Reference (not used in V1) | O66: — | P66: — | Q66: — | R66: — | S66: =IF(ABS(SUM(S62:S64)-1)<0.001,"PASS","WARN — V2 Reference (not used in V1)") -> WARN — V2 Reference (not used in V1) | T66: — | U66: — | V66: — | W66: — | X66: =IF(ABS(SUM(X62:X64)-1)<0.001,"PASS","WARN — V2 Reference (not used in V1)") -> WARN — V2 Reference (not used in V1) | Y66: — | Z66: — | AA66: — | AB66: — | AC66: =IF(ABS(SUM(AC62:AC64)-1)<0.001,"PASS","WARN — V2 Reference (not used in V1)") -> WARN — V2 Reference (not used in V1) | AD66: — | AE66: — | AF66: — | AG66: — | AH66: =IF(ABS(SUM(AH62:AH64)-1)<0.001,"PASS","WARN — V2 Reference (not used in V1)") -> WARN — V2 Reference (not used in V1) | AI66: — | AJ66: — | AK66: — | AL66: — | AM66: =IF(ABS(SUM(AM62:AM64)-1)<0.001,"PASS","WARN — V2 Reference (not used in V1)") -> WARN — V2 Reference (not used in V1) | AN66: — | AO66: — | AP66: — | AQ66: — | AR66: =IF(ABS(SUM(AR62:AR64)-1)<0.001,"PASS","WARN — V2 Reference (not used in V1)") -> WARN — V2 Reference (not used in V1)
A68: B3 — AVERAGE IS DEAL SIZE BY TIER
B70: Avg IS Deal Size — Institutional (>$50M) — Base | C70: $M / deal | D70: MSCI RCA; Marcus & Millichap 10-K avg deal value disclosures | E70: 80 | F70: 80 | G70: 80 | H70: 80 | I70: =SUM(E70:H70) -> 320 | J70: 82 | K70: 82 | L70: 82 | M70: 82 | N70: =SUM(J70:M70) -> 328 | O70: 84 | P70: 84 | Q70: 84 | R70: 84 | S70: =SUM(O70:R70) -> 336 | T70: 85 | U70: 85 | V70: 85 | W70: 85 | X70: =SUM(T70:W70) -> 340 | Y70: 86 | Z70: 86 | AA70: 86 | AB70: 86 | AC70: =SUM(Y70:AB70) -> 344 | AD70: 87 | AE70: 87 | AF70: 87 | AG70: 87 | AH70: =SUM(AD70:AG70) -> 348 | AI70: 88 | AJ70: 88 | AK70: 88 | AL70: 88 | AM70: =SUM(AI70:AL70) -> 352 | AN70: 89 | AO70: 89 | AP70: 89 | AQ70: 89 | AR70: =SUM(AN70:AQ70) -> 356
B71: Avg IS Deal Size — Institutional (>$50M) — Upside | E71: 80 | F71: 80 | G71: 80 | H71: 80 | I71: =SUM(E71:H71) -> 320 | J71: 82 | K71: 82 | L71: 82 | M71: 82 | N71: =SUM(J71:M71) -> 328 | O71: 86 | P71: 86 | Q71: 86 | R71: 86 | S71: =SUM(O71:R71) -> 344 | T71: 89 | U71: 89 | V71: 89 | W71: 89 | X71: =SUM(T71:W71) -> 356 | Y71: 91 | Z71: 91 | AA71: 91 | AB71: 91 | AC71: =SUM(Y71:AB71) -> 364 | AD71: 93 | AE71: 93 | AF71: 93 | AG71: 93 | AH71: =SUM(AD71:AG71) -> 372 | AI71: 95 | AJ71: 95 | AK71: 95 | AL71: 95 | AM71: =SUM(AI71:AL71) -> 380 | AN71: 97 | AO71: 97 | AP71: 97 | AQ71: 97 | AR71: =SUM(AN71:AQ71) -> 388
B72: Avg IS Deal Size — Institutional (>$50M) — Downside | E72: 80 | F72: 80 | G72: 80 | H72: 80 | I72: =SUM(E72:H72) -> 320 | J72: 82 | K72: 82 | L72: 82 | M72: 82 | N72: =SUM(J72:M72) -> 328 | O72: 79 | P72: 79 | Q72: 79 | R72: 79 | S72: =SUM(O72:R72) -> 316 | T72: 77 | U72: 77 | V72: 77 | W72: 77 | X72: =SUM(T72:W72) -> 308 | Y72: 78 | Z72: 78 | AA72: 78 | AB72: 78 | AC72: =SUM(Y72:AB72) -> 312 | AD72: 80 | AE72: 80 | AF72: 80 | AG72: 80 | AH72: =SUM(AD72:AG72) -> 320 | AI72: 82 | AJ72: 82 | AK72: 82 | AL72: 82 | AM72: =SUM(AI72:AL72) -> 328 | AN72: 84 | AO72: 84 | AP72: 84 | AQ72: 84 | AR72: =SUM(AN72:AQ72) -> 336
B73: Avg IS Deal Size — Institutional (>$50M) — ★ ACTIVE | E73: =IF('01 Cover & Control'!$C$19="Base",E70,IF('01 Cover & Control'!$C$19="Upside",E71,E72)) -> 80 | F73: =IF('01 Cover & Control'!$C$19="Base",F70,IF('01 Cover & Control'!$C$19="Upside",F71,F72)) -> 80 | G73: =IF('01 Cover & Control'!$C$19="Base",G70,IF('01 Cover & Control'!$C$19="Upside",G71,G72)) -> 80 | H73: =IF('01 Cover & Control'!$C$19="Base",H70,IF('01 Cover & Control'!$C$19="Upside",H71,H72)) -> 80 | I73: =SUM(E73:H73) -> 320 | J73: =IF('01 Cover & Control'!$C$19="Base",J70,IF('01 Cover & Control'!$C$19="Upside",J71,J72)) -> 82 | K73: =IF('01 Cover & Control'!$C$19="Base",K70,IF('01 Cover & Control'!$C$19="Upside",K71,K72)) -> 82 | L73: =IF('01 Cover & Control'!$C$19="Base",L70,IF('01 Cover & Control'!$C$19="Upside",L71,L72)) -> 82 | M73: =IF('01 Cover & Control'!$C$19="Base",M70,IF('01 Cover & Control'!$C$19="Upside",M71,M72)) -> 82 | N73: =SUM(J73:M73) -> 328 | O73: =IF('01 Cover & Control'!$C$19="Base",O70,IF('01 Cover & Control'!$C$19="Upside",O71,O72)) -> 84 | P73: =IF('01 Cover & Control'!$C$19="Base",P70,IF('01 Cover & Control'!$C$19="Upside",P71,P72)) -> 84 | Q73: =IF('01 Cover & Control'!$C$19="Base",Q70,IF('01 Cover & Control'!$C$19="Upside",Q71,Q72)) -> 84 | R73: =IF('01 Cover & Control'!$C$19="Base",R70,IF('01 Cover & Control'!$C$19="Upside",R71,R72)) -> 84 | S73: =SUM(O73:R73) -> 336 | T73: =IF('01 Cover & Control'!$C$19="Base",T70,IF('01 Cover & Control'!$C$19="Upside",T71,T72)) -> 85 | U73: =IF('01 Cover & Control'!$C$19="Base",U70,IF('01 Cover & Control'!$C$19="Upside",U71,U72)) -> 85 | V73: =IF('01 Cover & Control'!$C$19="Base",V70,IF('01 Cover & Control'!$C$19="Upside",V71,V72)) -> 85 | W73: =IF('01 Cover & Control'!$C$19="Base",W70,IF('01 Cover & Control'!$C$19="Upside",W71,W72)) -> 85 | X73: =SUM(T73:W73) -> 340 | Y73: =IF('01 Cover & Control'!$C$19="Base",Y70,IF('01 Cover & Control'!$C$19="Upside",Y71,Y72)) -> 86 | Z73: =IF('01 Cover & Control'!$C$19="Base",Z70,IF('01 Cover & Control'!$C$19="Upside",Z71,Z72)) -> 86 | AA73: =IF('01 Cover & Control'!$C$19="Base",AA70,IF('01 Cover & Control'!$C$19="Upside",AA71,AA72)) -> 86 | AB73: =IF('01 Cover & Control'!$C$19="Base",AB70,IF('01 Cover & Control'!$C$19="Upside",AB71,AB72)) -> 86 | AC73: =SUM(Y73:AB73) -> 344 | AD73: =IF('01 Cover & Control'!$C$19="Base",AD70,IF('01 Cover & Control'!$C$19="Upside",AD71,AD72)) -> 87 | AE73: =IF('01 Cover & Control'!$C$19="Base",AE70,IF('01 Cover & Control'!$C$19="Upside",AE71,AE72)) -> 87 | AF73: =IF('01 Cover & Control'!$C$19="Base",AF70,IF('01 Cover & Control'!$C$19="Upside",AF71,AF72)) -> 87 | AG73: =IF('01 Cover & Control'!$C$19="Base",AG70,IF('01 Cover & Control'!$C$19="Upside",AG71,AG72)) -> 87 | AH73: =SUM(AD73:AG73) -> 348 | AI73: =IF('01 Cover & Control'!$C$19="Base",AI70,IF('01 Cover & Control'!$C$19="Upside",AI71,AI72)) -> 88 | AJ73: =IF('01 Cover & Control'!$C$19="Base",AJ70,IF('01 Cover & Control'!$C$19="Upside",AJ71,AJ72)) -> 88 | AK73: =IF('01 Cover & Control'!$C$19="Base",AK70,IF('01 Cover & Control'!$C$19="Upside",AK71,AK72)) -> 88 | AL73: =IF('01 Cover & Control'!$C$19="Base",AL70,IF('01 Cover & Control'!$C$19="Upside",AL71,AL72)) -> 88 | AM73: =SUM(AI73:AL73) -> 352 | AN73: =IF('01 Cover & Control'!$C$19="Base",AN70,IF('01 Cover & Control'!$C$19="Upside",AN71,AN72)) -> 89 | AO73: =IF('01 Cover & Control'!$C$19="Base",AO70,IF('01 Cover & Control'!$C$19="Upside",AO71,AO72)) -> 89 | AP73: =IF('01 Cover & Control'!$C$19="Base",AP70,IF('01 Cover & Control'!$C$19="Upside",AP71,AP72)) -> 89 | AQ73: =IF('01 Cover & Control'!$C$19="Base",AQ70,IF('01 Cover & Control'!$C$19="Upside",AQ71,AQ72)) -> 89 | AR73: =SUM(AN73:AQ73) -> 356
B75: Avg IS Deal Size — Mid Market ($10–$50M) — Base | C75: $M / deal | D75: MSCI RCA; CBRE Research | E75: 21 | F75: 21 | G75: 21 | H75: 21 | I75: =SUM(E75:H75) -> 84 | J75: 21 | K75: 21 | L75: 21 | M75: 21 | N75: =SUM(J75:M75) -> 84 | O75: 22 | P75: 22 | Q75: 22 | R75: 22 | S75: =SUM(O75:R75) -> 88 | T75: 22 | U75: 22 | V75: 22 | W75: 22 | X75: =SUM(T75:W75) -> 88 | Y75: 23 | Z75: 23 | AA75: 23 | AB75: 23 | AC75: =SUM(Y75:AB75) -> 92 | AD75: 23 | AE75: 23 | AF75: 23 | AG75: 23 | AH75: =SUM(AD75:AG75) -> 92 | AI75: 23 | AJ75: 23 | AK75: 23 | AL75: 23 | AM75: =SUM(AI75:AL75) -> 92 | AN75: 24 | AO75: 24 | AP75: 24 | AQ75: 24 | AR75: =SUM(AN75:AQ75) -> 96
B76: Avg IS Deal Size — Mid Market ($10–$50M) — Upside | E76: 21 | F76: 21 | G76: 21 | H76: 21 | I76: =SUM(E76:H76) -> 84 | J76: 21 | K76: 21 | L76: 21 | M76: 21 | N76: =SUM(J76:M76) -> 84 | O76: 22 | P76: 22 | Q76: 22 | R76: 22 | S76: =SUM(O76:R76) -> 88 | T76: 23 | U76: 23 | V76: 23 | W76: 23 | X76: =SUM(T76:W76) -> 92 | Y76: 24 | Z76: 24 | AA76: 24 | AB76: 24 | AC76: =SUM(Y76:AB76) -> 96 | AD76: 24 | AE76: 24 | AF76: 24 | AG76: 24 | AH76: =SUM(AD76:AG76) -> 96 | AI76: 25 | AJ76: 25 | AK76: 25 | AL76: 25 | AM76: =SUM(AI76:AL76) -> 100 | AN76: 25 | AO76: 25 | AP76: 25 | AQ76: 25 | AR76: =SUM(AN76:AQ76) -> 100
B77: Avg IS Deal Size — Mid Market ($10–$50M) — Downside | E77: 21 | F77: 21 | G77: 21 | H77: 21 | I77: =SUM(E77:H77) -> 84 | J77: 21 | K77: 21 | L77: 21 | M77: 21 | N77: =SUM(J77:M77) -> 84 | O77: 20 | P77: 20 | Q77: 20 | R77: 20 | S77: =SUM(O77:R77) -> 80 | T77: 20 | U77: 20 | V77: 20 | W77: 20 | X77: =SUM(T77:W77) -> 80 | Y77: 20 | Z77: 20 | AA77: 20 | AB77: 20 | AC77: =SUM(Y77:AB77) -> 80 | AD77: 21 | AE77: 21 | AF77: 21 | AG77: 21 | AH77: =SUM(AD77:AG77) -> 84 | AI77: 21 | AJ77: 21 | AK77: 21 | AL77: 21 | AM77: =SUM(AI77:AL77) -> 84 | AN77: 22 | AO77: 22 | AP77: 22 | AQ77: 22 | AR77: =SUM(AN77:AQ77) -> 88
B78: Avg IS Deal Size — Mid Market ($10–$50M) — ★ ACTIVE | E78: =IF('01 Cover & Control'!$C$19="Base",E75,IF('01 Cover & Control'!$C$19="Upside",E76,E77)) -> 21 | F78: =IF('01 Cover & Control'!$C$19="Base",F75,IF('01 Cover & Control'!$C$19="Upside",F76,F77)) -> 21 | G78: =IF('01 Cover & Control'!$C$19="Base",G75,IF('01 Cover & Control'!$C$19="Upside",G76,G77)) -> 21 | H78: =IF('01 Cover & Control'!$C$19="Base",H75,IF('01 Cover & Control'!$C$19="Upside",H76,H77)) -> 21 | I78: =SUM(E78:H78) -> 84 | J78: =IF('01 Cover & Control'!$C$19="Base",J75,IF('01 Cover & Control'!$C$19="Upside",J76,J77)) -> 21 | K78: =IF('01 Cover & Control'!$C$19="Base",K75,IF('01 Cover & Control'!$C$19="Upside",K76,K77)) -> 21 | L78: =IF('01 Cover & Control'!$C$19="Base",L75,IF('01 Cover & Control'!$C$19="Upside",L76,L77)) -> 21 | M78: =IF('01 Cover & Control'!$C$19="Base",M75,IF('01 Cover & Control'!$C$19="Upside",M76,M77)) -> 21 | N78: =SUM(J78:M78) -> 84 | O78: =IF('01 Cover & Control'!$C$19="Base",O75,IF('01 Cover & Control'!$C$19="Upside",O76,O77)) -> 22 | P78: =IF('01 Cover & Control'!$C$19="Base",P75,IF('01 Cover & Control'!$C$19="Upside",P76,P77)) -> 22 | Q78: =IF('01 Cover & Control'!$C$19="Base",Q75,IF('01 Cover & Control'!$C$19="Upside",Q76,Q77)) -> 22 | R78: =IF('01 Cover & Control'!$C$19="Base",R75,IF('01 Cover & Control'!$C$19="Upside",R76,R77)) -> 22 | S78: =SUM(O78:R78) -> 88 | T78: =IF('01 Cover & Control'!$C$19="Base",T75,IF('01 Cover & Control'!$C$19="Upside",T76,T77)) -> 22 | U78: =IF('01 Cover & Control'!$C$19="Base",U75,IF('01 Cover & Control'!$C$19="Upside",U76,U77)) -> 22 | V78: =IF('01 Cover & Control'!$C$19="Base",V75,IF('01 Cover & Control'!$C$19="Upside",V76,V77)) -> 22 | W78: =IF('01 Cover & Control'!$C$19="Base",W75,IF('01 Cover & Control'!$C$19="Upside",W76,W77)) -> 22 | X78: =SUM(T78:W78) -> 88 | Y78: =IF('01 Cover & Control'!$C$19="Base",Y75,IF('01 Cover & Control'!$C$19="Upside",Y76,Y77)) -> 23 | Z78: =IF('01 Cover & Control'!$C$19="Base",Z75,IF('01 Cover & Control'!$C$19="Upside",Z76,Z77)) -> 23 | AA78: =IF('01 Cover & Control'!$C$19="Base",AA75,IF('01 Cover & Control'!$C$19="Upside",AA76,AA77)) -> 23 | AB78: =IF('01 Cover & Control'!$C$19="Base",AB75,IF('01 Cover & Control'!$C$19="Upside",AB76,AB77)) -> 23 | AC78: =SUM(Y78:AB78) -> 92 | AD78: =IF('01 Cover & Control'!$C$19="Base",AD75,IF('01 Cover & Control'!$C$19="Upside",AD76,AD77)) -> 23 | AE78: =IF('01 Cover & Control'!$C$19="Base",AE75,IF('01 Cover & Control'!$C$19="Upside",AE76,AE77)) -> 23 | AF78: =IF('01 Cover & Control'!$C$19="Base",AF75,IF('01 Cover & Control'!$C$19="Upside",AF76,AF77)) -> 23 | AG78: =IF('01 Cover & Control'!$C$19="Base",AG75,IF('01 Cover & Control'!$C$19="Upside",AG76,AG77)) -> 23 | AH78: =SUM(AD78:AG78) -> 92 | AI78: =IF('01 Cover & Control'!$C$19="Base",AI75,IF('01 Cover & Control'!$C$19="Upside",AI76,AI77)) -> 23 | AJ78: =IF('01 Cover & Control'!$C$19="Base",AJ75,IF('01 Cover & Control'!$C$19="Upside",AJ76,AJ77)) -> 23 | AK78: =IF('01 Cover & Control'!$C$19="Base",AK75,IF('01 Cover & Control'!$C$19="Upside",AK76,AK77)) -> 23 | AL78: =IF('01 Cover & Control'!$C$19="Base",AL75,IF('01 Cover & Control'!$C$19="Upside",AL76,AL77)) -> 23 | AM78: =SUM(AI78:AL78) -> 92 | AN78: =IF('01 Cover & Control'!$C$19="Base",AN75,IF('01 Cover & Control'!$C$19="Upside",AN76,AN77)) -> 24 | AO78: =IF('01 Cover & Control'!$C$19="Base",AO75,IF('01 Cover & Control'!$C$19="Upside",AO76,AO77)) -> 24 | AP78: =IF('01 Cover & Control'!$C$19="Base",AP75,IF('01 Cover & Control'!$C$19="Upside",AP76,AP77)) -> 24 | AQ78: =IF('01 Cover & Control'!$C$19="Base",AQ75,IF('01 Cover & Control'!$C$19="Upside",AQ76,AQ77)) -> 24 | AR78: =SUM(AN78:AQ78) -> 96
B80: Avg IS Deal Size — Small (<$10M) — Base | C80: $M / deal | D80: Marcus & Millichap 10-K; CoStar transaction data | E80: 4.3 | F80: 4.3 | G80: 4.3 | H80: 4.3 | I80: =SUM(E80:H80) -> 17.2 | J80: 4.4 | K80: 4.4 | L80: 4.4 | M80: 4.4 | N80: =SUM(J80:M80) -> 17.6 | O80: 4.5 | P80: 4.5 | Q80: 4.5 | R80: 4.5 | S80: =SUM(O80:R80) -> 18 | T80: 4.6 | U80: 4.6 | V80: 4.6 | W80: 4.6 | X80: =SUM(T80:W80) -> 18.4 | Y80: 4.7 | Z80: 4.7 | AA80: 4.7 | AB80: 4.7 | AC80: =SUM(Y80:AB80) -> 18.8 | AD80: 4.7 | AE80: 4.7 | AF80: 4.7 | AG80: 4.7 | AH80: =SUM(AD80:AG80) -> 18.8 | AI80: 4.8 | AJ80: 4.8 | AK80: 4.8 | AL80: 4.8 | AM80: =SUM(AI80:AL80) -> 19.2 | AN80: 4.8 | AO80: 4.8 | AP80: 4.8 | AQ80: 4.8 | AR80: =SUM(AN80:AQ80) -> 19.2
B81: Avg IS Deal Size — Small (<$10M) — Upside | E81: 4.3 | F81: 4.3 | G81: 4.3 | H81: 4.3 | I81: =SUM(E81:H81) -> 17.2 | J81: 4.4 | K81: 4.4 | L81: 4.4 | M81: 4.4 | N81: =SUM(J81:M81) -> 17.6 | O81: 4.6 | P81: 4.6 | Q81: 4.6 | R81: 4.6 | S81: =SUM(O81:R81) -> 18.4 | T81: 4.8 | U81: 4.8 | V81: 4.8 | W81: 4.8 | X81: =SUM(T81:W81) -> 19.2 | Y81: 4.9 | Z81: 4.9 | AA81: 4.9 | AB81: 4.9 | AC81: =SUM(Y81:AB81) -> 19.6 | AD81: 5 | AE81: 5 | AF81: 5 | AG81: 5 | AH81: =SUM(AD81:AG81) -> 20 | AI81: 5.1 | AJ81: 5.1 | AK81: 5.1 | AL81: 5.1 | AM81: =SUM(AI81:AL81) -> 20.4 | AN81: 5.2 | AO81: 5.2 | AP81: 5.2 | AQ81: 5.2 | AR81: =SUM(AN81:AQ81) -> 20.8
B82: Avg IS Deal Size — Small (<$10M) — Downside | E82: 4.3 | F82: 4.3 | G82: 4.3 | H82: 4.3 | I82: =SUM(E82:H82) -> 17.2 | J82: 4.4 | K82: 4.4 | L82: 4.4 | M82: 4.4 | N82: =SUM(J82:M82) -> 17.6 | O82: 4.2 | P82: 4.2 | Q82: 4.2 | R82: 4.2 | S82: =SUM(O82:R82) -> 16.8 | T82: 4.1 | U82: 4.1 | V82: 4.1 | W82: 4.1 | X82: =SUM(T82:W82) -> 16.4 | Y82: 4.1 | Z82: 4.1 | AA82: 4.1 | AB82: 4.1 | AC82: =SUM(Y82:AB82) -> 16.4 | AD82: 4.2 | AE82: 4.2 | AF82: 4.2 | AG82: 4.2 | AH82: =SUM(AD82:AG82) -> 16.8 | AI82: 4.3 | AJ82: 4.3 | AK82: 4.3 | AL82: 4.3 | AM82: =SUM(AI82:AL82) -> 17.2 | AN82: 4.4 | AO82: 4.4 | AP82: 4.4 | AQ82: 4.4 | AR82: =SUM(AN82:AQ82) -> 17.6
B83: Avg IS Deal Size — Small (<$10M) — ★ ACTIVE | E83: =IF('01 Cover & Control'!$C$19="Base",E80,IF('01 Cover & Control'!$C$19="Upside",E81,E82)) -> 4.3 | F83: =IF('01 Cover & Control'!$C$19="Base",F80,IF('01 Cover & Control'!$C$19="Upside",F81,F82)) -> 4.3 | G83: =IF('01 Cover & Control'!$C$19="Base",G80,IF('01 Cover & Control'!$C$19="Upside",G81,G82)) -> 4.3 | H83: =IF('01 Cover & Control'!$C$19="Base",H80,IF('01 Cover & Control'!$C$19="Upside",H81,H82)) -> 4.3 | I83: =SUM(E83:H83) -> 17.2 | J83: =IF('01 Cover & Control'!$C$19="Base",J80,IF('01 Cover & Control'!$C$19="Upside",J81,J82)) -> 4.4 | K83: =IF('01 Cover & Control'!$C$19="Base",K80,IF('01 Cover & Control'!$C$19="Upside",K81,K82)) -> 4.4 | L83: =IF('01 Cover & Control'!$C$19="Base",L80,IF('01 Cover & Control'!$C$19="Upside",L81,L82)) -> 4.4 | M83: =IF('01 Cover & Control'!$C$19="Base",M80,IF('01 Cover & Control'!$C$19="Upside",M81,M82)) -> 4.4 | N83: =SUM(J83:M83) -> 17.6 | O83: =IF('01 Cover & Control'!$C$19="Base",O80,IF('01 Cover & Control'!$C$19="Upside",O81,O82)) -> 4.5 | P83: =IF('01 Cover & Control'!$C$19="Base",P80,IF('01 Cover & Control'!$C$19="Upside",P81,P82)) -> 4.5 | Q83: =IF('01 Cover & Control'!$C$19="Base",Q80,IF('01 Cover & Control'!$C$19="Upside",Q81,Q82)) -> 4.5 | R83: =IF('01 Cover & Control'!$C$19="Base",R80,IF('01 Cover & Control'!$C$19="Upside",R81,R82)) -> 4.5 | S83: =SUM(O83:R83) -> 18 | T83: =IF('01 Cover & Control'!$C$19="Base",T80,IF('01 Cover & Control'!$C$19="Upside",T81,T82)) -> 4.6 | U83: =IF('01 Cover & Control'!$C$19="Base",U80,IF('01 Cover & Control'!$C$19="Upside",U81,U82)) -> 4.6 | V83: =IF('01 Cover & Control'!$C$19="Base",V80,IF('01 Cover & Control'!$C$19="Upside",V81,V82)) -> 4.6 | W83: =IF('01 Cover & Control'!$C$19="Base",W80,IF('01 Cover & Control'!$C$19="Upside",W81,W82)) -> 4.6 | X83: =SUM(T83:W83) -> 18.4 | Y83: =IF('01 Cover & Control'!$C$19="Base",Y80,IF('01 Cover & Control'!$C$19="Upside",Y81,Y82)) -> 4.7 | Z83: =IF('01 Cover & Control'!$C$19="Base",Z80,IF('01 Cover & Control'!$C$19="Upside",Z81,Z82)) -> 4.7 | AA83: =IF('01 Cover & Control'!$C$19="Base",AA80,IF('01 Cover & Control'!$C$19="Upside",AA81,AA82)) -> 4.7 | AB83: =IF('01 Cover & Control'!$C$19="Base",AB80,IF('01 Cover & Control'!$C$19="Upside",AB81,AB82)) -> 4.7 | AC83: =SUM(Y83:AB83) -> 18.8 | AD83: =IF('01 Cover & Control'!$C$19="Base",AD80,IF('01 Cover & Control'!$C$19="Upside",AD81,AD82)) -> 4.7 | AE83: =IF('01 Cover & Control'!$C$19="Base",AE80,IF('01 Cover & Control'!$C$19="Upside",AE81,AE82)) -> 4.7 | AF83: =IF('01 Cover & Control'!$C$19="Base",AF80,IF('01 Cover & Control'!$C$19="Upside",AF81,AF82)) -> 4.7 | AG83: =IF('01 Cover & Control'!$C$19="Base",AG80,IF('01 Cover & Control'!$C$19="Upside",AG81,AG82)) -> 4.7 | AH83: =SUM(AD83:AG83) -> 18.8 | AI83: =IF('01 Cover & Control'!$C$19="Base",AI80,IF('01 Cover & Control'!$C$19="Upside",AI81,AI82)) -> 4.8 | AJ83: =IF('01 Cover & Control'!$C$19="Base",AJ80,IF('01 Cover & Control'!$C$19="Upside",AJ81,AJ82)) -> 4.8 | AK83: =IF('01 Cover & Control'!$C$19="Base",AK80,IF('01 Cover & Control'!$C$19="Upside",AK81,AK82)) -> 4.8 | AL83: =IF('01 Cover & Control'!$C$19="Base",AL80,IF('01 Cover & Control'!$C$19="Upside",AL81,AL82)) -> 4.8 | AM83: =SUM(AI83:AL83) -> 19.2 | AN83: =IF('01 Cover & Control'!$C$19="Base",AN80,IF('01 Cover & Control'!$C$19="Upside",AN81,AN82)) -> 4.8 | AO83: =IF('01 Cover & Control'!$C$19="Base",AO80,IF('01 Cover & Control'!$C$19="Upside",AO81,AO82)) -> 4.8 | AP83: =IF('01 Cover & Control'!$C$19="Base",AP80,IF('01 Cover & Control'!$C$19="Upside",AP81,AP82)) -> 4.8 | AQ83: =IF('01 Cover & Control'!$C$19="Base",AQ80,IF('01 Cover & Control'!$C$19="Upside",AQ81,AQ82)) -> 4.8 | AR83: =SUM(AN83:AQ83) -> 19.2
A85: B4 — LEASING MARKET
B87: National Leasing Volume / Net Absorption — Base | C87: MSF / qtr | D87: CBRE MarketView; JLL Research; Cushman & Wakefield Net Absorption Reports | E87: 300 | F87: 300 | G87: 300 | H87: 300 | I87: =SUM(E87:H87) -> 1200 | J87: 310 | K87: 310 | L87: 310 | M87: 310 | N87: =SUM(J87:M87) -> 1240 | O87: 330 | P87: 330 | Q87: 330 | R87: 330 | S87: =SUM(O87:R87) -> 1320 | T87: 350 | U87: 350 | V87: 350 | W87: 350 | X87: =SUM(T87:W87) -> 1400 | Y87: 365 | Z87: 365 | AA87: 365 | AB87: 365 | AC87: =SUM(Y87:AB87) -> 1460 | AD87: 375 | AE87: 375 | AF87: 375 | AG87: 375 | AH87: =SUM(AD87:AG87) -> 1500 | AI87: 385 | AJ87: 385 | AK87: 385 | AL87: 385 | AM87: =SUM(AI87:AL87) -> 1540 | AN87: 395 | AO87: 395 | AP87: 395 | AQ87: 395 | AR87: =SUM(AN87:AQ87) -> 1580
B88: National Leasing Volume / Net Absorption — Upside | E88: 300 | F88: 300 | G88: 300 | H88: 300 | I88: =SUM(E88:H88) -> 1200 | J88: 310 | K88: 310 | L88: 310 | M88: 310 | N88: =SUM(J88:M88) -> 1240 | O88: 348 | P88: 348 | Q88: 348 | R88: 348 | S88: =SUM(O88:R88) -> 1392 | T88: 392 | U88: 392 | V88: 392 | W88: 392 | X88: =SUM(T88:W88) -> 1568 | Y88: 409 | Z88: 409 | AA88: 409 | AB88: 409 | AC88: =SUM(Y88:AB88) -> 1636 | AD88: 420 | AE88: 420 | AF88: 420 | AG88: 420 | AH88: =SUM(AD88:AG88) -> 1680 | AI88: 431 | AJ88: 431 | AK88: 431 | AL88: 431 | AM88: =SUM(AI88:AL88) -> 1724 | AN88: 442 | AO88: 442 | AP88: 442 | AQ88: 442 | AR88: =SUM(AN88:AQ88) -> 1768
B89: National Leasing Volume / Net Absorption — Downside | E89: 300 | F89: 300 | G89: 300 | H89: 300 | I89: =SUM(E89:H89) -> 1200 | J89: 310 | K89: 310 | L89: 310 | M89: 310 | N89: =SUM(J89:M89) -> 1240 | O89: 312 | P89: 312 | Q89: 312 | R89: 312 | S89: =SUM(O89:R89) -> 1248 | T89: 298 | U89: 298 | V89: 298 | W89: 298 | X89: =SUM(T89:W89) -> 1192 | Y89: 312 | Z89: 312 | AA89: 312 | AB89: 312 | AC89: =SUM(Y89:AB89) -> 1248 | AD89: 326 | AE89: 326 | AF89: 326 | AG89: 326 | AH89: =SUM(AD89:AG89) -> 1304 | AI89: 338 | AJ89: 338 | AK89: 338 | AL89: 338 | AM89: =SUM(AI89:AL89) -> 1352 | AN89: 350 | AO89: 350 | AP89: 350 | AQ89: 350 | AR89: =SUM(AN89:AQ89) -> 1400
B90: National Leasing Volume / Net Absorption — ★ ACTIVE | E90: =IF('01 Cover & Control'!$C$19="Base",E87,IF('01 Cover & Control'!$C$19="Upside",E88,E89)) -> 300 | F90: =IF('01 Cover & Control'!$C$19="Base",F87,IF('01 Cover & Control'!$C$19="Upside",F88,F89)) -> 300 | G90: =IF('01 Cover & Control'!$C$19="Base",G87,IF('01 Cover & Control'!$C$19="Upside",G88,G89)) -> 300 | H90: =IF('01 Cover & Control'!$C$19="Base",H87,IF('01 Cover & Control'!$C$19="Upside",H88,H89)) -> 300 | I90: =SUM(E90:H90) -> 1200 | J90: =IF('01 Cover & Control'!$C$19="Base",J87,IF('01 Cover & Control'!$C$19="Upside",J88,J89)) -> 310 | K90: =IF('01 Cover & Control'!$C$19="Base",K87,IF('01 Cover & Control'!$C$19="Upside",K88,K89)) -> 310 | L90: =IF('01 Cover & Control'!$C$19="Base",L87,IF('01 Cover & Control'!$C$19="Upside",L88,L89)) -> 310 | M90: =IF('01 Cover & Control'!$C$19="Base",M87,IF('01 Cover & Control'!$C$19="Upside",M88,M89)) -> 310 | N90: =SUM(J90:M90) -> 1240 | O90: =IF('01 Cover & Control'!$C$19="Base",O87,IF('01 Cover & Control'!$C$19="Upside",O88,O89)) -> 330 | P90: =IF('01 Cover & Control'!$C$19="Base",P87,IF('01 Cover & Control'!$C$19="Upside",P88,P89)) -> 330 | Q90: =IF('01 Cover & Control'!$C$19="Base",Q87,IF('01 Cover & Control'!$C$19="Upside",Q88,Q89)) -> 330 | R90: =IF('01 Cover & Control'!$C$19="Base",R87,IF('01 Cover & Control'!$C$19="Upside",R88,R89)) -> 330 | S90: =SUM(O90:R90) -> 1320 | T90: =IF('01 Cover & Control'!$C$19="Base",T87,IF('01 Cover & Control'!$C$19="Upside",T88,T89)) -> 350 | U90: =IF('01 Cover & Control'!$C$19="Base",U87,IF('01 Cover & Control'!$C$19="Upside",U88,U89)) -> 350 | V90: =IF('01 Cover & Control'!$C$19="Base",V87,IF('01 Cover & Control'!$C$19="Upside",V88,V89)) -> 350 | W90: =IF('01 Cover & Control'!$C$19="Base",W87,IF('01 Cover & Control'!$C$19="Upside",W88,W89)) -> 350 | X90: =SUM(T90:W90) -> 1400 | Y90: =IF('01 Cover & Control'!$C$19="Base",Y87,IF('01 Cover & Control'!$C$19="Upside",Y88,Y89)) -> 365 | Z90: =IF('01 Cover & Control'!$C$19="Base",Z87,IF('01 Cover & Control'!$C$19="Upside",Z88,Z89)) -> 365 | AA90: =IF('01 Cover & Control'!$C$19="Base",AA87,IF('01 Cover & Control'!$C$19="Upside",AA88,AA89)) -> 365 | AB90: =IF('01 Cover & Control'!$C$19="Base",AB87,IF('01 Cover & Control'!$C$19="Upside",AB88,AB89)) -> 365 | AC90: =SUM(Y90:AB90) -> 1460 | AD90: =IF('01 Cover & Control'!$C$19="Base",AD87,IF('01 Cover & Control'!$C$19="Upside",AD88,AD89)) -> 375 | AE90: =IF('01 Cover & Control'!$C$19="Base",AE87,IF('01 Cover & Control'!$C$19="Upside",AE88,AE89)) -> 375 | AF90: =IF('01 Cover & Control'!$C$19="Base",AF87,IF('01 Cover & Control'!$C$19="Upside",AF88,AF89)) -> 375 | AG90: =IF('01 Cover & Control'!$C$19="Base",AG87,IF('01 Cover & Control'!$C$19="Upside",AG88,AG89)) -> 375 | AH90: =SUM(AD90:AG90) -> 1500 | AI90: =IF('01 Cover & Control'!$C$19="Base",AI87,IF('01 Cover & Control'!$C$19="Upside",AI88,AI89)) -> 385 | AJ90: =IF('01 Cover & Control'!$C$19="Base",AJ87,IF('01 Cover & Control'!$C$19="Upside",AJ88,AJ89)) -> 385 | AK90: =IF('01 Cover & Control'!$C$19="Base",AK87,IF('01 Cover & Control'!$C$19="Upside",AK88,AK89)) -> 385 | AL90: =IF('01 Cover & Control'!$C$19="Base",AL87,IF('01 Cover & Control'!$C$19="Upside",AL88,AL89)) -> 385 | AM90: =SUM(AI90:AL90) -> 1540 | AN90: =IF('01 Cover & Control'!$C$19="Base",AN87,IF('01 Cover & Control'!$C$19="Upside",AN88,AN89)) -> 395 | AO90: =IF('01 Cover & Control'!$C$19="Base",AO87,IF('01 Cover & Control'!$C$19="Upside",AO88,AO89)) -> 395 | AP90: =IF('01 Cover & Control'!$C$19="Base",AP87,IF('01 Cover & Control'!$C$19="Upside",AP88,AP89)) -> 395 | AQ90: =IF('01 Cover & Control'!$C$19="Base",AQ87,IF('01 Cover & Control'!$C$19="Upside",AQ88,AQ89)) -> 395 | AR90: =SUM(AN90:AQ90) -> 1580
B92: National Market Average Rent — Blended — Base | C92: $ / SF / yr | D92: CBRE MarketView; JLL Research. Blended across office, industrial, retail. | E92: 30 | F92: 30 | G92: 30 | H92: 30 | I92: =SUM(E92:H92) -> 120 | J92: 31 | K92: 31 | L92: 31 | M92: 31 | N92: =SUM(J92:M92) -> 124 | O92: 32 | P92: 32 | Q92: 32 | R92: 32 | S92: =SUM(O92:R92) -> 128 | T92: 33 | U92: 33 | V92: 33 | W92: 33 | X92: =SUM(T92:W92) -> 132 | Y92: 34 | Z92: 34 | AA92: 34 | AB92: 34 | AC92: =SUM(Y92:AB92) -> 136 | AD92: 35 | AE92: 35 | AF92: 35 | AG92: 35 | AH92: =SUM(AD92:AG92) -> 140 | AI92: 36 | AJ92: 36 | AK92: 36 | AL92: 36 | AM92: =SUM(AI92:AL92) -> 144 | AN92: 37 | AO92: 37 | AP92: 37 | AQ92: 37 | AR92: =SUM(AN92:AQ92) -> 148
B93: National Market Average Rent — Blended — Upside | E93: 30 | F93: 30 | G93: 30 | H93: 30 | I93: =SUM(E93:H93) -> 120 | J93: 31 | K93: 31 | L93: 31 | M93: 31 | N93: =SUM(J93:M93) -> 124 | O93: 33 | P93: 33 | Q93: 33 | R93: 33 | S93: =SUM(O93:R93) -> 132 | T93: 35 | U93: 35 | V93: 35 | W93: 35 | X93: =SUM(T93:W93) -> 140 | Y93: 36 | Z93: 36 | AA93: 36 | AB93: 36 | AC93: =SUM(Y93:AB93) -> 144 | AD93: 37 | AE93: 37 | AF93: 37 | AG93: 37 | AH93: =SUM(AD93:AG93) -> 148 | AI93: 38 | AJ93: 38 | AK93: 38 | AL93: 38 | AM93: =SUM(AI93:AL93) -> 152 | AN93: 39 | AO93: 39 | AP93: 39 | AQ93: 39 | AR93: =SUM(AN93:AQ93) -> 156
B94: National Market Average Rent — Blended — Downside | E94: 30 | F94: 30 | G94: 30 | H94: 30 | I94: =SUM(E94:H94) -> 120 | J94: 31 | K94: 31 | L94: 31 | M94: 31 | N94: =SUM(J94:M94) -> 124 | O94: 30 | P94: 30 | Q94: 30 | R94: 30 | S94: =SUM(O94:R94) -> 120 | T94: 29 | U94: 29 | V94: 29 | W94: 29 | X94: =SUM(T94:W94) -> 116 | Y94: 30 | Z94: 30 | AA94: 30 | AB94: 30 | AC94: =SUM(Y94:AB94) -> 120 | AD94: 31 | AE94: 31 | AF94: 31 | AG94: 31 | AH94: =SUM(AD94:AG94) -> 124 | AI94: 32 | AJ94: 32 | AK94: 32 | AL94: 32 | AM94: =SUM(AI94:AL94) -> 128 | AN94: 33 | AO94: 33 | AP94: 33 | AQ94: 33 | AR94: =SUM(AN94:AQ94) -> 132
B95: National Market Average Rent — Blended — ★ ACTIVE | E95: =IF('01 Cover & Control'!$C$19="Base",E92,IF('01 Cover & Control'!$C$19="Upside",E93,E94)) -> 30 | F95: =IF('01 Cover & Control'!$C$19="Base",F92,IF('01 Cover & Control'!$C$19="Upside",F93,F94)) -> 30 | G95: =IF('01 Cover & Control'!$C$19="Base",G92,IF('01 Cover & Control'!$C$19="Upside",G93,G94)) -> 30 | H95: =IF('01 Cover & Control'!$C$19="Base",H92,IF('01 Cover & Control'!$C$19="Upside",H93,H94)) -> 30 | I95: =SUM(E95:H95) -> 120 | J95: =IF('01 Cover & Control'!$C$19="Base",J92,IF('01 Cover & Control'!$C$19="Upside",J93,J94)) -> 31 | K95: =IF('01 Cover & Control'!$C$19="Base",K92,IF('01 Cover & Control'!$C$19="Upside",K93,K94)) -> 31 | L95: =IF('01 Cover & Control'!$C$19="Base",L92,IF('01 Cover & Control'!$C$19="Upside",L93,L94)) -> 31 | M95: =IF('01 Cover & Control'!$C$19="Base",M92,IF('01 Cover & Control'!$C$19="Upside",M93,M94)) -> 31 | N95: =SUM(J95:M95) -> 124 | O95: =IF('01 Cover & Control'!$C$19="Base",O92,IF('01 Cover & Control'!$C$19="Upside",O93,O94)) -> 32 | P95: =IF('01 Cover & Control'!$C$19="Base",P92,IF('01 Cover & Control'!$C$19="Upside",P93,P94)) -> 32 | Q95: =IF('01 Cover & Control'!$C$19="Base",Q92,IF('01 Cover & Control'!$C$19="Upside",Q93,Q94)) -> 32 | R95: =IF('01 Cover & Control'!$C$19="Base",R92,IF('01 Cover & Control'!$C$19="Upside",R93,R94)) -> 32 | S95: =SUM(O95:R95) -> 128 | T95: =IF('01 Cover & Control'!$C$19="Base",T92,IF('01 Cover & Control'!$C$19="Upside",T93,T94)) -> 33 | U95: =IF('01 Cover & Control'!$C$19="Base",U92,IF('01 Cover & Control'!$C$19="Upside",U93,U94)) -> 33 | V95: =IF('01 Cover & Control'!$C$19="Base",V92,IF('01 Cover & Control'!$C$19="Upside",V93,V94)) -> 33 | W95: =IF('01 Cover & Control'!$C$19="Base",W92,IF('01 Cover & Control'!$C$19="Upside",W93,W94)) -> 33 | X95: =SUM(T95:W95) -> 132 | Y95: =IF('01 Cover & Control'!$C$19="Base",Y92,IF('01 Cover & Control'!$C$19="Upside",Y93,Y94)) -> 34 | Z95: =IF('01 Cover & Control'!$C$19="Base",Z92,IF('01 Cover & Control'!$C$19="Upside",Z93,Z94)) -> 34 | AA95: =IF('01 Cover & Control'!$C$19="Base",AA92,IF('01 Cover & Control'!$C$19="Upside",AA93,AA94)) -> 34 | AB95: =IF('01 Cover & Control'!$C$19="Base",AB92,IF('01 Cover & Control'!$C$19="Upside",AB93,AB94)) -> 34 | AC95: =SUM(Y95:AB95) -> 136 | AD95: =IF('01 Cover & Control'!$C$19="Base",AD92,IF('01 Cover & Control'!$C$19="Upside",AD93,AD94)) -> 35 | AE95: =IF('01 Cover & Control'!$C$19="Base",AE92,IF('01 Cover & Control'!$C$19="Upside",AE93,AE94)) -> 35 | AF95: =IF('01 Cover & Control'!$C$19="Base",AF92,IF('01 Cover & Control'!$C$19="Upside",AF93,AF94)) -> 35 | AG95: =IF('01 Cover & Control'!$C$19="Base",AG92,IF('01 Cover & Control'!$C$19="Upside",AG93,AG94)) -> 35 | AH95: =SUM(AD95:AG95) -> 140 | AI95: =IF('01 Cover & Control'!$C$19="Base",AI92,IF('01 Cover & Control'!$C$19="Upside",AI93,AI94)) -> 36 | AJ95: =IF('01 Cover & Control'!$C$19="Base",AJ92,IF('01 Cover & Control'!$C$19="Upside",AJ93,AJ94)) -> 36 | AK95: =IF('01 Cover & Control'!$C$19="Base",AK92,IF('01 Cover & Control'!$C$19="Upside",AK93,AK94)) -> 36 | AL95: =IF('01 Cover & Control'!$C$19="Base",AL92,IF('01 Cover & Control'!$C$19="Upside",AL93,AL94)) -> 36 | AM95: =SUM(AI95:AL95) -> 144 | AN95: =IF('01 Cover & Control'!$C$19="Base",AN92,IF('01 Cover & Control'!$C$19="Upside",AN93,AN94)) -> 37 | AO95: =IF('01 Cover & Control'!$C$19="Base",AO92,IF('01 Cover & Control'!$C$19="Upside",AO93,AO94)) -> 37 | AP95: =IF('01 Cover & Control'!$C$19="Base",AP92,IF('01 Cover & Control'!$C$19="Upside",AP93,AP94)) -> 37 | AQ95: =IF('01 Cover & Control'!$C$19="Base",AQ92,IF('01 Cover & Control'!$C$19="Upside",AQ93,AQ94)) -> 37 | AR95: =SUM(AN95:AQ95) -> 148
A97: B5 — CRE DEBT & ORIGINATIONS MARKET
B99: National CRE Origination Volume — Total Market — Base | C99: $B / qtr | D99: MBA Commercial / Multifamily Quarterly Origination Survey | E99: 120 | F99: 120 | G99: 120 | H99: 120 | I99: =SUM(E99:H99) -> 480 | J99: 128 | K99: 128 | L99: 128 | M99: 128 | N99: =SUM(J99:M99) -> 512 | O99: 140 | P99: 140 | Q99: 140 | R99: 140 | S99: =SUM(O99:R99) -> 560 | T99: 155 | U99: 155 | V99: 155 | W99: 155 | X99: =SUM(T99:W99) -> 620 | Y99: 165 | Z99: 165 | AA99: 165 | AB99: 165 | AC99: =SUM(Y99:AB99) -> 660 | AD99: 172 | AE99: 172 | AF99: 172 | AG99: 172 | AH99: =SUM(AD99:AG99) -> 688 | AI99: 178 | AJ99: 178 | AK99: 178 | AL99: 178 | AM99: =SUM(AI99:AL99) -> 712 | AN99: 184 | AO99: 184 | AP99: 184 | AQ99: 184 | AR99: =SUM(AN99:AQ99) -> 736
B100: National CRE Origination Volume — Total Market — Upside | E100: 120 | F100: 120 | G100: 120 | H100: 120 | I100: =SUM(E100:H100) -> 480 | J100: 128 | K100: 128 | L100: 128 | M100: 128 | N100: =SUM(J100:M100) -> 512 | O100: 148 | P100: 148 | Q100: 148 | R100: 148 | S100: =SUM(O100:R100) -> 592 | T100: 174 | U100: 174 | V100: 174 | W100: 174 | X100: =SUM(T100:W100) -> 696 | Y100: 185 | Z100: 185 | AA100: 185 | AB100: 185 | AC100: =SUM(Y100:AB100) -> 740 | AD100: 193 | AE100: 193 | AF100: 193 | AG100: 193 | AH100: =SUM(AD100:AG100) -> 772 | AI100: 199 | AJ100: 199 | AK100: 199 | AL100: 199 | AM100: =SUM(AI100:AL100) -> 796 | AN100: 206 | AO100: 206 | AP100: 206 | AQ100: 206 | AR100: =SUM(AN100:AQ100) -> 824
B101: National CRE Origination Volume — Total Market — Downside | E101: 120 | F101: 120 | G101: 120 | H101: 120 | I101: =SUM(E101:H101) -> 480 | J101: 128 | K101: 128 | L101: 128 | M101: 128 | N101: =SUM(J101:M101) -> 512 | O101: 130 | P101: 130 | Q101: 130 | R101: 130 | S101: =SUM(O101:R101) -> 520 | T101: 132 | U101: 132 | V101: 132 | W101: 132 | X101: =SUM(T101:W101) -> 528 | Y101: 142 | Z101: 142 | AA101: 142 | AB101: 142 | AC101: =SUM(Y101:AB101) -> 568 | AD101: 152 | AE101: 152 | AF101: 152 | AG101: 152 | AH101: =SUM(AD101:AG101) -> 608 | AI101: 160 | AJ101: 160 | AK101: 160 | AL101: 160 | AM101: =SUM(AI101:AL101) -> 640 | AN101: 168 | AO101: 168 | AP101: 168 | AQ101: 168 | AR101: =SUM(AN101:AQ101) -> 672
B102: National CRE Origination Volume — Total Market — ★ ACTIVE | E102: =IF('01 Cover & Control'!$C$19="Base",E99,IF('01 Cover & Control'!$C$19="Upside",E100,E101)) -> 120 | F102: =IF('01 Cover & Control'!$C$19="Base",F99,IF('01 Cover & Control'!$C$19="Upside",F100,F101)) -> 120 | G102: =IF('01 Cover & Control'!$C$19="Base",G99,IF('01 Cover & Control'!$C$19="Upside",G100,G101)) -> 120 | H102: =IF('01 Cover & Control'!$C$19="Base",H99,IF('01 Cover & Control'!$C$19="Upside",H100,H101)) -> 120 | I102: =SUM(E102:H102) -> 480 | J102: =IF('01 Cover & Control'!$C$19="Base",J99,IF('01 Cover & Control'!$C$19="Upside",J100,J101)) -> 128 | K102: =IF('01 Cover & Control'!$C$19="Base",K99,IF('01 Cover & Control'!$C$19="Upside",K100,K101)) -> 128 | L102: =IF('01 Cover & Control'!$C$19="Base",L99,IF('01 Cover & Control'!$C$19="Upside",L100,L101)) -> 128 | M102: =IF('01 Cover & Control'!$C$19="Base",M99,IF('01 Cover & Control'!$C$19="Upside",M100,M101)) -> 128 | N102: =SUM(J102:M102) -> 512 | O102: =IF('01 Cover & Control'!$C$19="Base",O99,IF('01 Cover & Control'!$C$19="Upside",O100,O101)) -> 140 | P102: =IF('01 Cover & Control'!$C$19="Base",P99,IF('01 Cover & Control'!$C$19="Upside",P100,P101)) -> 140 | Q102: =IF('01 Cover & Control'!$C$19="Base",Q99,IF('01 Cover & Control'!$C$19="Upside",Q100,Q101)) -> 140 | R102: =IF('01 Cover & Control'!$C$19="Base",R99,IF('01 Cover & Control'!$C$19="Upside",R100,R101)) -> 140 | S102: =SUM(O102:R102) -> 560 | T102: =IF('01 Cover & Control'!$C$19="Base",T99,IF('01 Cover & Control'!$C$19="Upside",T100,T101)) -> 155 | U102: =IF('01 Cover & Control'!$C$19="Base",U99,IF('01 Cover & Control'!$C$19="Upside",U100,U101)) -> 155 | V102: =IF('01 Cover & Control'!$C$19="Base",V99,IF('01 Cover & Control'!$C$19="Upside",V100,V101)) -> 155 | W102: =IF('01 Cover & Control'!$C$19="Base",W99,IF('01 Cover & Control'!$C$19="Upside",W100,W101)) -> 155 | X102: =SUM(T102:W102) -> 620 | Y102: =IF('01 Cover & Control'!$C$19="Base",Y99,IF('01 Cover & Control'!$C$19="Upside",Y100,Y101)) -> 165 | Z102: =IF('01 Cover & Control'!$C$19="Base",Z99,IF('01 Cover & Control'!$C$19="Upside",Z100,Z101)) -> 165 | AA102: =IF('01 Cover & Control'!$C$19="Base",AA99,IF('01 Cover & Control'!$C$19="Upside",AA100,AA101)) -> 165 | AB102: =IF('01 Cover & Control'!$C$19="Base",AB99,IF('01 Cover & Control'!$C$19="Upside",AB100,AB101)) -> 165 | AC102: =SUM(Y102:AB102) -> 660 | AD102: =IF('01 Cover & Control'!$C$19="Base",AD99,IF('01 Cover & Control'!$C$19="Upside",AD100,AD101)) -> 172 | AE102: =IF('01 Cover & Control'!$C$19="Base",AE99,IF('01 Cover & Control'!$C$19="Upside",AE100,AE101)) -> 172 | AF102: =IF('01 Cover & Control'!$C$19="Base",AF99,IF('01 Cover & Control'!$C$19="Upside",AF100,AF101)) -> 172 | AG102: =IF('01 Cover & Control'!$C$19="Base",AG99,IF('01 Cover & Control'!$C$19="Upside",AG100,AG101)) -> 172 | AH102: =SUM(AD102:AG102) -> 688 | AI102: =IF('01 Cover & Control'!$C$19="Base",AI99,IF('01 Cover & Control'!$C$19="Upside",AI100,AI101)) -> 178 | AJ102: =IF('01 Cover & Control'!$C$19="Base",AJ99,IF('01 Cover & Control'!$C$19="Upside",AJ100,AJ101)) -> 178 | AK102: =IF('01 Cover & Control'!$C$19="Base",AK99,IF('01 Cover & Control'!$C$19="Upside",AK100,AK101)) -> 178 | AL102: =IF('01 Cover & Control'!$C$19="Base",AL99,IF('01 Cover & Control'!$C$19="Upside",AL100,AL101)) -> 178 | AM102: =SUM(AI102:AL102) -> 712 | AN102: =IF('01 Cover & Control'!$C$19="Base",AN99,IF('01 Cover & Control'!$C$19="Upside",AN100,AN101)) -> 184 | AO102: =IF('01 Cover & Control'!$C$19="Base",AO99,IF('01 Cover & Control'!$C$19="Upside",AO100,AO101)) -> 184 | AP102: =IF('01 Cover & Control'!$C$19="Base",AP99,IF('01 Cover & Control'!$C$19="Upside",AP100,AP101)) -> 184 | AQ102: =IF('01 Cover & Control'!$C$19="Base",AQ99,IF('01 Cover & Control'!$C$19="Upside",AQ100,AQ101)) -> 184 | AR102: =SUM(AN102:AQ102) -> 736
B104: Refinancing Share of Total Originations — Base | C104: % | D104: MBA Quarterly Survey; Trepp loan maturity data | E104: 0.5 | F104: 0.5 | G104: 0.5 | H104: 0.5 | I104: =SUM(E104:H104) -> 2 | J104: 0.48 | K104: 0.48 | L104: 0.48 | M104: 0.48 | N104: =SUM(J104:M104) -> 1.92 | O104: 0.46 | P104: 0.46 | Q104: 0.46 | R104: 0.46 | S104: =SUM(O104:R104) -> 1.84 | T104: 0.45 | U104: 0.45 | V104: 0.45 | W104: 0.45 | X104: =SUM(T104:W104) -> 1.8 | Y104: 0.44 | Z104: 0.44 | AA104: 0.44 | AB104: 0.44 | AC104: =SUM(Y104:AB104) -> 1.76 | AD104: 0.43 | AE104: 0.43 | AF104: 0.43 | AG104: 0.43 | AH104: =SUM(AD104:AG104) -> 1.72 | AI104: 0.43 | AJ104: 0.43 | AK104: 0.43 | AL104: 0.43 | AM104: =SUM(AI104:AL104) -> 1.72 | AN104: 0.43 | AO104: 0.43 | AP104: 0.43 | AQ104: 0.43 | AR104: =SUM(AN104:AQ104) -> 1.72
B105: Refinancing Share of Total Originations — Upside | E105: 0.5 | F105: 0.5 | G105: 0.5 | H105: 0.5 | I105: =SUM(E105:H105) -> 2 | J105: 0.48 | K105: 0.48 | L105: 0.48 | M105: 0.48 | N105: =SUM(J105:M105) -> 1.92 | O105: 0.44 | P105: 0.44 | Q105: 0.44 | R105: 0.44 | S105: =SUM(O105:R105) -> 1.76 | T105: 0.41 | U105: 0.41 | V105: 0.41 | W105: 0.41 | X105: =SUM(T105:W105) -> 1.64 | Y105: 0.4 | Z105: 0.4 | AA105: 0.4 | AB105: 0.4 | AC105: =SUM(Y105:AB105) -> 1.6 | AD105: 0.39 | AE105: 0.39 | AF105: 0.39 | AG105: 0.39 | AH105: =SUM(AD105:AG105) -> 1.56 | AI105: 0.39 | AJ105: 0.39 | AK105: 0.39 | AL105: 0.39 | AM105: =SUM(AI105:AL105) -> 1.56 | AN105: 0.39 | AO105: 0.39 | AP105: 0.39 | AQ105: 0.39 | AR105: =SUM(AN105:AQ105) -> 1.56
B106: Refinancing Share of Total Originations — Downside | E106: 0.5 | F106: 0.5 | G106: 0.5 | H106: 0.5 | I106: =SUM(E106:H106) -> 2 | J106: 0.48 | K106: 0.48 | L106: 0.48 | M106: 0.48 | N106: =SUM(J106:M106) -> 1.92 | O106: 0.52 | P106: 0.52 | Q106: 0.52 | R106: 0.52 | S106: =SUM(O106:R106) -> 2.08 | T106: 0.58 | U106: 0.58 | V106: 0.58 | W106: 0.58 | X106: =SUM(T106:W106) -> 2.32 | Y106: 0.56 | Z106: 0.56 | AA106: 0.56 | AB106: 0.56 | AC106: =SUM(Y106:AB106) -> 2.24 | AD106: 0.54 | AE106: 0.54 | AF106: 0.54 | AG106: 0.54 | AH106: =SUM(AD106:AG106) -> 2.16 | AI106: 0.52 | AJ106: 0.52 | AK106: 0.52 | AL106: 0.52 | AM106: =SUM(AI106:AL106) -> 2.08 | AN106: 0.5 | AO106: 0.5 | AP106: 0.5 | AQ106: 0.5 | AR106: =SUM(AN106:AQ106) -> 2
B107: Refinancing Share of Total Originations — ★ ACTIVE | E107: =IF('01 Cover & Control'!$C$19="Base",E104,IF('01 Cover & Control'!$C$19="Upside",E105,E106)) -> 0.5 | F107: =IF('01 Cover & Control'!$C$19="Base",F104,IF('01 Cover & Control'!$C$19="Upside",F105,F106)) -> 0.5 | G107: =IF('01 Cover & Control'!$C$19="Base",G104,IF('01 Cover & Control'!$C$19="Upside",G105,G106)) -> 0.5 | H107: =IF('01 Cover & Control'!$C$19="Base",H104,IF('01 Cover & Control'!$C$19="Upside",H105,H106)) -> 0.5 | I107: =SUM(E107:H107) -> 2 | J107: =IF('01 Cover & Control'!$C$19="Base",J104,IF('01 Cover & Control'!$C$19="Upside",J105,J106)) -> 0.48 | K107: =IF('01 Cover & Control'!$C$19="Base",K104,IF('01 Cover & Control'!$C$19="Upside",K105,K106)) -> 0.48 | L107: =IF('01 Cover & Control'!$C$19="Base",L104,IF('01 Cover & Control'!$C$19="Upside",L105,L106)) -> 0.48 | M107: =IF('01 Cover & Control'!$C$19="Base",M104,IF('01 Cover & Control'!$C$19="Upside",M105,M106)) -> 0.48 | N107: =SUM(J107:M107) -> 1.92 | O107: =IF('01 Cover & Control'!$C$19="Base",O104,IF('01 Cover & Control'!$C$19="Upside",O105,O106)) -> 0.46 | P107: =IF('01 Cover & Control'!$C$19="Base",P104,IF('01 Cover & Control'!$C$19="Upside",P105,P106)) -> 0.46 | Q107: =IF('01 Cover & Control'!$C$19="Base",Q104,IF('01 Cover & Control'!$C$19="Upside",Q105,Q106)) -> 0.46 | R107: =IF('01 Cover & Control'!$C$19="Base",R104,IF('01 Cover & Control'!$C$19="Upside",R105,R106)) -> 0.46 | S107: =SUM(O107:R107) -> 1.84 | T107: =IF('01 Cover & Control'!$C$19="Base",T104,IF('01 Cover & Control'!$C$19="Upside",T105,T106)) -> 0.45 | U107: =IF('01 Cover & Control'!$C$19="Base",U104,IF('01 Cover & Control'!$C$19="Upside",U105,U106)) -> 0.45 | V107: =IF('01 Cover & Control'!$C$19="Base",V104,IF('01 Cover & Control'!$C$19="Upside",V105,V106)) -> 0.45 | W107: =IF('01 Cover & Control'!$C$19="Base",W104,IF('01 Cover & Control'!$C$19="Upside",W105,W106)) -> 0.45 | X107: =SUM(T107:W107) -> 1.8 | Y107: =IF('01 Cover & Control'!$C$19="Base",Y104,IF('01 Cover & Control'!$C$19="Upside",Y105,Y106)) -> 0.44 | Z107: =IF('01 Cover & Control'!$C$19="Base",Z104,IF('01 Cover & Control'!$C$19="Upside",Z105,Z106)) -> 0.44 | AA107: =IF('01 Cover & Control'!$C$19="Base",AA104,IF('01 Cover & Control'!$C$19="Upside",AA105,AA106)) -> 0.44 | AB107: =IF('01 Cover & Control'!$C$19="Base",AB104,IF('01 Cover & Control'!$C$19="Upside",AB105,AB106)) -> 0.44 | AC107: =SUM(Y107:AB107) -> 1.76 | AD107: =IF('01 Cover & Control'!$C$19="Base",AD104,IF('01 Cover & Control'!$C$19="Upside",AD105,AD106)) -> 0.43 | AE107: =IF('01 Cover & Control'!$C$19="Base",AE104,IF('01 Cover & Control'!$C$19="Upside",AE105,AE106)) -> 0.43 | AF107: =IF('01 Cover & Control'!$C$19="Base",AF104,IF('01 Cover & Control'!$C$19="Upside",AF105,AF106)) -> 0.43 | AG107: =IF('01 Cover & Control'!$C$19="Base",AG104,IF('01 Cover & Control'!$C$19="Upside",AG105,AG106)) -> 0.43 | AH107: =SUM(AD107:AG107) -> 1.72 | AI107: =IF('01 Cover & Control'!$C$19="Base",AI104,IF('01 Cover & Control'!$C$19="Upside",AI105,AI106)) -> 0.43 | AJ107: =IF('01 Cover & Control'!$C$19="Base",AJ104,IF('01 Cover & Control'!$C$19="Upside",AJ105,AJ106)) -> 0.43 | AK107: =IF('01 Cover & Control'!$C$19="Base",AK104,IF('01 Cover & Control'!$C$19="Upside",AK105,AK106)) -> 0.43 | AL107: =IF('01 Cover & Control'!$C$19="Base",AL104,IF('01 Cover & Control'!$C$19="Upside",AL105,AL106)) -> 0.43 | AM107: =SUM(AI107:AL107) -> 1.72 | AN107: =IF('01 Cover & Control'!$C$19="Base",AN104,IF('01 Cover & Control'!$C$19="Upside",AN105,AN106)) -> 0.43 | AO107: =IF('01 Cover & Control'!$C$19="Base",AO104,IF('01 Cover & Control'!$C$19="Upside",AO105,AO106)) -> 0.43 | AP107: =IF('01 Cover & Control'!$C$19="Base",AP104,IF('01 Cover & Control'!$C$19="Upside",AP105,AP106)) -> 0.43 | AQ107: =IF('01 Cover & Control'!$C$19="Base",AQ104,IF('01 Cover & Control'!$C$19="Upside",AQ105,AQ106)) -> 0.43 | AR107: =SUM(AN107:AQ107) -> 1.72
A111: SECTION C — FEE RATE ENVIRONMENT
A113: C1 — INVESTMENT SALES COMMISSION RATES (BPS)
B114: Industry norm: smaller deals = higher bps (rate compression on larger deals). CHECK row validates ordering. Source: MMI 10-K commission disclosures; industry surveys.
B116: IS Commission — Small Deals (<$10M) — Base | C116: bps | D116: Marcus & Millichap 10-K; industry surveys. Typical range: 100–200 bps. | E116: 175 | F116: 175 | G116: 175 | H116: 175 | I116: =SUM(E116:H116) -> 700 | J116: 175 | K116: 175 | L116: 175 | M116: 175 | N116: =SUM(J116:M116) -> 700 | O116: 175 | P116: 175 | Q116: 175 | R116: 175 | S116: =SUM(O116:R116) -> 700 | T116: 175 | U116: 175 | V116: 175 | W116: 175 | X116: =SUM(T116:W116) -> 700 | Y116: 175 | Z116: 175 | AA116: 175 | AB116: 175 | AC116: =SUM(Y116:AB116) -> 700 | AD116: 175 | AE116: 175 | AF116: 175 | AG116: 175 | AH116: =SUM(AD116:AG116) -> 700 | AI116: 175 | AJ116: 175 | AK116: 175 | AL116: 175 | AM116: =SUM(AI116:AL116) -> 700 | AN116: 175 | AO116: 175 | AP116: 175 | AQ116: 175 | AR116: =SUM(AN116:AQ116) -> 700
B117: IS Commission — Small Deals (<$10M) — Upside | E117: 175 | F117: 175 | G117: 175 | H117: 175 | I117: =SUM(E117:H117) -> 700 | J117: 175 | K117: 175 | L117: 175 | M117: 175 | N117: =SUM(J117:M117) -> 700 | O117: 175 | P117: 175 | Q117: 175 | R117: 175 | S117: =SUM(O117:R117) -> 700 | T117: 175 | U117: 175 | V117: 175 | W117: 175 | X117: =SUM(T117:W117) -> 700 | Y117: 175 | Z117: 175 | AA117: 175 | AB117: 175 | AC117: =SUM(Y117:AB117) -> 700 | AD117: 175 | AE117: 175 | AF117: 175 | AG117: 175 | AH117: =SUM(AD117:AG117) -> 700 | AI117: 175 | AJ117: 175 | AK117: 175 | AL117: 175 | AM117: =SUM(AI117:AL117) -> 700 | AN117: 175 | AO117: 175 | AP117: 175 | AQ117: 175 | AR117: =SUM(AN117:AQ117) -> 700
B118: IS Commission — Small Deals (<$10M) — Downside | E118: 175 | F118: 175 | G118: 175 | H118: 175 | I118: =SUM(E118:H118) -> 700 | J118: 175 | K118: 175 | L118: 175 | M118: 175 | N118: =SUM(J118:M118) -> 700 | O118: 175 | P118: 175 | Q118: 175 | R118: 175 | S118: =SUM(O118:R118) -> 700 | T118: 175 | U118: 175 | V118: 175 | W118: 175 | X118: =SUM(T118:W118) -> 700 | Y118: 175 | Z118: 175 | AA118: 175 | AB118: 175 | AC118: =SUM(Y118:AB118) -> 700 | AD118: 175 | AE118: 175 | AF118: 175 | AG118: 175 | AH118: =SUM(AD118:AG118) -> 700 | AI118: 175 | AJ118: 175 | AK118: 175 | AL118: 175 | AM118: =SUM(AI118:AL118) -> 700 | AN118: 175 | AO118: 175 | AP118: 175 | AQ118: 175 | AR118: =SUM(AN118:AQ118) -> 700
B119: IS Commission — Small Deals (<$10M) — ★ ACTIVE | E119: =IF('01 Cover & Control'!$C$19="Base",E116,IF('01 Cover & Control'!$C$19="Upside",E117,E118)) -> 175 | F119: =IF('01 Cover & Control'!$C$19="Base",F116,IF('01 Cover & Control'!$C$19="Upside",F117,F118)) -> 175 | G119: =IF('01 Cover & Control'!$C$19="Base",G116,IF('01 Cover & Control'!$C$19="Upside",G117,G118)) -> 175 | H119: =IF('01 Cover & Control'!$C$19="Base",H116,IF('01 Cover & Control'!$C$19="Upside",H117,H118)) -> 175 | I119: =SUM(E119:H119) -> 700 | J119: =IF('01 Cover & Control'!$C$19="Base",J116,IF('01 Cover & Control'!$C$19="Upside",J117,J118)) -> 175 | K119: =IF('01 Cover & Control'!$C$19="Base",K116,IF('01 Cover & Control'!$C$19="Upside",K117,K118)) -> 175 | L119: =IF('01 Cover & Control'!$C$19="Base",L116,IF('01 Cover & Control'!$C$19="Upside",L117,L118)) -> 175 | M119: =IF('01 Cover & Control'!$C$19="Base",M116,IF('01 Cover & Control'!$C$19="Upside",M117,M118)) -> 175 | N119: =SUM(J119:M119) -> 700 | O119: =IF('01 Cover & Control'!$C$19="Base",O116,IF('01 Cover & Control'!$C$19="Upside",O117,O118)) -> 175 | P119: =IF('01 Cover & Control'!$C$19="Base",P116,IF('01 Cover & Control'!$C$19="Upside",P117,P118)) -> 175 | Q119: =IF('01 Cover & Control'!$C$19="Base",Q116,IF('01 Cover & Control'!$C$19="Upside",Q117,Q118)) -> 175 | R119: =IF('01 Cover & Control'!$C$19="Base",R116,IF('01 Cover & Control'!$C$19="Upside",R117,R118)) -> 175 | S119: =SUM(O119:R119) -> 700 | T119: =IF('01 Cover & Control'!$C$19="Base",T116,IF('01 Cover & Control'!$C$19="Upside",T117,T118)) -> 175 | U119: =IF('01 Cover & Control'!$C$19="Base",U116,IF('01 Cover & Control'!$C$19="Upside",U117,U118)) -> 175 | V119: =IF('01 Cover & Control'!$C$19="Base",V116,IF('01 Cover & Control'!$C$19="Upside",V117,V118)) -> 175 | W119: =IF('01 Cover & Control'!$C$19="Base",W116,IF('01 Cover & Control'!$C$19="Upside",W117,W118)) -> 175 | X119: =SUM(T119:W119) -> 700 | Y119: =IF('01 Cover & Control'!$C$19="Base",Y116,IF('01 Cover & Control'!$C$19="Upside",Y117,Y118)) -> 175 | Z119: =IF('01 Cover & Control'!$C$19="Base",Z116,IF('01 Cover & Control'!$C$19="Upside",Z117,Z118)) -> 175 | AA119: =IF('01 Cover & Control'!$C$19="Base",AA116,IF('01 Cover & Control'!$C$19="Upside",AA117,AA118)) -> 175 | AB119: =IF('01 Cover & Control'!$C$19="Base",AB116,IF('01 Cover & Control'!$C$19="Upside",AB117,AB118)) -> 175 | AC119: =SUM(Y119:AB119) -> 700 | AD119: =IF('01 Cover & Control'!$C$19="Base",AD116,IF('01 Cover & Control'!$C$19="Upside",AD117,AD118)) -> 175 | AE119: =IF('01 Cover & Control'!$C$19="Base",AE116,IF('01 Cover & Control'!$C$19="Upside",AE117,AE118)) -> 175 | AF119: =IF('01 Cover & Control'!$C$19="Base",AF116,IF('01 Cover & Control'!$C$19="Upside",AF117,AF118)) -> 175 | AG119: =IF('01 Cover & Control'!$C$19="Base",AG116,IF('01 Cover & Control'!$C$19="Upside",AG117,AG118)) -> 175 | AH119: =SUM(AD119:AG119) -> 700 | AI119: =IF('01 Cover & Control'!$C$19="Base",AI116,IF('01 Cover & Control'!$C$19="Upside",AI117,AI118)) -> 175 | AJ119: =IF('01 Cover & Control'!$C$19="Base",AJ116,IF('01 Cover & Control'!$C$19="Upside",AJ117,AJ118)) -> 175 | AK119: =IF('01 Cover & Control'!$C$19="Base",AK116,IF('01 Cover & Control'!$C$19="Upside",AK117,AK118)) -> 175 | AL119: =IF('01 Cover & Control'!$C$19="Base",AL116,IF('01 Cover & Control'!$C$19="Upside",AL117,AL118)) -> 175 | AM119: =SUM(AI119:AL119) -> 700 | AN119: =IF('01 Cover & Control'!$C$19="Base",AN116,IF('01 Cover & Control'!$C$19="Upside",AN117,AN118)) -> 175 | AO119: =IF('01 Cover & Control'!$C$19="Base",AO116,IF('01 Cover & Control'!$C$19="Upside",AO117,AO118)) -> 175 | AP119: =IF('01 Cover & Control'!$C$19="Base",AP116,IF('01 Cover & Control'!$C$19="Upside",AP117,AP118)) -> 175 | AQ119: =IF('01 Cover & Control'!$C$19="Base",AQ116,IF('01 Cover & Control'!$C$19="Upside",AQ117,AQ118)) -> 175 | AR119: =SUM(AN119:AQ119) -> 700
B121: IS Commission — Mid Market ($10–$50M) — Base | C121: bps | D121: CBRE; JLL; broker interviews. Typical range: 75–120 bps. | E121: 110 | F121: 110 | G121: 110 | H121: 110 | I121: =SUM(E121:H121) -> 440 | J121: 110 | K121: 110 | L121: 110 | M121: 110 | N121: =SUM(J121:M121) -> 440 | O121: 110 | P121: 110 | Q121: 110 | R121: 110 | S121: =SUM(O121:R121) -> 440 | T121: 110 | U121: 110 | V121: 110 | W121: 110 | X121: =SUM(T121:W121) -> 440 | Y121: 110 | Z121: 110 | AA121: 110 | AB121: 110 | AC121: =SUM(Y121:AB121) -> 440 | AD121: 110 | AE121: 110 | AF121: 110 | AG121: 110 | AH121: =SUM(AD121:AG121) -> 440 | AI121: 110 | AJ121: 110 | AK121: 110 | AL121: 110 | AM121: =SUM(AI121:AL121) -> 440 | AN121: 110 | AO121: 110 | AP121: 110 | AQ121: 110 | AR121: =SUM(AN121:AQ121) -> 440
B122: IS Commission — Mid Market ($10–$50M) — Upside | E122: 114 | F122: 114 | G122: 114 | H122: 114 | I122: =SUM(E122:H122) -> 456 | J122: 114 | K122: 114 | L122: 114 | M122: 114 | N122: =SUM(J122:M122) -> 456 | O122: 114 | P122: 114 | Q122: 114 | R122: 114 | S122: =SUM(O122:R122) -> 456 | T122: 114 | U122: 114 | V122: 114 | W122: 114 | X122: =SUM(T122:W122) -> 456 | Y122: 114 | Z122: 114 | AA122: 114 | AB122: 114 | AC122: =SUM(Y122:AB122) -> 456 | AD122: 114 | AE122: 114 | AF122: 114 | AG122: 114 | AH122: =SUM(AD122:AG122) -> 456 | AI122: 114 | AJ122: 114 | AK122: 114 | AL122: 114 | AM122: =SUM(AI122:AL122) -> 456 | AN122: 114 | AO122: 114 | AP122: 114 | AQ122: 114 | AR122: =SUM(AN122:AQ122) -> 456
B123: IS Commission — Mid Market ($10–$50M) — Downside | E123: 105 | F123: 105 | G123: 105 | H123: 105 | I123: =SUM(E123:H123) -> 420 | J123: 105 | K123: 105 | L123: 105 | M123: 105 | N123: =SUM(J123:M123) -> 420 | O123: 105 | P123: 105 | Q123: 105 | R123: 105 | S123: =SUM(O123:R123) -> 420 | T123: 105 | U123: 105 | V123: 105 | W123: 105 | X123: =SUM(T123:W123) -> 420 | Y123: 105 | Z123: 105 | AA123: 105 | AB123: 105 | AC123: =SUM(Y123:AB123) -> 420 | AD123: 105 | AE123: 105 | AF123: 105 | AG123: 105 | AH123: =SUM(AD123:AG123) -> 420 | AI123: 105 | AJ123: 105 | AK123: 105 | AL123: 105 | AM123: =SUM(AI123:AL123) -> 420 | AN123: 105 | AO123: 105 | AP123: 105 | AQ123: 105 | AR123: =SUM(AN123:AQ123) -> 420
B124: IS Commission — Mid Market ($10–$50M) — ★ ACTIVE | E124: =IF('01 Cover & Control'!$C$19="Base",E121,IF('01 Cover & Control'!$C$19="Upside",E122,E123)) -> 110 | F124: =IF('01 Cover & Control'!$C$19="Base",F121,IF('01 Cover & Control'!$C$19="Upside",F122,F123)) -> 110 | G124: =IF('01 Cover & Control'!$C$19="Base",G121,IF('01 Cover & Control'!$C$19="Upside",G122,G123)) -> 110 | H124: =IF('01 Cover & Control'!$C$19="Base",H121,IF('01 Cover & Control'!$C$19="Upside",H122,H123)) -> 110 | I124: =SUM(E124:H124) -> 440 | J124: =IF('01 Cover & Control'!$C$19="Base",J121,IF('01 Cover & Control'!$C$19="Upside",J122,J123)) -> 110 | K124: =IF('01 Cover & Control'!$C$19="Base",K121,IF('01 Cover & Control'!$C$19="Upside",K122,K123)) -> 110 | L124: =IF('01 Cover & Control'!$C$19="Base",L121,IF('01 Cover & Control'!$C$19="Upside",L122,L123)) -> 110 | M124: =IF('01 Cover & Control'!$C$19="Base",M121,IF('01 Cover & Control'!$C$19="Upside",M122,M123)) -> 110 | N124: =SUM(J124:M124) -> 440 | O124: =IF('01 Cover & Control'!$C$19="Base",O121,IF('01 Cover & Control'!$C$19="Upside",O122,O123)) -> 110 | P124: =IF('01 Cover & Control'!$C$19="Base",P121,IF('01 Cover & Control'!$C$19="Upside",P122,P123)) -> 110 | Q124: =IF('01 Cover & Control'!$C$19="Base",Q121,IF('01 Cover & Control'!$C$19="Upside",Q122,Q123)) -> 110 | R124: =IF('01 Cover & Control'!$C$19="Base",R121,IF('01 Cover & Control'!$C$19="Upside",R122,R123)) -> 110 | S124: =SUM(O124:R124) -> 440 | T124: =IF('01 Cover & Control'!$C$19="Base",T121,IF('01 Cover & Control'!$C$19="Upside",T122,T123)) -> 110 | U124: =IF('01 Cover & Control'!$C$19="Base",U121,IF('01 Cover & Control'!$C$19="Upside",U122,U123)) -> 110 | V124: =IF('01 Cover & Control'!$C$19="Base",V121,IF('01 Cover & Control'!$C$19="Upside",V122,V123)) -> 110 | W124: =IF('01 Cover & Control'!$C$19="Base",W121,IF('01 Cover & Control'!$C$19="Upside",W122,W123)) -> 110 | X124: =SUM(T124:W124) -> 440 | Y124: =IF('01 Cover & Control'!$C$19="Base",Y121,IF('01 Cover & Control'!$C$19="Upside",Y122,Y123)) -> 110 | Z124: =IF('01 Cover & Control'!$C$19="Base",Z121,IF('01 Cover & Control'!$C$19="Upside",Z122,Z123)) -> 110 | AA124: =IF('01 Cover & Control'!$C$19="Base",AA121,IF('01 Cover & Control'!$C$19="Upside",AA122,AA123)) -> 110 | AB124: =IF('01 Cover & Control'!$C$19="Base",AB121,IF('01 Cover & Control'!$C$19="Upside",AB122,AB123)) -> 110 | AC124: =SUM(Y124:AB124) -> 440 | AD124: =IF('01 Cover & Control'!$C$19="Base",AD121,IF('01 Cover & Control'!$C$19="Upside",AD122,AD123)) -> 110 | AE124: =IF('01 Cover & Control'!$C$19="Base",AE121,IF('01 Cover & Control'!$C$19="Upside",AE122,AE123)) -> 110 | AF124: =IF('01 Cover & Control'!$C$19="Base",AF121,IF('01 Cover & Control'!$C$19="Upside",AF122,AF123)) -> 110 | AG124: =IF('01 Cover & Control'!$C$19="Base",AG121,IF('01 Cover & Control'!$C$19="Upside",AG122,AG123)) -> 110 | AH124: =SUM(AD124:AG124) -> 440 | AI124: =IF('01 Cover & Control'!$C$19="Base",AI121,IF('01 Cover & Control'!$C$19="Upside",AI122,AI123)) -> 110 | AJ124: =IF('01 Cover & Control'!$C$19="Base",AJ121,IF('01 Cover & Control'!$C$19="Upside",AJ122,AJ123)) -> 110 | AK124: =IF('01 Cover & Control'!$C$19="Base",AK121,IF('01 Cover & Control'!$C$19="Upside",AK122,AK123)) -> 110 | AL124: =IF('01 Cover & Control'!$C$19="Base",AL121,IF('01 Cover & Control'!$C$19="Upside",AL122,AL123)) -> 110 | AM124: =SUM(AI124:AL124) -> 440 | AN124: =IF('01 Cover & Control'!$C$19="Base",AN121,IF('01 Cover & Control'!$C$19="Upside",AN122,AN123)) -> 110 | AO124: =IF('01 Cover & Control'!$C$19="Base",AO121,IF('01 Cover & Control'!$C$19="Upside",AO122,AO123)) -> 110 | AP124: =IF('01 Cover & Control'!$C$19="Base",AP121,IF('01 Cover & Control'!$C$19="Upside",AP122,AP123)) -> 110 | AQ124: =IF('01 Cover & Control'!$C$19="Base",AQ121,IF('01 Cover & Control'!$C$19="Upside",AQ122,AQ123)) -> 110 | AR124: =SUM(AN124:AQ124) -> 440
B126: IS Commission — Institutional (>$50M) — Base | C126: bps | D126: Newmark; CBRE Capital Markets; MSCI RCA. Typical range: 40–75 bps. | E126: 55 | F126: 55 | G126: 55 | H126: 55 | I126: =SUM(E126:H126) -> 220 | J126: 55 | K126: 55 | L126: 55 | M126: 55 | N126: =SUM(J126:M126) -> 220 | O126: 55 | P126: 55 | Q126: 55 | R126: 55 | S126: =SUM(O126:R126) -> 220 | T126: 55 | U126: 55 | V126: 55 | W126: 55 | X126: =SUM(T126:W126) -> 220 | Y126: 55 | Z126: 55 | AA126: 55 | AB126: 55 | AC126: =SUM(Y126:AB126) -> 220 | AD126: 55 | AE126: 55 | AF126: 55 | AG126: 55 | AH126: =SUM(AD126:AG126) -> 220 | AI126: 55 | AJ126: 55 | AK126: 55 | AL126: 55 | AM126: =SUM(AI126:AL126) -> 220 | AN126: 55 | AO126: 55 | AP126: 55 | AQ126: 55 | AR126: =SUM(AN126:AQ126) -> 220
B127: IS Commission — Institutional (>$50M) — Upside | E127: 58 | F127: 58 | G127: 58 | H127: 58 | I127: =SUM(E127:H127) -> 232 | J127: 58 | K127: 58 | L127: 58 | M127: 58 | N127: =SUM(J127:M127) -> 232 | O127: 58 | P127: 58 | Q127: 58 | R127: 58 | S127: =SUM(O127:R127) -> 232 | T127: 58 | U127: 58 | V127: 58 | W127: 58 | X127: =SUM(T127:W127) -> 232 | Y127: 58 | Z127: 58 | AA127: 58 | AB127: 58 | AC127: =SUM(Y127:AB127) -> 232 | AD127: 58 | AE127: 58 | AF127: 58 | AG127: 58 | AH127: =SUM(AD127:AG127) -> 232 | AI127: 58 | AJ127: 58 | AK127: 58 | AL127: 58 | AM127: =SUM(AI127:AL127) -> 232 | AN127: 58 | AO127: 58 | AP127: 58 | AQ127: 58 | AR127: =SUM(AN127:AQ127) -> 232
B128: IS Commission — Institutional (>$50M) — Downside | E128: 52 | F128: 52 | G128: 52 | H128: 52 | I128: =SUM(E128:H128) -> 208 | J128: 52 | K128: 52 | L128: 52 | M128: 52 | N128: =SUM(J128:M128) -> 208 | O128: 52 | P128: 52 | Q128: 52 | R128: 52 | S128: =SUM(O128:R128) -> 208 | T128: 52 | U128: 52 | V128: 52 | W128: 52 | X128: =SUM(T128:W128) -> 208 | Y128: 52 | Z128: 52 | AA128: 52 | AB128: 52 | AC128: =SUM(Y128:AB128) -> 208 | AD128: 52 | AE128: 52 | AF128: 52 | AG128: 52 | AH128: =SUM(AD128:AG128) -> 208 | AI128: 52 | AJ128: 52 | AK128: 52 | AL128: 52 | AM128: =SUM(AI128:AL128) -> 208 | AN128: 52 | AO128: 52 | AP128: 52 | AQ128: 52 | AR128: =SUM(AN128:AQ128) -> 208
B129: IS Commission — Institutional (>$50M) — ★ ACTIVE | E129: =IF('01 Cover & Control'!$C$19="Base",E126,IF('01 Cover & Control'!$C$19="Upside",E127,E128)) -> 55 | F129: =IF('01 Cover & Control'!$C$19="Base",F126,IF('01 Cover & Control'!$C$19="Upside",F127,F128)) -> 55 | G129: =IF('01 Cover & Control'!$C$19="Base",G126,IF('01 Cover & Control'!$C$19="Upside",G127,G128)) -> 55 | H129: =IF('01 Cover & Control'!$C$19="Base",H126,IF('01 Cover & Control'!$C$19="Upside",H127,H128)) -> 55 | I129: =SUM(E129:H129) -> 220 | J129: =IF('01 Cover & Control'!$C$19="Base",J126,IF('01 Cover & Control'!$C$19="Upside",J127,J128)) -> 55 | K129: =IF('01 Cover & Control'!$C$19="Base",K126,IF('01 Cover & Control'!$C$19="Upside",K127,K128)) -> 55 | L129: =IF('01 Cover & Control'!$C$19="Base",L126,IF('01 Cover & Control'!$C$19="Upside",L127,L128)) -> 55 | M129: =IF('01 Cover & Control'!$C$19="Base",M126,IF('01 Cover & Control'!$C$19="Upside",M127,M128)) -> 55 | N129: =SUM(J129:M129) -> 220 | O129: =IF('01 Cover & Control'!$C$19="Base",O126,IF('01 Cover & Control'!$C$19="Upside",O127,O128)) -> 55 | P129: =IF('01 Cover & Control'!$C$19="Base",P126,IF('01 Cover & Control'!$C$19="Upside",P127,P128)) -> 55 | Q129: =IF('01 Cover & Control'!$C$19="Base",Q126,IF('01 Cover & Control'!$C$19="Upside",Q127,Q128)) -> 55 | R129: =IF('01 Cover & Control'!$C$19="Base",R126,IF('01 Cover & Control'!$C$19="Upside",R127,R128)) -> 55 | S129: =SUM(O129:R129) -> 220 | T129: =IF('01 Cover & Control'!$C$19="Base",T126,IF('01 Cover & Control'!$C$19="Upside",T127,T128)) -> 55 | U129: =IF('01 Cover & Control'!$C$19="Base",U126,IF('01 Cover & Control'!$C$19="Upside",U127,U128)) -> 55 | V129: =IF('01 Cover & Control'!$C$19="Base",V126,IF('01 Cover & Control'!$C$19="Upside",V127,V128)) -> 55 | W129: =IF('01 Cover & Control'!$C$19="Base",W126,IF('01 Cover & Control'!$C$19="Upside",W127,W128)) -> 55 | X129: =SUM(T129:W129) -> 220 | Y129: =IF('01 Cover & Control'!$C$19="Base",Y126,IF('01 Cover & Control'!$C$19="Upside",Y127,Y128)) -> 55 | Z129: =IF('01 Cover & Control'!$C$19="Base",Z126,IF('01 Cover & Control'!$C$19="Upside",Z127,Z128)) -> 55 | AA129: =IF('01 Cover & Control'!$C$19="Base",AA126,IF('01 Cover & Control'!$C$19="Upside",AA127,AA128)) -> 55 | AB129: =IF('01 Cover & Control'!$C$19="Base",AB126,IF('01 Cover & Control'!$C$19="Upside",AB127,AB128)) -> 55 | AC129: =SUM(Y129:AB129) -> 220 | AD129: =IF('01 Cover & Control'!$C$19="Base",AD126,IF('01 Cover & Control'!$C$19="Upside",AD127,AD128)) -> 55 | AE129: =IF('01 Cover & Control'!$C$19="Base",AE126,IF('01 Cover & Control'!$C$19="Upside",AE127,AE128)) -> 55 | AF129: =IF('01 Cover & Control'!$C$19="Base",AF126,IF('01 Cover & Control'!$C$19="Upside",AF127,AF128)) -> 55 | AG129: =IF('01 Cover & Control'!$C$19="Base",AG126,IF('01 Cover & Control'!$C$19="Upside",AG127,AG128)) -> 55 | AH129: =SUM(AD129:AG129) -> 220 | AI129: =IF('01 Cover & Control'!$C$19="Base",AI126,IF('01 Cover & Control'!$C$19="Upside",AI127,AI128)) -> 55 | AJ129: =IF('01 Cover & Control'!$C$19="Base",AJ126,IF('01 Cover & Control'!$C$19="Upside",AJ127,AJ128)) -> 55 | AK129: =IF('01 Cover & Control'!$C$19="Base",AK126,IF('01 Cover & Control'!$C$19="Upside",AK127,AK128)) -> 55 | AL129: =IF('01 Cover & Control'!$C$19="Base",AL126,IF('01 Cover & Control'!$C$19="Upside",AL127,AL128)) -> 55 | AM129: =SUM(AI129:AL129) -> 220 | AN129: =IF('01 Cover & Control'!$C$19="Base",AN126,IF('01 Cover & Control'!$C$19="Upside",AN127,AN128)) -> 55 | AO129: =IF('01 Cover & Control'!$C$19="Base",AO126,IF('01 Cover & Control'!$C$19="Upside",AO127,AO128)) -> 55 | AP129: =IF('01 Cover & Control'!$C$19="Base",AP126,IF('01 Cover & Control'!$C$19="Upside",AP127,AP128)) -> 55 | AQ129: =IF('01 Cover & Control'!$C$19="Base",AQ126,IF('01 Cover & Control'!$C$19="Upside",AQ127,AQ128)) -> 55 | AR129: =SUM(AN129:AQ129) -> 220
B131: ✔ CHECK: IS Bps Ordering (Small > Mid > Institutional) | D131: Small deals must carry higher bps than mid; mid higher than institutional. | E131: — | F131: — | G131: — | H131: — | I131: =IF(AND(I119>I124,I124>I129),"PASS","WARN — V2 Reference (not used in V1)") -> PASS | J131: — | K131: — | L131: — | M131: — | N131: =IF(AND(N119>N124,N124>N129),"PASS","WARN — V2 Reference (not used in V1)") -> PASS | O131: — | P131: — | Q131: — | R131: — | S131: =IF(AND(S119>S124,S124>S129),"PASS","WARN — V2 Reference (not used in V1)") -> PASS | T131: — | U131: — | V131: — | W131: — | X131: =IF(AND(X119>X124,X124>X129),"PASS","WARN — V2 Reference (not used in V1)") -> PASS | Y131: — | Z131: — | AA131: — | AB131: — | AC131: =IF(AND(AC119>AC124,AC124>AC129),"PASS","WARN — V2 Reference (not used in V1)") -> PASS | AD131: — | AE131: — | AF131: — | AG131: — | AH131: =IF(AND(AH119>AH124,AH124>AH129),"PASS","WARN — V2 Reference (not used in V1)") -> PASS | AI131: — | AJ131: — | AK131: — | AL131: — | AM131: =IF(AND(AM119>AM124,AM124>AM129),"PASS","WARN — V2 Reference (not used in V1)") -> PASS | AN131: — | AO131: — | AP131: — | AQ131: — | AR131: =IF(AND(AR119>AR124,AR124>AR129),"PASS","WARN — V2 Reference (not used in V1)") -> PASS
A133: C2 — DEBT & EQUITY PLACEMENT FEES
B135: Debt Placement Bps — Acquisition Financing — Base | C135: bps | D135: MBA; internal contract norms. Typical range: 50–100 bps. | E135: 65 | F135: 65 | G135: 65 | H135: 65 | I135: =SUM(E135:H135) -> 260 | J135: 65 | K135: 65 | L135: 65 | M135: 65 | N135: =SUM(J135:M135) -> 260 | O135: 65 | P135: 65 | Q135: 65 | R135: 65 | S135: =SUM(O135:R135) -> 260 | T135: 65 | U135: 65 | V135: 65 | W135: 65 | X135: =SUM(T135:W135) -> 260 | Y135: 65 | Z135: 65 | AA135: 65 | AB135: 65 | AC135: =SUM(Y135:AB135) -> 260 | AD135: 65 | AE135: 65 | AF135: 65 | AG135: 65 | AH135: =SUM(AD135:AG135) -> 260 | AI135: 65 | AJ135: 65 | AK135: 65 | AL135: 65 | AM135: =SUM(AI135:AL135) -> 260 | AN135: 65 | AO135: 65 | AP135: 65 | AQ135: 65 | AR135: =SUM(AN135:AQ135) -> 260
B136: Debt Placement Bps — Acquisition Financing — Upside | E136: 70 | F136: 70 | G136: 70 | H136: 70 | I136: =SUM(E136:H136) -> 280 | J136: 70 | K136: 70 | L136: 70 | M136: 70 | N136: =SUM(J136:M136) -> 280 | O136: 70 | P136: 70 | Q136: 70 | R136: 70 | S136: =SUM(O136:R136) -> 280 | T136: 70 | U136: 70 | V136: 70 | W136: 70 | X136: =SUM(T136:W136) -> 280 | Y136: 70 | Z136: 70 | AA136: 70 | AB136: 70 | AC136: =SUM(Y136:AB136) -> 280 | AD136: 70 | AE136: 70 | AF136: 70 | AG136: 70 | AH136: =SUM(AD136:AG136) -> 280 | AI136: 70 | AJ136: 70 | AK136: 70 | AL136: 70 | AM136: =SUM(AI136:AL136) -> 280 | AN136: 70 | AO136: 70 | AP136: 70 | AQ136: 70 | AR136: =SUM(AN136:AQ136) -> 280
B137: Debt Placement Bps — Acquisition Financing — Downside | E137: 60 | F137: 60 | G137: 60 | H137: 60 | I137: =SUM(E137:H137) -> 240 | J137: 60 | K137: 60 | L137: 60 | M137: 60 | N137: =SUM(J137:M137) -> 240 | O137: 60 | P137: 60 | Q137: 60 | R137: 60 | S137: =SUM(O137:R137) -> 240 | T137: 60 | U137: 60 | V137: 60 | W137: 60 | X137: =SUM(T137:W137) -> 240 | Y137: 60 | Z137: 60 | AA137: 60 | AB137: 60 | AC137: =SUM(Y137:AB137) -> 240 | AD137: 60 | AE137: 60 | AF137: 60 | AG137: 60 | AH137: =SUM(AD137:AG137) -> 240 | AI137: 60 | AJ137: 60 | AK137: 60 | AL137: 60 | AM137: =SUM(AI137:AL137) -> 240 | AN137: 60 | AO137: 60 | AP137: 60 | AQ137: 60 | AR137: =SUM(AN137:AQ137) -> 240
...

Sheet 03 Operational Assumptions
A1: 03 | OPERATIONAL ASSUMPTIONS — FIRM-CONTROLLED DRIVERS
A2: Scenario-sensitive rows: Base / Upside / Downside / Active. Active rows link to Tab 01 C19. Static tables use different column layout (noted inline). | E2: ='01 Cover & Control'!C19 -> Base
B3: Assumption / Row | C3: Units | D3: Source / Notes | E3: 2023A Q1 | F3: 2023A Q2 | G3: 2023A Q3 | H3: 2023A Q4 | I3: 2023A Annual | J3: 2024A Q1 | K3: 2024A Q2 | L3: 2024A Q3 | M3: 2024A Q4 | N3: 2024A Annual | O3: 2025A Q1 | P3: 2025A Q2 | Q3: 2025A Q3 | R3: 2025A Q4 | S3: 2025A Annual | T3: 2026E Q1 | U3: 2026E Q2 | V3: 2026E Q3 | W3: 2026E Q4 | X3: 2026E Annual | Y3: 2027E Q1 | Z3: 2027E Q2 | AA3: 2027E Q3 | AB3: 2027E Q4 | AC3: 2027E Annual | AD3: 2028E Q1 | AE3: 2028E Q2 | AF3: 2028E Q3 | AG3: 2028E Q4 | AH3: 2028E Annual | AI3: 2029E Q1 | AJ3: 2029E Q2 | AK3: 2029E Q3 | AL3: 2029E Q4 | AM3: 2029E Annual | AN3: 2030E Q1 | AO3: 2030E Q2 | AP3: 2030E Q3 | AQ3: 2030E Q4 | AR3: 2030E Annual
A5: SECTION A — HEADCOUNT PLAN | EPE = Beginning HC + (Hires × Ramp Factor) − Attrition
A7: Beginning Headcount: input once per year (Q1 of each year). Hires & Attrition Rate: scenario-keyed quarterly inputs. Attrition rate applied to Beginning HC in the Producer Engine: Attrition = Rate × Beginning HC. Historical period: enter actuals. Forecast period: scenario-keyed inputs.
A9: LEASING — HEADCOUNT
B11: Beginning HC — Rainmaker | C11: # | D11: Input: actuals for hist period; forecast = prior yr ending HC. Used directly in EPE formula. | E11: 8 | I11: =SUM(E11:H11) -> 8 | N11: =SUM(J11:M11) -> 0 | S11: =SUM(O11:R11) -> 0 | X11: =SUM(T11:W11) -> 0 | AC11: =SUM(Y11:AB11) -> 0 | AH11: =SUM(AD11:AG11) -> 0 | AM11: =SUM(AI11:AL11) -> 0 | AR11: =SUM(AN11:AQ11) -> 0
B12: Gross Hires / Qtr — Rainmaker — Base | C12: #/qtr | D12: Scenario-keyed. Upside = faster hiring. Downside = slower/failed hiring. | E12: 0.5 | F12: 0.5 | G12: 0.5 | H12: 0.5 | I12: =SUM(E12:H12) -> 2 | J12: 0.5 | K12: 0.5 | L12: 0.5 | M12: 0.5 | N12: =SUM(J12:M12) -> 2 | O12: 0.5 | P12: 0.5 | Q12: 0.5 | R12: 0.5 | S12: =SUM(O12:R12) -> 2 | T12: 0.5 | U12: 0.5 | V12: 0.5 | W12: 0.5 | X12: =SUM(T12:W12) -> 2 | Y12: 0.5 | Z12: 0.5 | AA12: 0.5 | AB12: 0.5 | AC12: =SUM(Y12:AB12) -> 2 | AD12: 0.5 | AE12: 0.5 | AF12: 0.5 | AG12: 0.5 | AH12: =SUM(AD12:AG12) -> 2 | AI12: 0.5 | AJ12: 0.5 | AK12: 0.5 | AL12: 0.5 | AM12: =SUM(AI12:AL12) -> 2 | AN12: 0.5 | AO12: 0.5 | AP12: 0.5 | AQ12: 0.5 | AR12: =SUM(AN12:AQ12) -> 2
B13: Gross Hires / Qtr — Rainmaker — Upside | E13: 0.55 | F13: 0.55 | G13: 0.55 | H13: 0.55 | I13: =SUM(E13:H13) -> 2.2 | J13: 0.55 | K13: 0.55 | L13: 0.55 | M13: 0.55 | N13: =SUM(J13:M13) -> 2.2 | O13: 0.55 | P13: 0.55 | Q13: 0.55 | R13: 0.55 | S13: =SUM(O13:R13) -> 2.2 | T13: 0.55 | U13: 0.55 | V13: 0.55 | W13: 0.55 | X13: =SUM(T13:W13) -> 2.2 | Y13: 0.55 | Z13: 0.55 | AA13: 0.55 | AB13: 0.55 | AC13: =SUM(Y13:AB13) -> 2.2 | AD13: 0.55 | AE13: 0.55 | AF13: 0.55 | AG13: 0.55 | AH13: =SUM(AD13:AG13) -> 2.2 | AI13: 0.55 | AJ13: 0.55 | AK13: 0.55 | AL13: 0.55 | AM13: =SUM(AI13:AL13) -> 2.2 | AN13: 0.55 | AO13: 0.55 | AP13: 0.55 | AQ13: 0.55 | AR13: =SUM(AN13:AQ13) -> 2.2
B14: Gross Hires / Qtr — Rainmaker — Downside | E14: 0.42 | F14: 0.42 | G14: 0.42 | H14: 0.42 | I14: =SUM(E14:H14) -> 1.68 | J14: 0.42 | K14: 0.42 | L14: 0.42 | M14: 0.42 | N14: =SUM(J14:M14) -> 1.68 | O14: 0.42 | P14: 0.42 | Q14: 0.42 | R14: 0.42 | S14: =SUM(O14:R14) -> 1.68 | T14: 0.42 | U14: 0.42 | V14: 0.42 | W14: 0.42 | X14: =SUM(T14:W14) -> 1.68 | Y14: 0.42 | Z14: 0.42 | AA14: 0.42 | AB14: 0.42 | AC14: =SUM(Y14:AB14) -> 1.68 | AD14: 0.42 | AE14: 0.42 | AF14: 0.42 | AG14: 0.42 | AH14: =SUM(AD14:AG14) -> 1.68 | AI14: 0.42 | AJ14: 0.42 | AK14: 0.42 | AL14: 0.42 | AM14: =SUM(AI14:AL14) -> 1.68 | AN14: 0.42 | AO14: 0.42 | AP14: 0.42 | AQ14: 0.42 | AR14: =SUM(AN14:AQ14) -> 1.68
B15: Gross Hires / Qtr — Rainmaker — ★ ACTIVE | E15: =IF('01 Cover & Control'!$C$19="Base",E12,IF('01 Cover & Control'!$C$19="Upside",E13,E14)) -> 0.5 | F15: =IF('01 Cover & Control'!$C$19="Base",F12,IF('01 Cover & Control'!$C$19="Upside",F13,F14)) -> 0.5 | G15: =IF('01 Cover & Control'!$C$19="Base",G12,IF('01 Cover & Control'!$C$19="Upside",G13,G14)) -> 0.5 | H15: =IF('01 Cover & Control'!$C$19="Base",H12,IF('01 Cover & Control'!$C$19="Upside",H13,H14)) -> 0.5 | I15: =SUM(E15:H15) -> 2 | J15: =IF('01 Cover & Control'!$C$19="Base",J12,IF('01 Cover & Control'!$C$19="Upside",J13,J14)) -> 0.5 | K15: =IF('01 Cover & Control'!$C$19="Base",K12,IF('01 Cover & Control'!$C$19="Upside",K13,K14)) -> 0.5 | L15: =IF('01 Cover & Control'!$C$19="Base",L12,IF('01 Cover & Control'!$C$19="Upside",L13,L14)) -> 0.5 | M15: =IF('01 Cover & Control'!$C$19="Base",M12,IF('01 Cover & Control'!$C$19="Upside",M13,M14)) -> 0.5 | N15: =SUM(J15:M15) -> 2 | O15: =IF('01 Cover & Control'!$C$19="Base",O12,IF('01 Cover & Control'!$C$19="Upside",O13,O14)) -> 0.5 | P15: =IF('01 Cover & Control'!$C$19="Base",P12,IF('01 Cover & Control'!$C$19="Upside",P13,P14)) -> 0.5 | Q15: =IF('01 Cover & Control'!$C$19="Base",Q12,IF('01 Cover & Control'!$C$19="Upside",Q13,Q14)) -> 0.5 | R15: =IF('01 Cover & Control'!$C$19="Base",R12,IF('01 Cover & Control'!$C$19="Upside",R13,R14)) -> 0.5 | S15: =SUM(O15:R15) -> 2 | T15: =IF('01 Cover & Control'!$C$19="Base",T12,IF('01 Cover & Control'!$C$19="Upside",T13,T14)) -> 0.5 | U15: =IF('01 Cover & Control'!$C$19="Base",U12,IF('01 Cover & Control'!$C$19="Upside",U13,U14)) -> 0.5 | V15: =IF('01 Cover & Control'!$C$19="Base",V12,IF('01 Cover & Control'!$C$19="Upside",V13,V14)) -> 0.5 | W15: =IF('01 Cover & Control'!$C$19="Base",W12,IF('01 Cover & Control'!$C$19="Upside",W13,W14)) -> 0.5 | X15: =SUM(T15:W15) -> 2 | Y15: =IF('01 Cover & Control'!$C$19="Base",Y12,IF('01 Cover & Control'!$C$19="Upside",Y13,Y14)) -> 0.5 | Z15: =IF('01 Cover & Control'!$C$19="Base",Z12,IF('01 Cover & Control'!$C$19="Upside",Z13,Z14)) -> 0.5 | AA15: =IF('01 Cover & Control'!$C$19="Base",AA12,IF('01 Cover & Control'!$C$19="Upside",AA13,AA14)) -> 0.5 | AB15: =IF('01 Cover & Control'!$C$19="Base",AB12,IF('01 Cover & Control'!$C$19="Upside",AB13,AB14)) -> 0.5 | AC15: =SUM(Y15:AB15) -> 2 | AD15: =IF('01 Cover & Control'!$C$19="Base",AD12,IF('01 Cover & Control'!$C$19="Upside",AD13,AD14)) -> 0.5 | AE15: =IF('01 Cover & Control'!$C$19="Base",AE12,IF('01 Cover & Control'!$C$19="Upside",AE13,AE14)) -> 0.5 | AF15: =IF('01 Cover & Control'!$C$19="Base",AF12,IF('01 Cover & Control'!$C$19="Upside",AF13,AF14)) -> 0.5 | AG15: =IF('01 Cover & Control'!$C$19="Base",AG12,IF('01 Cover & Control'!$C$19="Upside",AG13,AG14)) -> 0.5 | AH15: =SUM(AD15:AG15) -> 2 | AI15: =IF('01 Cover & Control'!$C$19="Base",AI12,IF('01 Cover & Control'!$C$19="Upside",AI13,AI14)) -> 0.5 | AJ15: =IF('01 Cover & Control'!$C$19="Base",AJ12,IF('01 Cover & Control'!$C$19="Upside",AJ13,AJ14)) -> 0.5 | AK15: =IF('01 Cover & Control'!$C$19="Base",AK12,IF('01 Cover & Control'!$C$19="Upside",AK13,AK14)) -> 0.5 | AL15: =IF('01 Cover & Control'!$C$19="Base",AL12,IF('01 Cover & Control'!$C$19="Upside",AL13,AL14)) -> 0.5 | AM15: =SUM(AI15:AL15) -> 2 | AN15: =IF('01 Cover & Control'!$C$19="Base",AN12,IF('01 Cover & Control'!$C$19="Upside",AN13,AN14)) -> 0.5 | AO15: =IF('01 Cover & Control'!$C$19="Base",AO12,IF('01 Cover & Control'!$C$19="Upside",AO13,AO14)) -> 0.5 | AP15: =IF('01 Cover & Control'!$C$19="Base",AP12,IF('01 Cover & Control'!$C$19="Upside",AP13,AP14)) -> 0.5 | AQ15: =IF('01 Cover & Control'!$C$19="Base",AQ12,IF('01 Cover & Control'!$C$19="Upside",AQ13,AQ14)) -> 0.5 | AR15: =SUM(AN15:AQ15) -> 2
B16: Attrition Rate — Rainmaker — Base | C16: %/qtr | D16: Quarterly attrition rate applied to Beginning HC. Upside = lower attrition (strong market). Downside = higher (competitors poach). | E16: 0.02 | F16: 0.02 | G16: 0.02 | H16: 0.02 | I16: =SUM(E16:H16) -> 0.08 | J16: 0.02 | K16: 0.02 | L16: 0.02 | M16: 0.02 | N16: =SUM(J16:M16) -> 0.08 | O16: 0.02 | P16: 0.02 | Q16: 0.02 | R16: 0.02 | S16: =SUM(O16:R16) -> 0.08 | T16: 0.02 | U16: 0.02 | V16: 0.02 | W16: 0.02 | X16: =SUM(T16:W16) -> 0.08 | Y16: 0.02 | Z16: 0.02 | AA16: 0.02 | AB16: 0.02 | AC16: =SUM(Y16:AB16) -> 0.08 | AD16: 0.02 | AE16: 0.02 | AF16: 0.02 | AG16: 0.02 | AH16: =SUM(AD16:AG16) -> 0.08 | AI16: 0.02 | AJ16: 0.02 | AK16: 0.02 | AL16: 0.02 | AM16: =SUM(AI16:AL16) -> 0.08 | AN16: 0.02 | AO16: 0.02 | AP16: 0.02 | AQ16: 0.02 | AR16: =SUM(AN16:AQ16) -> 0.08
B17: Attrition Rate — Rainmaker — Upside | E17: 0.018 | F17: 0.018 | G17: 0.018 | H17: 0.018 | I17: =SUM(E17:H17) -> 0.072 | J17: 0.018 | K17: 0.018 | L17: 0.018 | M17: 0.018 | N17: =SUM(J17:M17) -> 0.072 | O17: 0.018 | P17: 0.018 | Q17: 0.018 | R17: 0.018 | S17: =SUM(O17:R17) -> 0.072 | T17: 0.018 | U17: 0.018 | V17: 0.018 | W17: 0.018 | X17: =SUM(T17:W17) -> 0.072 | Y17: 0.018 | Z17: 0.018 | AA17: 0.018 | AB17: 0.018 | AC17: =SUM(Y17:AB17) -> 0.072 | AD17: 0.018 | AE17: 0.018 | AF17: 0.018 | AG17: 0.018 | AH17: =SUM(AD17:AG17) -> 0.072 | AI17: 0.018 | AJ17: 0.018 | AK17: 0.018 | AL17: 0.018 | AM17: =SUM(AI17:AL17) -> 0.072 | AN17: 0.018 | AO17: 0.018 | AP17: 0.018 | AQ17: 0.018 | AR17: =SUM(AN17:AQ17) -> 0.072
B18: Attrition Rate — Rainmaker — Downside | E18: 0.03 | F18: 0.03 | G18: 0.03 | H18: 0.03 | I18: =SUM(E18:H18) -> 0.12 | J18: 0.03 | K18: 0.03 | L18: 0.03 | M18: 0.03 | N18: =SUM(J18:M18) -> 0.12 | O18: 0.03 | P18: 0.03 | Q18: 0.03 | R18: 0.03 | S18: =SUM(O18:R18) -> 0.12 | T18: 0.03 | U18: 0.03 | V18: 0.03 | W18: 0.03 | X18: =SUM(T18:W18) -> 0.12 | Y18: 0.03 | Z18: 0.03 | AA18: 0.03 | AB18: 0.03 | AC18: =SUM(Y18:AB18) -> 0.12 | AD18: 0.03 | AE18: 0.03 | AF18: 0.03 | AG18: 0.03 | AH18: =SUM(AD18:AG18) -> 0.12 | AI18: 0.03 | AJ18: 0.03 | AK18: 0.03 | AL18: 0.03 | AM18: =SUM(AI18:AL18) -> 0.12 | AN18: 0.03 | AO18: 0.03 | AP18: 0.03 | AQ18: 0.03 | AR18: =SUM(AN18:AQ18) -> 0.12
B19: Attrition Rate — Rainmaker — ★ ACTIVE | E19: =IF('01 Cover & Control'!$C$19="Base",E16,IF('01 Cover & Control'!$C$19="Upside",E17,E18)) -> 0.02 | F19: =IF('01 Cover & Control'!$C$19="Base",F16,IF('01 Cover & Control'!$C$19="Upside",F17,F18)) -> 0.02 | G19: =IF('01 Cover & Control'!$C$19="Base",G16,IF('01 Cover & Control'!$C$19="Upside",G17,G18)) -> 0.02 | H19: =IF('01 Cover & Control'!$C$19="Base",H16,IF('01 Cover & Control'!$C$19="Upside",H17,H18)) -> 0.02 | I19: =AVERAGE(E19:H19) -> 0.02 | J19: =IF('01 Cover & Control'!$C$19="Base",J16,IF('01 Cover & Control'!$C$19="Upside",J17,J18)) -> 0.02 | K19: =IF('01 Cover & Control'!$C$19="Base",K16,IF('01 Cover & Control'!$C$19="Upside",K17,K18)) -> 0.02 | L19: =IF('01 Cover & Control'!$C$19="Base",L16,IF('01 Cover & Control'!$C$19="Upside",L17,L18)) -> 0.02 | M19: =IF('01 Cover & Control'!$C$19="Base",M16,IF('01 Cover & Control'!$C$19="Upside",M17,M18)) -> 0.02 | N19: =AVERAGE(J19:M19) -> 0.02 | O19: =IF('01 Cover & Control'!$C$19="Base",O16,IF('01 Cover & Control'!$C$19="Upside",O17,O18)) -> 0.02 | P19: =IF('01 Cover & Control'!$C$19="Base",P16,IF('01 Cover & Control'!$C$19="Upside",P17,P18)) -> 0.02 | Q19: =IF('01 Cover & Control'!$C$19="Base",Q16,IF('01 Cover & Control'!$C$19="Upside",Q17,Q18)) -> 0.02 | R19: =IF('01 Cover & Control'!$C$19="Base",R16,IF('01 Cover & Control'!$C$19="Upside",R17,R18)) -> 0.02 | S19: =AVERAGE(O19:R19) -> 0.02 | T19: =IF('01 Cover & Control'!$C$19="Base",T16,IF('01 Cover & Control'!$C$19="Upside",T17,T18)) -> 0.02 | U19: =IF('01 Cover & Control'!$C$19="Base",U16,IF('01 Cover & Control'!$C$19="Upside",U17,U18)) -> 0.02 | V19: =IF('01 Cover & Control'!$C$19="Base",V16,IF('01 Cover & Control'!$C$19="Upside",V17,V18)) -> 0.02 | W19: =IF('01 Cover & Control'!$C$19="Base",W16,IF('01 Cover & Control'!$C$19="Upside",W17,W18)) -> 0.02 | X19: =AVERAGE(T19:W19) -> 0.02 | Y19: =IF('01 Cover & Control'!$C$19="Base",Y16,IF('01 Cover & Control'!$C$19="Upside",Y17,Y18)) -> 0.02 | Z19: =IF('01 Cover & Control'!$C$19="Base",Z16,IF('01 Cover & Control'!$C$19="Upside",Z17,Z18)) -> 0.02 | AA19: =IF('01 Cover & Control'!$C$19="Base",AA16,IF('01 Cover & Control'!$C$19="Upside",AA17,AA18)) -> 0.02 | AB19: =IF('01 Cover & Control'!$C$19="Base",AB16,IF('01 Cover & Control'!$C$19="Upside",AB17,AB18)) -> 0.02 | AC19: =AVERAGE(Y19:AB19) -> 0.02 | AD19: =IF('01 Cover & Control'!$C$19="Base",AD16,IF('01 Cover & Control'!$C$19="Upside",AD17,AD18)) -> 0.02 | AE19: =IF('01 Cover & Control'!$C$19="Base",AE16,IF('01 Cover & Control'!$C$19="Upside",AE17,AE18)) -> 0.02 | AF19: =IF('01 Cover & Control'!$C$19="Base",AF16,IF('01 Cover & Control'!$C$19="Upside",AF17,AF18)) -> 0.02 | AG19: =IF('01 Cover & Control'!$C$19="Base",AG16,IF('01 Cover & Control'!$C$19="Upside",AG17,AG18)) -> 0.02 | AH19: =AVERAGE(AD19:AG19) -> 0.02 | AI19: =IF('01 Cover & Control'!$C$19="Base",AI16,IF('01 Cover & Control'!$C$19="Upside",AI17,AI18)) -> 0.02 | AJ19: =IF('01 Cover & Control'!$C$19="Base",AJ16,IF('01 Cover & Control'!$C$19="Upside",AJ17,AJ18)) -> 0.02 | AK19: =IF('01 Cover & Control'!$C$19="Base",AK16,IF('01 Cover & Control'!$C$19="Upside",AK17,AK18)) -> 0.02 | AL19: =IF('01 Cover & Control'!$C$19="Base",AL16,IF('01 Cover & Control'!$C$19="Upside",AL17,AL18)) -> 0.02 | AM19: =AVERAGE(AI19:AL19) -> 0.02 | AN19: =IF('01 Cover & Control'!$C$19="Base",AN16,IF('01 Cover & Control'!$C$19="Upside",AN17,AN18)) -> 0.02 | AO19: =IF('01 Cover & Control'!$C$19="Base",AO16,IF('01 Cover & Control'!$C$19="Upside",AO17,AO18)) -> 0.02 | AP19: =IF('01 Cover & Control'!$C$19="Base",AP16,IF('01 Cover & Control'!$C$19="Upside",AP17,AP18)) -> 0.02 | AQ19: =IF('01 Cover & Control'!$C$19="Base",AQ16,IF('01 Cover & Control'!$C$19="Upside",AQ17,AQ18)) -> 0.02 | AR19: =AVERAGE(AN19:AQ19) -> 0.02
B21: Beginning HC — Core | C21: # | D21: Input: actuals for hist period; forecast = prior yr ending HC. Used directly in EPE formula. | E21: 14 | I21: =SUM(E21:H21) -> 14 | N21: =SUM(J21:M21) -> 0 | S21: =SUM(O21:R21) -> 0 | X21: =SUM(T21:W21) -> 0 | AC21: =SUM(Y21:AB21) -> 0 | AH21: =SUM(AD21:AG21) -> 0 | AM21: =SUM(AI21:AL21) -> 0 | AR21: =SUM(AN21:AQ21) -> 0
B22: Gross Hires / Qtr — Core — Base | C22: #/qtr | D22: Scenario-keyed. Upside = faster hiring. Downside = slower/failed hiring. | E22: 1.5 | F22: 1.5 | G22: 1.5 | H22: 1.5 | I22: =SUM(E22:H22) -> 6 | J22: 1.5 | K22: 1.5 | L22: 1.5 | M22: 1.5 | N22: =SUM(J22:M22) -> 6 | O22: 1.5 | P22: 1.5 | Q22: 1.5 | R22: 1.5 | S22: =SUM(O22:R22) -> 6 | T22: 1.5 | U22: 1.5 | V22: 1.5 | W22: 1.5 | X22: =SUM(T22:W22) -> 6 | Y22: 1.5 | Z22: 1.5 | AA22: 1.5 | AB22: 1.5 | AC22: =SUM(Y22:AB22) -> 6 | AD22: 1.5 | AE22: 1.5 | AF22: 1.5 | AG22: 1.5 | AH22: =SUM(AD22:AG22) -> 6 | AI22: 1.5 | AJ22: 1.5 | AK22: 1.5 | AL22: 1.5 | AM22: =SUM(AI22:AL22) -> 6 | AN22: 1.5 | AO22: 1.5 | AP22: 1.5 | AQ22: 1.5 | AR22: =SUM(AN22:AQ22) -> 6
B23: Gross Hires / Qtr — Core — Upside | E23: 1.65 | F23: 1.65 | G23: 1.65 | H23: 1.65 | I23: =SUM(E23:H23) -> 6.6 | J23: 1.65 | K23: 1.65 | L23: 1.65 | M23: 1.65 | N23: =SUM(J23:M23) -> 6.6 | O23: 1.65 | P23: 1.65 | Q23: 1.65 | R23: 1.65 | S23: =SUM(O23:R23) -> 6.6 | T23: 1.65 | U23: 1.65 | V23: 1.65 | W23: 1.65 | X23: =SUM(T23:W23) -> 6.6 | Y23: 1.65 | Z23: 1.65 | AA23: 1.65 | AB23: 1.65 | AC23: =SUM(Y23:AB23) -> 6.6 | AD23: 1.65 | AE23: 1.65 | AF23: 1.65 | AG23: 1.65 | AH23: =SUM(AD23:AG23) -> 6.6 | AI23: 1.65 | AJ23: 1.65 | AK23: 1.65 | AL23: 1.65 | AM23: =SUM(AI23:AL23) -> 6.6 | AN23: 1.65 | AO23: 1.65 | AP23: 1.65 | AQ23: 1.65 | AR23: =SUM(AN23:AQ23) -> 6.6
B24: Gross Hires / Qtr — Core — Downside | E24: 1.28 | F24: 1.28 | G24: 1.28 | H24: 1.28 | I24: =SUM(E24:H24) -> 5.12 | J24: 1.28 | K24: 1.28 | L24: 1.28 | M24: 1.28 | N24: =SUM(J24:M24) -> 5.12 | O24: 1.28 | P24: 1.28 | Q24: 1.28 | R24: 1.28 | S24: =SUM(O24:R24) -> 5.12 | T24: 1.28 | U24: 1.28 | V24: 1.28 | W24: 1.28 | X24: =SUM(T24:W24) -> 5.12 | Y24: 1.28 | Z24: 1.28 | AA24: 1.28 | AB24: 1.28 | AC24: =SUM(Y24:AB24) -> 5.12 | AD24: 1.28 | AE24: 1.28 | AF24: 1.28 | AG24: 1.28 | AH24: =SUM(AD24:AG24) -> 5.12 | AI24: 1.28 | AJ24: 1.28 | AK24: 1.28 | AL24: 1.28 | AM24: =SUM(AI24:AL24) -> 5.12 | AN24: 1.28 | AO24: 1.28 | AP24: 1.28 | AQ24: 1.28 | AR24: =SUM(AN24:AQ24) -> 5.12
B25: Gross Hires / Qtr — Core — ★ ACTIVE | E25: =IF('01 Cover & Control'!$C$19="Base",E22,IF('01 Cover & Control'!$C$19="Upside",E23,E24)) -> 1.5 | F25: =IF('01 Cover & Control'!$C$19="Base",F22,IF('01 Cover & Control'!$C$19="Upside",F23,F24)) -> 1.5 | G25: =IF('01 Cover & Control'!$C$19="Base",G22,IF('01 Cover & Control'!$C$19="Upside",G23,G24)) -> 1.5 | H25: =IF('01 Cover & Control'!$C$19="Base",H22,IF('01 Cover & Control'!$C$19="Upside",H23,H24)) -> 1.5 | I25: =SUM(E25:H25) -> 6 | J25: =IF('01 Cover & Control'!$C$19="Base",J22,IF('01 Cover & Control'!$C$19="Upside",J23,J24)) -> 1.5 | K25: =IF('01 Cover & Control'!$C$19="Base",K22,IF('01 Cover & Control'!$C$19="Upside",K23,K24)) -> 1.5 | L25: =IF('01 Cover & Control'!$C$19="Base",L22,IF('01 Cover & Control'!$C$19="Upside",L23,L24)) -> 1.5 | M25: =IF('01 Cover & Control'!$C$19="Base",M22,IF('01 Cover & Control'!$C$19="Upside",M23,M24)) -> 1.5 | N25: =SUM(J25:M25) -> 6 | O25: =IF('01 Cover & Control'!$C$19="Base",O22,IF('01 Cover & Control'!$C$19="Upside",O23,O24)) -> 1.5 | P25: =IF('01 Cover & Control'!$C$19="Base",P22,IF('01 Cover & Control'!$C$19="Upside",P23,P24)) -> 1.5 | Q25: =IF('01 Cover & Control'!$C$19="Base",Q22,IF('01 Cover & Control'!$C$19="Upside",Q23,Q24)) -> 1.5 | R25: =IF('01 Cover & Control'!$C$19="Base",R22,IF('01 Cover & Control'!$C$19="Upside",R23,R24)) -> 1.5 | S25: =SUM(O25:R25) -> 6 | T25: =IF('01 Cover & Control'!$C$19="Base",T22,IF('01 Cover & Control'!$C$19="Upside",T23,T24)) -> 1.5 | U25: =IF('01 Cover & Control'!$C$19="Base",U22,IF('01 Cover & Control'!$C$19="Upside",U23,U24)) -> 1.5 | V25: =IF('01 Cover & Control'!$C$19="Base",V22,IF('01 Cover & Control'!$C$19="Upside",V23,V24)) -> 1.5 | W25: =IF('01 Cover & Control'!$C$19="Base",W22,IF('01 Cover & Control'!$C$19="Upside",W23,W24)) -> 1.5 | X25: =SUM(T25:W25) -> 6 | Y25: =IF('01 Cover & Control'!$C$19="Base",Y22,IF('01 Cover & Control'!$C$19="Upside",Y23,Y24)) -> 1.5 | Z25: =IF('01 Cover & Control'!$C$19="Base",Z22,IF('01 Cover & Control'!$C$19="Upside",Z23,Z24)) -> 1.5 | AA25: =IF('01 Cover & Control'!$C$19="Base",AA22,IF('01 Cover & Control'!$C$19="Upside",AA23,AA24)) -> 1.5 | AB25: =IF('01 Cover & Control'!$C$19="Base",AB22,IF('01 Cover & Control'!$C$19="Upside",AB23,AB24)) -> 1.5 | AC25: =SUM(Y25:AB25) -> 6 | AD25: =IF('01 Cover & Control'!$C$19="Base",AD22,IF('01 Cover & Control'!$C$19="Upside",AD23,AD24)) -> 1.5 | AE25: =IF('01 Cover & Control'!$C$19="Base",AE22,IF('01 Cover & Control'!$C$19="Upside",AE23,AE24)) -> 1.5 | AF25: =IF('01 Cover & Control'!$C$19="Base",AF22,IF('01 Cover & Control'!$C$19="Upside",AF23,AF24)) -> 1.5 | AG25: =IF('01 Cover & Control'!$C$19="Base",AG22,IF('01 Cover & Control'!$C$19="Upside",AG23,AG24)) -> 1.5 | AH25: =SUM(AD25:AG25) -> 6 | AI25: =IF('01 Cover & Control'!$C$19="Base",AI22,IF('01 Cover & Control'!$C$19="Upside",AI23,AI24)) -> 1.5 | AJ25: =IF('01 Cover & Control'!$C$19="Base",AJ22,IF('01 Cover & Control'!$C$19="Upside",AJ23,AJ24)) -> 1.5 | AK25: =IF('01 Cover & Control'!$C$19="Base",AK22,IF('01 Cover & Control'!$C$19="Upside",AK23,AK24)) -> 1.5 | AL25: =IF('01 Cover & Control'!$C$19="Base",AL22,IF('01 Cover & Control'!$C$19="Upside",AL23,AL24)) -> 1.5 | AM25: =SUM(AI25:AL25) -> 6 | AN25: =IF('01 Cover & Control'!$C$19="Base",AN22,IF('01 Cover & Control'!$C$19="Upside",AN23,AN24)) -> 1.5 | AO25: =IF('01 Cover & Control'!$C$19="Base",AO22,IF('01 Cover & Control'!$C$19="Upside",AO23,AO24)) -> 1.5 | AP25: =IF('01 Cover & Control'!$C$19="Base",AP22,IF('01 Cover & Control'!$C$19="Upside",AP23,AP24)) -> 1.5 | AQ25: =IF('01 Cover & Control'!$C$19="Base",AQ22,IF('01 Cover & Control'!$C$19="Upside",AQ23,AQ24)) -> 1.5 | AR25: =SUM(AN25:AQ25) -> 6
B26: Attrition Rate — Core — Base | C26: %/qtr | D26: Quarterly attrition rate applied to Beginning HC. Upside = lower attrition (strong market). Downside = higher (competitors poach). | E26: 0.04 | F26: 0.04 | G26: 0.04 | H26: 0.04 | I26: =SUM(E26:H26) -> 0.16 | J26: 0.04 | K26: 0.04 | L26: 0.04 | M26: 0.04 | N26: =SUM(J26:M26) -> 0.16 | O26: 0.04 | P26: 0.04 | Q26: 0.04 | R26: 0.04 | S26: =SUM(O26:R26) -> 0.16 | T26: 0.04 | U26: 0.04 | V26: 0.04 | W26: 0.04 | X26: =SUM(T26:W26) -> 0.16 | Y26: 0.04 | Z26: 0.04 | AA26: 0.04 | AB26: 0.04 | AC26: =SUM(Y26:AB26) -> 0.16 | AD26: 0.04 | AE26: 0.04 | AF26: 0.04 | AG26: 0.04 | AH26: =SUM(AD26:AG26) -> 0.16 | AI26: 0.04 | AJ26: 0.04 | AK26: 0.04 | AL26: 0.04 | AM26: =SUM(AI26:AL26) -> 0.16 | AN26: 0.04 | AO26: 0.04 | AP26: 0.04 | AQ26: 0.04 | AR26: =SUM(AN26:AQ26) -> 0.16
B27: Attrition Rate — Core — Upside | E27: 0.035 | F27: 0.035 | G27: 0.035 | H27: 0.035 | I27: =SUM(E27:H27) -> 0.14 | J27: 0.035 | K27: 0.035 | L27: 0.035 | M27: 0.035 | N27: =SUM(J27:M27) -> 0.14 | O27: 0.035 | P27: 0.035 | Q27: 0.035 | R27: 0.035 | S27: =SUM(O27:R27) -> 0.14 | T27: 0.035 | U27: 0.035 | V27: 0.035 | W27: 0.035 | X27: =SUM(T27:W27) -> 0.14 | Y27: 0.035 | Z27: 0.035 | AA27: 0.035 | AB27: 0.035 | AC27: =SUM(Y27:AB27) -> 0.14 | AD27: 0.035 | AE27: 0.035 | AF27: 0.035 | AG27: 0.035 | AH27: =SUM(AD27:AG27) -> 0.14 | AI27: 0.035 | AJ27: 0.035 | AK27: 0.035 | AL27: 0.035 | AM27: =SUM(AI27:AL27) -> 0.14 | AN27: 0.035 | AO27: 0.035 | AP27: 0.035 | AQ27: 0.035 | AR27: =SUM(AN27:AQ27) -> 0.14
B28: Attrition Rate — Core — Downside | E28: 0.055 | F28: 0.055 | G28: 0.055 | H28: 0.055 | I28: =SUM(E28:H28) -> 0.22 | J28: 0.055 | K28: 0.055 | L28: 0.055 | M28: 0.055 | N28: =SUM(J28:M28) -> 0.22 | O28: 0.055 | P28: 0.055 | Q28: 0.055 | R28: 0.055 | S28: =SUM(O28:R28) -> 0.22 | T28: 0.055 | U28: 0.055 | V28: 0.055 | W28: 0.055 | X28: =SUM(T28:W28) -> 0.22 | Y28: 0.055 | Z28: 0.055 | AA28: 0.055 | AB28: 0.055 | AC28: =SUM(Y28:AB28) -> 0.22 | AD28: 0.055 | AE28: 0.055 | AF28: 0.055 | AG28: 0.055 | AH28: =SUM(AD28:AG28) -> 0.22 | AI28: 0.055 | AJ28: 0.055 | AK28: 0.055 | AL28: 0.055 | AM28: =SUM(AI28:AL28) -> 0.22 | AN28: 0.055 | AO28: 0.055 | AP28: 0.055 | AQ28: 0.055 | AR28: =SUM(AN28:AQ28) -> 0.22
B29: Attrition Rate — Core — ★ ACTIVE | E29: =IF('01 Cover & Control'!$C$19="Base",E26,IF('01 Cover & Control'!$C$19="Upside",E27,E28)) -> 0.04 | F29: =IF('01 Cover & Control'!$C$19="Base",F26,IF('01 Cover & Control'!$C$19="Upside",F27,F28)) -> 0.04 | G29: =IF('01 Cover & Control'!$C$19="Base",G26,IF('01 Cover & Control'!$C$19="Upside",G27,G28)) -> 0.04 | H29: =IF('01 Cover & Control'!$C$19="Base",H26,IF('01 Cover & Control'!$C$19="Upside",H27,H28)) -> 0.04 | I29: =AVERAGE(E29:H29) -> 0.04 | J29: =IF('01 Cover & Control'!$C$19="Base",J26,IF('01 Cover & Control'!$C$19="Upside",J27,J28)) -> 0.04 | K29: =IF('01 Cover & Control'!$C$19="Base",K26,IF('01 Cover & Control'!$C$19="Upside",K27,K28)) -> 0.04 | L29: =IF('01 Cover & Control'!$C$19="Base",L26,IF('01 Cover & Control'!$C$19="Upside",L27,L28)) -> 0.04 | M29: =IF('01 Cover & Control'!$C$19="Base",M26,IF('01 Cover & Control'!$C$19="Upside",M27,M28)) -> 0.04 | N29: =AVERAGE(J29:M29) -> 0.04 | O29: =IF('01 Cover & Control'!$C$19="Base",O26,IF('01 Cover & Control'!$C$19="Upside",O27,O28)) -> 0.04 | P29: =IF('01 Cover & Control'!$C$19="Base",P26,IF('01 Cover & Control'!$C$19="Upside",P27,P28)) -> 0.04 | Q29: =IF('01 Cover & Control'!$C$19="Base",Q26,IF('01 Cover & Control'!$C$19="Upside",Q27,Q28)) -> 0.04 | R29: =IF('01 Cover & Control'!$C$19="Base",R26,IF('01 Cover & Control'!$C$19="Upside",R27,R28)) -> 0.04 | S29: =AVERAGE(O29:R29) -> 0.04 | T29: =IF('01 Cover & Control'!$C$19="Base",T26,IF('01 Cover & Control'!$C$19="Upside",T27,T28)) -> 0.04 | U29: =IF('01 Cover & Control'!$C$19="Base",U26,IF('01 Cover & Control'!$C$19="Upside",U27,U28)) -> 0.04 | V29: =IF('01 Cover & Control'!$C$19="Base",V26,IF('01 Cover & Control'!$C$19="Upside",V27,V28)) -> 0.04 | W29: =IF('01 Cover & Control'!$C$19="Base",W26,IF('01 Cover & Control'!$C$19="Upside",W27,W28)) -> 0.04 | X29: =AVERAGE(T29:W29) -> 0.04 | Y29: =IF('01 Cover & Control'!$C$19="Base",Y26,IF('01 Cover & Control'!$C$19="Upside",Y27,Y28)) -> 0.04 | Z29: =IF('01 Cover & Control'!$C$19="Base",Z26,IF('01 Cover & Control'!$C$19="Upside",Z27,Z28)) -> 0.04 | AA29: =IF('01 Cover & Control'!$C$19="Base",AA26,IF('01 Cover & Control'!$C$19="Upside",AA27,AA28)) -> 0.04 | AB29: =IF('01 Cover & Control'!$C$19="Base",AB26,IF('01 Cover & Control'!$C$19="Upside",AB27,AB28)) -> 0.04 | AC29: =AVERAGE(Y29:AB29) -> 0.04 | AD29: =IF('01 Cover & Control'!$C$19="Base",AD26,IF('01 Cover & Control'!$C$19="Upside",AD27,AD28)) -> 0.04 | AE29: =IF('01 Cover & Control'!$C$19="Base",AE26,IF('01 Cover & Control'!$C$19="Upside",AE27,AE28)) -> 0.04 | AF29: =IF('01 Cover & Control'!$C$19="Base",AF26,IF('01 Cover & Control'!$C$19="Upside",AF27,AF28)) -> 0.04 | AG29: =IF('01 Cover & Control'!$C$19="Base",AG26,IF('01 Cover & Control'!$C$19="Upside",AG27,AG28)) -> 0.04 | AH29: =AVERAGE(AD29:AG29) -> 0.04 | AI29: =IF('01 Cover & Control'!$C$19="Base",AI26,IF('01 Cover & Control'!$C$19="Upside",AI27,AI28)) -> 0.04 | AJ29: =IF('01 Cover & Control'!$C$19="Base",AJ26,IF('01 Cover & Control'!$C$19="Upside",AJ27,AJ28)) -> 0.04 | AK29: =IF('01 Cover & Control'!$C$19="Base",AK26,IF('01 Cover & Control'!$C$19="Upside",AK27,AK28)) -> 0.04 | AL29: =IF('01 Cover & Control'!$C$19="Base",AL26,IF('01 Cover & Control'!$C$19="Upside",AL27,AL28)) -> 0.04 | AM29: =AVERAGE(AI29:AL29) -> 0.04 | AN29: =IF('01 Cover & Control'!$C$19="Base",AN26,IF('01 Cover & Control'!$C$19="Upside",AN27,AN28)) -> 0.04 | AO29: =IF('01 Cover & Control'!$C$19="Base",AO26,IF('01 Cover & Control'!$C$19="Upside",AO27,AO28)) -> 0.04 | AP29: =IF('01 Cover & Control'!$C$19="Base",AP26,IF('01 Cover & Control'!$C$19="Upside",AP27,AP28)) -> 0.04 | AQ29: =IF('01 Cover & Control'!$C$19="Base",AQ26,IF('01 Cover & Control'!$C$19="Upside",AQ27,AQ28)) -> 0.04 | AR29: =AVERAGE(AN29:AQ29) -> 0.04
B31: Beginning HC — Junior | C31: # | D31: Input: actuals for hist period; forecast = prior yr ending HC. Used directly in EPE formula. | E31: 10 | I31: =SUM(E31:H31) -> 10 | N31: =SUM(J31:M31) -> 0 | S31: =SUM(O31:R31) -> 0 | X31: =SUM(T31:W31) -> 0 | AC31: =SUM(Y31:AB31) -> 0 | AH31: =SUM(AD31:AG31) -> 0 | AM31: =SUM(AI31:AL31) -> 0 | AR31: =SUM(AN31:AQ31) -> 0
B32: Gross Hires / Qtr — Junior — Base | C32: #/qtr | D32: Scenario-keyed. Upside = faster hiring. Downside = slower/failed hiring. | E32: 2 | F32: 2 | G32: 2 | H32: 2 | I32: =SUM(E32:H32) -> 8 | J32: 2 | K32: 2 | L32: 2 | M32: 2 | N32: =SUM(J32:M32) -> 8 | O32: 2 | P32: 2 | Q32: 2 | R32: 2 | S32: =SUM(O32:R32) -> 8 | T32: 2 | U32: 2 | V32: 2 | W32: 2 | X32: =SUM(T32:W32) -> 8 | Y32: 2 | Z32: 2 | AA32: 2 | AB32: 2 | AC32: =SUM(Y32:AB32) -> 8 | AD32: 2 | AE32: 2 | AF32: 2 | AG32: 2 | AH32: =SUM(AD32:AG32) -> 8 | AI32: 2 | AJ32: 2 | AK32: 2 | AL32: 2 | AM32: =SUM(AI32:AL32) -> 8 | AN32: 2 | AO32: 2 | AP32: 2 | AQ32: 2 | AR32: =SUM(AN32:AQ32) -> 8
B33: Gross Hires / Qtr — Junior — Upside | E33: 2.2 | F33: 2.2 | G33: 2.2 | H33: 2.2 | I33: =SUM(E33:H33) -> 8.8 | J33: 2.2 | K33: 2.2 | L33: 2.2 | M33: 2.2 | N33: =SUM(J33:M33) -> 8.8 | O33: 2.2 | P33: 2.2 | Q33: 2.2 | R33: 2.2 | S33: =SUM(O33:R33) -> 8.8 | T33: 2.2 | U33: 2.2 | V33: 2.2 | W33: 2.2 | X33: =SUM(T33:W33) -> 8.8 | Y33: 2.2 | Z33: 2.2 | AA33: 2.2 | AB33: 2.2 | AC33: =SUM(Y33:AB33) -> 8.8 | AD33: 2.2 | AE33: 2.2 | AF33: 2.2 | AG33: 2.2 | AH33: =SUM(AD33:AG33) -> 8.8 | AI33: 2.2 | AJ33: 2.2 | AK33: 2.2 | AL33: 2.2 | AM33: =SUM(AI33:AL33) -> 8.8 | AN33: 2.2 | AO33: 2.2 | AP33: 2.2 | AQ33: 2.2 | AR33: =SUM(AN33:AQ33) -> 8.8
B34: Gross Hires / Qtr — Junior — Downside | E34: 1.7 | F34: 1.7 | G34: 1.7 | H34: 1.7 | I34: =SUM(E34:H34) -> 6.8 | J34: 1.7 | K34: 1.7 | L34: 1.7 | M34: 1.7 | N34: =SUM(J34:M34) -> 6.8 | O34: 1.7 | P34: 1.7 | Q34: 1.7 | R34: 1.7 | S34: =SUM(O34:R34) -> 6.8 | T34: 1.7 | U34: 1.7 | V34: 1.7 | W34: 1.7 | X34: =SUM(T34:W34) -> 6.8 | Y34: 1.7 | Z34: 1.7 | AA34: 1.7 | AB34: 1.7 | AC34: =SUM(Y34:AB34) -> 6.8 | AD34: 1.7 | AE34: 1.7 | AF34: 1.7 | AG34: 1.7 | AH34: =SUM(AD34:AG34) -> 6.8 | AI34: 1.7 | AJ34: 1.7 | AK34: 1.7 | AL34: 1.7 | AM34: =SUM(AI34:AL34) -> 6.8 | AN34: 1.7 | AO34: 1.7 | AP34: 1.7 | AQ34: 1.7 | AR34: =SUM(AN34:AQ34) -> 6.8
B35: Gross Hires / Qtr — Junior — ★ ACTIVE | E35: =IF('01 Cover & Control'!$C$19="Base",E32,IF('01 Cover & Control'!$C$19="Upside",E33,E34)) -> 2 | F35: =IF('01 Cover & Control'!$C$19="Base",F32,IF('01 Cover & Control'!$C$19="Upside",F33,F34)) -> 2 | G35: =IF('01 Cover & Control'!$C$19="Base",G32,IF('01 Cover & Control'!$C$19="Upside",G33,G34)) -> 2 | H35: =IF('01 Cover & Control'!$C$19="Base",H32,IF('01 Cover & Control'!$C$19="Upside",H33,H34)) -> 2 | I35: =SUM(E35:H35) -> 8 | J35: =IF('01 Cover & Control'!$C$19="Base",J32,IF('01 Cover & Control'!$C$19="Upside",J33,J34)) -> 2 | K35: =IF('01 Cover & Control'!$C$19="Base",K32,IF('01 Cover & Control'!$C$19="Upside",K33,K34)) -> 2 | L35: =IF('01 Cover & Control'!$C$19="Base",L32,IF('01 Cover & Control'!$C$19="Upside",L33,L34)) -> 2 | M35: =IF('01 Cover & Control'!$C$19="Base",M32,IF('01 Cover & Control'!$C$19="Upside",M33,M34)) -> 2 | N35: =SUM(J35:M35) -> 8 | O35: =IF('01 Cover & Control'!$C$19="Base",O32,IF('01 Cover & Control'!$C$19="Upside",O33,O34)) -> 2 | P35: =IF('01 Cover & Control'!$C$19="Base",P32,IF('01 Cover & Control'!$C$19="Upside",P33,P34)) -> 2 | Q35: =IF('01 Cover & Control'!$C$19="Base",Q32,IF('01 Cover & Control'!$C$19="Upside",Q33,Q34)) -> 2 | R35: =IF('01 Cover & Control'!$C$19="Base",R32,IF('01 Cover & Control'!$C$19="Upside",R33,R34)) -> 2 | S35: =SUM(O35:R35) -> 8 | T35: =IF('01 Cover & Control'!$C$19="Base",T32,IF('01 Cover & Control'!$C$19="Upside",T33,T34)) -> 2 | U35: =IF('01 Cover & Control'!$C$19="Base",U32,IF('01 Cover & Control'!$C$19="Upside",U33,U34)) -> 2 | V35: =IF('01 Cover & Control'!$C$19="Base",V32,IF('01 Cover & Control'!$C$19="Upside",V33,V34)) -> 2 | W35: =IF('01 Cover & Control'!$C$19="Base",W32,IF('01 Cover & Control'!$C$19="Upside",W33,W34)) -> 2 | X35: =SUM(T35:W35) -> 8 | Y35: =IF('01 Cover & Control'!$C$19="Base",Y32,IF('01 Cover & Control'!$C$19="Upside",Y33,Y34)) -> 2 | Z35: =IF('01 Cover & Control'!$C$19="Base",Z32,IF('01 Cover & Control'!$C$19="Upside",Z33,Z34)) -> 2 | AA35: =IF('01 Cover & Control'!$C$19="Base",AA32,IF('01 Cover & Control'!$C$19="Upside",AA33,AA34)) -> 2 | AB35: =IF('01 Cover & Control'!$C$19="Base",AB32,IF('01 Cover & Control'!$C$19="Upside",AB33,AB34)) -> 2 | AC35: =SUM(Y35:AB35) -> 8 | AD35: =IF('01 Cover & Control'!$C$19="Base",AD32,IF('01 Cover & Control'!$C$19="Upside",AD33,AD34)) -> 2 | AE35: =IF('01 Cover & Control'!$C$19="Base",AE32,IF('01 Cover & Control'!$C$19="Upside",AE33,AE34)) -> 2 | AF35: =IF('01 Cover & Control'!$C$19="Base",AF32,IF('01 Cover & Control'!$C$19="Upside",AF33,AF34)) -> 2 | AG35: =IF('01 Cover & Control'!$C$19="Base",AG32,IF('01 Cover & Control'!$C$19="Upside",AG33,AG34)) -> 2 | AH35: =SUM(AD35:AG35) -> 8 | AI35: =IF('01 Cover & Control'!$C$19="Base",AI32,IF('01 Cover & Control'!$C$19="Upside",AI33,AI34)) -> 2 | AJ35: =IF('01 Cover & Control'!$C$19="Base",AJ32,IF('01 Cover & Control'!$C$19="Upside",AJ33,AJ34)) -> 2 | AK35: =IF('01 Cover & Control'!$C$19="Base",AK32,IF('01 Cover & Control'!$C$19="Upside",AK33,AK34)) -> 2 | AL35: =IF('01 Cover & Control'!$C$19="Base",AL32,IF('01 Cover & Control'!$C$19="Upside",AL33,AL34)) -> 2 | AM35: =SUM(AI35:AL35) -> 8 | AN35: =IF('01 Cover & Control'!$C$19="Base",AN32,IF('01 Cover & Control'!$C$19="Upside",AN33,AN34)) -> 2 | AO35: =IF('01 Cover & Control'!$C$19="Base",AO32,IF('01 Cover & Control'!$C$19="Upside",AO33,AO34)) -> 2 | AP35: =IF('01 Cover & Control'!$C$19="Base",AP32,IF('01 Cover & Control'!$C$19="Upside",AP33,AP34)) -> 2 | AQ35: =IF('01 Cover & Control'!$C$19="Base",AQ32,IF('01 Cover & Control'!$C$19="Upside",AQ33,AQ34)) -> 2 | AR35: =SUM(AN35:AQ35) -> 8
B36: Attrition Rate — Junior — Base | C36: %/qtr | D36: Quarterly attrition rate applied to Beginning HC. Upside = lower attrition (strong market). Downside = higher (competitors poach). | E36: 0.06 | F36: 0.06 | G36: 0.06 | H36: 0.06 | I36: =SUM(E36:H36) -> 0.24 | J36: 0.06 | K36: 0.06 | L36: 0.06 | M36: 0.06 | N36: =SUM(J36:M36) -> 0.24 | O36: 0.06 | P36: 0.06 | Q36: 0.06 | R36: 0.06 | S36: =SUM(O36:R36) -> 0.24 | T36: 0.06 | U36: 0.06 | V36: 0.06 | W36: 0.06 | X36: =SUM(T36:W36) -> 0.24 | Y36: 0.06 | Z36: 0.06 | AA36: 0.06 | AB36: 0.06 | AC36: =SUM(Y36:AB36) -> 0.24 | AD36: 0.06 | AE36: 0.06 | AF36: 0.06 | AG36: 0.06 | AH36: =SUM(AD36:AG36) -> 0.24 | AI36: 0.06 | AJ36: 0.06 | AK36: 0.06 | AL36: 0.06 | AM36: =SUM(AI36:AL36) -> 0.24 | AN36: 0.06 | AO36: 0.06 | AP36: 0.06 | AQ36: 0.06 | AR36: =SUM(AN36:AQ36) -> 0.24
B37: Attrition Rate — Junior — Upside | E37: 0.052 | F37: 0.052 | G37: 0.052 | H37: 0.052 | I37: =SUM(E37:H37) -> 0.208 | J37: 0.052 | K37: 0.052 | L37: 0.052 | M37: 0.052 | N37: =SUM(J37:M37) -> 0.208 | O37: 0.052 | P37: 0.052 | Q37: 0.052 | R37: 0.052 | S37: =SUM(O37:R37) -> 0.208 | T37: 0.052 | U37: 0.052 | V37: 0.052 | W37: 0.052 | X37: =SUM(T37:W37) -> 0.208 | Y37: 0.052 | Z37: 0.052 | AA37: 0.052 | AB37: 0.052 | AC37: =SUM(Y37:AB37) -> 0.208 | AD37: 0.052 | AE37: 0.052 | AF37: 0.052 | AG37: 0.052 | AH37: =SUM(AD37:AG37) -> 0.208 | AI37: 0.052 | AJ37: 0.052 | AK37: 0.052 | AL37: 0.052 | AM37: =SUM(AI37:AL37) -> 0.208 | AN37: 0.052 | AO37: 0.052 | AP37: 0.052 | AQ37: 0.052 | AR37: =SUM(AN37:AQ37) -> 0.208
B38: Attrition Rate — Junior — Downside | E38: 0.08 | F38: 0.08 | G38: 0.08 | H38: 0.08 | I38: =SUM(E38:H38) -> 0.32 | J38: 0.08 | K38: 0.08 | L38: 0.08 | M38: 0.08 | N38: =SUM(J38:M38) -> 0.32 | O38: 0.08 | P38: 0.08 | Q38: 0.08 | R38: 0.08 | S38: =SUM(O38:R38) -> 0.32 | T38: 0.08 | U38: 0.08 | V38: 0.08 | W38: 0.08 | X38: =SUM(T38:W38) -> 0.32 | Y38: 0.08 | Z38: 0.08 | AA38: 0.08 | AB38: 0.08 | AC38: =SUM(Y38:AB38) -> 0.32 | AD38: 0.08 | AE38: 0.08 | AF38: 0.08 | AG38: 0.08 | AH38: =SUM(AD38:AG38) -> 0.32 | AI38: 0.08 | AJ38: 0.08 | AK38: 0.08 | AL38: 0.08 | AM38: =SUM(AI38:AL38) -> 0.32 | AN38: 0.08 | AO38: 0.08 | AP38: 0.08 | AQ38: 0.08 | AR38: =SUM(AN38:AQ38) -> 0.32
B39: Attrition Rate — Junior — ★ ACTIVE | E39: =IF('01 Cover & Control'!$C$19="Base",E36,IF('01 Cover & Control'!$C$19="Upside",E37,E38)) -> 0.06 | F39: =IF('01 Cover & Control'!$C$19="Base",F36,IF('01 Cover & Control'!$C$19="Upside",F37,F38)) -> 0.06 | G39: =IF('01 Cover & Control'!$C$19="Base",G36,IF('01 Cover & Control'!$C$19="Upside",G37,G38)) -> 0.06 | H39: =IF('01 Cover & Control'!$C$19="Base",H36,IF('01 Cover & Control'!$C$19="Upside",H37,H38)) -> 0.06 | I39: =AVERAGE(E39:H39) -> 0.06 | J39: =IF('01 Cover & Control'!$C$19="Base",J36,IF('01 Cover & Control'!$C$19="Upside",J37,J38)) -> 0.06 | K39: =IF('01 Cover & Control'!$C$19="Base",K36,IF('01 Cover & Control'!$C$19="Upside",K37,K38)) -> 0.06 | L39: =IF('01 Cover & Control'!$C$19="Base",L36,IF('01 Cover & Control'!$C$19="Upside",L37,L38)) -> 0.06 | M39: =IF('01 Cover & Control'!$C$19="Base",M36,IF('01 Cover & Control'!$C$19="Upside",M37,M38)) -> 0.06 | N39: =AVERAGE(J39:M39) -> 0.06 | O39: =IF('01 Cover & Control'!$C$19="Base",O36,IF('01 Cover & Control'!$C$19="Upside",O37,O38)) -> 0.06 | P39: =IF('01 Cover & Control'!$C$19="Base",P36,IF('01 Cover & Control'!$C$19="Upside",P37,P38)) -> 0.06 | Q39: =IF('01 Cover & Control'!$C$19="Base",Q36,IF('01 Cover & Control'!$C$19="Upside",Q37,Q38)) -> 0.06 | R39: =IF('01 Cover & Control'!$C$19="Base",R36,IF('01 Cover & Control'!$C$19="Upside",R37,R38)) -> 0.06 | S39: =AVERAGE(O39:R39) -> 0.06 | T39: =IF('01 Cover & Control'!$C$19="Base",T36,IF('01 Cover & Control'!$C$19="Upside",T37,T38)) -> 0.06 | U39: =IF('01 Cover & Control'!$C$19="Base",U36,IF('01 Cover & Control'!$C$19="Upside",U37,U38)) -> 0.06 | V39: =IF('01 Cover & Control'!$C$19="Base",V36,IF('01 Cover & Control'!$C$19="Upside",V37,V38)) -> 0.06 | W39: =IF('01 Cover & Control'!$C$19="Base",W36,IF('01 Cover & Control'!$C$19="Upside",W37,W38)) -> 0.06 | X39: =AVERAGE(T39:W39) -> 0.06 | Y39: =IF('01 Cover & Control'!$C$19="Base",Y36,IF('01 Cover & Control'!$C$19="Upside",Y37,Y38)) -> 0.06 | Z39: =IF('01 Cover & Control'!$C$19="Base",Z36,IF('01 Cover & Control'!$C$19="Upside",Z37,Z38)) -> 0.06 | AA39: =IF('01 Cover & Control'!$C$19="Base",AA36,IF('01 Cover & Control'!$C$19="Upside",AA37,AA38)) -> 0.06 | AB39: =IF('01 Cover & Control'!$C$19="Base",AB36,IF('01 Cover & Control'!$C$19="Upside",AB37,AB38)) -> 0.06 | AC39: =AVERAGE(Y39:AB39) -> 0.06 | AD39: =IF('01 Cover & Control'!$C$19="Base",AD36,IF('01 Cover & Control'!$C$19="Upside",AD37,AD38)) -> 0.06 | AE39: =IF('01 Cover & Control'!$C$19="Base",AE36,IF('01 Cover & Control'!$C$19="Upside",AE37,AE38)) -> 0.06 | AF39: =IF('01 Cover & Control'!$C$19="Base",AF36,IF('01 Cover & Control'!$C$19="Upside",AF37,AF38)) -> 0.06 | AG39: =IF('01 Cover & Control'!$C$19="Base",AG36,IF('01 Cover & Control'!$C$19="Upside",AG37,AG38)) -> 0.06 | AH39: =AVERAGE(AD39:AG39) -> 0.06 | AI39: =IF('01 Cover & Control'!$C$19="Base",AI36,IF('01 Cover & Control'!$C$19="Upside",AI37,AI38)) -> 0.06 | AJ39: =IF('01 Cover & Control'!$C$19="Base",AJ36,IF('01 Cover & Control'!$C$19="Upside",AJ37,AJ38)) -> 0.06 | AK39: =IF('01 Cover & Control'!$C$19="Base",AK36,IF('01 Cover & Control'!$C$19="Upside",AK37,AK38)) -> 0.06 | AL39: =IF('01 Cover & Control'!$C$19="Base",AL36,IF('01 Cover & Control'!$C$19="Upside",AL37,AL38)) -> 0.06 | AM39: =AVERAGE(AI39:AL39) -> 0.06 | AN39: =IF('01 Cover & Control'!$C$19="Base",AN36,IF('01 Cover & Control'!$C$19="Upside",AN37,AN38)) -> 0.06 | AO39: =IF('01 Cover & Control'!$C$19="Base",AO36,IF('01 Cover & Control'!$C$19="Upside",AO37,AO38)) -> 0.06 | AP39: =IF('01 Cover & Control'!$C$19="Base",AP36,IF('01 Cover & Control'!$C$19="Upside",AP37,AP38)) -> 0.06 | AQ39: =IF('01 Cover & Control'!$C$19="Base",AQ36,IF('01 Cover & Control'!$C$19="Upside",AQ37,AQ38)) -> 0.06 | AR39: =AVERAGE(AN39:AQ39) -> 0.06
A43: INVESTMENT SALES — HEADCOUNT
B45: Beginning HC — Rainmaker | C45: # | D45: Input: actuals for hist period; forecast = prior yr ending HC. Used directly in EPE formula. | E45: 6 | I45: =SUM(E45:H45) -> 6 | N45: =SUM(J45:M45) -> 0 | S45: =SUM(O45:R45) -> 0 | X45: =SUM(T45:W45) -> 0 | AC45: =SUM(Y45:AB45) -> 0 | AH45: =SUM(AD45:AG45) -> 0 | AM45: =SUM(AI45:AL45) -> 0 | AR45: =SUM(AN45:AQ45) -> 0
B46: Gross Hires / Qtr — Rainmaker — Base | C46: #/qtr | D46: Scenario-keyed. Upside = faster hiring. Downside = slower/failed hiring. | E46: 0.4 | F46: 0.4 | G46: 0.4 | H46: 0.4 | I46: =SUM(E46:H46) -> 1.6 | J46: 0.4 | K46: 0.4 | L46: 0.4 | M46: 0.4 | N46: =SUM(J46:M46) -> 1.6 | O46: 0.4 | P46: 0.4 | Q46: 0.4 | R46: 0.4 | S46: =SUM(O46:R46) -> 1.6 | T46: 0.4 | U46: 0.4 | V46: 0.4 | W46: 0.4 | X46: =SUM(T46:W46) -> 1.6 | Y46: 0.4 | Z46: 0.4 | AA46: 0.4 | AB46: 0.4 | AC46: =SUM(Y46:AB46) -> 1.6 | AD46: 0.4 | AE46: 0.4 | AF46: 0.4 | AG46: 0.4 | AH46: =SUM(AD46:AG46) -> 1.6 | AI46: 0.4 | AJ46: 0.4 | AK46: 0.4 | AL46: 0.4 | AM46: =SUM(AI46:AL46) -> 1.6 | AN46: 0.4 | AO46: 0.4 | AP46: 0.4 | AQ46: 0.4 | AR46: =SUM(AN46:AQ46) -> 1.6
B47: Gross Hires / Qtr — Rainmaker — Upside | E47: 0.45 | F47: 0.45 | G47: 0.45 | H47: 0.45 | I47: =SUM(E47:H47) -> 1.8 | J47: 0.45 | K47: 0.45 | L47: 0.45 | M47: 0.45 | N47: =SUM(J47:M47) -> 1.8 | O47: 0.45 | P47: 0.45 | Q47: 0.45 | R47: 0.45 | S47: =SUM(O47:R47) -> 1.8 | T47: 0.45 | U47: 0.45 | V47: 0.45 | W47: 0.45 | X47: =SUM(T47:W47) -> 1.8 | Y47: 0.45 | Z47: 0.45 | AA47: 0.45 | AB47: 0.45 | AC47: =SUM(Y47:AB47) -> 1.8 | AD47: 0.45 | AE47: 0.45 | AF47: 0.45 | AG47: 0.45 | AH47: =SUM(AD47:AG47) -> 1.8 | AI47: 0.45 | AJ47: 0.45 | AK47: 0.45 | AL47: 0.45 | AM47: =SUM(AI47:AL47) -> 1.8 | AN47: 0.45 | AO47: 0.45 | AP47: 0.45 | AQ47: 0.45 | AR47: =SUM(AN47:AQ47) -> 1.8
B48: Gross Hires / Qtr — Rainmaker — Downside | E48: 0.34 | F48: 0.34 | G48: 0.34 | H48: 0.34 | I48: =SUM(E48:H48) -> 1.36 | J48: 0.34 | K48: 0.34 | L48: 0.34 | M48: 0.34 | N48: =SUM(J48:M48) -> 1.36 | O48: 0.34 | P48: 0.34 | Q48: 0.34 | R48: 0.34 | S48: =SUM(O48:R48) -> 1.36 | T48: 0.34 | U48: 0.34 | V48: 0.34 | W48: 0.34 | X48: =SUM(T48:W48) -> 1.36 | Y48: 0.34 | Z48: 0.34 | AA48: 0.34 | AB48: 0.34 | AC48: =SUM(Y48:AB48) -> 1.36 | AD48: 0.34 | AE48: 0.34 | AF48: 0.34 | AG48: 0.34 | AH48: =SUM(AD48:AG48) -> 1.36 | AI48: 0.34 | AJ48: 0.34 | AK48: 0.34 | AL48: 0.34 | AM48: =SUM(AI48:AL48) -> 1.36 | AN48: 0.34 | AO48: 0.34 | AP48: 0.34 | AQ48: 0.34 | AR48: =SUM(AN48:AQ48) -> 1.36
B49: Gross Hires / Qtr — Rainmaker — ★ ACTIVE | E49: =IF('01 Cover & Control'!$C$19="Base",E46,IF('01 Cover & Control'!$C$19="Upside",E47,E48)) -> 0.4 | F49: =IF('01 Cover & Control'!$C$19="Base",F46,IF('01 Cover & Control'!$C$19="Upside",F47,F48)) -> 0.4 | G49: =IF('01 Cover & Control'!$C$19="Base",G46,IF('01 Cover & Control'!$C$19="Upside",G47,G48)) -> 0.4 | H49: =IF('01 Cover & Control'!$C$19="Base",H46,IF('01 Cover & Control'!$C$19="Upside",H47,H48)) -> 0.4 | I49: =SUM(E49:H49) -> 1.6 | J49: =IF('01 Cover & Control'!$C$19="Base",J46,IF('01 Cover & Control'!$C$19="Upside",J47,J48)) -> 0.4 | K49: =IF('01 Cover & Control'!$C$19="Base",K46,IF('01 Cover & Control'!$C$19="Upside",K47,K48)) -> 0.4 | L49: =IF('01 Cover & Control'!$C$19="Base",L46,IF('01 Cover & Control'!$C$19="Upside",L47,L48)) -> 0.4 | M49: =IF('01 Cover & Control'!$C$19="Base",M46,IF('01 Cover & Control'!$C$19="Upside",M47,M48)) -> 0.4 | N49: =SUM(J49:M49) -> 1.6 | O49: =IF('01 Cover & Control'!$C$19="Base",O46,IF('01 Cover & Control'!$C$19="Upside",O47,O48)) -> 0.4 | P49: =IF('01 Cover & Control'!$C$19="Base",P46,IF('01 Cover & Control'!$C$19="Upside",P47,P48)) -> 0.4 | Q49: =IF('01 Cover & Control'!$C$19="Base",Q46,IF('01 Cover & Control'!$C$19="Upside",Q47,Q48)) -> 0.4 | R49: =IF('01 Cover & Control'!$C$19="Base",R46,IF('01 Cover & Control'!$C$19="Upside",R47,R48)) -> 0.4 | S49: =SUM(O49:R49) -> 1.6 | T49: =IF('01 Cover & Control'!$C$19="Base",T46,IF('01 Cover & Control'!$C$19="Upside",T47,T48)) -> 0.4 | U49: =IF('01 Cover & Control'!$C$19="Base",U46,IF('01 Cover & Control'!$C$19="Upside",U47,U48)) -> 0.4 | V49: =IF('01 Cover & Control'!$C$19="Base",V46,IF('01 Cover & Control'!$C$19="Upside",V47,V48)) -> 0.4 | W49: =IF('01 Cover & Control'!$C$19="Base",W46,IF('01 Cover & Control'!$C$19="Upside",W47,W48)) -> 0.4 | X49: =SUM(T49:W49) -> 1.6 | Y49: =IF('01 Cover & Control'!$C$19="Base",Y46,IF('01 Cover & Control'!$C$19="Upside",Y47,Y48)) -> 0.4 | Z49: =IF('01 Cover & Control'!$C$19="Base",Z46,IF('01 Cover & Control'!$C$19="Upside",Z47,Z48)) -> 0.4 | AA49: =IF('01 Cover & Control'!$C$19="Base",AA46,IF('01 Cover & Control'!$C$19="Upside",AA47,AA48)) -> 0.4 | AB49: =IF('01 Cover & Control'!$C$19="Base",AB46,IF('01 Cover & Control'!$C$19="Upside",AB47,AB48)) -> 0.4 | AC49: =SUM(Y49:AB49) -> 1.6 | AD49: =IF('01 Cover & Control'!$C$19="Base",AD46,IF('01 Cover & Control'!$C$19="Upside",AD47,AD48)) -> 0.4 | AE49: =IF('01 Cover & Control'!$C$19="Base",AE46,IF('01 Cover & Control'!$C$19="Upside",AE47,AE48)) -> 0.4 | AF49: =IF('01 Cover & Control'!$C$19="Base",AF46,IF('01 Cover & Control'!$C$19="Upside",AF47,AF48)) -> 0.4 | AG49: =IF('01 Cover & Control'!$C$19="Base",AG46,IF('01 Cover & Control'!$C$19="Upside",AG47,AG48)) -> 0.4 | AH49: =SUM(AD49:AG49) -> 1.6 | AI49: =IF('01 Cover & Control'!$C$19="Base",AI46,IF('01 Cover & Control'!$C$19="Upside",AI47,AI48)) -> 0.4 | AJ49: =IF('01 Cover & Control'!$C$19="Base",AJ46,IF('01 Cover & Control'!$C$19="Upside",AJ47,AJ48)) -> 0.4 | AK49: =IF('01 Cover & Control'!$C$19="Base",AK46,IF('01 Cover & Control'!$C$19="Upside",AK47,AK48)) -> 0.4 | AL49: =IF('01 Cover & Control'!$C$19="Base",AL46,IF('01 Cover & Control'!$C$19="Upside",AL47,AL48)) -> 0.4 | AM49: =SUM(AI49:AL49) -> 1.6 | AN49: =IF('01 Cover & Control'!$C$19="Base",AN46,IF('01 Cover & Control'!$C$19="Upside",AN47,AN48)) -> 0.4 | AO49: =IF('01 Cover & Control'!$C$19="Base",AO46,IF('01 Cover & Control'!$C$19="Upside",AO47,AO48)) -> 0.4 | AP49: =IF('01 Cover & Control'!$C$19="Base",AP46,IF('01 Cover & Control'!$C$19="Upside",AP47,AP48)) -> 0.4 | AQ49: =IF('01 Cover & Control'!$C$19="Base",AQ46,IF('01 Cover & Control'!$C$19="Upside",AQ47,AQ48)) -> 0.4 | AR49: =SUM(AN49:AQ49) -> 1.6
B50: Attrition Rate — Rainmaker — Base | C50: %/qtr | D50: Quarterly attrition rate applied to Beginning HC. Upside = lower attrition (strong market). Downside = higher (competitors poach). | E50: 0.02 | F50: 0.02 | G50: 0.02 | H50: 0.02 | I50: =SUM(E50:H50) -> 0.08 | J50: 0.02 | K50: 0.02 | L50: 0.02 | M50: 0.02 | N50: =SUM(J50:M50) -> 0.08 | O50: 0.02 | P50: 0.02 | Q50: 0.02 | R50: 0.02 | S50: =SUM(O50:R50) -> 0.08 | T50: 0.02 | U50: 0.02 | V50: 0.02 | W50: 0.02 | X50: =SUM(T50:W50) -> 0.08 | Y50: 0.02 | Z50: 0.02 | AA50: 0.02 | AB50: 0.02 | AC50: =SUM(Y50:AB50) -> 0.08 | AD50: 0.02 | AE50: 0.02 | AF50: 0.02 | AG50: 0.02 | AH50: =SUM(AD50:AG50) -> 0.08 | AI50: 0.02 | AJ50: 0.02 | AK50: 0.02 | AL50: 0.02 | AM50: =SUM(AI50:AL50) -> 0.08 | AN50: 0.02 | AO50: 0.02 | AP50: 0.02 | AQ50: 0.02 | AR50: =SUM(AN50:AQ50) -> 0.08
B51: Attrition Rate — Rainmaker — Upside | E51: 0.018 | F51: 0.018 | G51: 0.018 | H51: 0.018 | I51: =SUM(E51:H51) -> 0.072 | J51: 0.018 | K51: 0.018 | L51: 0.018 | M51: 0.018 | N51: =SUM(J51:M51) -> 0.072 | O51: 0.018 | P51: 0.018 | Q51: 0.018 | R51: 0.018 | S51: =SUM(O51:R51) -> 0.072 | T51: 0.018 | U51: 0.018 | V51: 0.018 | W51: 0.018 | X51: =SUM(T51:W51) -> 0.072 | Y51: 0.018 | Z51: 0.018 | AA51: 0.018 | AB51: 0.018 | AC51: =SUM(Y51:AB51) -> 0.072 | AD51: 0.018 | AE51: 0.018 | AF51: 0.018 | AG51: 0.018 | AH51: =SUM(AD51:AG51) -> 0.072 | AI51: 0.018 | AJ51: 0.018 | AK51: 0.018 | AL51: 0.018 | AM51: =SUM(AI51:AL51) -> 0.072 | AN51: 0.018 | AO51: 0.018 | AP51: 0.018 | AQ51: 0.018 | AR51: =SUM(AN51:AQ51) -> 0.072
B52: Attrition Rate — Rainmaker — Downside | E52: 0.03 | F52: 0.03 | G52: 0.03 | H52: 0.03 | I52: =SUM(E52:H52) -> 0.12 | J52: 0.03 | K52: 0.03 | L52: 0.03 | M52: 0.03 | N52: =SUM(J52:M52) -> 0.12 | O52: 0.03 | P52: 0.03 | Q52: 0.03 | R52: 0.03 | S52: =SUM(O52:R52) -> 0.12 | T52: 0.03 | U52: 0.03 | V52: 0.03 | W52: 0.03 | X52: =SUM(T52:W52) -> 0.12 | Y52: 0.03 | Z52: 0.03 | AA52: 0.03 | AB52: 0.03 | AC52: =SUM(Y52:AB52) -> 0.12 | AD52: 0.03 | AE52: 0.03 | AF52: 0.03 | AG52: 0.03 | AH52: =SUM(AD52:AG52) -> 0.12 | AI52: 0.03 | AJ52: 0.03 | AK52: 0.03 | AL52: 0.03 | AM52: =SUM(AI52:AL52) -> 0.12 | AN52: 0.03 | AO52: 0.03 | AP52: 0.03 | AQ52: 0.03 | AR52: =SUM(AN52:AQ52) -> 0.12
B53: Attrition Rate — Rainmaker — ★ ACTIVE | E53: =IF('01 Cover & Control'!$C$19="Base",E50,IF('01 Cover & Control'!$C$19="Upside",E51,E52)) -> 0.02 | F53: =IF('01 Cover & Control'!$C$19="Base",F50,IF('01 Cover & Control'!$C$19="Upside",F51,F52)) -> 0.02 | G53: =IF('01 Cover & Control'!$C$19="Base",G50,IF('01 Cover & Control'!$C$19="Upside",G51,G52)) -> 0.02 | H53: =IF('01 Cover & Control'!$C$19="Base",H50,IF('01 Cover & Control'!$C$19="Upside",H51,H52)) -> 0.02 | I53: =AVERAGE(E53:H53) -> 0.02 | J53: =IF('01 Cover & Control'!$C$19="Base",J50,IF('01 Cover & Control'!$C$19="Upside",J51,J52)) -> 0.02 | K53: =IF('01 Cover & Control'!$C$19="Base",K50,IF('01 Cover & Control'!$C$19="Upside",K51,K52)) -> 0.02 | L53: =IF('01 Cover & Control'!$C$19="Base",L50,IF('01 Cover & Control'!$C$19="Upside",L51,L52)) -> 0.02 | M53: =IF('01 Cover & Control'!$C$19="Base",M50,IF('01 Cover & Control'!$C$19="Upside",M51,M52)) -> 0.02 | N53: =AVERAGE(J53:M53) -> 0.02 | O53: =IF('01 Cover & Control'!$C$19="Base",O50,IF('01 Cover & Control'!$C$19="Upside",O51,O52)) -> 0.02 | P53: =IF('01 Cover & Control'!$C$19="Base",P50,IF('01 Cover & Control'!$C$19="Upside",P51,P52)) -> 0.02 | Q53: =IF('01 Cover & Control'!$C$19="Base",Q50,IF('01 Cover & Control'!$C$19="Upside",Q51,Q52)) -> 0.02 | R53: =IF('01 Cover & Control'!$C$19="Base",R50,IF('01 Cover & Control'!$C$19="Upside",R51,R52)) -> 0.02 | S53: =AVERAGE(O53:R53) -> 0.02 | T53: =IF('01 Cover & Control'!$C$19="Base",T50,IF('01 Cover & Control'!$C$19="Upside",T51,T52)) -> 0.02 | U53: =IF('01 Cover & Control'!$C$19="Base",U50,IF('01 Cover & Control'!$C$19="Upside",U51,U52)) -> 0.02 | V53: =IF('01 Cover & Control'!$C$19="Base",V50,IF('01 Cover & Control'!$C$19="Upside",V51,V52)) -> 0.02 | W53: =IF('01 Cover & Control'!$C$19="Base",W50,IF('01 Cover & Control'!$C$19="Upside",W51,W52)) -> 0.02 | X53: =AVERAGE(T53:W53) -> 0.02 | Y53: =IF('01 Cover & Control'!$C$19="Base",Y50,IF('01 Cover & Control'!$C$19="Upside",Y51,Y52)) -> 0.02 | Z53: =IF('01 Cover & Control'!$C$19="Base",Z50,IF('01 Cover & Control'!$C$19="Upside",Z51,Z52)) -> 0.02 | AA53: =IF('01 Cover & Control'!$C$19="Base",AA50,IF('01 Cover & Control'!$C$19="Upside",AA51,AA52)) -> 0.02 | AB53: =IF('01 Cover & Control'!$C$19="Base",AB50,IF('01 Cover & Control'!$C$19="Upside",AB51,AB52)) -> 0.02 | AC53: =AVERAGE(Y53:AB53) -> 0.02 | AD53: =IF('01 Cover & Control'!$C$19="Base",AD50,IF('01 Cover & Control'!$C$19="Upside",AD51,AD52)) -> 0.02 | AE53: =IF('01 Cover & Control'!$C$19="Base",AE50,IF('01 Cover & Control'!$C$19="Upside",AE51,AE52)) -> 0.02 | AF53: =IF('01 Cover & Control'!$C$19="Base",AF50,IF('01 Cover & Control'!$C$19="Upside",AF51,AF52)) -> 0.02 | AG53: =IF('01 Cover & Control'!$C$19="Base",AG50,IF('01 Cover & Control'!$C$19="Upside",AG51,AG52)) -> 0.02 | AH53: =AVERAGE(AD53:AG53) -> 0.02 | AI53: =IF('01 Cover & Control'!$C$19="Base",AI50,IF('01 Cover & Control'!$C$19="Upside",AI51,AI52)) -> 0.02 | AJ53: =IF('01 Cover & Control'!$C$19="Base",AJ50,IF('01 Cover & Control'!$C$19="Upside",AJ51,AJ52)) -> 0.02 | AK53: =IF('01 Cover & Control'!$C$19="Base",AK50,IF('01 Cover & Control'!$C$19="Upside",AK51,AK52)) -> 0.02 | AL53: =IF('01 Cover & Control'!$C$19="Base",AL50,IF('01 Cover & Control'!$C$19="Upside",AL51,AL52)) -> 0.02 | AM53: =AVERAGE(AI53:AL53) -> 0.02 | AN53: =IF('01 Cover & Control'!$C$19="Base",AN50,IF('01 Cover & Control'!$C$19="Upside",AN51,AN52)) -> 0.02 | AO53: =IF('01 Cover & Control'!$C$19="Base",AO50,IF('01 Cover & Control'!$C$19="Upside",AO51,AO52)) -> 0.02 | AP53: =IF('01 Cover & Control'!$C$19="Base",AP50,IF('01 Cover & Control'!$C$19="Upside",AP51,AP52)) -> 0.02 | AQ53: =IF('01 Cover & Control'!$C$19="Base",AQ50,IF('01 Cover & Control'!$C$19="Upside",AQ51,AQ52)) -> 0.02 | AR53: =AVERAGE(AN53:AQ53) -> 0.02
B55: Beginning HC — Core | C55: # | D55: Input: actuals for hist period; forecast = prior yr ending HC. Used directly in EPE formula. | E55: 12 | I55: =SUM(E55:H55) -> 12 | N55: =SUM(J55:M55) -> 0 | S55: =SUM(O55:R55) -> 0 | X55: =SUM(T55:W55) -> 0 | AC55: =SUM(Y55:AB55) -> 0 | AH55: =SUM(AD55:AG55) -> 0 | AM55: =SUM(AI55:AL55) -> 0 | AR55: =SUM(AN55:AQ55) -> 0
B56: Gross Hires / Qtr — Core — Base | C56: #/qtr | D56: Scenario-keyed. Upside = faster hiring. Downside = slower/failed hiring. | E56: 1.2 | F56: 1.2 | G56: 1.2 | H56: 1.2 | I56: =SUM(E56:H56) -> 4.8 | J56: 1.2 | K56: 1.2 | L56: 1.2 | M56: 1.2 | N56: =SUM(J56:M56) -> 4.8 | O56: 1.2 | P56: 1.2 | Q56: 1.2 | R56: 1.2 | S56: =SUM(O56:R56) -> 4.8 | T56: 1.2 | U56: 1.2 | V56: 1.2 | W56: 1.2 | X56: =SUM(T56:W56) -> 4.8 | Y56: 1.2 | Z56: 1.2 | AA56: 1.2 | AB56: 1.2 | AC56: =SUM(Y56:AB56) -> 4.8 | AD56: 1.2 | AE56: 1.2 | AF56: 1.2 | AG56: 1.2 | AH56: =SUM(AD56:AG56) -> 4.8 | AI56: 1.2 | AJ56: 1.2 | AK56: 1.2 | AL56: 1.2 | AM56: =SUM(AI56:AL56) -> 4.8 | AN56: 1.2 | AO56: 1.2 | AP56: 1.2 | AQ56: 1.2 | AR56: =SUM(AN56:AQ56) -> 4.8
B57: Gross Hires / Qtr — Core — Upside | E57: 1.32 | F57: 1.32 | G57: 1.32 | H57: 1.32 | I57: =SUM(E57:H57) -> 5.28 | J57: 1.32 | K57: 1.32 | L57: 1.32 | M57: 1.32 | N57: =SUM(J57:M57) -> 5.28 | O57: 1.32 | P57: 1.32 | Q57: 1.32 | R57: 1.32 | S57: =SUM(O57:R57) -> 5.28 | T57: 1.32 | U57: 1.32 | V57: 1.32 | W57: 1.32 | X57: =SUM(T57:W57) -> 5.28 | Y57: 1.32 | Z57: 1.32 | AA57: 1.32 | AB57: 1.32 | AC57: =SUM(Y57:AB57) -> 5.28 | AD57: 1.32 | AE57: 1.32 | AF57: 1.32 | AG57: 1.32 | AH57: =SUM(AD57:AG57) -> 5.28 | AI57: 1.32 | AJ57: 1.32 | AK57: 1.32 | AL57: 1.32 | AM57: =SUM(AI57:AL57) -> 5.28 | AN57: 1.32 | AO57: 1.32 | AP57: 1.32 | AQ57: 1.32 | AR57: =SUM(AN57:AQ57) -> 5.28
B58: Gross Hires / Qtr — Core — Downside | E58: 1.02 | F58: 1.02 | G58: 1.02 | H58: 1.02 | I58: =SUM(E58:H58) -> 4.08 | J58: 1.02 | K58: 1.02 | L58: 1.02 | M58: 1.02 | N58: =SUM(J58:M58) -> 4.08 | O58: 1.02 | P58: 1.02 | Q58: 1.02 | R58: 1.02 | S58: =SUM(O58:R58) -> 4.08 | T58: 1.02 | U58: 1.02 | V58: 1.02 | W58: 1.02 | X58: =SUM(T58:W58) -> 4.08 | Y58: 1.02 | Z58: 1.02 | AA58: 1.02 | AB58: 1.02 | AC58: =SUM(Y58:AB58) -> 4.08 | AD58: 1.02 | AE58: 1.02 | AF58: 1.02 | AG58: 1.02 | AH58: =SUM(AD58:AG58) -> 4.08 | AI58: 1.02 | AJ58: 1.02 | AK58: 1.02 | AL58: 1.02 | AM58: =SUM(AI58:AL58) -> 4.08 | AN58: 1.02 | AO58: 1.02 | AP58: 1.02 | AQ58: 1.02 | AR58: =SUM(AN58:AQ58) -> 4.08
B59: Gross Hires / Qtr — Core — ★ ACTIVE | E59: =IF('01 Cover & Control'!$C$19="Base",E56,IF('01 Cover & Control'!$C$19="Upside",E57,E58)) -> 1.2 | F59: =IF('01 Cover & Control'!$C$19="Base",F56,IF('01 Cover & Control'!$C$19="Upside",F57,F58)) -> 1.2 | G59: =IF('01 Cover & Control'!$C$19="Base",G56,IF('01 Cover & Control'!$C$19="Upside",G57,G58)) -> 1.2 | H59: =IF('01 Cover & Control'!$C$19="Base",H56,IF('01 Cover & Control'!$C$19="Upside",H57,H58)) -> 1.2 | I59: =SUM(E59:H59) -> 4.8 | J59: =IF('01 Cover & Control'!$C$19="Base",J56,IF('01 Cover & Control'!$C$19="Upside",J57,J58)) -> 1.2 | K59: =IF('01 Cover & Control'!$C$19="Base",K56,IF('01 Cover & Control'!$C$19="Upside",K57,K58)) -> 1.2 | L59: =IF('01 Cover & Control'!$C$19="Base",L56,IF('01 Cover & Control'!$C$19="Upside",L57,L58)) -> 1.2 | M59: =IF('01 Cover & Control'!$C$19="Base",M56,IF('01 Cover & Control'!$C$19="Upside",M57,M58)) -> 1.2 | N59: =SUM(J59:M59) -> 4.8 | O59: =IF('01 Cover & Control'!$C$19="Base",O56,IF('01 Cover & Control'!$C$19="Upside",O57,O58)) -> 1.2 | P59: =IF('01 Cover & Control'!$C$19="Base",P56,IF('01 Cover & Control'!$C$19="Upside",P57,P58)) -> 1.2 | Q59: =IF('01 Cover & Control'!$C$19="Base",Q56,IF('01 Cover & Control'!$C$19="Upside",Q57,Q58)) -> 1.2 | R59: =IF('01 Cover & Control'!$C$19="Base",R56,IF('01 Cover & Control'!$C$19="Upside",R57,R58)) -> 1.2 | S59: =SUM(O59:R59) -> 4.8 | T59: =IF('01 Cover & Control'!$C$19="Base",T56,IF('01 Cover & Control'!$C$19="Upside",T57,T58)) -> 1.2 | U59: =IF('01 Cover & Control'!$C$19="Base",U56,IF('01 Cover & Control'!$C$19="Upside",U57,U58)) -> 1.2 | V59: =IF('01 Cover & Control'!$C$19="Base",V56,IF('01 Cover & Control'!$C$19="Upside",V57,V58)) -> 1.2 | W59: =IF('01 Cover & Control'!$C$19="Base",W56,IF('01 Cover & Control'!$C$19="Upside",W57,W58)) -> 1.2 | X59: =SUM(T59:W59) -> 4.8 | Y59: =IF('01 Cover & Control'!$C$19="Base",Y56,IF('01 Cover & Control'!$C$19="Upside",Y57,Y58)) -> 1.2 | Z59: =IF('01 Cover & Control'!$C$19="Base",Z56,IF('01 Cover & Control'!$C$19="Upside",Z57,Z58)) -> 1.2 | AA59: =IF('01 Cover & Control'!$C$19="Base",AA56,IF('01 Cover & Control'!$C$19="Upside",AA57,AA58)) -> 1.2 | AB59: =IF('01 Cover & Control'!$C$19="Base",AB56,IF('01 Cover & Control'!$C$19="Upside",AB57,AB58)) -> 1.2 | AC59: =SUM(Y59:AB59) -> 4.8 | AD59: =IF('01 Cover & Control'!$C$19="Base",AD56,IF('01 Cover & Control'!$C$19="Upside",AD57,AD58)) -> 1.2 | AE59: =IF('01 Cover & Control'!$C$19="Base",AE56,IF('01 Cover & Control'!$C$19="Upside",AE57,AE58)) -> 1.2 | AF59: =IF('01 Cover & Control'!$C$19="Base",AF56,IF('01 Cover & Control'!$C$19="Upside",AF57,AF58)) -> 1.2 | AG59: =IF('01 Cover & Control'!$C$19="Base",AG56,IF('01 Cover & Control'!$C$19="Upside",AG57,AG58)) -> 1.2 | AH59: =SUM(AD59:AG59) -> 4.8 | AI59: =IF('01 Cover & Control'!$C$19="Base",AI56,IF('01 Cover & Control'!$C$19="Upside",AI57,AI58)) -> 1.2 | AJ59: =IF('01 Cover & Control'!$C$19="Base",AJ56,IF('01 Cover & Control'!$C$19="Upside",AJ57,AJ58)) -> 1.2 | AK59: =IF('01 Cover & Control'!$C$19="Base",AK56,IF('01 Cover & Control'!$C$19="Upside",AK57,AK58)) -> 1.2 | AL59: =IF('01 Cover & Control'!$C$19="Base",AL56,IF('01 Cover & Control'!$C$19="Upside",AL57,AL58)) -> 1.2 | AM59: =SUM(AI59:AL59) -> 4.8 | AN59: =IF('01 Cover & Control'!$C$19="Base",AN56,IF('01 Cover & Control'!$C$19="Upside",AN57,AN58)) -> 1.2 | AO59: =IF('01 Cover & Control'!$C$19="Base",AO56,IF('01 Cover & Control'!$C$19="Upside",AO57,AO58)) -> 1.2 | AP59: =IF('01 Cover & Control'!$C$19="Base",AP56,IF('01 Cover & Control'!$C$19="Upside",AP57,AP58)) -> 1.2 | AQ59: =IF('01 Cover & Control'!$C$19="Base",AQ56,IF('01 Cover & Control'!$C$19="Upside",AQ57,AQ58)) -> 1.2 | AR59: =SUM(AN59:AQ59) -> 4.8
B60: Attrition Rate — Core — Base | C60: %/qtr | D60: Quarterly attrition rate applied to Beginning HC. Upside = lower attrition (strong market). Downside = higher (competitors poach). | E60: 0.04 | F60: 0.04 | G60: 0.04 | H60: 0.04 | I60: =SUM(E60:H60) -> 0.16 | J60: 0.04 | K60: 0.04 | L60: 0.04 | M60: 0.04 | N60: =SUM(J60:M60) -> 0.16 | O60: 0.04 | P60: 0.04 | Q60: 0.04 | R60: 0.04 | S60: =SUM(O60:R60) -> 0.16 | T60: 0.04 | U60: 0.04 | V60: 0.04 | W60: 0.04 | X60: =SUM(T60:W60) -> 0.16 | Y60: 0.04 | Z60: 0.04 | AA60: 0.04 | AB60: 0.04 | AC60: =SUM(Y60:AB60) -> 0.16 | AD60: 0.04 | AE60: 0.04 | AF60: 0.04 | AG60: 0.04 | AH60: =SUM(AD60:AG60) -> 0.16 | AI60: 0.04 | AJ60: 0.04 | AK60: 0.04 | AL60: 0.04 | AM60: =SUM(AI60:AL60) -> 0.16 | AN60: 0.04 | AO60: 0.04 | AP60: 0.04 | AQ60: 0.04 | AR60: =SUM(AN60:AQ60) -> 0.16
B61: Attrition Rate — Core — Upside | E61: 0.035 | F61: 0.035 | G61: 0.035 | H61: 0.035 | I61: =SUM(E61:H61) -> 0.14 | J61: 0.035 | K61: 0.035 | L61: 0.035 | M61: 0.035 | N61: =SUM(J61:M61) -> 0.14 | O61: 0.035 | P61: 0.035 | Q61: 0.035 | R61: 0.035 | S61: =SUM(O61:R61) -> 0.14 | T61: 0.035 | U61: 0.035 | V61: 0.035 | W61: 0.035 | X61: =SUM(T61:W61) -> 0.14 | Y61: 0.035 | Z61: 0.035 | AA61: 0.035 | AB61: 0.035 | AC61: =SUM(Y61:AB61) -> 0.14 | AD61: 0.035 | AE61: 0.035 | AF61: 0.035 | AG61: 0.035 | AH61: =SUM(AD61:AG61) -> 0.14 | AI61: 0.035 | AJ61: 0.035 | AK61: 0.035 | AL61: 0.035 | AM61: =SUM(AI61:AL61) -> 0.14 | AN61: 0.035 | AO61: 0.035 | AP61: 0.035 | AQ61: 0.035 | AR61: =SUM(AN61:AQ61) -> 0.14
B62: Attrition Rate — Core — Downside | E62: 0.055 | F62: 0.055 | G62: 0.055 | H62: 0.055 | I62: =SUM(E62:H62) -> 0.22 | J62: 0.055 | K62: 0.055 | L62: 0.055 | M62: 0.055 | N62: =SUM(J62:M62) -> 0.22 | O62: 0.055 | P62: 0.055 | Q62: 0.055 | R62: 0.055 | S62: =SUM(O62:R62) -> 0.22 | T62: 0.055 | U62: 0.055 | V62: 0.055 | W62: 0.055 | X62: =SUM(T62:W62) -> 0.22 | Y62: 0.055 | Z62: 0.055 | AA62: 0.055 | AB62: 0.055 | AC62: =SUM(Y62:AB62) -> 0.22 | AD62: 0.055 | AE62: 0.055 | AF62: 0.055 | AG62: 0.055 | AH62: =SUM(AD62:AG62) -> 0.22 | AI62: 0.055 | AJ62: 0.055 | AK62: 0.055 | AL62: 0.055 | AM62: =SUM(AI62:AL62) -> 0.22 | AN62: 0.055 | AO62: 0.055 | AP62: 0.055 | AQ62: 0.055 | AR62: =SUM(AN62:AQ62) -> 0.22
B63: Attrition Rate — Core — ★ ACTIVE | E63: =IF('01 Cover & Control'!$C$19="Base",E60,IF('01 Cover & Control'!$C$19="Upside",E61,E62)) -> 0.04 | F63: =IF('01 Cover & Control'!$C$19="Base",F60,IF('01 Cover & Control'!$C$19="Upside",F61,F62)) -> 0.04 | G63: =IF('01 Cover & Control'!$C$19="Base",G60,IF('01 Cover & Control'!$C$19="Upside",G61,G62)) -> 0.04 | H63: =IF('01 Cover & Control'!$C$19="Base",H60,IF('01 Cover & Control'!$C$19="Upside",H61,H62)) -> 0.04 | I63: =AVERAGE(E63:H63) -> 0.04 | J63: =IF('01 Cover & Control'!$C$19="Base",J60,IF('01 Cover & Control'!$C$19="Upside",J61,J62)) -> 0.04 | K63: =IF('01 Cover & Control'!$C$19="Base",K60,IF('01 Cover & Control'!$C$19="Upside",K61,K62)) -> 0.04 | L63: =IF('01 Cover & Control'!$C$19="Base",L60,IF('01 Cover & Control'!$C$19="Upside",L61,L62)) -> 0.04 | M63: =IF('01 Cover & Control'!$C$19="Base",M60,IF('01 Cover & Control'!$C$19="Upside",M61,M62)) -> 0.04 | N63: =AVERAGE(J63:M63) -> 0.04 | O63: =IF('01 Cover & Control'!$C$19="Base",O60,IF('01 Cover & Control'!$C$19="Upside",O61,O62)) -> 0.04 | P63: =IF('01 Cover & Control'!$C$19="Base",P60,IF('01 Cover & Control'!$C$19="Upside",P61,P62)) -> 0.04 | Q63: =IF('01 Cover & Control'!$C$19="Base",Q60,IF('01 Cover & Control'!$C$19="Upside",Q61,Q62)) -> 0.04 | R63: =IF('01 Cover & Control'!$C$19="Base",R60,IF('01 Cover & Control'!$C$19="Upside",R61,R62)) -> 0.04 | S63: =AVERAGE(O63:R63) -> 0.04 | T63: =IF('01 Cover & Control'!$C$19="Base",T60,IF('01 Cover & Control'!$C$19="Upside",T61,T62)) -> 0.04 | U63: =IF('01 Cover & Control'!$C$19="Base",U60,IF('01 Cover & Control'!$C$19="Upside",U61,U62)) -> 0.04 | V63: =IF('01 Cover & Control'!$C$19="Base",V60,IF('01 Cover & Control'!$C$19="Upside",V61,V62)) -> 0.04 | W63: =IF('01 Cover & Control'!$C$19="Base",W60,IF('01 Cover & Control'!$C$19="Upside",W61,W62)) -> 0.04 | X63: =AVERAGE(T63:W63) -> 0.04 | Y63: =IF('01 Cover & Control'!$C$19="Base",Y60,IF('01 Cover & Control'!$C$19="Upside",Y61,Y62)) -> 0.04 | Z63: =IF('01 Cover & Control'!$C$19="Base",Z60,IF('01 Cover & Control'!$C$19="Upside",Z61,Z62)) -> 0.04 | AA63: =IF('01 Cover & Control'!$C$19="Base",AA60,IF('01 Cover & Control'!$C$19="Upside",AA61,AA62)) -> 0.04 | AB63: =IF('01 Cover & Control'!$C$19="Base",AB60,IF('01 Cover & Control'!$C$19="Upside",AB61,AB62)) -> 0.04 | AC63: =AVERAGE(Y63:AB63) -> 0.04 | AD63: =IF('01 Cover & Control'!$C$19="Base",AD60,IF('01 Cover & Control'!$C$19="Upside",AD61,AD62)) -> 0.04 | AE63: =IF('01 Cover & Control'!$C$19="Base",AE60,IF('01 Cover & Control'!$C$19="Upside",AE61,AE62)) -> 0.04 | AF63: =IF('01 Cover & Control'!$C$19="Base",AF60,IF('01 Cover & Control'!$C$19="Upside",AF61,AF62)) -> 0.04 | AG63: =IF('01 Cover & Control'!$C$19="Base",AG60,IF('01 Cover & Control'!$C$19="Upside",AG61,AG62)) -> 0.04 | AH63: =AVERAGE(AD63:AG63) -> 0.04 | AI63: =IF('01 Cover & Control'!$C$19="Base",AI60,IF('01 Cover & Control'!$C$19="Upside",AI61,AI62)) -> 0.04 | AJ63: =IF('01 Cover & Control'!$C$19="Base",AJ60,IF('01 Cover & Control'!$C$19="Upside",AJ61,AJ62)) -> 0.04 | AK63: =IF('01 Cover & Control'!$C$19="Base",AK60,IF('01 Cover & Control'!$C$19="Upside",AK61,AK62)) -> 0.04 | AL63: =IF('01 Cover & Control'!$C$19="Base",AL60,IF('01 Cover & Control'!$C$19="Upside",AL61,AL62)) -> 0.04 | AM63: =AVERAGE(AI63:AL63) -> 0.04 | AN63: =IF('01 Cover & Control'!$C$19="Base",AN60,IF('01 Cover & Control'!$C$19="Upside",AN61,AN62)) -> 0.04 | AO63: =IF('01 Cover & Control'!$C$19="Base",AO60,IF('01 Cover & Control'!$C$19="Upside",AO61,AO62)) -> 0.04 | AP63: =IF('01 Cover & Control'!$C$19="Base",AP60,IF('01 Cover & Control'!$C$19="Upside",AP61,AP62)) -> 0.04 | AQ63: =IF('01 Cover & Control'!$C$19="Base",AQ60,IF('01 Cover & Control'!$C$19="Upside",AQ61,AQ62)) -> 0.04 | AR63: =AVERAGE(AN63:AQ63) -> 0.04
B65: Beginning HC — Junior | C65: # | D65: Input: actuals for hist period; forecast = prior yr ending HC. Used directly in EPE formula. | E65: 9 | I65: =SUM(E65:H65) -> 9 | N65: =SUM(J65:M65) -> 0 | S65: =SUM(O65:R65) -> 0 | X65: =SUM(T65:W65) -> 0 | AC65: =SUM(Y65:AB65) -> 0 | AH65: =SUM(AD65:AG65) -> 0 | AM65: =SUM(AI65:AL65) -> 0 | AR65: =SUM(AN65:AQ65) -> 0
B66: Gross Hires / Qtr — Junior — Base | C66: #/qtr | D66: Scenario-keyed. Upside = faster hiring. Downside = slower/failed hiring. | E66: 1.5 | F66: 1.5 | G66: 1.5 | H66: 1.5 | I66: =SUM(E66:H66) -> 6 | J66: 1.5 | K66: 1.5 | L66: 1.5 | M66: 1.5 | N66: =SUM(J66:M66) -> 6 | O66: 1.5 | P66: 1.5 | Q66: 1.5 | R66: 1.5 | S66: =SUM(O66:R66) -> 6 | T66: 1.5 | U66: 1.5 | V66: 1.5 | W66: 1.5 | X66: =SUM(T66:W66) -> 6 | Y66: 1.5 | Z66: 1.5 | AA66: 1.5 | AB66: 1.5 | AC66: =SUM(Y66:AB66) -> 6 | AD66: 1.5 | AE66: 1.5 | AF66: 1.5 | AG66: 1.5 | AH66: =SUM(AD66:AG66) -> 6 | AI66: 1.5 | AJ66: 1.5 | AK66: 1.5 | AL66: 1.5 | AM66: =SUM(AI66:AL66) -> 6 | AN66: 1.5 | AO66: 1.5 | AP66: 1.5 | AQ66: 1.5 | AR66: =SUM(AN66:AQ66) -> 6
B67: Gross Hires / Qtr — Junior — Upside | E67: 1.65 | F67: 1.65 | G67: 1.65 | H67: 1.65 | I67: =SUM(E67:H67) -> 6.6 | J67: 1.65 | K67: 1.65 | L67: 1.65 | M67: 1.65 | N67: =SUM(J67:M67) -> 6.6 | O67: 1.65 | P67: 1.65 | Q67: 1.65 | R67: 1.65 | S67: =SUM(O67:R67) -> 6.6 | T67: 1.65 | U67: 1.65 | V67: 1.65 | W67: 1.65 | X67: =SUM(T67:W67) -> 6.6 | Y67: 1.65 | Z67: 1.65 | AA67: 1.65 | AB67: 1.65 | AC67: =SUM(Y67:AB67) -> 6.6 | AD67: 1.65 | AE67: 1.65 | AF67: 1.65 | AG67: 1.65 | AH67: =SUM(AD67:AG67) -> 6.6 | AI67: 1.65 | AJ67: 1.65 | AK67: 1.65 | AL67: 1.65 | AM67: =SUM(AI67:AL67) -> 6.6 | AN67: 1.65 | AO67: 1.65 | AP67: 1.65 | AQ67: 1.65 | AR67: =SUM(AN67:AQ67) -> 6.6
B68: Gross Hires / Qtr — Junior — Downside | E68: 1.28 | F68: 1.28 | G68: 1.28 | H68: 1.28 | I68: =SUM(E68:H68) -> 5.12 | J68: 1.28 | K68: 1.28 | L68: 1.28 | M68: 1.28 | N68: =SUM(J68:M68) -> 5.12 | O68: 1.28 | P68: 1.28 | Q68: 1.28 | R68: 1.28 | S68: =SUM(O68:R68) -> 5.12 | T68: 1.28 | U68: 1.28 | V68: 1.28 | W68: 1.28 | X68: =SUM(T68:W68) -> 5.12 | Y68: 1.28 | Z68: 1.28 | AA68: 1.28 | AB68: 1.28 | AC68: =SUM(Y68:AB68) -> 5.12 | AD68: 1.28 | AE68: 1.28 | AF68: 1.28 | AG68: 1.28 | AH68: =SUM(AD68:AG68) -> 5.12 | AI68: 1.28 | AJ68: 1.28 | AK68: 1.28 | AL68: 1.28 | AM68: =SUM(AI68:AL68) -> 5.12 | AN68: 1.28 | AO68: 1.28 | AP68: 1.28 | AQ68: 1.28 | AR68: =SUM(AN68:AQ68) -> 5.12
B69: Gross Hires / Qtr — Junior — ★ ACTIVE | E69: =IF('01 Cover & Control'!$C$19="Base",E66,IF('01 Cover & Control'!$C$19="Upside",E67,E68)) -> 1.5 | F69: =IF('01 Cover & Control'!$C$19="Base",F66,IF('01 Cover & Control'!$C$19="Upside",F67,F68)) -> 1.5 | G69: =IF('01 Cover & Control'!$C$19="Base",G66,IF('01 Cover & Control'!$C$19="Upside",G67,G68)) -> 1.5 | H69: =IF('01 Cover & Control'!$C$19="Base",H66,IF('01 Cover & Control'!$C$19="Upside",H67,H68)) -> 1.5 | I69: =SUM(E69:H69) -> 6 | J69: =IF('01 Cover & Control'!$C$19="Base",J66,IF('01 Cover & Control'!$C$19="Upside",J67,J68)) -> 1.5 | K69: =IF('01 Cover & Control'!$C$19="Base",K66,IF('01 Cover & Control'!$C$19="Upside",K67,K68)) -> 1.5 | L69: =IF('01 Cover & Control'!$C$19="Base",L66,IF('01 Cover & Control'!$C$19="Upside",L67,L68)) -> 1.5 | M69: =IF('01 Cover & Control'!$C$19="Base",M66,IF('01 Cover & Control'!$C$19="Upside",M67,M68)) -> 1.5 | N69: =SUM(J69:M69) -> 6 | O69: =IF('01 Cover & Control'!$C$19="Base",O66,IF('01 Cover & Control'!$C$19="Upside",O67,O68)) -> 1.5 | P69: =IF('01 Cover & Control'!$C$19="Base",P66,IF('01 Cover & Control'!$C$19="Upside",P67,P68)) -> 1.5 | Q69: =IF('01 Cover & Control'!$C$19="Base",Q66,IF('01 Cover & Control'!$C$19="Upside",Q67,Q68)) -> 1.5 | R69: =IF('01 Cover & Control'!$C$19="Base",R66,IF('01 Cover & Control'!$C$19="Upside",R67,R68)) -> 1.5 | S69: =SUM(O69:R69) -> 6 | T69: =IF('01 Cover & Control'!$C$19="Base",T66,IF('01 Cover & Control'!$C$19="Upside",T67,T68)) -> 1.5 | U69: =IF('01 Cover & Control'!$C$19="Base",U66,IF('01 Cover & Control'!$C$19="Upside",U67,U68)) -> 1.5 | V69: =IF('01 Cover & Control'!$C$19="Base",V66,IF('01 Cover & Control'!$C$19="Upside",V67,V68)) -> 1.5 | W69: =IF('01 Cover & Control'!$C$19="Base",W66,IF('01 Cover & Control'!$C$19="Upside",W67,W68)) -> 1.5 | X69: =SUM(T69:W69) -> 6 | Y69: =IF('01 Cover & Control'!$C$19="Base",Y66,IF('01 Cover & Control'!$C$19="Upside",Y67,Y68)) -> 1.5 | Z69: =IF('01 Cover & Control'!$C$19="Base",Z66,IF('01 Cover & Control'!$C$19="Upside",Z67,Z68)) -> 1.5 | AA69: =IF('01 Cover & Control'!$C$19="Base",AA66,IF('01 Cover & Control'!$C$19="Upside",AA67,AA68)) -> 1.5 | AB69: =IF('01 Cover & Control'!$C$19="Base",AB66,IF('01 Cover & Control'!$C$19="Upside",AB67,AB68)) -> 1.5 | AC69: =SUM(Y69:AB69) -> 6 | AD69: =IF('01 Cover & Control'!$C$19="Base",AD66,IF('01 Cover & Control'!$C$19="Upside",AD67,AD68)) -> 1.5 | AE69: =IF('01 Cover & Control'!$C$19="Base",AE66,IF('01 Cover & Control'!$C$19="Upside",AE67,AE68)) -> 1.5 | AF69: =IF('01 Cover & Control'!$C$19="Base",AF66,IF('01 Cover & Control'!$C$19="Upside",AF67,AF68)) -> 1.5 | AG69: =IF('01 Cover & Control'!$C$19="Base",AG66,IF('01 Cover & Control'!$C$19="Upside",AG67,AG68)) -> 1.5 | AH69: =SUM(AD69:AG69) -> 6 | AI69: =IF('01 Cover & Control'!$C$19="Base",AI66,IF('01 Cover & Control'!$C$19="Upside",AI67,AI68)) -> 1.5 | AJ69: =IF('01 Cover & Control'!$C$19="Base",AJ66,IF('01 Cover & Control'!$C$19="Upside",AJ67,AJ68)) -> 1.5 | AK69: =IF('01 Cover & Control'!$C$19="Base",AK66,IF('01 Cover & Control'!$C$19="Upside",AK67,AK68)) -> 1.5 | AL69: =IF('01 Cover & Control'!$C$19="Base",AL66,IF('01 Cover & Control'!$C$19="Upside",AL67,AL68)) -> 1.5 | AM69: =SUM(AI69:AL69) -> 6 | AN69: =IF('01 Cover & Control'!$C$19="Base",AN66,IF('01 Cover & Control'!$C$19="Upside",AN67,AN68)) -> 1.5 | AO69: =IF('01 Cover & Control'!$C$19="Base",AO66,IF('01 Cover & Control'!$C$19="Upside",AO67,AO68)) -> 1.5 | AP69: =IF('01 Cover & Control'!$C$19="Base",AP66,IF('01 Cover & Control'!$C$19="Upside",AP67,AP68)) -> 1.5 | AQ69: =IF('01 Cover & Control'!$C$19="Base",AQ66,IF('01 Cover & Control'!$C$19="Upside",AQ67,AQ68)) -> 1.5 | AR69: =SUM(AN69:AQ69) -> 6
B70: Attrition Rate — Junior — Base | C70: %/qtr | D70: Quarterly attrition rate applied to Beginning HC. Upside = lower attrition (strong market). Downside = higher (competitors poach). | E70: 0.06 | F70: 0.06 | G70: 0.06 | H70: 0.06 | I70: =SUM(E70:H70) -> 0.24 | J70: 0.06 | K70: 0.06 | L70: 0.06 | M70: 0.06 | N70: =SUM(J70:M70) -> 0.24 | O70: 0.06 | P70: 0.06 | Q70: 0.06 | R70: 0.06 | S70: =SUM(O70:R70) -> 0.24 | T70: 0.06 | U70: 0.06 | V70: 0.06 | W70: 0.06 | X70: =SUM(T70:W70) -> 0.24 | Y70: 0.06 | Z70: 0.06 | AA70: 0.06 | AB70: 0.06 | AC70: =SUM(Y70:AB70) -> 0.24 | AD70: 0.06 | AE70: 0.06 | AF70: 0.06 | AG70: 0.06 | AH70: =SUM(AD70:AG70) -> 0.24 | AI70: 0.06 | AJ70: 0.06 | AK70: 0.06 | AL70: 0.06 | AM70: =SUM(AI70:AL70) -> 0.24 | AN70: 0.06 | AO70: 0.06 | AP70: 0.06 | AQ70: 0.06 | AR70: =SUM(AN70:AQ70) -> 0.24
B71: Attrition Rate — Junior — Upside | E71: 0.052 | F71: 0.052 | G71: 0.052 | H71: 0.052 | I71: =SUM(E71:H71) -> 0.208 | J71: 0.052 | K71: 0.052 | L71: 0.052 | M71: 0.052 | N71: =SUM(J71:M71) -> 0.208 | O71: 0.052 | P71: 0.052 | Q71: 0.052 | R71: 0.052 | S71: =SUM(O71:R71) -> 0.208 | T71: 0.052 | U71: 0.052 | V71: 0.052 | W71: 0.052 | X71: =SUM(T71:W71) -> 0.208 | Y71: 0.052 | Z71: 0.052 | AA71: 0.052 | AB71: 0.052 | AC71: =SUM(Y71:AB71) -> 0.208 | AD71: 0.052 | AE71: 0.052 | AF71: 0.052 | AG71: 0.052 | AH71: =SUM(AD71:AG71) -> 0.208 | AI71: 0.052 | AJ71: 0.052 | AK71: 0.052 | AL71: 0.052 | AM71: =SUM(AI71:AL71) -> 0.208 | AN71: 0.052 | AO71: 0.052 | AP71: 0.052 | AQ71: 0.052 | AR71: =SUM(AN71:AQ71) -> 0.208
B72: Attrition Rate — Junior — Downside | E72: 0.08 | F72: 0.08 | G72: 0.08 | H72: 0.08 | I72: =SUM(E72:H72) -> 0.32 | J72: 0.08 | K72: 0.08 | L72: 0.08 | M72: 0.08 | N72: =SUM(J72:M72) -> 0.32 | O72: 0.08 | P72: 0.08 | Q72: 0.08 | R72: 0.08 | S72: =SUM(O72:R72) -> 0.32 | T72: 0.08 | U72: 0.08 | V72: 0.08 | W72: 0.08 | X72: =SUM(T72:W72) -> 0.32 | Y72: 0.08 | Z72: 0.08 | AA72: 0.08 | AB72: 0.08 | AC72: =SUM(Y72:AB72) -> 0.32 | AD72: 0.08 | AE72: 0.08 | AF72: 0.08 | AG72: 0.08 | AH72: =SUM(AD72:AG72) -> 0.32 | AI72: 0.08 | AJ72: 0.08 | AK72: 0.08 | AL72: 0.08 | AM72: =SUM(AI72:AL72) -> 0.32 | AN72: 0.08 | AO72: 0.08 | AP72: 0.08 | AQ72: 0.08 | AR72: =SUM(AN72:AQ72) -> 0.32
