Workbook

Sheet COVER
A2: INSTITUTIONAL M&A MERGER MODEL
A4: The Walt Disney Company
A5: Acquisition of 21st Century Fox (RemainCo / TFCF)
A7: Closed March 20, 2019 · Total consideration $69,456mm · Double-dummy structure
A9: Workbook: Wave 1 build (COVER · README · CONTROL · ASSUMPTIONS · DIS_HIST · FOX_HIST · S&U · PPA)
A11: Version | B11: Wave 1 v1.0
A12: Prepared by | B12: M&A Deal Team - Lead Associate
A13: Model status | B13: =CONTROL!B23 -> MODEL OK
A15: Note: historical foundations (DIS_HIST, FOX_HIST) are LOCKED; PPA values are PRELIMINARY reference pending FY2019 10-K validation.
A16: Units: $ in millions except per-share and shares.

Sheet README
A1: README - Documentation, Sources & Conventions
A4: SOURCE REGISTER
A5: DIS-10K-18 | B5: Disney FY2018 Form 10-K (FYE 9/29/2018) - IS/BS/CF, segments
A6: DIS-10K-16 | B6: Disney FY2016 Form 10-K - FY2016 comparatives & reclassifications
A7: 21CF-10K-18 | B7: 21st Century Fox FY2018 Form 10-K (FYE 6/30/2018) - 21CF total, segments, equity affiliates
A8: FOX-ER-19 | B8: Fox Corporation FY2019 earnings release (8-K Ex.99.1) - New Fox combined carve-out
A9: PROFORMA-A | B9: Disney 8-K/A Ex.99.4 - RemainCo pro forma (Path A, authoritative)
A10: PROFORMA-D | B10: Disney 8-K/A Ex.99.3 - Disney combined pro forma; PPA notes (b)/(c); RSN removal
A11: DIS-10K-19 | B11: Disney FY2019 Form 10-K - FINAL PPA (PENDING validation)
A13: COLOR LEGEND
A14: Blue = hardcoded input
A15: Black = in-sheet formula
A16: Green = link to another worksheet
A17: Red = audit check / flag
A19: CONVENTIONS & NOTES
A20: Units: $ in millions except per-share and shares.
A21: Negatives shown in parentheses; zeros shown as "-".
A22: FY alignment: Disney FYE late-September; RemainCo FYE June 30 (noted on each sheet).
A23: Dependency: left-to-right (a sheet references only sheets to its left).
A24: DIS_HIST and FOX_HIST are LOCKED standalone foundations.
A25: PPA figures are PRELIMINARY pro forma reference - to be validated vs Disney FY2019 10-K.
... A28: CHANGE LOG
A29: Wave 1 v1.0 | B29: Initial build: COVER, README, CONTROL, ASSUMPTIONS, DIS_HIST, FOX_HIST, S&U, PPA

Sheet CONTROL
A1: CONTROL - Dashboard & Audit Gate (Wave 1)
A2: Scenario toggles · key deal outputs · audit panel · MODEL OK
A4: SCENARIO TOGGLES
A5: Scenario (Base / Upside / Downside) | B5: Base
A6: Iterative calculation (Off / On) | B6: Off
A8: KEY DEAL OUTPUTS (Wave 1)
A9: Total consideration | B9: ='S&U'!B12 -> 69456
A10: Net new acquisition debt | B10: ='S&U'!B18 -> 19603
A11: Assumed 21CF debt (book) | B11: =ASSUMPTIONS!B15 -> 19208
A12: 21CF holders ownership % | B12: ='S&U'!B31/'S&U'!B32 -> 0.16998893
A13: Preliminary goodwill - RemainCo | B13: =PPA!B22 -> 34897
A14: Preliminary goodwill - Hulu | B14: =PPA!B33 -> 12774
A15: Total preliminary goodwill | B15: =PPA!B36 -> 47671
A17: AUDIT PANEL
A18: DIS_HIST status | B18: =DIS_HIST!B123 -> OK
A19: FOX_HIST status | B19: =FOX_HIST!B61 -> OK
A20: S&U status | B20: ='S&U'!B37 -> OK
A21: PPA status | B21: =PPA!B38 -> OK
A23: MODEL OK (Wave 1) | B23: =IF(AND(B18="OK",B19="OK",B20="OK",B21="OK"),"MODEL OK","CHECK ERRORS") -> MODEL OK
A25: WORKBOOK BUILD STATUS
A26: COVER | B26: COMPLETE
A27: README | B27: COMPLETE
A28: CONTROL | B28: COMPLETE
A29: ASSUMPTIONS | B29: COMPLETE
A30: DIS_HIST | B30: LOCKED
A31: DIS_PROJ | B31: COMPLETE
A32: FOX_HIST | B32: LOCKED
A33: FOX_PROJ | B33: COMPLETE
A34: S&U | B34: COMPLETE
A35: PPA | B35: COMPLETE
A36: PPA_DA | B36: COMPLETE
A37: SYNERGIES | B37: COMPLETE
... A48: Legend: | B48: Green = COMPLETE / LOCKED · Yellow = DEFERRED (HULU, RSN, PF_BS, PF_CF)

Sheet ASSUMPTIONS
A1: ASSUMPTIONS - Global Inputs, Transaction Terms & Forecast Drivers
A2: $ in millions except per-share; blue = input, black = formula, green = link, red = check. Active case driven by CONTROL scenario toggle.
A4: TRANSACTION TERMS
A5: Cash consideration | B5: 35703 | H5: Disney 8-K/A Ex.99.3/99.4
A6: Stock consideration (307mm sh × $110.00 close) | B6: 33753
A7: Total consideration | B7: =B5+B6 -> 69456
A8: New Disney shares issued to 21CF (mm) | B8: 307
A9: Disney closing price (3/19/2019) | B9: 110
A10: 15-day VWAP (through 3/15/2019) | B10: 114.1801
A11: Exchange ratio (= $38.00 / VWAP) | B11: 0.3328
A12: Per-share 21CF consideration value | B12: 51.572626
A13: New debt incurred (gross) | B13: 35703
A14: Debt repaid from acquired RemainCo cash | B14: 16100
A15: Assumed 21CF debt (book) | B15: 19208
A16: Assumed 21CF debt (fair value) | B16: 22800
A17: Acquired RemainCo cash | B17: 26337
A18: Payment to New Fox (tax true-up) | B18: 2000
A19: Transaction fees & expenses | B19: 150
... A22: Revised equity value (Jun-2018) | B22: 71300
A24: TAX & UNITS REFERENCE
A25: U.S. federal statutory rate (post-TCJA) | B25: 0.21 | H25: FY2018 results distorted by one-time TCJA items
A26: Units: $ in millions; shares in millions; per-share in $.
A27: FY alignment: Disney FYE late-Sept; RemainCo FYE June 30.
A29: SCENARIO SELECTION
A30: Active scenario (linked from CONTROL) | B30: =CONTROL!B5 -> Base
A31: Scenario index (1=Base, 2=Upside, 3=Downside) | B31: =IF(CONTROL!B5="Upside",2,IF(CONTROL!B5="Downside",3,1)) -> 1
A33: DRIVER | B33: Hist ref | C33: Base | D33: Upside | E33: Downside | F33: Active | H33: Source / rationale
A34: A. DISNEY STANDALONE - revenue, margin & corporate drivers
A35: Media Networks - revenue growth (%) | B35: 0.017 | C35: 0.03 | D35: 0.045 | E35: 0.01 | F35: =CHOOSE($B$31,C35,D35,E35) -> 0.03 | H35: Hist FY16–18 CAGR 1.7% (DIS_HIST). Affiliate fees vs cord-cutting; ESPN pressure.
A36: Parks & Resorts - revenue growth (%) | B36: 0.0935 | C36: 0.06 | D36: 0.08 | E36: 0.02 | F36: =CHOOSE($B$31,C36,D36,E36) -> 0.06 | H36: Hist CAGR 9.4%. Capacity/pricing; cyclical downside.
A37: Studio — revenue growth (%) | B37: 0.0285 | C37: 0.04 | D37: 0.08 | E37: -0.02 | F37: =CHOOSE($B$31,C37,D37,E37) -> 0.04 | H37: Hist CAGR 2.9% (volatile, slate-driven).
A38: Consumer Products & IM — revenue growth (%) | B38: -0.0827 | C38: -0.02 | D38: 0.01 | E38: -0.06 | F38: =CHOOSE($B$31,C38,D38,E38) -> -0.02 | H38: Hist CAGR -8.3%. Secular licensing/games decline.
A39: Media Networks — operating margin (%) | B39: 0.2704 | C39: 0.27 | D39: 0.285 | E39: 0.25 | F39: =CHOOSE($B$31,C39,D39,E39) -> 0.27 | H39: Hist FY18 27.0% (DIS_HIST segment OI).
A40: Parks & Resorts — operating margin (%) | B40: 0.2202 | C40: 0.22 | D40: 0.235 | E40: 0.19 | F40: =CHOOSE($B$31,C40,D40,E40) -> 0.22 | H40: Hist FY18 22.0%.
A41: Studio — operating margin (%) | B41: 0.2984 | C41: 0.28 | D41: 0.31 | E41: 0.24 | F41: =CHOOSE($B$31,C41,D41,E41) -> 0.28 | H41: Hist FY18 29.8% (mix-dependent).
A42: Consumer Products & IM — operating margin (%) | B42: 0.3509 | C42: 0.35 | D42: 0.365 | E42: 0.32 | F42: =CHOOSE($B$31,C42,D42,E42) -> 0.35 | H42: Hist FY18 35.1%.
A43: D&A — % of revenue | B43: 0.0507 | C43: 0.05 | D43: 0.05 | E43: 0.05 | F43: =CHOOSE($B$31,C43,D43,E43) -> 0.05 | H43: Hist FY18 5.1%. Capex-linked.
A44: Capex — % of revenue | B44: 0.0751 | C44: 0.07 | D44: 0.06 | E44: 0.085 | F44: =CHOOSE($B$31,C44,D44,E44) -> 0.07 | H44: Hist FY18 7.5%. Park investment cycle.
A45: Net working capital — Δ as % of Δrevenue | B45: 0 | C45: 0 | D45: 0 | E45: 0 | F45: =CHOOSE($B$31,C45,D45,E45) -> 0 | H45: Disney WC near-neutral; assume flat.
A46: Effective tax rate — normalized (%) | B46: 0.24 | C46: 0.24 | D46: 0.22 | E46: 0.26 | F46: =CHOOSE($B$31,C46,D46,E46) -> 0.24 | H46: Post-TCJA 21% fed + state. FY18 (~8%) distorted; pre-TCJA ~33%.
... A50: Diluted shares — standalone (mm) | B50: 1507 | C50: 1488 | D50: 1488 | E50: 1488 | F50: =CHOOSE($B$31,C50,D50,E50) -> 1488 | H50: FY18 diluted 1,507; period-end 1,488; buybacks paused.
A51: B. FOX REMAINCO STANDALONE — revenue, margin & below-the-line
A52: Cable Network Programming — revenue growth (%) | B52: 0.0927 | C52: 0.05 | D52: 0.07 | E52: 0.02 | F52: =CHOOSE($B$31,C52,D52,E52) -> 0.05 | H52: Hist CAGR 9.3% (incl. Star India; RSNs held-for-sale excluded in continuing).
A53: Filmed Entertainment — revenue growth (%) | B53: 0.0141 | C53: 0.03 | D53: 0.06 | E53: -0.02 | F53: =CHOOSE($B$31,C53,D53,E53) -> 0.03 | H53: Hist CAGR 1.4% (slate-driven).
A54: RemainCo OIBDA margin (%) | B54: 0.2026 | C54: 0.205 | D54: 0.22 | E54: 0.18 | F54: =CHOOSE($B$31,C54,D54,E54) -> 0.205 | H54: Hist FY18 20.3% (FOX_HIST).
A55: D&A — % of revenue | B55: 0.0198 | C55: 0.02 | D55: 0.02 | E55: 0.02 | F55: =CHOOSE($B$31,C55,D55,E55) -> 0.02 | H55: Hist FY18 2.0%.
A56: Capex — % of revenue | C56: 0.02 | D56: 0.015 | E56: 0.03 | F56: =CHOOSE($B$31,C56,D56,E56) -> 0.02 | H56: Content/networks capex-light; no separate RemainCo capex disclosed — analyst estimate.
A57: Hulu — equity-method loss ($mm/yr, pre-consol.) | B57: -445 | C57: -600 | D57: -450 | E57: -750 | F57: =CHOOSE($B$31,C57,D57,E57) -> -600 | H57: Hist FY18 -445 (growing); consolidates at close (see HULU).
A58: Interest rate — assumed 21CF debt (%) | B58: 0.0627 | C58: 0.06 | D58: 0.06 | E58: 0.06 | F58: =CHOOSE($B$31,C58,D58,E58) -> 0.06 | H58: Hist ~$1.2B / $19.2B book ≈ 6.3% coupon.
A59: Effective tax rate — normalized (%) | B59: 0.24 | C59: 0.24 | D59: 0.22 | E59: 0.26 | F59: =CHOOSE($B$31,C59,D59,E59) -> 0.24 | H59: Post-TCJA; FY18 distorted.
A60: C. SYNERGIES (management case — to be TESTED, not given)
A61: Run-rate cost synergies ($mm) | C61: 2000 | D61: 2500 | E61: 1500 | F61: =CHOOSE($B$31,C61,D61,E61) -> 2000 | H61: Mgmt guidance: ≥$2.0B by FY2021.
A62: Costs to achieve — total ($mm, one-time) | C62: 1400 | D62: 1000 | E62: 2000 | F62: =CHOOSE($B$31,C62,D62,E62) -> 1400 | H62: Est. ~0.5–1.0× run-rate (deal-typical).
A63: Revenue synergies ($mm) | C63: 0 | D63: 0 | E63: 0 | F63: =CHOOSE($B$31,C63,D63,E63) -> 0 | H63: Excluded (conservative).
A64: Synergy realization phasing (% of run-rate): | C64: FY2019E | D64: FY2020E | E64: FY2021E | F64: FY2022E | G64: FY2023E
A65: Cost-synergy realized (%) | C65: 0.1 | D65: 0.5 | E65: 0.9 | F65: 1 | G65: 1 | H65: Ramp to full run-rate by FY2021 per guidance.
A66: Costs-to-achieve incurred (%) | C66: 0.4 | D66: 0.4 | E66: 0.2 | F66: 0 | G66: 0 | H66: Front-loaded integration spend.
A67: D. DEBT & FINANCING
A68: New acquisition debt rate (%) | B68: 0.033 | C68: 0.033 | D68: 0.03 | E68: 0.04 | F68: =CHOOSE($B$31,C68,D68,E68) -> 0.033 | H68: Phase 3 weighted-avg ~3.3%.
A69: Assumed 21CF debt coupon (%) | B69: 0.0627 | C69: 0.06 | D69: 0.06 | E69: 0.06 | F69: =CHOOSE($B$31,C69,D69,E69) -> 0.06 | H69: Book interest / debt.
A70: Debt FV-premium amortization ($mm/yr) | B70: 205 | C70: 205 | D70: 205 | E70: 205 | F70: =CHOOSE($B$31,C70,D70,E70) -> 205 | H70: PROFORMA-D e3a: ~$205mm/yr interest benefit.
A71: RSN sale proceeds ($mm) | C71: 13070 | D71: 13070 | E71: 13070 | F71: =CHOOSE($B$31,C71,D71,E71) -> 13070 | H71: Sinclair $9,600 + YES $3,470 (FY2019).
A72: RSN proceeds applied to debt (%) | B72: 1 | C72: 1 | D72: 1 | E72: 1 | F72: =CHOOSE($B$31,C72,D72,E72) -> 1 | H72: Mandatory paydown.
A73: Minimum operating cash ($mm) | C73: 4000 | D73: 4000 | E73: 4000 | F73: =CHOOSE($B$31,C73,D73,E73) -> 4000 | H73: Liquidity floor (assumption).
A74: FCF cash sweep to debt (%) | B74: 0.5 | C74: 0.5 | D74: 0.75 | E74: 0.25 | F74: =CHOOSE($B$31,C74,D74,E74) -> 0.5 | H74: Delever priority post-close.
A75: E. PURCHASE ACCOUNTING (PPA) — amortization & tax
A76: Intangibles — useful life (yrs, wtd) | B76: 11 | C76: 11 | D76: 11 | E76: 11 | F76: =CHOOSE($B$31,C76,D76,E76) -> 11 | H76: Phase 4 framework; finite-lived SL.
A77: Film — recent releases life (SYD, yrs wtd) | B77: 8 | C77: 8 | D77: 8 | E77: 8 | F77: =CHOOSE($B$31,C77,D77,E77) -> 8 | H77: Phase 4 framework.
A78: Film — library life (SL, yrs wtd) | B78: 9 | C78: 9 | D78: 9 | E78: 9 | F78: =CHOOSE($B$31,C78,D78,E78) -> 9 | H78: Phase 4 framework.
A79: Hulu intangibles — life (yrs, wtd) | B79: 10 | C79: 10 | D79: 10 | E79: 10 | F79: =CHOOSE($B$31,C79,D79,E79) -> 10 | H79: Phase 4 framework.
A80: Deferred-tax rate on step-ups (%) | B80: 0.24 | C80: 0.24 | D80: 0.24 | E80: 0.24 | F80: =CHOOSE($B$31,C80,D80,E80) -> 0.24 | H80: Blended fed+state; non-taxable reorg → DTL.
A81: Goodwill amortization ($mm) | C81: 0 | D81: 0 | E81: 0 | F81: =CHOOSE($B$31,C81,D81,E81) -> 0 | H81: None — impairment-only (ASC 350); non-deductible.
A82: F. PRO FORMA COMBINATION
A83: Intercompany eliminations (DIS↔RemainCo, $mm) | C83: 0 | D83: 0 | E83: 0 | F83: =CHOOSE($B$31,C83,D83,E83) -> 0 | H83: Minimal direct intercompany; assume ~0.
A84: Combined effective tax rate (%) | B84: 0.24 | C84: 0.24 | D84: 0.22 | E84: 0.26 | F84: =CHOOSE($B$31,C84,D84,E84) -> 0.24 | H84: Blended normalized.
A85: RemainCo NCI — fair value ($mm) | B85: 2747 | C85: 2747 | D85: 2747 | E85: 2747 | F85: =CHOOSE($B$31,C85,D85,E85) -> 2747 | H85: PPA (b9), preliminary.
A86: Hulu NCI 30% — fair value ($mm) | B86: 4500 | C86: 4500 | D86: 4500 | E86: 4500 | F86: =CHOOSE($B$31,C86,D86,E86) -> 4500 | H86: PPA (c), preliminary.
A87: Hulu redeemable NCI 10% — fair value ($mm) | B87: 1500 | C87: 1500 | D87: 1500 | E87: 1500 | F87: =CHOOSE($B$31,C87,D87,E87) -> 1500 | H87: PPA (c), preliminary.
A88: Hulu remeasurement gain — one-time ($mm) | B88: 4669 | C88: 4669 | D88: 4669 | E88: 4669 | F88: =CHOOSE($B$31,C88,D88,E88) -> 4669 | H88: Excluded from ongoing EPS.
A89: G. MACRO / TIMING
A90: Projection horizon | B90: FY2019E – FY2023E (5 years)
A91: Disney fiscal year-end | B91: Late September
A92: RemainCo fiscal year-end | B92: June 30
A93: Acquisition close date | B93: March 20, 2019
A95: CHECK: active scenario resolves (1–3) | B95: =IF(AND($B$31>=1,$B$31<=3),"OK","CHECK") -> OK

Sheet DIS_HIST
A1: DIS_HIST - The Walt Disney Company - Standalone Historicals (LOCKED)
A2: $ in millions except per share & shares; fiscal year ended late September; all 52-week years
A4: Line item ($mm) | B4: FY2016 | C4: FY2017 | D4: FY2018 | F4: Source
A5: INCOME STATEMENT
A6: Services revenue | B6: 47130 | C6: 46843 | D6: 50869 | F6: DIS FY2018 10-K (FYE 9/29/18) & FY2016 10-K; LOCKED dataset, IS p.62
A7: Products revenue | B7: 8502 | C7: 8294 | D7: 8565
A8: Total revenues | B8: =B6+B7 -> 55632 | C8: =C6+C7 -> 55137 | D8: =D6+D7 -> 59434
A9: Cost of services (excl. D&A) | B9: -24653 | C9: -25320 | D9: -27528
A10: Cost of products (excl. D&A) | B10: -5340 | C10: -4986 | D10: -5198
A11: Selling, general, administrative & other | B11: -8754 | C11: -8176 | D11: -8860
A12: Depreciation and amortization | B12: -2527 | C12: -2782 | D12: -3011
A13: Total costs and expenses | B13: =SUM(B9:B12) -> -41274 | C13: =SUM(C9:C12) -> -41264 | D13: =SUM(D9:D12) -> -44597
A14: Restructuring and impairment charges | B14: -156 | C14: -98 | D14: -33
A15: Other income, net | B15: 0 | C15: 78 | D15: 601
A16: Interest expense, net | B16: -260 | C16: -385 | D16: -574
A17: Equity in the income (loss) of investees | B17: 926 | C17: 320 | D17: -102
A18: Income before income taxes | B18: =B8+B13+B14+B15+B16+B17 -> 14868 | C18: =C8+C13+C14+C15+C16+C17 -> 13788 | D18: =D8+D13+D14+D15+D16+D17 -> 14729
A19: Income taxes | B19: -5078 | C19: -4422 | D19: -1663
A20: Net income | B20: =B18+B19 -> 9790 | C20: =C18+C19 -> 9366 | D20: =D18+D19 -> 13066
A21: Less: net income attributable to NCI | B21: -399 | C21: -386 | D21: -468
A22: Net income attributable to Disney | B22: =B20+B21 -> 9391 | C22: =C20+C21 -> 8980 | D22: =D20+D21 -> 12598
A24: Diluted weighted-average shares | B24: 1639 | C24: 1578 | D24: 1507
A25: Basic weighted-average shares | B25: 1629 | C25: 1568 | D25: 1499
A26: Diluted EPS (reported) | B26: 5.73 | C26: 5.69 | D26: 8.36
A27: Diluted EPS (computed) | B27: =B22/B24 -> 5.7297132 | C27: =C22/C24 -> 5.6907478 | D27: =D22/D24 -> 8.3596549
A28: BALANCE SHEET
A29: Cash and cash equivalents | B29: 4610 | C29: 4017 | D29: 4150 | F29: DIS FY2018 10-K (FYE 9/29/18) & FY2016 10-K; LOCKED dataset, BS p.64
A30: Receivables | B30: 9065 | C30: 8633 | D30: 9334
A31: Inventories | B31: 1390 | C31: 1373 | D31: 1392
A32: Television costs and advances | B32: 1208 | C32: 1278 | D32: 1314
A33: Other current assets | B33: 693 | C33: 588 | D33: 635
A34: Total current assets | B34: =SUM(B29:B33) -> 16966 | C34: =SUM(C29:C33) -> 15889 | D34: =SUM(D29:D33) -> 16825
A35: Film and television costs | B35: 6339 | C35: 7481 | D35: 7888
A36: Investments | B36: 4280 | C36: 3202 | D36: 2899
A37: Attractions, buildings and equipment | B37: 50270 | C37: 54043 | D37: 55238
A38: Accumulated depreciation | B38: -26849 | C38: -29037 | D38: -30764
A39: Projects in progress | B39: 2684 | C39: 2145 | D39: 3942
A40: Land | B40: 1244 | C40: 1255 | D40: 1124
A41: Parks, resorts and other property, net | B41: =SUM(B37:B40) -> 27349 | C41: =SUM(C37:C40) -> 28406 | D41: =SUM(D37:D40) -> 29540
A42: Intangible assets, net | B42: 6949 | C42: 6995 | D42: 6812
A43: Goodwill | B43: 27810 | C43: 31426 | D43: 31269
A44: Other assets | B44: 2340 | C44: 2390 | D44: 3365
A45: TOTAL ASSETS | B45: =B34+B35+B36+B41+B42+B43+B44 -> 92033 | C45: =C34+C35+C36+C41+C42+C43+C44 -> 95789 | D45: =D34+D35+D36+D41+D42+D43+D44 -> 98598
A46: Accounts payable and other accrued liabilities | B46: 9130 | C46: 8855 | D46: 9479
A47: Current portion of borrowings | B47: 3687 | C47: 6172 | D47: 3790
A48: Deferred revenue and other (FY16: unearned royalties) | B48: 4025 | C48: 4568 | D48: 4591
A49: Total current liabilities | B49: =SUM(B46:B48) -> 16842 | C49: =SUM(C46:C48) -> 19595 | D49: =SUM(D46:D48) -> 17860
A50: Borrowings (long-term) | B50: 16483 | C50: 19119 | D50: 17084
A51: Deferred income taxes | B51: 3679 | C51: 4480 | D51: 3109
A52: Other long-term liabilities | B52: 7706 | C52: 6443 | D52: 6590
A53: Total liabilities | B53: =B49+B50+B51+B52 -> 44710 | C53: =C49+C50+C51+C52 -> 49637 | D53: =D49+D50+D51+D52 -> 44643
A54: Redeemable noncontrolling interests | B54: 0 | C54: 1148 | D54: 1123
A55: Common stock | B55: 35859 | C55: 36248 | D55: 36779
A56: Retained earnings | B56: 66088 | C56: 72606 | D56: 82679
A57: Accumulated other comprehensive loss | B57: -3979 | C57: -3528 | D57: -3097
A58: Treasury stock, at cost | B58: -54703 | C58: -64011 | D58: -67588
A59: Total Disney shareholders' equity | B59: =SUM(B55:B58) -> 43265 | C59: =SUM(C55:C58) -> 41315 | D59: =SUM(D55:D58) -> 48773
A60: Noncontrolling interests | B60: 4058 | C60: 3689 | D60: 4059
A61: Total equity | B61: =B59+B60 -> 47323 | C61: =C59+C60 -> 45004 | D61: =D59+D60 -> 52832
A62: TOTAL LIABILITIES AND EQUITY | B62: =B53+B54+B61 -> 92033 | C62: =C53+C54+C61 -> 95789 | D62: =D53+D54+D61 -> 98598
A63: CHECK: Assets − Liab − Equity (=0) | B63: =B45-B62 -> 0 | C63: =C45-C62 -> 0 | D63: =D45-D62 -> 0
A64: CASH FLOW STATEMENT
A65: Net income | B65: =B20 -> 9790 | C65: =C20 -> 9366 | D65: =D20 -> 13066 | F65: ties to IS net income
A66: Depreciation and amortization | B66: 2527 | C66: 2782 | D66: 3011
A67: Gains on acquisitions and dispositions | B67: -26 | C67: -289 | D67: -560
A68: Deferred income taxes | B68: 1214 | C68: 334 | D68: -1573
A69: Equity in the (income) loss of investees | B69: -926 | C69: -320 | D69: 102
A70: Cash distributions from equity investees | B70: 799 | C70: 788 | D70: 775
A71: Net change in film and television costs | B71: -101 | C71: -1075 | D71: -523
A72: Equity-based compensation | B72: 393 | C72: 364 | D72: 393
A73: Other | B73: 674 | C73: 503 | D73: 441
A74: Δ Receivables | B74: -393 | C74: 107 | D74: -720
A75: Δ Inventories | B75: 186 | C75: -5 | D75: -17
A76: Δ Other assets | B76: -443 | C76: -52 | D76: -927
A77: Δ Accounts payable and accrued liabilities | B77: 40 | C77: -368 | D77: 235
A78: Δ Income taxes | B78: -598 | C78: 208 | D78: 592
A79: Cash provided by operations | B79: =B65+SUM(B66:B78) -> 13136 | C79: =C65+SUM(C66:C78) -> 12343 | D79: =D65+SUM(D66:D78) -> 14295
A80: Investments in parks, resorts & other property | B80: -4773 | C80: -3623 | D80: -4465
A81: Acquisitions | B81: -850 | C81: -417 | D81: -1581
A82: Other investing activities | B82: -135 | C82: -71 | D82: 710
A83: Cash used in investing activities | B83: =SUM(B80:B82) -> -5758 | C83: =SUM(C80:C82) -> -4111 | D83: =SUM(D80:D82) -> -5336
A84: Commercial paper borrowings, net | B84: -920 | C84: 1247 | D84: -1768
A85: Borrowings | B85: 6065 | C85: 4820 | D85: 1056
A86: Reduction of borrowings | B86: -2205 | C86: -2364 | D86: -1871
A87: Dividends | B87: -2313 | C87: -2445 | D87: -2515
A88: Repurchases of common stock | B88: -7499 | C88: -9368 | D88: -3577
A89: Proceeds from exercise of stock options | B89: 259 | C89: 276 | D89: 210
A90: Contributions from NCI holders | B90: 0 | C90: 17 | D90: 399
A91: Other financing activities | B91: -607 | C91: -1142 | D91: -777
A92: Cash used in financing activities | B92: =SUM(B84:B91) -> -7220 | C92: =SUM(C84:C91) -> -8959 | D92: =SUM(D84:D91) -> -8843
A93: Impact of exchange rates on cash | B93: -123 | C93: 31 | D93: -25
A94: Change in cash, cash equiv. & restricted cash | B94: =B79+B83+B92+B93 -> 35 | C94: =C79+C83+C92+C93 -> -696 | D94: =D79+D83+D92+D93 -> 91
A95: Cash, beginning of year | B95: 4725 | C95: =B96 -> 4760 | D95: =C96 -> 4064
A96: Cash, end of year | B96: =B95+B94 -> 4760 | C96: =C95+C94 -> 4064 | D96: =D95+D94 -> 4155
A97: Memo: restricted cash (in other assets) | B97: 150 | C97: 47 | D97: 5
A98: CHECK: CF end cash − (BS cash + restricted) (=0) | B98: =B96-(B29+B97) -> 0 | C98: =C96-(C29+C97) -> 0 | D98: =D96-(D29+D97) -> 0
A100: Supplemental: interest paid | B100: 395 | C100: 466 | D100: 631
A101: Supplemental: income taxes paid | B101: 4133 | C101: 3801 | D101: 2503
A102: SUPPORTING SCHEDULES
A103: Current portion of borrowings | B103: 3687 | C103: 6172 | D103: 3790 | F103: Debt schedule
...

Sheet DIS_PROJ
A1: DIS_PROJ - The Walt Disney Company - Standalone Forecast
A2: $ in millions except per share; FY2018A linked from DIS_HIST; FY2019E–FY2023E driven by ASSUMPTIONS active case. Segment taxonomy = locked FY16–18 (4-segment).
A4: Line item ($mm) | B4: FY2018A | C4: FY2019E | D4: FY2020E | E4: FY2021E | F4: FY2022E | G4: FY2023E | H4: Driver / source
A5: SEGMENT FORECAST (revenue · margin · operating income)
A6: Media Networks - revenue growth % | C6: =ASSUMPTIONS!F35 -> 0.03 | D6: =ASSUMPTIONS!F35 -> 0.03 | E6: =ASSUMPTIONS!F35 -> 0.03 | F6: =ASSUMPTIONS!F35 -> 0.03 | G6: =ASSUMPTIONS!F35 -> 0.03 | H6: ASSUMPTIONS!F35
A7: Media Networks - revenue | B7: =DIS_HIST!D110 -> 24500 | C7: =B7*(1+C6) -> 25235 | D7: =C7*(1+D6) -> 25992.05 | E7: =D7*(1+E6) -> 26771.811 | F7: =E7*(1+F6) -> 27574.966 | G7: =F7*(1+G6) -> 28402.215
A8: Media Networks - operating margin % | B8: =DIS_HIST!D117/DIS_HIST!D110 -> 0.27040816 | C8: =ASSUMPTIONS!F39 -> 0.27 | D8: =ASSUMPTIONS!F39 -> 0.27 | E8: =ASSUMPTIONS!F39 -> 0.27 | F8: =ASSUMPTIONS!F39 -> 0.27 | G8: =ASSUMPTIONS!F39 -> 0.27 | H8: ASSUMPTIONS!F39
A9: Media Networks - operating income | B9: =DIS_HIST!D117 -> 6625 | C9: =C7*C8 -> 6813.45 | D9: =D7*D8 -> 7017.8535 | E9: =E7*E8 -> 7228.3891 | F9: =F7*F8 -> 7445.2408 | G9: =G7*G8 -> 7668.598
A10: Parks & Resorts - revenue growth % | C10: =ASSUMPTIONS!F36 -> 0.06 | D10: =ASSUMPTIONS!F36 -> 0.06 | E10: =ASSUMPTIONS!F36 -> 0.06 | F10: =ASSUMPTIONS!F36 -> 0.06 | G10: =ASSUMPTIONS!F36 -> 0.06 | H10: ASSUMPTIONS!F36
A11: Parks & Resorts - revenue | B11: =DIS_HIST!D111 -> 20296 | C11: =B11*(1+C10) -> 21513.76 | D11: =C11*(1+D10) -> 22804.586 | E11: =D11*(1+E10) -> 24172.861 | F11: =E11*(1+F10) -> 25623.232 | G11: =F11*(1+G10) -> 27160.626
A12: Parks & Resorts - operating margin % | B12: =DIS_HIST!D118/DIS_HIST!D111 -> 0.22019117 | C12: =ASSUMPTIONS!F40 -> 0.22 | D12: =ASSUMPTIONS!F40 -> 0.22 | E12: =ASSUMPTIONS!F40 -> 0.22 | F12: =ASSUMPTIONS!F40 -> 0.22 | G12: =ASSUMPTIONS!F40 -> 0.22 | H12: ASSUMPTIONS!F40
A13: Parks & Resorts - operating income | B13: =DIS_HIST!D118 -> 4469 | C13: =C11*C12 -> 4733.0272 | D13: =D11*D12 -> 5017.0088 | E13: =E11*E12 -> 5318.0294 | F13: =F11*F12 -> 5637.1111 | G13: =G11*G12 -> 5975.3378
A14: Studio Entertainment - revenue growth % | C14: =ASSUMPTIONS!F37 -> 0.04 | D14: =ASSUMPTIONS!F37 -> 0.04 | E14: =ASSUMPTIONS!F37 -> 0.04 | F14: =ASSUMPTIONS!F37 -> 0.04 | G14: =ASSUMPTIONS!F37 -> 0.04 | H14: ASSUMPTIONS!F37
A15: Studio Entertainment - revenue | B15: =DIS_HIST!D112 -> 9987 | C15: =B15*(1+C14) -> 10386.48 | D15: =C15*(1+D14) -> 10801.939 | E15: =D15*(1+E14) -> 11234.017 | F15: =E15*(1+F14) -> 11683.377 | G15: =F15*(1+G14) -> 12150.713
A16: Studio Entertainment - operating margin % | B16: =DIS_HIST!D119/DIS_HIST!D112 -> 0.2983879 | C16: =ASSUMPTIONS!F41 -> 0.28 | D16: =ASSUMPTIONS!F41 -> 0.28 | E16: =ASSUMPTIONS!F41 -> 0.28 | F16: =ASSUMPTIONS!F41 -> 0.28 | G16: =ASSUMPTIONS!F41 -> 0.28 | H16: ASSUMPTIONS!F41
A17: Studio Entertainment - operating income | B17: =DIS_HIST!D119 -> 2980 | C17: =C15*C16 -> 2908.2144 | D17: =D15*D16 -> 3024.543 | E17: =E15*E16 -> 3145.5247 | F17: =F15*F16 -> 3271.3457 | G17: =G15*G16 -> 3402.1995
A18: Consumer Products & Interactive Media - revenue growth % | C18: =ASSUMPTIONS!F38 -> -0.02 | D18: =ASSUMPTIONS!F38 -> -0.02 | E18: =ASSUMPTIONS!F38 -> -0.02 | F18: =ASSUMPTIONS!F38 -> -0.02 | G18: =ASSUMPTIONS!F38 -> -0.02 | H18: ASSUMPTIONS!F38
A19: Consumer Products & Interactive Media - revenue | B19: =DIS_HIST!D113 -> 4651 | C19: =B19*(1+C18) -> 4557.98 | D19: =C19*(1+D18) -> 4466.8204 | E19: =D19*(1+E18) -> 4377.484 | F19: =E19*(1+F18) -> 4289.9343 | G19: =F19*(1+G18) -> 4204.1356
A20: Consumer Products & Interactive Media - operating margin % | B20: =DIS_HIST!D120/DIS_HIST!D113 -> 0.35089228 | C20: =ASSUMPTIONS!F42 -> 0.35 | D20: =ASSUMPTIONS!F42 -> 0.35 | E20: =ASSUMPTIONS!F42 -> 0.35 | F20: =ASSUMPTIONS!F42 -> 0.35 | G20: =ASSUMPTIONS!F42 -> 0.35 | H20: ASSUMPTIONS!F42
A21: Consumer Products & Interactive Media - operating income | B21: =DIS_HIST!D120 -> 1632 | C21: =C19*C20 -> 1595.293 | D21: =D19*D20 -> 1563.3871 | E21: =E19*E20 -> 1532.1194 | F21: =F19*F20 -> 1501.477 | G21: =G19*G20 -> 1471.4475
A22: CONSOLIDATED INCOME STATEMENT
A23: Consolidated revenue | B23: =SUM(B7,B11,B15,B19) -> 59434 | C23: =SUM(C7,C11,C15,C19) -> 61693.22 | D23: =SUM(D7,D11,D15,D19) -> 64065.395 | E23: =SUM(E7,E11,E15,E19) -> 66556.173 | F23: =SUM(F7,F11,F15,F19) -> 69171.51 | G23: =SUM(G7,G11,G15,G19) -> 71917.689
A24: Total segment operating income | B24: =SUM(B9,B13,B17,B21) -> 15706 | C24: =SUM(C9,C13,C17,C21) -> 16049.985 | D24: =SUM(D9,D13,D17,D21) -> 16622.792 | E24: =SUM(E9,E13,E17,E21) -> 17224.063 | F24: =SUM(F9,F13,F17,F21) -> 17855.175 | G24: =SUM(G9,G13,G17,G21) -> 18517.583
A25: Corporate, unallocated & amortization | B25: =(DIS_HIST!D8+DIS_HIST!D13)-B24 -> -869 | C25: =C23*($B$25/$B$23) -> -902.03264 | D25: =D23*($B$25/$B$23) -> -936.71684 | E25: =E23*($B$25/$B$23) -> -973.13515 | F25: =F23*($B$25/$B$23) -> -1011.3747 | G25: =G23*($B$25/$B$23) -> -1051.5273 | H25: Calibrated FY18A; held as % of revenue
A26: Operating income (EBIT) | B26: =B24+B25 -> 14837 | C26: =C24+C25 -> 15147.952 | D26: =D24+D25 -> 15686.076 | E26: =E24+E25 -> 16250.927 | F26: =F24+F25 -> 16843.8 | G26: =G24+G25 -> 17466.055
A27: Depreciation & amortization | B27: =DIS_HIST!D66 -> 3011 | C27: =C23*ASSUMPTIONS!$F$43 -> 3084.661 | D27: =D23*ASSUMPTIONS!$F$43 -> 3203.2698 | E27: =E23*ASSUMPTIONS!$F$43 -> 3327.8086 | F27: =F23*ASSUMPTIONS!$F$43 -> 3458.5755 | G27: =G23*ASSUMPTIONS!$F$43 -> 3595.8845 | H27: ASSUMPTIONS D&A % of revenue
A28: EBITDA | B28: =B26+B27 -> 17848 | C28: =C26+C27 -> 18232.613 | D28: =D26+D27 -> 18889.345 | E28: =E26+E27 -> 19578.736 | F28: =F26+F27 -> 20302.375 | G28: =G26+G27 -> 21061.94
A29: Restructuring & impairment | B29: =DIS_HIST!D14 -> -33 | C29: 0 | D29: 0 | E29: 0 | F29: 0 | G29: 0 | H29: Non-recurring; forecast 0
A30: Other income, net | B30: =DIS_HIST!D15 -> 601 | C30: 0 | D30: 0 | E30: 0 | F30: 0 | G30: 0 | H30: FY18 one-time gains; forecast 0
A31: Equity in income of investees | B31: =DIS_HIST!D17 -> -102 | C31: 0 | D31: 0 | E31: 0 | F31: 0 | G31: 0
A32: Net debt (held at FY18A) - memo | B32: =DIS_HIST!D105 -> 20874 | C32: =$B$32 -> 20874 | D32: =$B$32 -> 20874 | E32: =$B$32 -> 20874 | F32: =$B$32 -> 20874 | G32: =$B$32 -> 20874 | H32: Standalone capital structure held flat
A33: Interest rate (standalone) - memo | C33: =ASSUMPTIONS!$F$47 -> 0.035 | D33: =ASSUMPTIONS!$F$47 -> 0.035 | E33: =ASSUMPTIONS!$F$47 -> 0.035 | F33: =ASSUMPTIONS!$F$47 -> 0.035 | G33: =ASSUMPTIONS!$F$47 -> 0.035
A34: Net interest expense | B34: =DIS_HIST!D16 -> -574 | C34: =-C32*C33 -> -730.59 | D34: =-D32*D33 -> -730.59 | E34: =-E32*E33 -> -730.59 | F34: =-F32*F33 -> -730.59 | G34: =-G32*G33 -> -730.59
A35: Income before income taxes (EBT) | B35: =B26+B29+B30+B31+B34 -> 14729 | C35: =C26+C29+C30+C31+C34 -> 14417.362 | D35: =D26+D29+D30+D31+D34 -> 14955.486 | E35: =E26+E29+E30+E31+E34 -> 15520.337 | F35: =F26+F29+F30+F31+F34 -> 16113.21 | G35: =G26+G29+G30+G31+G34 -> 16735.465
A36: Effective tax rate - memo | C36: =ASSUMPTIONS!$F$46 -> 0.24 | D36: =ASSUMPTIONS!$F$46 -> 0.24 | E36: =ASSUMPTIONS!$F$46 -> 0.24 | F36: =ASSUMPTIONS!$F$46 -> 0.24 | G36: =ASSUMPTIONS!$F$46 -> 0.24
A37: Income taxes | B37: =DIS_HIST!D19 -> -1663 | C37: =-C35*C36 -> -3460.1669 | D37: =-D35*D36 -> -3589.3165 | E37: =-E35*E36 -> -3724.881 | F37: =-F35*F36 -> -3867.1704 | G37: =-G35*G36 -> -4016.5117 | H37: FY18A actual (TCJA); forecast normalized
A38: Net income | B38: =B35+B37 -> 13066 | C38: =C35+C37 -> 10957.195 | D38: =D35+D37 -> 11366.169 | E38: =E35+E37 -> 11795.456 | F38: =F35+F37 -> 12246.04 | G38: =G35+G37 -> 12718.954
A39: Less: NI attributable to NCI | B39: =DIS_HIST!D21 -> -468 | C39: =C38*($B$39/$B$38) -> -392.4665 | D39: =D38*($B$39/$B$38) -> -407.11519 | E39: =E38*($B$39/$B$38) -> -422.49147 | F39: =F38*($B$39/$B$38) -> -438.63053 | G39: =G38*($B$39/$B$38) -> -455.56944
A40: Net income attributable to Disney | B40: =B38+B39 -> 12598 | C40: =C38+C39 -> 10564.729 | D40: =D38+D39 -> 10959.054 | E40: =E38+E39 -> 11372.965 | F40: =F38+F39 -> 11807.409 | G40: =G38+G39 -> 12263.384
A41: Diluted weighted-avg shares | B41: =DIS_HIST!D24 -> 1507 | C41: =ASSUMPTIONS!$F$50 -> 1488 | D41: =ASSUMPTIONS!$F$50 -> 1488 | E41: =ASSUMPTIONS!$F$50 -> 1488 | F41: =ASSUMPTIONS!$F$50 -> 1488 | G41: =ASSUMPTIONS!$F$50 -> 1488 | H41: Buybacks paused post-deal
A42: Diluted EPS | B42: =B40/B41 -> 8.3596549 | C42: =C40/C41 -> 7.099952 | D42: =D40/D41 -> 7.3649556 | E42: =E40/E41 -> 7.6431216 | F42: =F40/F41 -> 7.9350867 | G42: =G40/G41 -> 8.2415217
A43: KEY METRICS (summary)
A44: EBITDA | B44: =B28 -> 17848 | C44: =C28 -> 18232.613 | D44: =D28 -> 18889.345 | E44: =E28 -> 19578.736 | F44: =F28 -> 20302.375 | G44: =G28 -> 21061.94
A45: EBIT | B45: =B26 -> 14837 | C45: =C26 -> 15147.952 | D45: =D26 -> 15686.076 | E45: =E26 -> 16250.927 | F45: =F26 -> 16843.8 | G45: =G26 -> 17466.055
A46: EBT (pre-tax income) | B46: =B35 -> 14729 | C46: =C35 -> 14417.362 | D46: =D35 -> 14955.486 | E46: =E35 -> 15520.337 | F46: =F35 -> 16113.21 | G46: =G35 -> 16735.465
A47: Net income attributable to Disney | B47: =B40 -> 12598 | C47: =C40 -> 10564.729 | D47: =D40 -> 10959.054 | E47: =E40 -> 11372.965 | F47: =F40 -> 11807.409 | G47: =G40 -> 12263.384
A48: SUPPORTING SCHEDULES
A49: D&A - % of revenue | C49: =ASSUMPTIONS!$F$43 -> 0.05 | D49: =ASSUMPTIONS!$F$43 -> 0.05 | E49: =ASSUMPTIONS!$F$43 -> 0.05 | F49: =ASSUMPTIONS!$F$43 -> 0.05 | G49: =ASSUMPTIONS!$F$43 -> 0.05
A50: D&A - $ | B50: =B27 -> 3011 | C50: =C27 -> 3084.661 | D50: =D27 -> 3203.2698 | E50: =E27 -> 3327.8086 | F50: =F27 -> 3458.5755 | G50: =G27 -> 3595.8845
A51: Capex - % of revenue | C51: =ASSUMPTIONS!$F$44 -> 0.07 | D51: =ASSUMPTIONS!$F$44 -> 0.07 | E51: =ASSUMPTIONS!$F$44 -> 0.07 | F51: =ASSUMPTIONS!$F$44 -> 0.07 | G51: =ASSUMPTIONS!$F$44 -> 0.07
A52: Capex - $ | B52: =-DIS_HIST!D80 -> 4465 | C52: =C23*ASSUMPTIONS!$F$44 -> 4318.5254 | D52: =D23*ASSUMPTIONS!$F$44 -> 4484.5777 | E52: =E23*ASSUMPTIONS!$F$44 -> 4658.9321 | F52: =F23*ASSUMPTIONS!$F$44 -> 4842.0057 | G52: =G23*ASSUMPTIONS!$F$44 -> 5034.2383
A53: Working capital - Δ% of Δrevenue | C53: =ASSUMPTIONS!$F$45 -> 0 | D53: =ASSUMPTIONS!$F$45 -> 0 | E53: =ASSUMPTIONS!$F$45 -> 0 | F53: =ASSUMPTIONS!$F$45 -> 0 | G53: =ASSUMPTIONS!$F$45 -> 0
A54: Working capital - change | C54: =(C23-B23)*ASSUMPTIONS!$F$45 -> 0 | D54: =(D23-C23)*ASSUMPTIONS!$F$45 -> 0 | E54: =(E23-D23)*ASSUMPTIONS!$F$45 -> 0 | F54: =(F23-E23)*ASSUMPTIONS!$F$45 -> 0 | G54: =(G23-F23)*ASSUMPTIONS!$F$45 -> 0 | H54: Disney WC near-neutral
A55: Effective tax rate | C55: =ASSUMPTIONS!$F$46 -> 0.24 | D55: =ASSUMPTIONS!$F$46 -> 0.24 | E55: =ASSUMPTIONS!$F$46 -> 0.24 | F55: =ASSUMPTIONS!$F$46 -> 0.24 | G55: =ASSUMPTIONS!$F$46 -> 0.24
A56: Diluted shares (mm) | B56: =B41 -> 1507 | C56: =C41 -> 1488 | D56: =D41 -> 1488 | E56: =E41 -> 1488 | F56: =F41 -> 1488 | G56: =G41 -> 1488
A57: Dividend per share ($) | C57: =ASSUMPTIONS!$F$48 -> 1.76 | D57: =ASSUMPTIONS!$F$48 -> 1.76 | E57: =ASSUMPTIONS!$F$48 -> 1.76 | F57: =ASSUMPTIONS!$F$48 -> 1.76 | G57: =ASSUMPTIONS!$F$48 -> 1.76
A58: Share repurchases ($mm) | C58: =ASSUMPTIONS!$F$49 -> 0 | D58: =ASSUMPTIONS!$F$49 -> 0 | E58: =ASSUMPTIONS!$F$49 -> 0 | F58: =ASSUMPTIONS!$F$49 -> 0 | G58: =ASSUMPTIONS!$F$49 -> 0
A59: AUDIT CHECKS (red = must be ~0)
A60: Segment revenue ties to consolidated (=0) | B60: =B23-SUM(B7,B11,B15,B19) -> 0 | C60: =C23-SUM(C7,C11,C15,C19) -> 0 | D60: =D23-SUM(D7,D11,D15,D19) -> 0 | E60: =E23-SUM(E7,E11,E15,E19) -> 0 | F60: =F23-SUM(F7,F11,F15,F19) -> 0 | G60: =G23-SUM(G7,G11,G15,G19) -> 0
A61: Segment OI ties to total (=0) | B61: =B24-SUM(B9,B13,B17,B21) -> 0 | C61: =C24-SUM(C9,C13,C17,C21) -> 0 | D61: =D24-SUM(D9,D13,D17,D21) -> 0 | E61: =E24-SUM(E9,E13,E17,E21) -> 0 | F61: =F24-SUM(F9,F13,F17,F21) -> 0 | G61: =G24-SUM(G9,G13,G17,G21) -> 0
A62: FY18A consolidated revenue ties to DIS_HIST (=0) | B62: =B23-DIS_HIST!D8 -> 0
A63: FY18A EBT ties to DIS_HIST (=0) | B63: =B35-DIS_HIST!D18 -> 0
A64: FY18A net income to Disney ties (=0) | B64: =B40-DIS_HIST!D22 -> 0
A65: FY18A diluted EPS ties (≈0) | B65: =B42-DIS_HIST!D26 -> -0.0003450564
A67: SHEET STATUS | B67: =IF(AND(ABS(B60)<1,ABS(C60)<1,ABS(B61)<1,ABS(C61)<1,ABS(B62)<1,ABS(B63)<1,ABS(B64)<1,ABS(B65)<0.01),"OK","CHECK") -> OK

Sheet FOX_HIST
A1: FOX_HIST - Fox RemainCo (TFCF) - Standalone Historicals
A2: $ in millions except per share & shares; fiscal year ended June 30; authoritative pro forma RemainCo
A4: Line item ($mm) | B4: FY2016 | C4: FY2017 | D4: FY2018 | F4: Source
A5: INCOME STATEMENT (Path A - RemainCo)
A6: Revenues | B6: 19111 | C6: 19307 | D6: 20851 | F6: Disney 8-K/A Ex.99.4 RemainCo Pro Forma (Path A); LOCKED
A7: Operating expenses | B7: -12575 | C7: -12747 | D7: -13855
A8: Selling, general and administrative | B8: -2449 | C8: -2444 | D8: -2771
A9: OIBDA (Rev − OpEx − SG&A) | B9: =B6+B7+B8 -> 4087 | C9: =C6+C7+C8 -> 4116 | D9: =D6+D7+D8 -> 4225
A10: Depreciation and amortization | B10: -363 | C10: -388 | D10: -413
A11: Impairment and restructuring charges | B11: -268 | C11: -150 | D11: -56
A12: EBIT (operating income) | B12: =B9+B10+B11 -> 3456 | C12: =C9+C10+C11 -> 3578 | D12: =D9+D10+D11 -> 3756
A13: Equity earnings (losses) of affiliates | B13: -35 | C13: -42 | D13: -563
A14: Interest expense, net | B14: -1166 | C14: -1195 | D14: -1205
A15: Interest income | B15: 33 | C15: 34 | D15: 39
A16: Other, net | B16: -244 | C16: -253 | D16: -571
A17: Pre-tax income (continuing operations) | B17: =B12+B13+B14+B15+B16 -> 2044 | C17: =C12+C13+C14+C15+C16 -> 2122 | D17: =D12+D13+D14+D15+D16 -> 1456
A18: Income tax benefit (expense) | B18: -347 | C18: -522 | D18: 196
A19: Income from continuing operations | B19: =B17+B18 -> 1697 | C19: =C17+C18 -> 1600 | D19: =D17+D18 -> 1652
A20: Less: NI attributable to NCI | B20: -226 | C20: -237 | D20: -257
A21: Net income attributable to RemainCo | B21: =B19+B20 -> 1471 | C21: =C19+C20 -> 1363 | D21: =D19+D20 -> 1395
A23: Diluted weighted-avg shares | B23: 1943 | C23: 1854 | D23: 1852
A24: Diluted EPS (reported) | B24: 0.76 | C24: 0.73 | D24: 0.75
A25: Diluted EPS (computed) | B25: =B21/B23 -> 0.75707669 | C25: =C21/C23 -> 0.73516721 | D25: =D21/D23 -> 0.75323974
A26: CHECK: EPS computed − reported (≈0) | B26: =B25-B24 -> -0.0029233145 | C26: =C25-C24 -> 0.005167206 | D26: =D25-D24 -> 0.0032397408
A27: CARVE-OUT BRIDGE (21CF total → RemainCo revenue)
A28: 21CF total revenue | B28: 27326 | C28: 28500 | D28: 30400 | F28: 21CF FY2018 10-K
A29: Less: New Fox (FOX) revenue removed (ASC 205) | B29: -8948 | C29: -9977 | D29: -10215 | F29: Ex.99.4 FOX col
A30: Plus: intercompany reversal (3.c) | B30: 733 | C30: 784 | D30: 666 | F30: Ex.99.4 adj 3.c
A31: RemainCo revenue | B31: =B28+B29+B30 -> 19111 | C31: =C28+C29+C30 -> 19307 | D31: =D28+D29+D30 -> 20851
A32: CHECK: bridge − Path A revenue (=0) | B32: =B31-B6 -> 0 | C32: =C31-C6 -> 0 | D32: =D31-D6 -> 0
A33: Memo - corporate allocation (combined vs ASC 205): ~$310mm FY18
A34: EQUITY AFFILIATES & KEY ITEMS
A35: Sky (39%, sold to cash Oct-2018; excl. FY18) | B35: 383 | C35: 338 | D35: 426 | F35: excluded from acquired RemainCo
A36: Hulu (30%, retained equity method) | B36: -157 | C36: -215 | D36: -445 | F36: → 60% consolidation post-close
A37: Other equity affiliates | B37: -260 | C37: -164 | D37: -119
A39: RSN revenue (held-for-sale, FY2018 only) | D39: 4331 | F39: Ex.99.3 RSN removal col
A40: RSN OIBDA (held-for-sale, FY2018 only) | D40: 2013
A41: SEGMENTS - 21CF TOTAL (reference)
A42: Cable Network Programming - revenue | B42: 15029 | C42: 16130 | D42: 17946
A43: Television - revenue | B43: 5105 | C43: 5649 | D43: 5162
A44: Filmed Entertainment - revenue | B44: 8505 | C44: 8235 | D44: 8747
A45: Other, Corporate & Eliminations - revenue | B45: -1313 | C45: -1514 | D45: -1455
A46: Total 21CF revenue | B46: =SUM(B42:B45) -> 27326 | C46: =SUM(C42:C45) -> 28500 | D46: =SUM(D42:D45) -> 30400
A47: CHECK: segment total − 21CF total (=0) | B47: =B46-B28 -> 0 | C47: =C46-C28 -> 0 | D47: =D46-D28 -> 0
A48: Cable Network Programming - OIBDA | B48: 5145 | C48: 5601 | D48: 6173
A49: Television - OIBDA | B49: 744 | C49: 894 | D49: 362
A50: Filmed Entertainment - OIBDA | B50: 1085 | C50: 1051 | D50: 962
A51: Other - OIBDA | B51: -377 | C51: -373 | D51: -465
A52: Total 21CF Segment OIBDA | B52: =SUM(B48:B51) -> 6597 | C52: =SUM(C48:C51) -> 7173 | D52: =SUM(D48:D51) -> 7032
A53: REMAINCO BALANCE SHEET ANCHORS (12/31/2018)
A54: Total assets | D54: 57341 | F54: Disney 8-K/A Ex.99.4 RemainCo Pro Forma (Path A); LOCKED
A55: Cash (incl. ~$15.1B Sky + $6.5B dividend) | D55: 26337
A56: Total borrowings (current 887 + non-curr 18,321) | D56: 19208
A57: Total equity | D57: 20793
A58: Goodwill (book) / Intangibles (book) | C58: 7584 | D58: 3111
A59: Redeemable NCI (book) | D59: 470
A61: SHEET STATUS | B61: =IF(AND(ABS(B26)<1,ABS(C26)<1,ABS(D26)<1,ABS(B32)<1,ABS(C32)<1,ABS(D32)<1,ABS(B47)<1,ABS(C47)<1,ABS(D47)<1),"OK","CHECK") -> OK

Sheet FOX_PROJ
A1: FOX_PROJ - Fox RemainCo (TFCF) - Standalone Forecast
A2: $ in millions; FY2018A linked from FOX_HIST (Path A); FY2019E–FY2023E driven by ASSUMPTIONS active case. Hulu equity-method; Sky excluded; RSN held-for-sale carried in Cable base, removed in RSN tab.
A4: Line item ($mm) | B4: FY2018A | C4: FY2019E | D4: FY2020E | E4: FY2021E | F4: FY2022E | G4: FY2023E | H4: Driver / source
A5: SEGMENT REVENUE FORECAST (approved RemainCo structure)
A6: Cable Networks & Other - revenue growth % | C6: =ASSUMPTIONS!F52 -> 0.05 | D6: =ASSUMPTIONS!F52 -> 0.05 | E6: =ASSUMPTIONS!F52 -> 0.05 | F6: =ASSUMPTIONS!F52 -> 0.05 | G6: =ASSUMPTIONS!F52 -> 0.05 | H6: ASSUMPTIONS!F52
A7: Cable Networks & Other (incl. RSN held-for-sale) | B7: =FOX_HIST!D6-FOX_HIST!D44 -> 12104 | C7: =B7*(1+C6) -> 12709.2 | D7: =C7*(1+D6) -> 13344.66 | E7: =D7*(1+E6) -> 14011.893 | F7: =E7*(1+F6) -> 14712.488 | G7: =F7*(1+G6) -> 15448.112 | H7: remainco consol. − Filmed (FOX_HIST)
A8: Filmed Entertainment - revenue growth % | C8: =ASSUMPTIONS!F53 -> 0.03 | D8: =ASSUMPTIONS!F53 -> 0.03 | E8: =ASSUMPTIONS!F53 -> 0.03 | F8: =ASSUMPTIONS!F53 -> 0.03 | G8: =ASSUMPTIONS!F53 -> 0.03 | H8: ASSUMPTIONS!F53
A9: Filmed Entertainment - revenue | B9: =FOX_HIST!D44 -> 8747 | C9: =B9*(1+C8) -> 9009.41 | D9: =C9*(1+D8) -> 9279.6923 | E9: =D9*(1+E8) -> 9558.0831 | F9: =E9*(1+F8) -> 9844.8256 | G9: =F9*(1+G8) -> 10140.17
A10: Consolidated revenue | B10: =B7+B9 -> 20851 | C10: =C7+C9 -> 21718.61 | D10: =D7+D9 -> 22624.352 | E10: =E7+E9 -> 23569.976 | F10: =F7+F9 -> 24557.313 | G10: =G7+G9 -> 25588.282
A11: MARGIN & OIBDA
A12: RemainCo OIBDA margin % | B12: =FOX_HIST!D9/FOX_HIST!D6 -> 0.20262817 | C12: =ASSUMPTIONS!F54 -> 0.205 | D12: =ASSUMPTIONS!F54 -> 0.205 | E12: =ASSUMPTIONS!F54 -> 0.205 | F12: =ASSUMPTIONS!F54 -> 0.205 | G12: =ASSUMPTIONS!F54 -> 0.205 | H12: ASSUMPTIONS!F54 (single blended RemainCo margin)
A13: Cable Networks & Other - OIBDA | B13: =B7*B12 -> 2452.6114 | C13: =C7*C12 -> 2605.386 | D13: =D7*D12 -> 2735.6553 | E13: =E7*E12 -> 2872.4381 | F13: =F7*F12 -> 3016.06 | G13: =G7*G12 -> 3166.863
A14: Filmed Entertainment - OIBDA | B14: =B9*B12 -> 1772.3886 | C14: =C9*C12 -> 1846.929 | D14: =D9*D12 -> 1902.3369 | E14: =E9*E12 -> 1959.407 | F14: =F9*F12 -> 2018.1892 | G14: =G9*G12 -> 2078.7349
A15: Consolidated OIBDA | B15: =B13+B14 -> 4225 | C15: =C13+C14 -> 4452.3151 | D15: =D13+D14 -> 4637.9922 | E15: =E13+E14 -> 4831.8451 | F15: =F13+F14 -> 5034.2492 | G15: =G13+G14 -> 5245.5979
A16: INCOME STATEMENT (OIBDA → net income)
A17: Depreciation & amortization | B17: =FOX_HIST!D10 -> -413 | C17: =-C10*ASSUMPTIONS!$F$55 -> -434.3722 | D17: =-D10*ASSUMPTIONS!$F$55 -> -452.48705 | E17: =-E10*ASSUMPTIONS!$F$55 -> -471.39952 | F17: =-F10*ASSUMPTIONS!$F$55 -> -491.14626 | G17: =-G10*ASSUMPTIONS!$F$55 -> -511.76565 | H17: ASSUMPTIONS D&A % of revenue
A18: Impairment & restructuring | B18: =FOX_HIST!D11 -> -56 | C18: 0 | D18: 0 | E18: 0 | F18: 0 | G18: 0 | H18: Non-recurring; forecast 0
A19: EBIT (operating income) | B19: =B15+B17+B18 -> 3756 | C19: =C15+C17+C18 -> 4017.9429 | D19: =D15+D17+D18 -> 4185.5052 | E19: =E15+E17+E18 -> 4360.4456 | F19: =F15+F17+F18 -> 4543.1029 | G19: =G15+G17+G18 -> 4733.8322
A20: EBITDA | B20: =B19-B17 -> 4169 | C20: =C19-C17 -> 4452.3151 | D20: =D19-D17 -> 4637.9922 | E20: =E19-E17 -> 4831.8451 | F20: =F19-F17 -> 5034.2492 | G20: =G19-G17 -> 5245.5979 | H20: ebit + d&a
A21: Equity earnings (losses) - Hulu | B21: =FOX_HIST!D13 -> -563 | C21: =ASSUMPTIONS!$F$57 -> -600 | D21: =ASSUMPTIONS!$F$57 -> -600 | E21: =ASSUMPTIONS!$F$57 -> -600 | F21: =ASSUMPTIONS!$F$57 -> -600 | G21: =ASSUMPTIONS!$F$57 -> -600 | H21: Hulu equity-method (ASSUMPTIONS); Sky excluded
A22: RemainCo debt (held flat) - memo | B22: =FOX_HIST!D56 -> 19208 | C22: =$B$22 -> 19208 | D22: =$B$22 -> 19208 | E22: =$B$22 -> 19208 | F22: =$B$22 -> 19208 | G22: =$B$22 -> 19208 | H22: Standalone debt held at FY18A
A23: Interest rate (assumed debt) - memo | C23: =ASSUMPTIONS!$F$58 -> 0.06 | D23: =ASSUMPTIONS!$F$58 -> 0.06 | E23: =ASSUMPTIONS!$F$58 -> 0.06 | F23: =ASSUMPTIONS!$F$58 -> 0.06 | G23: =ASSUMPTIONS!$F$58 -> 0.06
A24: Net interest expense | B24: =FOX_HIST!D14 -> -1205 | C24: =-C22*C23 -> -1152.48 | D24: =-D22*D23 -> -1152.48 | E24: =-E22*E23 -> -1152.48 | F24: =-F22*F23 -> -1152.48 | G24: =-G22*G23 -> -1152.48
A25: Interest income | B25: =FOX_HIST!D15 -> 39 | C25: 0 | D25: 0 | E25: 0 | F25: 0 | G25: 0
A26: Other, net | B26: =FOX_HIST!D16 -> -571 | C26: 0 | D26: 0 | E26: 0 | F26: 0 | G26: 0
A27: Income before income taxes (EBT) | B27: =B19+B21+B24+B25+B26 -> 1456 | C27: =C19+C21+C24+C25+C26 -> 2265.4629 | D27: =D19+D21+D24+D25+D26 -> 2433.0252 | E27: =E19+E21+E24+E25+E26 -> 2607.9656 | F27: =F19+F21+F24+F25+F26 -> 2790.6229 | G27: =G19+G21+G24+G25+G26 -> 2981.3522
A28: Effective tax rate - memo | C28: =ASSUMPTIONS!$F$59 -> 0.24 | D28: =ASSUMPTIONS!$F$59 -> 0.24 | E28: =ASSUMPTIONS!$F$59 -> 0.24 | F28: =ASSUMPTIONS!$F$59 -> 0.24 | G28: =ASSUMPTIONS!$F$59 -> 0.24
A29: Income tax (expense) benefit | B29: =FOX_HIST!D18 -> 196 | C29: =-C27*C28 -> -543.71108 | D29: =-D27*D28 -> -583.92604 | E29: =-E27*E28 -> -625.91174 | F29: =-F27*F28 -> -669.74951 | G29: =-G27*G28 -> -715.52454 | H29: FY18A actual (TCJA); forecast normalized
A30: Income from continuing operations | B30: =B27+B29 -> 1652 | C30: =C27+C29 -> 1721.7518 | D30: =D27+D29 -> 1849.0991 | E30: =E27+E29 -> 1982.0538 | F30: =F27+F29 -> 2120.8734 | G30: =G27+G29 -> 2265.8277
A31: Less: NI attributable to NCI | B31: =FOX_HIST!D20 -> -257 | C31: =C30*($B$31/$B$30) -> -267.85121 | D31: =D30*($B$31/$B$30) -> -287.66252 | E31: =E30*($B$31/$B$30) -> -308.34615 | F31: =F30*($B$31/$B$30) -> -329.94218 | G31: =G30*($B$31/$B$30) -> -352.49257
A32: Net income attributable to RemainCo | B32: =B30+B31 -> 1395 | C32: =C30+C31 -> 1453.9006 | D32: =D30+D31 -> 1561.4366 | E32: =E30+E31 -> 1673.7077 | F32: =F30+F31 -> 1790.9313 | G32: =G30+G31 -> 1913.3351
A33: KEY METRICS (summary)
A34: Revenue | B34: =B10 -> 20851 | C34: =C10 -> 21718.61 | D34: =D10 -> 22624.352 | E34: =E10 -> 23569.976 | F34: =F10 -> 24557.313 | G34: =G10 -> 25588.282
A35: OIBDA | B35: =B15 -> 4225 | C35: =C15 -> 4452.3151 | D35: =D15 -> 4637.9922 | E35: =E15 -> 4831.8451 | F35: =F15 -> 5034.2492 | G35: =G15 -> 5245.5979
A36: EBITDA | B36: =B20 -> 4169 | C36: =C20 -> 4452.3151 | D36: =D20 -> 4637.9922 | E36: =E20 -> 4831.8451 | F36: =F20 -> 5034.2492 | G36: =G20 -> 5245.5979
A37: EBIT | B37: =B19 -> 3756 | C37: =C19 -> 4017.9429 | D37: =D19 -> 4185.5052 | E37: =E19 -> 4360.4456 | F37: =F19 -> 4543.1029 | G37: =G19 -> 4733.8322
A38: EBT (pre-tax income) | B38: =B27 -> 1456 | C38: =C27 -> 2265.4629 | D38: =D27 -> 2433.0252 | E38: =E27 -> 2607.9656 | F38: =F27 -> 2790.6229 | G38: =G27 -> 2981.3522
A39: Net income attributable to RemainCo | B39: =B32 -> 1395 | C39: =C32 -> 1453.9006 | D39: =D32 -> 1561.4366 | E39: =E32 -> 1673.7077 | F39: =F32 -> 1790.9313 | G39: =G32 -> 1913.3351
A40: SUPPORTING SCHEDULES
A41: D&A - % of revenue | C41: =ASSUMPTIONS!$F$55 -> 0.02 | D41: =ASSUMPTIONS!$F$55 -> 0.02 | E41: =ASSUMPTIONS!$F$55 -> 0.02 | F41: =ASSUMPTIONS!$F$55 -> 0.02 | G41: =ASSUMPTIONS!$F$55 -> 0.02
A42: D&A - $ | B42: =-B17 -> 413 | C42: =-C17 -> 434.3722 | D42: =-D17 -> 452.48705 | E42: =-E17 -> 471.39952 | F42: =-F17 -> 491.14626 | G42: =-G17 -> 511.76565
A43: Capex - % of revenue | C43: =ASSUMPTIONS!$F$56 -> 0.02 | D43: =ASSUMPTIONS!$F$56 -> 0.02 | E43: =ASSUMPTIONS!$F$56 -> 0.02 | F43: =ASSUMPTIONS!$F$56 -> 0.02 | G43: =ASSUMPTIONS!$F$56 -> 0.02
A44: Capex - $ | C44: =C10*ASSUMPTIONS!$F$56 -> 434.3722 | D44: =D10*ASSUMPTIONS!$F$56 -> 452.48705 | E44: =E10*ASSUMPTIONS!$F$56 -> 471.39952 | F44: =F10*ASSUMPTIONS!$F$56 -> 491.14626 | G44: =G10*ASSUMPTIONS!$F$56 -> 511.76565
A45: Working capital - Δ% of Δrevenue | C45: =ASSUMPTIONS!$F$45 -> 0 | D45: =ASSUMPTIONS!$F$45 -> 0 | E45: =ASSUMPTIONS!$F$45 -> 0 | F45: =ASSUMPTIONS!$F$45 -> 0 | G45: =ASSUMPTIONS!$F$45 -> 0
A46: Working capital - change | C46: =(C10-B10)*ASSUMPTIONS!$F$45 -> 0 | D46: =(D10-C10)*ASSUMPTIONS!$F$45 -> 0 | E46: =(E10-D10)*ASSUMPTIONS!$F$45 -> 0 | F46: =(F10-E10)*ASSUMPTIONS!$F$45 -> 0 | G46: =(G10-F10)*ASSUMPTIONS!$F$45 -> 0
A47: Effective tax rate | C47: =ASSUMPTIONS!$F$59 -> 0.24 | D47: =ASSUMPTIONS!$F$59 -> 0.24 | E47: =ASSUMPTIONS!$F$59 -> 0.24 | F47: =ASSUMPTIONS!$F$59 -> 0.24 | G47: =ASSUMPTIONS!$F$59 -> 0.24
A48: Income tax - $ | B48: =B29 -> 196 | C48: =C29 -> -543.71108 | D48: =D29 -> -583.92604 | E48: =E29 -> -625.91174 | F48: =F29 -> -669.74951 | G48: =G29 -> -715.52454
A49: RemainCo debt (held flat) | B49: =B22 -> 19208 | C49: =C22 -> 19208 | D49: =D22 -> 19208 | E49: =E22 -> 19208 | F49: =F22 -> 19208 | G49: =G22 -> 19208
A50: Interest expense - $ | B50: =B24 -> -1205 | C50: =C24 -> -1152.48 | D50: =D24 -> -1152.48 | E50: =E24 -> -1152.48 | F50: =F24 -> -1152.48 | G50: =G24 -> -1152.48
A51: Hulu equity income / (loss) | B51: =B21 -> -563 | C51: =C21 -> -600 | D51: =D21 -> -600 | E51: =E21 -> -600 | F51: =F21 -> -600 | G51: =G21 -> -600 | H51: Equity-method retained
A52: AUDIT CHECKS (red = must be ~0)
A53: Segment revenue ties to consolidated (=0) | B53: =B10-(B7+B9) -> 0 | C53: =C10-(C7+C9) -> 0 | D53: =D10-(D7+D9) -> 0 | E53: =E10-(E7+E9) -> 0 | F53: =F10-(F7+F9) -> 0 | G53: =G10-(G7+G9) -> 0
A54: Segment OIBDA ties to consolidated (=0) | B54: =B15-(B13+B14) -> 0 | C54: =C15-(C13+C14) -> 0 | D54: =D15-(D13+D14) -> 0 | E54: =E15-(E13+E14) -> 0 | F54: =F15-(F13+F14) -> 0 | G54: =G15-(G13+G14) -> 0
A55: FY18A revenue ties to FOX_HIST (=0) | B55: =B10-FOX_HIST!D6 -> 0
A56: FY18A OIBDA ties to FOX_HIST (=0) | B56: =B15-FOX_HIST!D9 -> 0
A57: FY18A EBIT ties to FOX_HIST (=0) | B57: =B19-FOX_HIST!D12 -> 0
A58: FY18A net income attributable ties (=0) | B58: =B32-FOX_HIST!D21 -> 0
A60: SHEET STATUS | B60: =IF(AND(ABS(B53)<1,ABS(C53)<1,ABS(B54)<1,ABS(C54)<1,ABS(B55)<1,ABS(B56)<1,ABS(B57)<1,ABS(B58)<1),"OK","CHECK") -> OK

Sheet S&U
A1: S&U - Sources & Uses (Phase 3, approved)
A2: $ in millions; green = link to ASSUMPTIONS; red = check
A4: SOURCES OF FUNDS
A5: New Disney common stock issued to 21CF holders | B5: =ASSUMPTIONS!B6 -> 33753
A6: New debt incurred ("New Indebtedness") | B6: =ASSUMPTIONS!B13 -> 35703
A7: Total financing sources | B7: =B5+B6 -> 69456
A9: USES OF FUNDS
A10: Stock consideration to 21CF holders | B10: =ASSUMPTIONS!B6 -> 33753
A11: Cash consideration to 21CF holders | B11: =ASSUMPTIONS!B5 -> 35703
A12: Total equity purchase price | B12: =B10+B11 -> 69456
A13: CHECK: Sources − Uses (=0) | B13: =B7-B12 -> 0
A15: TRANSACTION CASH BRIDGE
A16: Gross new borrowings | B16: =ASSUMPTIONS!B13 -> 35703
A17: Less: repaid from acquired RemainCo cash | B17: =-ASSUMPTIONS!B14 -> -16100
A18: Net new acquisition debt | B18: =B16+B17 -> 19603
A19: Assumed 21CF debt (book; FV ~22,800) | B19: =ASSUMPTIONS!B15 -> 19208
A20: Acquired RemainCo cash | B20: =ASSUMPTIONS!B17 -> 26337
A21: Payment to New Fox (tax true-up) | B21: =ASSUMPTIONS!B18 -> 2000
A22: Transaction fees & expenses | B22: =ASSUMPTIONS!B19 -> 150
A24: VALUE RECONCILIATION
A25: Announced equity value (Dec-2017) | B25: =ASSUMPTIONS!B21 -> 52400
A26: Revised equity value (Jun-2018) | B26: =ASSUMPTIONS!B22 -> 71300
A27: Recorded consideration (Mar-2019) | B27: =B12 -> 69456
A29: OWNERSHIP FRAMEWORK
A30: Disney legacy shares (basic, mm) | B30: =ASSUMPTIONS!B20 -> 1499
A31: New shares issued to 21CF holders (mm) | B31: =ASSUMPTIONS!B8 -> 307
A32: Total New Disney shares (mm) | B32: =B30+B31 -> 1806
A33: 21CF holders ownership % | B33: =B31/B32 -> 0.16998893
A34: Disney holders ownership % | B34: =B30/B32 -> 0.83001107
A35: Per-share value / exchange ratio | B35: =ASSUMPTIONS!B12 -> 51.572626 | C35: =ASSUMPTIONS!B11 -> 0.3328
A37: SHEET STATUS | B37: =IF(ABS(B13)<1,"OK","CHECK") -> OK

Sheet PPA
A1: PPA - Purchase Price Allocation
A2: $ in millions; blue = preliminary reference (to be validated vs Disney FY2019 10-K); green = link; red = check
A4: SCHEDULE 4A - RemainCo (preliminary reference)
A5: Purchase consideration | B5: ='S&U'!B12 -> 69456 | F5: from S&U
A6: RemainCo book equity | B6: =FOX_HIST!D57 -> 20793 | F6: from FOX_HIST anchors
A7: RemainCo redeemable NCI (book) | B7: =FOX_HIST!D59 -> 470
A8: Eliminate: book goodwill | B8: -7584 | F8: Disney 8-K/A Ex.99.3 (b2)
A9: Eliminate: book intangibles | B9: -3111
A10: Eliminate: book investments | B10: -376
A11: Eliminate: book film & TV costs | B11: -4832
A12: Step-up: film & TV costs to FV | B12: 10442 | F12: (b3)
A13: Step-up: intangibles to FV | B13: 25732 | F13: (b4)
A14: Step-up: RemainCo 30% Hulu to FV | B14: 4500 | F14: (b5)
A15: Step-up: other equity affiliates to FV | B15: 1272 | F15: (b5)
A16: FV adj: deferred revenue | B16: 529 | F16: (b6)
A17: FV adj: debt to fair value | B17: -3601 | F17: (b7)
A18: FV adj: deferred taxes | B18: -5843 | F18: (b8)
A19: FV adj: NCI to fair value | B19: -2747 | F19: (b9)
A20: FV adj: redeemable NCI to fair value | B20: -1085 | F20: (b9)
A21: FV of net identifiable assets acquired | B21: =B6+B7+SUM(B8:B20) -> 34559
A22: GOODWILL - RemainCo (preliminary) | B22: =B5-B21 -> 34897
A23: Memo: FV of 100% identifiable net assets | B23: =B21+(-B19)+(-B20) -> 38391
A24: Memo: goodwill via standard formula | B24: =B5+(-B19)+(-B20)-B23 -> 34897
A25: CHECK: goodwill identity (=0) | B25: =B22-B24 -> 0
A27: SCHEDULE 4B - Hulu consolidation (preliminary reference)
A28: FV of New Disney 60% interest | B28: 9000 | F28: Ex.99.3 (c)
A29: + NCI (30%) at fair value | B29: 4500
A30: + Redeemable NCI (10%) at fair value | B30: 1500
A31: Total Hulu fair value (100%) | B31: =B28+B29+B30 -> 15000
A32: − FV of identifiable net assets | B32: -2226
A33: GOODWILL - Hulu (preliminary) | B33: =B31+B32 -> 12774
A34: Memo: Hulu remeasurement gain (one-time) | B34: 4669 | F34: (c) FV 4,500 vs CV (169)
A36: TOTAL PRELIMINARY GOODWILL (RemainCo + Hulu) | B36: =B22+B33 -> 47671
A38: SHEET STATUS | B38: =IF(ABS(B25)<1,"OK","CHECK") -> OK

Sheet PPA_DA
A1: PPA_DA - Purchase Accounting Depreciation & Amortization Schedule
A2: $ in millions; FV step-ups linked from PPA; lives & rates linked from ASSUMPTIONS active case. Amortization of preliminary step-ups - to be validated vs Disney FY2019 10-K.
A4: Asset class | B4: FV step-up | C4: Life (yrs) | D4: FY2019E | E4: FY2020E | F4: FY2021E | G4: FY2022E | H4: FY2023E | I4: Method / source
A5: INTANGIBLE ASSET AMORTIZATION
A6: RemainCo intangibles (finite-lived) | B6: =PPA!B13 -> 25732 | C6: =ASSUMPTIONS!F76 -> 11 | D6: =$B$6/$C$6 -> 2339.2727 | E6: =$B$6/$C$6 -> 2339.2727 | F6: =$B$6/$C$6 -> 2339.2727 | G6: =$B$6/$C$6 -> 2339.2727 | H6: =$B$6/$C$6 -> 2339.2727 | I6: SL 11yr; PPA (b4) $25,732
A7: FILM & TELEVISION STEP-UP AMORTIZATION
A8: Film & TV step-up (total) | B8: =PPA!B12 -> 10442 | I8: PPA (b3) $10,442; allocated below
A9: Recent-releases share of film step-up (%) | B9: 0.5 | I9: Analyst allocation; refine w/ FY2019 10-K detail
A10: Film - recent releases (SYD) | B10: =$B$8*$B$9 -> 5221 | C10: =ASSUMPTIONS!F77 -> 8 | D10: =$B$10*($C$10-0)/($C$10*($C$10+1)/2) -> 1160.2222 | E10: =$B$10*($C$10-1)/($C$10*($C$10+1)/2) -> 1015.1944 | F10: =$B$10*($C$10-2)/($C$10*($C$10+1)/2) -> 870.16667 | G10: =$B$10*($C$10-3)/($C$10*($C$10+1)/2) -> 725.13889 | H10: =$B$10*($C$10-4)/($C$10*($C$10+1)/2) -> 580.11111 | I10: Sum-of-years-digits 8yr (accelerated)
A11: Film - library (SL) | B11: =$B$8*(1-$B$9) -> 5221 | C11: =ASSUMPTIONS!F78 -> 9 | D11: =$B$11/$C$11 -> 580.11111 | E11: =$B$11/$C$11 -> 580.11111 | F11: =$B$11/$C$11 -> 580.11111 | G11: =$B$11/$C$11 -> 580.11111 | H11: =$B$11/$C$11 -> 580.11111 | I11: SL 9yr
A12: HULU INTANGIBLE AMORTIZATION
A13: Hulu intangibles (trade name, tech, subs) | B13: 2324 | C13: =ASSUMPTIONS!F79 -> 10 | D13: =$B$13/$C$13 -> 232.4 | E13: =$B$13/$C$13 -> 232.4 | F13: =$B$13/$C$13 -> 232.4 | G13: =$B$13/$C$13 -> 232.4 | H13: =$B$13/$C$13 -> 232.4 | I13: SL 10yr; PPA (c1) $2,324
A14: TOTAL INCREMENTAL PPA AMORTIZATION
A15: Total incremental PPA amortization | D15: =D6+D10+D11+D13 -> 4312.0061 | E15: =E6+E10+E11+E13 -> 4166.9783 | F15: =F6+F10+F11+F13 -> 4021.9505 | G15: =G6+G10+G11+G13 -> 3876.9227 | H15: =H6+H10+H11+H13 -> 3731.8949
A16: DEBT FAIR VALUE PREMIUM (reference - interest, not amortization expense)
A17: Debt FV premium (recorded) | B17: =PPA!B17 -> -3601 | I17: PPA (b7) FV adj
A18: Premium amortization (interest benefit) | D18: =ASSUMPTIONS!$F$70 -> 205 | E18: =ASSUMPTIONS!$F$70 -> 205 | F18: =ASSUMPTIONS!$F$70 -> 205 | G18: =ASSUMPTIONS!$F$70 -> 205 | H18: =ASSUMPTIONS!$F$70 -> 205 | I18: Reduces interest expense ~$205/yr (ASSUMPTIONS F70)
A19: P&L IMPACT
A20: EBIT impact (amortization expense) | D20: =-D15 -> -4312.0061 | E20: =-E15 -> -4166.9783 | F20: =-F15 -> -4021.9505 | G20: =-G15 -> -3876.9227 | H20: =-H15 -> -3731.8949
A21: Add: debt FV premium amort (interest benefit) | D21: =D18 -> 205 | E21: =E18 -> 205 | F21: =F18 -> 205 | G21: =G18 -> 205 | H21: =H18 -> 205
A22: Pretax impact | D22: =D20+D21 -> -4107.0061 | E22: =E20+E21 -> -3961.9783 | F22: =F20+F21 -> -3816.9505 | G22: =G20+G21 -> -3671.9227 | H22: =H20+H21 -> -3526.8949
A23: Deferred-tax rate on step-ups (memo) | D23: =ASSUMPTIONS!$F$80 -> 0.24 | E23: =ASSUMPTIONS!$F$80 -> 0.24 | F23: =ASSUMPTIONS!$F$80 -> 0.24 | G23: =ASSUMPTIONS!$F$80 -> 0.24 | H23: =ASSUMPTIONS!$F$80 -> 0.24
A24: After-tax impact | D24: =D22*(1-D23) -> -3121.3246 | E24: =E22*(1-E23) -> -3011.1035 | F24: =F22*(1-F23) -> -2900.8824 | G24: =G22*(1-G23) -> -2790.6613 | H24: =H22*(1-H23) -> -2680.4402
A25: AUDIT CHECKS (red = must be ~0)
A26: Intangibles SL ties (annual×life − FV =0) | B26: =D6*C6-B6 -> 0
A27: Film library SL ties (=0) | B27: =D11*C11-B11 -> 0
A28: Hulu SL ties (=0) | B28: =D13*C13-B13 -> 0
A29: Film recent SYD yr-1 ties (=0) | B29: =D10-B10*C10/(C10*(C10+1)/2) -> 0
A30: Film split ties to total (=0) | B30: =B10+B11-B8 -> 0
A31: Total ties to components, FY2019E (=0) | B31: =D15-(D6+D10+D11+D13) -> 0
A33: SHEET STATUS | B33: =IF(AND(ABS(B26)<1,ABS(B27)<1,ABS(B28)<1,ABS(B29)<1,ABS(B30)<1,ABS(B31)<1),"OK","CHECK") -> OK

Sheet SYNERGIES
A1: SYNERGIES - Synergy Realization Engine (test of management case)
A2: $ in millions; drivers linked to ASSUMPTIONS active case. Management guided ≥$2.0B run-rate by FY2021 - modeled here to be TESTED, not assumed. Default OFF unless scenario applies it downstream.
A4: Item ($mm) | B4: Run-rate / total | C4: FY2019E | D4: FY2020E | E4: FY2021E | F4: FY2022E | G4: FY2023E | H4: Driver / source
A5: SYNERGY CASE SELECTION (management guidance under test)
A6: Base case run-rate cost synergies | B6: =ASSUMPTIONS!C61 -> 2000 | H6: Mgmt: ≥$2.0B by FY2021
A7: Upside case run-rate | B7: =ASSUMPTIONS!D61 -> 2500
A8: Downside case run-rate | B8: =ASSUMPTIONS!E61 -> 1500
A9: Active run-rate (selected by CONTROL scenario) | B9: =ASSUMPTIONS!F61 -> 2000 | H9: CHOOSE on CONTROL scenario
A10: REALIZATION PHASING (approved ramp)
A11: Cost-synergy realized (% of run-rate) | C11: =ASSUMPTIONS!C65 -> 0.1 | D11: =ASSUMPTIONS!D65 -> 0.5 | E11: =ASSUMPTIONS!E65 -> 0.9 | F11: =ASSUMPTIONS!F65 -> 1 | G11: =ASSUMPTIONS!G65 -> 1 | H11: Approved ramp 10 / 50 / 90 / 100 / 100
A12: Costs-to-achieve incurred (% of total) | C12: =ASSUMPTIONS!C66 -> 0.4 | D12: =ASSUMPTIONS!D66 -> 0.4 | E12: =ASSUMPTIONS!E66 -> 0.2 | F12: =ASSUMPTIONS!F66 -> 0 | G12: =ASSUMPTIONS!G66 -> 0 | H12: Front-loaded 40 / 40 / 20 / 0 / 0
A13: COST SYNERGIES
A14: Run-rate cost synergies | B14: =ASSUMPTIONS!F61 -> 2000
A15: Cost synergies realized | C15: =$B$14*C11 -> 200 | D15: =$B$14*D11 -> 1000 | E15: =$B$14*E11 -> 1800 | F15: =$B$14*F11 -> 2000 | G15: =$B$14*G11 -> 2000
A16: REVENUE SYNERGIES
A17: Run-rate revenue synergies | B17: =ASSUMPTIONS!F63 -> 0 | H17: Excluded (conservative; base 0)
A18: Revenue synergies realized | C18: =$B$17*C11 -> 0 | D18: =$B$17*D11 -> 0 | E18: =$B$17*E11 -> 0 | F18: =$B$17*F11 -> 0 | G18: =$B$17*G11 -> 0
A19: INTEGRATION COSTS (costs to achieve)
A20: Total costs to achieve (one-time) | B20: =ASSUMPTIONS!F62 -> 1400
A21: Costs to achieve incurred | C21: =$B$20*C12 -> 560 | D21: =$B$20*D12 -> 560 | E21: =$B$20*E12 -> 280 | F21: =$B$20*F12 -> 0 | G21: =$B$20*G12 -> 0
A22: P&L IMPACT
A23: EBITDA impact (recurring) | C23: =C15+C18 -> 200 | D23: =D15+D18 -> 1000 | E23: =E15+E18 -> 1800 | F23: =F15+F18 -> 2000 | G23: =G15+G18 -> 2000
A24: EBIT impact | C24: =C23 -> 200 | D24: =D23 -> 1000 | E24: =E23 -> 1800 | F24: =F23 -> 2000 | G24: =G23 -> 2000 | H24: EBITDA impact (synergies create no D&A)
A25: Less: costs to achieve (one-time) | C25: =-C21 -> -560 | D25: =-D21 -> -560 | E25: =-E21 -> -280 | F25: =-F21 -> 0 | G25: =-G21 -> 0
A26: Pretax synergy impact | C26: =C24+C25 -> -360 | D26: =D24+D25 -> 440 | E26: =E24+E25 -> 1520 | F26: =F24+F25 -> 2000 | G26: =G24+G25 -> 2000
A27: Combined tax rate (memo) | C27: =ASSUMPTIONS!$F$84 -> 0.24 | D27: =ASSUMPTIONS!$F$84 -> 0.24 | E27: =ASSUMPTIONS!$F$84 -> 0.24 | F27: =ASSUMPTIONS!$F$84 -> 0.24 | G27: =ASSUMPTIONS!$F$84 -> 0.24
A28: After-tax synergy impact | C28: =C26*(1-C27) -> -273.6 | D28: =D26*(1-D27) -> 334.4 | E28: =E26*(1-E27) -> 1155.2 | F28: =F26*(1-F27) -> 1520 | G28: =G26*(1-G27) -> 1520
A29: AUDIT CHECKS (red = must be ~0)
A30: Full run-rate realized by FY2023 (=0) | B30: =G15-B14 -> 0
A31: Costs-to-achieve fully incurred (=0) | B31: =SUM(C21:G21)-B20 -> 0
A32: Realization ramp reaches 100% in FY2023 (=0) | B32: =G11-1 -> 0
A33: Costs-to-achieve %% sums to 100%% (=0) | B33: =SUM(C12:G12)-1 -> 0
A34: Active run-rate within case range (=0 if valid) | B34: =IF(OR(B9=B6,B9=B7,B9=B8),0,1) -> 0
A36: SHEET STATUS | B36: =IF(AND(ABS(B30)<1,ABS(B31)<1,ABS(B32)<0.001,ABS(B33)<0.001,B34=0),"OK","CHECK") -> OK

Sheet DEBT
A1: DEBT - Acquisition Financing & Debt Paydown Engine
A2: $ in millions. Two tranches: new acquisition debt + assumed 21CF notes. Waterfall: RSN proceeds + cash sweep -> new debt first, excess -> assumed. Interest on beginning balances (non-circular). Drivers link ASSUMPTIONS; EBITDA from PF_IS.
A4: ($mm) | B4: At close | C4: FY2019E | D4: FY2020E | E4: FY2021E | F4: FY2022E | G4: FY2023E | H4: Notes
A5: DEBT STRUCTURE AT CLOSE
A6: New acquisition debt | B6: ='S&U'!B18 -> 19603 | H6: Net new borrowings (S&U)
A7: Assumed 21CF debt (book) | B7: =ASSUMPTIONS!B15 -> 19208 | H7: FV ~22,800; premium amortized in interest
A8: Total debt at close | B8: =B6+B7 -> 38811
A9: NEW ACQUISITION DEBT - ROLL-FORWARD
A10: Beginning balance | C10: =B6 -> 19603 | D10: =C14 -> 188.48539 | E10: =D14 -> 0 | F10: =E14 -> 0 | G10: =F14 -> 0
A11: Additions | C11: 0 | D11: 0 | E11: 0 | F11: 0 | G11: 0
A12: RSN-proceeds paydown | C12: =-MIN(C10,C39) -> -13070 | D12: =-MIN(D10,D39) -> 0 | E12: =-MIN(E10,E39) -> 0 | F12: =-MIN(F10,F39) -> 0 | G12: =-MIN(G10,G39) -> 0
A13: Cash-sweep paydown | C13: =-MIN(C10+C12,C38) -> -6344.5146 | D13: =-MIN(D10+D12,D38) -> -188.48539 | E13: =-MIN(E10+E12,E38) -> 0 | F13: =-MIN(F10+F12,F38) -> 0 | G13: =-MIN(G10+G12,G38) -> 0
A14: Ending balance | C14: =C10+C11+C12+C13 -> 188.48539 | D14: =D10+D11+D12+D13 -> 0 | E14: =E10+E11+E12+E13 -> 0 | F14: =F10+F11+F12+F13 -> 0 | G14: =G10+G11+G12+G13 -> 0
A15: ASSUMED 21CF DEBT - ROLL-FORWARD
A16: Beginning balance | C16: =B7 -> 19208 | D16: =C19 -> 19208 | E16: =D19 -> 12164.074 | F16: =E19 -> 4112.4839 | G16: =F19 -> 0
A17: Additions | C17: 0 | D17: 0 | E17: 0 | F17: 0 | G17: 0
A18: Cash-sweep paydown (excess) | C18: =-MIN(C16,MAX(0,C40-C10)) -> 0 | D18: =-MIN(D16,MAX(0,D40-D10)) -> -7043.9261 | E18: =-MIN(E16,MAX(0,E40-E10)) -> -8051.5899 | F18: =-MIN(F16,MAX(0,F40-F10)) -> -4112.4839 | G18: =-MIN(G16,MAX(0,G40-G10)) -> 0
A19: Ending balance | C19: =C16+C17+C18 -> 19208 | D19: =D16+D17+D18 -> 12164.074 | E19: =E16+E17+E18 -> 4112.4839 | F19: =F16+F17+F18 -> 0 | G19: =G16+G17+G18 -> 0
A20: TOTAL DEBT
A21: Beginning balance | C21: =C10+C16 -> 38811 | D21: =D10+D16 -> 19396.485 | E21: =E10+E16 -> 12164.074 | F21: =F10+F16 -> 4112.4839 | G21: =G10+G16 -> 0
A22: Additions | C22: =C11+C17 -> 0 | D22: =D11+D17 -> 0 | E22: =E11+E17 -> 0 | F22: =F11+F17 -> 0 | G22: =G11+G17 -> 0
A23: Total paydowns | C23: =C12+C13+C18 -> -19414.515 | D23: =D12+D13+D18 -> -7232.4115 | E23: =E12+E13+E18 -> -8051.5899 | F23: =F12+F13+F18 -> -4112.4839 | G23: =G12+G13+G18 -> 0
A24: Ending balance | C24: =C14+C19 -> 19396.485 | D24: =D14+D19 -> 12164.074 | E24: =E14+E19 -> 4112.4839 | F24: =F14+F19 -> 0 | G24: =G14+G19 -> 0
A25: Weighted avg balance (memo) | C25: =(C21+C24)/2 -> 29103.743 | D25: =(D21+D24)/2 -> 15780.28 | E25: =(E21+E24)/2 -> 8138.2789 | F25: =(F21+F24)/2 -> 2056.242 | G25: =(G21+G24)/2 -> 0
A26: INTEREST EXPENSE
A27: New acquisition debt interest | C27: =C10*ASSUMPTIONS!F68 -> 646.899 | D27: =D10*ASSUMPTIONS!F68 -> 6.220018 | E27: =E10*ASSUMPTIONS!F68 -> 0 | F27: =F10*ASSUMPTIONS!F68 -> 0 | G27: =G10*ASSUMPTIONS!F68 -> 0 | H27: Beginning balance x rate
A28: Assumed 21CF interest (gross) | C28: =C16*ASSUMPTIONS!F69 -> 1152.48 | D28: =D16*ASSUMPTIONS!F69 -> 1152.48 | E28: =E16*ASSUMPTIONS!F69 -> 729.84443 | F28: =F16*ASSUMPTIONS!F69 -> 246.74904 | G28: =G16*ASSUMPTIONS!F69 -> 0
A29: Less: FV-premium amortization | C29: =-ASSUMPTIONS!F70*IF(C16>0,1,0) -> -205 | D29: =-ASSUMPTIONS!F70*IF(D16>0,1,0) -> -205 | E29: =-ASSUMPTIONS!F70*IF(E16>0,1,0) -> -205 | F29: =-ASSUMPTIONS!F70*IF(F16>0,1,0) -> -205 | G29: =-ASSUMPTIONS!F70*IF(G16>0,1,0) -> 0
A30: Total interest expense | C30: =C27+C28+C29 -> 1594.379 | D30: =D27+D28+D29 -> 953.70002 | E30: =E27+E28+E29 -> 524.84443 | F30: =F27+F28+F29 -> 41.749036 | G30: =G27+G28+G29 -> 0
A31: Effective rate on avg debt (memo) | C31: =IF(C25=0,0,C30/C25) -> 0.05478261 | D31: =IF(D25=0,0,D30/D25) -> 0.060436193 | E31: =IF(E25=0,0,E30/E25) -> 0.064490839 | F31: =IF(F25=0,0,F30/F25) -> 0.020303562 | G31: =IF(G25=0,0,G30/G25) -> 0
A32: CASH FLOW & SWEEP (paydown capacity, proxy)
A33: Pro forma EBITDA | C33: =PF_IS!C15 -> 22884.928 | D33: =PF_IS!D15 -> 24527.338 | E33: =PF_IS!E15 -> 26210.581 | F33: =PF_IS!F15 -> 27336.625 | G33: =PF_IS!G15 -> 28307.538 | H33: From PF_IS
A34: Less: combined capex | C34: =-(DIS_PROJ!C52+FOX_PROJ!C44) -> -4752.8976 | D34: =-(DIS_PROJ!D52+FOX_PROJ!D44) -> -4937.0647 | E34: =-(DIS_PROJ!E52+FOX_PROJ!E44) -> -5130.3316 | F34: =-(DIS_PROJ!F52+FOX_PROJ!F44) -> -5333.152 | G34: =-(DIS_PROJ!G52+FOX_PROJ!G44) -> -5546.0039
A35: Less: cash taxes | C35: =PF_IS!C33 -> -3848.6222 | D35: =PF_IS!D33 -> -4171.7498 | E35: =PF_IS!E33 -> -4452.2253 | F35: =PF_IS!F33 -> -4754.2953 | G35: =PF_IS!G33 -> -5008.6315
A36: Less: cash interest | C36: =-C30 -> -1594.379 | D36: =-D30 -> -953.70002 | E36: =-E30 -> -524.84443 | F36: =-F30 -> -41.749036 | G36: =-G30 -> 0
A37: FCF available for paydown | C37: =C33+C34+C35+C36 -> 12689.029 | D37: =D33+D34+D35+D36 -> 14464.823 | E37: =E33+E34+E35+E36 -> 16103.18 | F37: =F33+F34+F35+F36 -> 17207.428 | G37: =G33+G34+G35+G36 -> 17752.902
A38: Cash sweep to debt | C38: =ASSUMPTIONS!F74*MAX(0,C37) -> 6344.5146 | D38: =ASSUMPTIONS!F74*MAX(0,D37) -> 7232.4115 | E38: =ASSUMPTIONS!F74*MAX(0,E37) -> 8051.5899 | F38: =ASSUMPTIONS!F74*MAX(0,F37) -> 8603.7142 | G38: =ASSUMPTIONS!F74*MAX(0,G37) -> 8876.4512
A39: RSN-proceeds available | C39: =ASSUMPTIONS!F71*ASSUMPTIONS!F72 -> 13070 | D39: 0 | E39: 0 | F39: 0 | G39: 0
A40: Total paydown available | C40: =C38+C39 -> 19414.515 | D40: =D38+D39 -> 7232.4115 | E40: =E38+E39 -> 8051.5899 | F40: =F38+F39 -> 8603.7142 | G40: =G38+G39 -> 8876.4512
A41: LEVERAGE
A42: Total debt / EBITDA | C42: =IF(C33=0,0,C24/C33) -> 0.84756593 | D42: =IF(D33=0,0,D24/D33) -> 0.49593943 | E42: =IF(E33=0,0,E24/E33) -> 0.15690167 | F42: =IF(F33=0,0,F24/F33) -> 0 | G42: =IF(G33=0,0,G24/G33) -> 0
A43: Cash (assumed min operating) | C43: =ASSUMPTIONS!F73 -> 4000 | D43: =ASSUMPTIONS!F73 -> 4000 | E43: =ASSUMPTIONS!F73 -> 4000 | F43: =ASSUMPTIONS!F73 -> 4000 | G43: =ASSUMPTIONS!F73 -> 4000
A44: Net debt / EBITDA | C44: =IF(C33=0,0,(C24-C43)/C33) -> 0.67277841 | D44: =IF(D33=0,0,(D24-D43)/D33) -> 0.3328561 | E44: =IF(E33=0,0,(E24-E43)/E33) -> 0.0042915467 | F44: =IF(F33=0,0,(F24-F43)/F33) -> -0.14632384 | G44: =IF(G33=0,0,(G24-G43)/G33) -> -0.14130512
A46: AUDIT CHECKS (red = must be ~0)
A47: Beg + Add - Paydowns = End (total, FY19E =0) | C47: =C24-(C21+C22+C23) -> 0
A48: Total debt tie at close (=0) | C48: =B8-(B6+B7) -> 0
A49: Total = tranches every year (FY19E..23E max abs) | C49: =MAX(ABS(C24-C14-C19),ABS(G24-G14-G19)) -> 0
A50: Interest = components (FY19E =0) | C50: =C30-(C27+C28+C29) -> 0
A51: Leverage tie: Debt/EBITDA x EBITDA - Debt (FY19E =0) | C51: =C42*C33-C24 -> 0
A52: Ending debt non-negative (min across yrs, >=0) | C52: =MIN(C14:G14,C19:G19) -> 0
A54: SHEET STATUS | B54: =IF(AND(ABS(C47)<1,ABS(B48)<1,C49<1,ABS(C50)<1,ABS(C51)<1,C52>=-0.5),"OK","CHECK") -> OK

Sheet HULU
A1: HULU — Step Acquisition & Consolidation
A2: $ in millions; fair values linked from PPA Schedule 4B
A4: OWNERSHIP & REMEASUREMENT (preliminary reference)
A5: FV of New Disney 60% interest | B5: =PPA!B28 -> 9000
A6: NCI (30%) at fair value | B6: =PPA!B29 -> 4500
A7: Redeemable NCI (10%) at fair value | B7: =PPA!B30 -> 1500
A8: Total Hulu fair value (100%) | B8: =B5+B6+B7 -> 15000
A9: Goodwill — Hulu (preliminary) | B9: =PPA!B33 -> 12774
A10: Remeasurement gain (one-time, to earnings) | B10: =PPA!B34 -> 4669
A12: STATUS: To be completed in later phase
A13: Hulu P&L consolidation, NCI allocation roll-forward, and elimination of equity-method losses to be completed.

Sheet RSN
A1: RSN — Regional Sports Networks (Held-for-Sale)
A2: $ in millions; FY2018 results linked from FOX_HIST; disposal group per Phase 4
A4: HELD-FOR-SALE CARVE-OUT (reference)
A5: RSN revenue (FY2018) | B5: =FOX_HIST!D39 -> 4331
A6: RSN OIBDA (FY2018) | B6: =FOX_HIST!D40 -> 2013
A7: Disposal-group net assets at fair value | B7: 12848 | F7: Disney 8-K/A Ex.99.3 (g)
A8: Estimated sale proceeds (Sinclair + YES) | B8: 13070
A10: STATUS: To be completed in later phase
A11: Removal of RSN from continuing pro forma, gain/loss on sale, and debt paydown to be completed.

Sheet PF_IS
A1: PF_IS - Pro Forma Income Statement (combined New Disney)
A2: $ in millions except per share. Bridge: Disney standalone + Fox RemainCo + Synergies − PPA_DA = Pro Forma. Links: DIS_PROJ, FOX_PROJ, SYNERGIES, PPA_DA (yr cols D–H), ASSUMPTIONS.
A4: REVENUE | C4: FY2019E | D4: FY2020E | E4: FY2021E | F4: FY2022E | G4: FY2023E
A5: Disney standalone | C5: =DIS_PROJ!C23 -> 61693.22 | D5: =DIS_PROJ!D23 -> 64065.395 | E5: =DIS_PROJ!E23 -> 66556.173 | F5: =DIS_PROJ!F23 -> 69171.51 | G5: =DIS_PROJ!G23 -> 71917.689
A6: Fox RemainCo standalone | C6: =FOX_PROJ!C10 -> 21718.61 | D6: =FOX_PROJ!D10 -> 22624.352 | E6: =FOX_PROJ!E10 -> 23569.976 | F6: =FOX_PROJ!F10 -> 24557.313 | G6: =FOX_PROJ!G10 -> 25588.282
A7: + Synergies | C7: =SYNERGIES!C18 -> 0 | D7: =SYNERGIES!D18 -> 0 | E7: =SYNERGIES!E18 -> 0 | F7: =SYNERGIES!F18 -> 0 | G7: =SYNERGIES!G18 -> 0
A8: − PPA purchase-accounting | C8: 0 | D8: 0 | E8: 0 | F8: 0 | G8: 0
A9: Pro forma revenue | C9: =C5+C6+C7+C8 -> 83411.83 | D9: =D5+D6+D7+D8 -> 86689.747 | E9: =E5+E6+E7+E8 -> 90126.149 | F9: =F5+F6+F7+F8 -> 93728.823 | G9: =G5+G6+G7+G8 -> 97505.972
A10: EBITDA
A11: Disney standalone | C11: =DIS_PROJ!C28 -> 18232.613 | D11: =DIS_PROJ!D28 -> 18889.345 | E11: =DIS_PROJ!E28 -> 19578.736 | F11: =DIS_PROJ!F28 -> 20302.375 | G11: =DIS_PROJ!G28 -> 21061.94
A12: Fox RemainCo standalone | C12: =FOX_PROJ!C20 -> 4452.3151 | D12: =FOX_PROJ!D20 -> 4637.9922 | E12: =FOX_PROJ!E20 -> 4831.8451 | F12: =FOX_PROJ!F20 -> 5034.2492 | G12: =FOX_PROJ!G20 -> 5245.5979
A13: + Synergies | C13: =SYNERGIES!C23 -> 200 | D13: =SYNERGIES!D23 -> 1000 | E13: =SYNERGIES!E23 -> 1800 | F13: =SYNERGIES!F23 -> 2000 | G13: =SYNERGIES!G23 -> 2000
A14: − PPA purchase-accounting | C14: 0 | D14: 0 | E14: 0 | F14: 0 | G14: 0
A15: Pro forma EBITDA | C15: =C11+C12+C13+C14 -> 22884.928 | D15: =D11+D12+D13+D14 -> 24527.338 | E15: =E11+E12+E13+E14 -> 26210.581 | F15: =F11+F12+F13+F14 -> 27336.625 | G15: =G11+G12+G13+G14 -> 28307.538
A16: EBIT
A17: Disney standalone | C17: =DIS_PROJ!C26 -> 15147.952 | D17: =DIS_PROJ!D26 -> 15686.076 | E17: =DIS_PROJ!E26 -> 16250.927 | F17: =DIS_PROJ!F26 -> 16843.8 | G17: =DIS_PROJ!G26 -> 17466.055
A18: Fox RemainCo standalone | C18: =FOX_PROJ!C19 -> 4017.9429 | D18: =FOX_PROJ!D19 -> 4185.5052 | E18: =FOX_PROJ!E19 -> 4360.4456 | F18: =FOX_PROJ!F19 -> 4543.1029 | G18: =FOX_PROJ!G19 -> 4733.8322
A19: + Synergies | C19: =SYNERGIES!C26 -> -360 | D19: =SYNERGIES!D26 -> 440 | E19: =SYNERGIES!E26 -> 1520 | F19: =SYNERGIES!F26 -> 2000 | G19: =SYNERGIES!G26 -> 2000
A20: − PPA purchase-accounting | C20: =PPA_DA!D20 -> -4312.0061 | D20: =PPA_DA!E20 -> -4166.9783 | E20: =PPA_DA!F20 -> -4021.9505 | F20: =PPA_DA!G20 -> -3876.9227 | G20: =PPA_DA!H20 -> -3731.8949
A21: Pro forma EBIT | C21: =C17+C18+C19+C20 -> 14493.889 | D21: =D17+D18+D19+D20 -> 16144.603 | E21: =E17+E18+E19+E20 -> 18109.422 | F21: =F17+F18+F19+F20 -> 19509.98 | G21: =G17+G18+G19+G20 -> 20467.993
A22: EBT (pre-tax income)
A23: Disney standalone | C23: =DIS_PROJ!C35 -> 14417.362 | D23: =DIS_PROJ!D35 -> 14955.486 | E23: =DIS_PROJ!E35 -> 15520.337 | F23: =DIS_PROJ!F35 -> 16113.21 | G23: =DIS_PROJ!G35 -> 16735.465
A24: Fox RemainCo standalone | C24: =FOX_PROJ!C27 -> 2265.4629 | D24: =FOX_PROJ!D27 -> 2433.0252 | E24: =FOX_PROJ!E27 -> 2607.9656 | F24: =FOX_PROJ!F27 -> 2790.6229 | G24: =FOX_PROJ!G27 -> 2981.3522
A25: + Synergies | C25: =SYNERGIES!C26 -> -360 | D25: =SYNERGIES!D26 -> 440 | E25: =SYNERGIES!E26 -> 1520 | F25: =SYNERGIES!F26 -> 2000 | G25: =SYNERGIES!G26 -> 2000
A26: − PPA purchase-accounting | C26: =PPA_DA!D22 -> -4107.0061 | D26: =PPA_DA!E22 -> -3961.9783 | E26: =PPA_DA!F22 -> -3816.9505 | F26: =PPA_DA!G22 -> -3671.9227 | G26: =PPA_DA!H22 -> -3526.8949
A27: Pro forma EBT | C27: =C23+C24+C25+C26+C66 -> 11568.92 | D27: =D23+D24+D25+D26+D66 -> 13860.312 | E27: =E23+E24+E25+E26+E66 -> 16253.988 | F27: =F23+F24+F25+F26+F66 -> 18137.641 | G27: =G23+G24+G25+G26+G66 -> 19342.403
A28: INCOME TAXES
A29: Disney standalone | C29: =DIS_PROJ!C37 -> -3460.1669 | D29: =DIS_PROJ!D37 -> -3589.3165 | E29: =DIS_PROJ!E37 -> -3724.881 | F29: =DIS_PROJ!F37 -> -3867.1704 | G29: =DIS_PROJ!G37 -> -4016.5117
A30: Fox RemainCo standalone | C30: =FOX_PROJ!C29 -> -543.71108 | D30: =FOX_PROJ!D29 -> -583.92604 | E30: =FOX_PROJ!E29 -> -625.91174 | F30: =FOX_PROJ!F29 -> -669.74951 | G30: =FOX_PROJ!G29 -> -715.52454
A31: + Synergies | C31: 0 | D31: 0 | E31: 0 | F31: 0 | G31: 0
A32: − PPA purchase-accounting | C32: 0 | D32: 0 | E32: 0 | F32: 0 | G32: 0
A33: Pro forma income taxes | C33: =C29+C30+C31+C32+C67 -> -3848.6222 | D33: =D29+D30+D31+D32+D67 -> -4171.7498 | E33: =E29+E30+E31+E32+E67 -> -4452.2253 | F33: =F29+F30+F31+F32+F67 -> -4754.2953 | G33: =G29+G30+G31+G32+G67 -> -5008.6315
A34: NET INCOME
A35: Disney standalone | C35: =DIS_PROJ!C38 -> 10957.195 | D35: =DIS_PROJ!D38 -> 11366.169 | E35: =DIS_PROJ!E38 -> 11795.456 | F35: =DIS_PROJ!F38 -> 12246.04 | G35: =DIS_PROJ!G38 -> 12718.954
A36: Fox RemainCo standalone | C36: =FOX_PROJ!C30 -> 1721.7518 | D36: =FOX_PROJ!D30 -> 1849.0991 | E36: =FOX_PROJ!E30 -> 1982.0538 | F36: =FOX_PROJ!F30 -> 2120.8734 | G36: =FOX_PROJ!G30 -> 2265.8277
A37: + Synergies | C37: =SYNERGIES!C28 -> -273.6 | D37: =SYNERGIES!D28 -> 334.4 | E37: =SYNERGIES!E28 -> 1155.2 | F37: =SYNERGIES!F28 -> 1520 | G37: =SYNERGIES!G28 -> 1520
A38: − PPA purchase-accounting | C38: =PPA_DA!D24 -> -3121.3246 | D38: =PPA_DA!E24 -> -3011.1035 | E38: =PPA_DA!F24 -> -2900.8824 | F38: =PPA_DA!G24 -> -2790.6613 | G38: =PPA_DA!H24 -> -2680.4402
A39: Pro forma net income (before NCI) | C39: =C35+C36+C37+C38+C68 -> 8792.379 | D39: =D35+D36+D37+D38+D68 -> 10533.837 | E39: =E35+E36+E37+E38+E68 -> 12353.031 | F39: =F35+F36+F37+F38+F68 -> 13784.607 | G39: =G35+G36+G37+G38+G68 -> 14700.226
A40: Disney standalone | C40: =DIS_PROJ!C39 -> -392.4665 | D40: =DIS_PROJ!D39 -> -407.11519 | E40: =DIS_PROJ!E39 -> -422.49147 | F40: =DIS_PROJ!F39 -> -438.63053 | G40: =DIS_PROJ!G39 -> -455.56944
A41: Fox RemainCo standalone | C41: =FOX_PROJ!C31 -> -267.85121 | D41: =FOX_PROJ!D31 -> -287.66252 | E41: =FOX_PROJ!E31 -> -308.34615 | F41: =FOX_PROJ!F31 -> -329.94218 | G41: =FOX_PROJ!G31 -> -352.49257
A42: + Synergies | C42: 0 | D42: 0 | E42: 0 | F42: 0 | G42: 0
A43: − PPA purchase-accounting | C43: 0 | D43: 0 | E43: 0 | F43: 0 | G43: 0
A44: Pro forma noncontrolling interests | C44: =C40+C41+C42+C43 -> -660.31771 | D44: =D40+D41+D42+D43 -> -694.77771 | E44: =E40+E41+E42+E43 -> -730.83762 | F44: =F40+F41+F42+F43 -> -768.57271 | G44: =G40+G41+G42+G43 -> -808.06201
A45: Net income attributable to New Disney | C45: =C39+C44 -> 8132.0613 | D45: =D39+D44 -> 9839.0598 | E45: =E39+E44 -> 11622.193 | F45: =F39+F44 -> 13016.035 | G45: =G39+G44 -> 13892.164
A46: DILUTED SHARES
A47: Disney standalone diluted shares | C47: =DIS_PROJ!C41 -> 1488 | D47: =DIS_PROJ!D41 -> 1488 | E47: =DIS_PROJ!E41 -> 1488 | F47: =DIS_PROJ!F41 -> 1488 | G47: =DIS_PROJ!G41 -> 1488
A48: + New Disney shares issued to 21CF | C48: ='S&U'!$B$31 -> 307 | D48: ='S&U'!$B$31 -> 307 | E48: ='S&U'!$B$31 -> 307 | F48: ='S&U'!$B$31 -> 307 | G48: ='S&U'!$B$31 -> 307
A49: Pro forma diluted shares | C49: =C47+C48 -> 1795 | D49: =D47+D48 -> 1795 | E49: =E47+E48 -> 1795 | F49: =F47+F48 -> 1795 | G49: =G47+G48 -> 1795
A50: EPS
A51: Disney standalone diluted EPS (memo) | C51: =DIS_PROJ!C42 -> 7.099952 | D51: =DIS_PROJ!D42 -> 7.3649556 | E51: =DIS_PROJ!E42 -> 7.6431216 | F51: =DIS_PROJ!F42 -> 7.9350867 | G51: =DIS_PROJ!G42 -> 8.2415217
A52: Pro forma diluted EPS | C52: =C45/C49 -> 4.5303963 | D52: =D45/D49 -> 5.4813704 | E52: =E45/E49 -> 6.4747595 | F52: =F45/F49 -> 7.2512727 | G52: =G45/G49 -> 7.7393672
A54: AUDIT CHECKS (red = must be ~0)
A55: Combined revenue tie (PF − DIS − FOX − syn, FY19E =0) | C55: =C9-(C5+C6+C7+C8) -> 0
A56: Combined EBIT tie (FY19E =0) | C56: =C21-(C17+C18+C19+C20) -> 0
A57: Combined net income tie (PF NI attr − components, FY19E =0) | C57: =C45-(DIS_PROJ!C40+FOX_PROJ!C32+SYNERGIES!C28+PPA_DA!D24+C68) -> 0
A58: EPS calculation tie (PF EPS×shares − NI attr, FY19E =0) | C58: =C52*C49-C45 -> 0
A60: SHEET STATUS | B60: =IF(AND(ABS(C55)<1,ABS(C56)<1,ABS(C57)<1,ABS(C58)<1,ABS(C75)<0.01),"OK","CHECK") -> OK
A62: DEBT FINANCING INTEGRATION (drives EBT -> Taxes -> NI -> EPS above)
A63: Remove Fox standalone interest (add-back) | C63: =-FOX_PROJ!C24 -> 1152.48 | D63: =-FOX_PROJ!D24 -> 1152.48 | E63: =-FOX_PROJ!E24 -> 1152.48 | F63: =-FOX_PROJ!F24 -> 1152.48 | G63: =-FOX_PROJ!G24 -> 1152.48 | H63: Replaced by DEBT schedule
A64: Less: new acquisition debt interest | C64: =-DEBT!C27 -> -646.899 | D64: =-DEBT!D27 -> -6.220018 | E64: =-DEBT!E27 -> 0 | F64: =-DEBT!F27 -> 0 | G64: =-DEBT!G27 -> 0
A65: Less: assumed 21CF interest (DEBT) | C65: =-DEBT!C28 -> -1152.48 | D65: =-DEBT!D28 -> -1152.48 | E65: =-DEBT!E28 -> -729.84443 | F65: =-DEBT!F28 -> -246.74904 | G65: =-DEBT!G28 -> 0 | H65: Premium benefit stays in PPA layer
A66: Net financing adjustment - pre-tax | C66: =C63+C64+C65 -> -646.899 | D66: =D63+D64+D65 -> -6.220018 | E66: =E63+E64+E65 -> 422.63557 | F66: =F63+F64+F65 -> 905.73096 | G66: =G63+G64+G65 -> 1152.48
A67: Tax effect at combined rate | C67: =-C66*ASSUMPTIONS!F84 -> 155.25576 | D67: =-D66*ASSUMPTIONS!F84 -> 1.4928043 | E67: =-E66*ASSUMPTIONS!F84 -> -101.43254 | F67: =-F66*ASSUMPTIONS!F84 -> -217.37543 | G67: =-G66*ASSUMPTIONS!F84 -> -276.5952
A68: Net financing adjustment - after-tax | C68: =C66+C67 -> -491.64324 | D68: =D66+D67 -> -4.7272137 | E68: =E66+E67 -> 321.20303 | F68: =F66+F67 -> 688.35553 | G68: =G66+G67 -> 875.8848
A70: EPS RECONCILIATION: PRE- vs POST-DEBT INTEGRATION
A71: Pro forma diluted EPS - before integration | C71: =(C45-C68)/C49 -> 4.8042922 | D71: =(D45-D68)/D49 -> 5.4840039 | E71: =(E45-E68)/E49 -> 6.2958163 | F71: =(F45-F68)/F49 -> 6.8677877 | G71: =(G45-G68)/G49 -> 7.2514091
A72: Impact of DEBT financing (per share) | C72: =C68/C49 -> -0.27389596 | D72: =D68/D49 -> -0.0026335452 | E72: =E68/E49 -> 0.17894319 | F72: =F68/F49 -> 0.38348498 | G72: =G68/G49 -> 0.48795811
A73: Pro forma diluted EPS - after integration | C73: =C45/C49 -> 4.5303963 | D73: =D45/D49 -> 5.4813704 | E73: =E45/E49 -> 6.4747595 | F73: =F45/F49 -> 7.2512727 | G73: =G45/G49 -> 7.7393672
A75: Recon tie: before + impact − after (FY19E =0) | C75: =C71+C72-C73 -> 0

Sheet PF_BS
A1: PF_BS — Pro Forma Balance Sheet (opening)
A2: $ in millions; opening combined balance sheet at close + roll-forward
A4: Line item ($mm) | B4: DIS | C4: FOX RemainCo | D4: PPA adj | E4: Synergies | F4: Debt | G4: Hulu | H4: RSN | I4: Pro Forma
A5: OPENING BALANCE SHEET (structure)
A6: Cash and cash equivalents
A7: Receivables
A8: Film, TV & content
A9: Investments
A10: Property, net
A11: Intangible assets
A12: Goodwill
A13: Other assets
A14: TOTAL ASSETS
A15: Borrowings
A16: Deferred income taxes
... A24: Opening-BS bridge (DIS + RemainCo at FV + PPA goodwill/step-ups + new debt/equity) to be completed.

Sheet PF_CF
A1: PF_CF — Pro Forma Cash Flow
A2: $ in millions; combined indirect-method cash flow
A4: Line item ($mm) | B4: FY2019E | C4: FY2020E | D4: FY2021E | E4: FY2022E | F4: FY2023E
A5: COMBINED CASH FLOW (structure)
A6: Net income
A7: Depreciation & amortization
A8: PPA amortization
A9: Working capital
A10: Cash from operations
A11: Capex
A12: RSN sale proceeds
A13: Cash from investing
A14: Debt repayment
A15: Dividends
A16: Cash from financing
... A21: Indirect-method build and cash tie-out to be completed after PF_IS / PF_BS.

Sheet ACCR_DIL
A1: ACCR_DIL - Accretion / (Dilution) Analysis
A2: Pro forma EPS vs Disney standalone. Per-share bridge decomposes every driver incl. share issuance; cash-EPS view strips non-cash PPA amortization. Links: DIS_PROJ, FOX_PROJ, SYNERGIES, PPA_DA (yr D-H), PF_IS.
A4: Metric | C4: FY2019E | D4: FY2020E | E4: FY2021E | F4: FY2022E | G4: FY2023E
A5: EPS SUMMARY
A6: Disney standalone diluted EPS | C6: =DIS_PROJ!C42 -> 7.099952 | D6: =DIS_PROJ!D42 -> 7.3649556 | E6: =DIS_PROJ!E42 -> 7.6431216 | F6: =DIS_PROJ!F42 -> 7.9350867 | G6: =DIS_PROJ!G42 -> 8.2415217
A7: Pro forma diluted EPS | C7: =PF_IS!C52 -> 4.5303963 | D7: =PF_IS!D52 -> 5.4813704 | E7: =PF_IS!E52 -> 6.4747595 | F7: =PF_IS!F52 -> 7.2512727 | G7: =PF_IS!G52 -> 7.7393672
A8: Accretion / (dilution) - $ | C8: =C7-C6 -> -2.5695557 | D8: =D7-D6 -> -1.8835852 | E8: =E7-E6 -> -1.1683621 | F8: =F7-F6 -> -0.68381398 | G8: =G7-G6 -> -0.50215454
A9: Accretion / (dilution) - % | C9: =IF(C6=0,0,C8/C6) -> -0.36191171 | D9: =IF(D6=0,0,D8/D6) -> -0.2557497 | E9: =IF(E6=0,0,E8/E6) -> -0.15286452 | F9: =IF(F6=0,0,F8/F6) -> -0.086175994 | G9: =IF(G6=0,0,G8/G6) -> -0.060929833
A10: memo: pro forma / Disney diluted shares | C10: =PF_IS!C49 -> 1795 | D10: =PF_IS!D49 -> 1795 | E10: =PF_IS!E49 -> 1795 | F10: =PF_IS!F49 -> 1795 | G10: =PF_IS!G49 -> 1795
A11: EPS BRIDGE (Disney standalone -> Pro forma, $/sh)
A12: Disney standalone EPS | C12: =DIS_PROJ!C42 -> 7.099952 | D12: =DIS_PROJ!D42 -> 7.3649556 | E12: =DIS_PROJ!E42 -> 7.6431216 | F12: =DIS_PROJ!F42 -> 7.9350867 | G12: =DIS_PROJ!G42 -> 8.2415217
A13: (−) Dilution from new shares issued | C13: =DIS_PROJ!C40/PF_IS!C49-DIS_PROJ!C42 -> -1.2143093 | D13: =DIS_PROJ!D40/PF_IS!D49-DIS_PROJ!D42 -> -1.2596331 | E13: =DIS_PROJ!E40/PF_IS!E49-DIS_PROJ!E42 -> -1.307208 | F13: =DIS_PROJ!F40/PF_IS!F49-DIS_PROJ!F42 -> -1.357143 | G13: =DIS_PROJ!G40/PF_IS!G49-DIS_PROJ!G42 -> -1.4095527
A14: (+) Fox earnings contribution | C14: =FOX_PROJ!C32/PF_IS!C49 -> 0.80997245 | D14: =FOX_PROJ!D32/PF_IS!D49 -> 0.86988112 | E14: =FOX_PROJ!E32/PF_IS!E49 -> 0.93242768 | F14: =FOX_PROJ!F32/PF_IS!F49 -> 0.99773329 | G14: =FOX_PROJ!G32/PF_IS!G49 -> 1.0659249
A15: (+) Cost & revenue synergies | C15: =SYNERGIES!C24*(1-ASSUMPTIONS!F84)/PF_IS!C49 -> 0.084679666 | D15: =SYNERGIES!D24*(1-ASSUMPTIONS!F84)/PF_IS!D49 -> 0.42339833 | E15: =SYNERGIES!E24*(1-ASSUMPTIONS!F84)/PF_IS!E49 -> 0.76211699 | F15: =SYNERGIES!F24*(1-ASSUMPTIONS!F84)/PF_IS!F49 -> 0.84679666 | G15: =SYNERGIES!G24*(1-ASSUMPTIONS!F84)/PF_IS!G49 -> 0.84679666
A16: (−) Integration costs | C16: =(SYNERGIES!C28-SYNERGIES!C24*(1-ASSUMPTIONS!F84))/PF_IS!C49 -> -0.23710306 | D16: =(SYNERGIES!D28-SYNERGIES!D24*(1-ASSUMPTIONS!F84))/PF_IS!D49 -> -0.23710306 | E16: =(SYNERGIES!E28-SYNERGIES!E24*(1-ASSUMPTIONS!F84))/PF_IS!E49 -> -0.11855153 | F16: =(SYNERGIES!F28-SYNERGIES!F24*(1-ASSUMPTIONS!F84))/PF_IS!F49 -> 0 | G16: =(SYNERGIES!G28-SYNERGIES!G24*(1-ASSUMPTIONS!F84))/PF_IS!G49 -> 0
A17: (−) PPA amortization | C17: =PPA_DA!D24/PF_IS!C49 -> -1.7388995 | D17: =PPA_DA!E24/PF_IS!D49 -> -1.677495 | E17: =PPA_DA!F24/PF_IS!E49 -> -1.6160905 | F17: =PPA_DA!G24/PF_IS!F49 -> -1.5546859 | G17: =PPA_DA!H24/PF_IS!G49 -> -1.4932814
A18: (+/−) Financing costs (DEBT) | C18: =PF_IS!C68/PF_IS!C49 -> -0.27389596 | D18: =PF_IS!D68/PF_IS!D49 -> -0.0026335452 | E18: =PF_IS!E68/PF_IS!E49 -> 0.17894319 | F18: =PF_IS!F68/PF_IS!F49 -> 0.38348498 | G18: =PF_IS!G68/PF_IS!G49 -> 0.48795811
A19: = Pro forma EPS | C19: =C12+C13+C14+C15+C16+C17+C18 -> 4.5303963 | D19: =D12+D13+D14+D15+D16+D17+D18 -> 5.4813704 | E19: =E12+E13+E14+E15+E16+E17+E18 -> 6.4747595 | F19: =F12+F13+F14+F15+F16+F17+F18 -> 7.2512727 | G19: =G12+G13+G14+G15+G16+G17+G18 -> 7.7393672
A20: DRIVER CONTRIBUTION TO NET INCOME ($mm, after-tax)
A21: Disney net income attributable | C21: =DIS_PROJ!C40 -> 10564.729 | D21: =DIS_PROJ!D40 -> 10959.054 | E21: =DIS_PROJ!E40 -> 11372.965 | F21: =DIS_PROJ!F40 -> 11807.409 | G21: =DIS_PROJ!G40 -> 12263.384
A22: Fox net income attributable | C22: =FOX_PROJ!C32 -> 1453.9006 | D22: =FOX_PROJ!D32 -> 1561.4366 | E22: =FOX_PROJ!E32 -> 1673.7077 | F22: =FOX_PROJ!F32 -> 1790.9313 | G22: =FOX_PROJ!G32 -> 1913.3351
A23: Cost & revenue synergies | C23: =SYNERGIES!C24*(1-ASSUMPTIONS!F84) -> 152 | D23: =SYNERGIES!D24*(1-ASSUMPTIONS!F84) -> 760 | E23: =SYNERGIES!E24*(1-ASSUMPTIONS!F84) -> 1368 | F23: =SYNERGIES!F24*(1-ASSUMPTIONS!F84) -> 1520 | G23: =SYNERGIES!G24*(1-ASSUMPTIONS!F84) -> 1520
A24: Integration costs | C24: =SYNERGIES!C28-SYNERGIES!C24*(1-ASSUMPTIONS!F84) -> -425.6 | D24: =SYNERGIES!D28-SYNERGIES!D24*(1-ASSUMPTIONS!F84) -> -425.6 | E24: =SYNERGIES!E28-SYNERGIES!E24*(1-ASSUMPTIONS!F84) -> -212.8 | F24: =SYNERGIES!F28-SYNERGIES!F24*(1-ASSUMPTIONS!F84) -> 0 | G24: =SYNERGIES!G28-SYNERGIES!G24*(1-ASSUMPTIONS!F84) -> 0
A25: PPA amortization | C25: =PPA_DA!D24 -> -3121.3246 | D25: =PPA_DA!E24 -> -3011.1035 | E25: =PPA_DA!F24 -> -2900.8824 | F25: =PPA_DA!G24 -> -2790.6613 | G25: =PPA_DA!H24 -> -2680.4402
A26: Financing (DEBT integration) | C26: =PF_IS!C68 -> -491.64324 | D26: =PF_IS!D68 -> -4.7272137 | E26: =PF_IS!E68 -> 321.20303 | F26: =PF_IS!F68 -> 688.35553 | G26: =PF_IS!G68 -> 875.8848
A27: = Pro forma net income attributable | C27: =C21+C22+C23+C24+C25+C26 -> 8132.0613 | D27: =D21+D22+D23+D24+D25+D26 -> 9839.0598 | E27: =E21+E22+E23+E24+E25+E26 -> 11622.193 | F27: =F21+F22+F23+F24+F25+F26 -> 13016.035 | G27: =G21+G22+G23+G24+G25+G26 -> 13892.164
A28: CASH EPS (excl. non-cash PPA step-up amortization)
A29: Pro forma net income attributable | C29: =PF_IS!C45 -> 8132.0613 | D29: =PF_IS!D45 -> 9839.0598 | E29: =PF_IS!E45 -> 11622.193 | F29: =PF_IS!F45 -> 13016.035 | G29: =PF_IS!G45 -> 13892.164
A30: Add back: PPA step-up amort, after-tax | C30: =PPA_DA!D15*(1-ASSUMPTIONS!F84) -> 3277.1246 | D30: =PPA_DA!E15*(1-ASSUMPTIONS!F84) -> 3166.9035 | E30: =PPA_DA!F15*(1-ASSUMPTIONS!F84) -> 3056.6824 | F30: =PPA_DA!G15*(1-ASSUMPTIONS!F84) -> 2946.4613 | G30: =PPA_DA!H15*(1-ASSUMPTIONS!F84) -> 2836.2402
A31: Cash pro forma net income | C31: =C29+C30 -> 11409.186 | D31: =D29+D30 -> 13005.963 | E31: =E29+E30 -> 14678.876 | F31: =F29+F30 -> 15962.496 | G31: =G29+G30 -> 16728.404
A32: Cash pro forma EPS | C32: =C31/PF_IS!C49 -> 6.3560924 | D32: =D31/PF_IS!D49 -> 7.245662 | E32: =E31/PF_IS!E49 -> 8.1776466 | F32: =F31/PF_IS!F49 -> 8.8927553 | G32: =G31/PF_IS!G49 -> 9.3194453
A33: Cash accretion / (dilution) - $ | C33: =C32-C6 -> -0.74385958 | D33: =D32-D6 -> -0.11929357 | E33: =E32-E6 -> 0.53452501 | F33: =F32-F6 -> 0.95766862 | G33: =G32-G6 -> 1.0779235
A34: Cash accretion / (dilution) - % | C34: =IF(C6=0,0,C33/C6) -> -0.10476966 | D34: =IF(D6=0,0,D33/D6) -> -0.016197459 | E34: =IF(E6=0,0,E33/E6) -> 0.069935431 | F34: =IF(F6=0,0,F33/F6) -> 0.12068786 | G34: =IF(G6=0,0,G33/G6) -> 0.13079181
A35: CUMULATIVE VALUE CREATION (running; FY2023E col = 5-yr total)
A36: Cumulative incremental NI vs standalone ($mm) | C36: =PF_IS!C45-DIS_PROJ!C40 -> -2432.6673 | D36: =C36+(PF_IS!D45-DIS_PROJ!D40) -> -3552.6614 | E36: =D36+(PF_IS!E45-DIS_PROJ!E40) -> -3303.433 | F36: =E36+(PF_IS!F45-DIS_PROJ!F40) -> -2094.8075 | G36: =F36+(PF_IS!G45-DIS_PROJ!G40) -> -466.02775
A37: Cumulative net synergies, after-tax ($mm) | C37: =SYNERGIES!C28 -> -273.6 | D37: =C37+(SYNERGIES!D28) -> 60.8 | E37: =D37+(SYNERGIES!E28) -> 1216 | F37: =E37+(SYNERGIES!F28) -> 2736 | G37: =F37+(SYNERGIES!G28) -> 4256
A38: Cumulative PPA amortization, after-tax ($mm) | C38: =PPA_DA!D24 -> -3121.3246 | D38: =C38+(PPA_DA!E24) -> -6132.4281 | E38: =D38+(PPA_DA!F24) -> -9033.3105 | F38: =E38+(PPA_DA!G24) -> -11823.972 | G38: =F38+(PPA_DA!H24) -> -14504.412
A39: Cumulative financing impact, after-tax ($mm) | C39: =PF_IS!C68 -> -491.64324 | D39: =C39+(PF_IS!D68) -> -496.37045 | E39: =D39+(PF_IS!E68) -> -175.16742 | F39: =E39+(PF_IS!F68) -> 513.18811 | G39: =F39+(PF_IS!G68) -> 1389.0729
A40: Cumulative GAAP accretion / (dilution) ($/sh) | C40: =PF_IS!C52-DIS_PROJ!C42 -> -2.5695557 | D40: =C40+(PF_IS!D52-DIS_PROJ!D42) -> -4.453141 | E40: =D40+(PF_IS!E52-DIS_PROJ!E42) -> -5.6215031 | F40: =E40+(PF_IS!F52-DIS_PROJ!F42) -> -6.305317 | G40: =F40+(PF_IS!G52-DIS_PROJ!G42) -> -6.8074716
A41: Cumulative cash accretion / (dilution) ($/sh) | C41: =C32-C6 -> -0.74385958 | D41: =C41+(D32-D6) -> -0.86315315 | E41: =D41+(E32-E6) -> -0.32862815 | F41: =E41+(F32-F6) -> 0.62904048 | G41: =F41+(G32-G6) -> 1.706964
A43: AUDIT CHECKS (red = must be ~0)
A44: EPS bridge ties to PF EPS (FY19E =0) | C44: =C19-PF_IS!C52 -> 0
A45: Driver $ sum = PF NI attributable (FY19E =0) | C45: =C27-PF_IS!C45 -> 0
A46: Accretion $ = PF EPS − DIS EPS (FY19E =0) | C46: =C8-(PF_IS!C52-DIS_PROJ!C42) -> 0
A47: Synergy split ties to PF_IS (FY19E =0) | C47: =(C23+C24)-SYNERGIES!C28 -> 0
A48: Cash EPS ≥ GAAP EPS (min add-back, ≥0) | C48: =MIN(C30:G30) -> 2836.2402
A50: SHEET STATUS | B50: =IF(AND(ABS(C44)<0.01,ABS(C45)<1,ABS(C46)<0.01,ABS(C47)<1,C48>=0),"OK","CHECK") -> OK

Sheet SENS
A1: SENS - Sensitivity & Scenario Analysis
A2: Robustness of cash-accretion conclusions. Analytical perturbations of the live model (exact at FY2023E: all debt repaid by FY2022E, so no second-order paydown effect). $/sh; A/(D) vs Disney standalone.
A4: 1 · SYNERGY SENSITIVITY - FY2023E
A5: Synergy realization (% of run-rate) | C5: Cash EPS | D5: Cash A/(D) %
B6: 0.5 | C6: =(ACCR_DIL!$G$31+(SYNERGIES!$G$24*(1-ASSUMPTIONS!$F$84))*(B6-1))/PF_IS!$G$49 -> 8.8960469 | D6: =C6/ACCR_DIL!$G$6-1 -> 0.079418005
B7: 0.75 | C7: =(ACCR_DIL!$G$31+(SYNERGIES!$G$24*(1-ASSUMPTIONS!$F$84))*(B7-1))/PF_IS!$G$49 -> 9.1077461 | D7: =C7/ACCR_DIL!$G$6-1 -> 0.10510491
A8: base case | B8: 1 | C8: =(ACCR_DIL!$G$31+(SYNERGIES!$G$24*(1-ASSUMPTIONS!$F$84))*(B8-1))/PF_IS!$G$49 -> 9.3194453 | D8: =C8/ACCR_DIL!$G$6-1 -> 0.13079181
B9: 1.25 | C9: =(ACCR_DIL!$G$31+(SYNERGIES!$G$24*(1-ASSUMPTIONS!$F$84))*(B9-1))/PF_IS!$G$49 -> 9.5311444 | D9: =C9/ACCR_DIL!$G$6-1 -> 0.15647871
B10: 1.5 | C10: =(ACCR_DIL!$G$31+(SYNERGIES!$G$24*(1-ASSUMPTIONS!$F$84))*(B10-1))/PF_IS!$G$49 -> 9.7428436 | D10: =C10/ACCR_DIL!$G$6-1 -> 0.18216561
A12: 2 · FINANCING SENSITIVITY - new-acquisition debt rate
A13: New-acq debt rate | C13: Cash EPS FY19E | D13: Cash A/(D)% FY19E | E13: Cash EPS FY23E | F13: Cash A/(D)% FY23E
B14: 0.02 | C14: =(ACCR_DIL!$C$31-DEBT!$C$10*(B14-ASSUMPTIONS!$F$68)*(1-ASSUMPTIONS!$F$84))/PF_IS!$C$49 -> 6.4639908 | D14: =C14/ACCR_DIL!$C$6-1 -> -0.089572602 | E14: =(ACCR_DIL!$G$31-DEBT!$G$10*(B14-ASSUMPTIONS!$F$68)*(1-ASSUMPTIONS!$F$84))/PF_IS!$G$49 -> 9.3194453 | F14: =E14/ACCR_DIL!$G$6-1 -> 0.13079181
B15: 0.03 | C15: =(ACCR_DIL!$C$31-DEBT!$C$10*(B15-ASSUMPTIONS!$F$68)*(1-ASSUMPTIONS!$F$84))/PF_IS!$C$49 -> 6.3809921 | D15: =C15/ACCR_DIL!$C$6-1 -> -0.10126265 | E15: =(ACCR_DIL!$G$31-DEBT!$G$10*(B15-ASSUMPTIONS!$F$68)*(1-ASSUMPTIONS!$F$84))/PF_IS!$G$49 -> 9.3194453 | F15: =E15/ACCR_DIL!$G$6-1 -> 0.13079181
B16: 0.04 | C16: =(ACCR_DIL!$C$31-DEBT!$C$10*(B16-ASSUMPTIONS!$F$68)*(1-ASSUMPTIONS!$F$84))/PF_IS!$C$49 -> 6.2979933 | D16: =C16/ACCR_DIL!$C$6-1 -> -0.1129527 | E16: =(ACCR_DIL!$G$31-DEBT!$G$10*(B16-ASSUMPTIONS!$F$68)*(1-ASSUMPTIONS!$F$84))/PF_IS!$G$49 -> 9.3194453 | F16: =E16/ACCR_DIL!$G$6-1 -> 0.13079181
B17: 0.05 | C17: =(ACCR_DIL!$C$31-DEBT!$C$10*(B17-ASSUMPTIONS!$F$68)*(1-ASSUMPTIONS!$F$84))/PF_IS!$C$49 -> 6.2149945 | D17: =C17/ACCR_DIL!$C$6-1 -> -0.12464274 | E17: =(ACCR_DIL!$G$31-DEBT!$G$10*(B17-ASSUMPTIONS!$F$68)*(1-ASSUMPTIONS!$F$84))/PF_IS!$G$49 -> 9.3194453 | F17: =E17/ACCR_DIL!$G$6-1 -> 0.13079181
B18: 0.06 | C18: =(ACCR_DIL!$C$31-DEBT!$C$10*(B18-ASSUMPTIONS!$F$68)*(1-ASSUMPTIONS!$F$84))/PF_IS!$C$49 -> 6.1319957 | D18: =C18/ACCR_DIL!$C$6-1 -> -0.13633279 | E18: =(ACCR_DIL!$G$31-DEBT!$G$10*(B18-ASSUMPTIONS!$F$68)*(1-ASSUMPTIONS!$F$84))/PF_IS!$G$49 -> 9.3194453 | F18: =E18/ACCR_DIL!$G$6-1 -> 0.13079181
A19: Note: FY2023E is invariant to the new-acq rate - the debt is fully retired by FY2020E (new-acq balance = 0). Financing-rate risk is concentrated in FY2019E.
A21: 3 · TWO-WAY MATRIX - Cash A/(D) % (rows: synergy % · cols: new-acq rate)
A22: 3a · FY2023E Cash A/(D) % (terminal year - financing-invariant, see note)
B23: Syn ↓ / Rate → | C23: 0.02 | D23: 0.03 | E23: 0.04 | F23: 0.05 | G23: 0.06
B24: 0.5 | C24: =((ACCR_DIL!$G$31+(SYNERGIES!$G$24*(1-ASSUMPTIONS!$F$84))*($B24-1)-DEBT!$G$10*(C$23-ASSUMPTIONS!$F$68)*(1-ASSUMPTIONS!$F$84))/PF_IS!$G$49)/ACCR_DIL!$G$6-1 -> 0.079418005 | D24: =((ACCR_DIL!$G$31+(SYNERGIES!$G$24*(1-ASSUMPTIONS!$F$84))*($B24-1)-DEBT!$G$10*(D$23-ASSUMPTIONS!$F$68)*(1-ASSUMPTIONS!$F$84))/PF_IS!$G$49)/ACCR_DIL!$G$6-1 -> 0.079418005 | E24: =((ACCR_DIL!$G$31+(SYNERGIES!$G$24*(1-ASSUMPTIONS!$F$84))*($B24-1)-DEBT!$G$10*(E$23-ASSUMPTIONS!$F$68)*(1-ASSUMPTIONS!$F$84))/PF_IS!$G$49)/ACCR_DIL!$G$6-1 -> 0.079418005 | F24: =((ACCR_DIL!$G$31+(SYNERGIES!$G$24*(1-ASSUMPTIONS!$F$84))*($B24-1)-DEBT!$G$10*(F$23-ASSUMPTIONS!$F$68)*(1-ASSUMPTIONS!$F$84))/PF_IS!$G$49)/ACCR_DIL!$G$6-1 -> 0.079418005 | G24: =((ACCR_DIL!$G$31+(SYNERGIES!$G$24*(1-ASSUMPTIONS!$F$84))*($B24-1)-DEBT!$G$10*(G$23-ASSUMPTIONS!$F$68)*(1-ASSUMPTIONS!$F$84))/PF_IS!$G$49)/ACCR_DIL!$G$6-1 -> 0.079418005
B25: 0.75 | C25: =((ACCR_DIL!$G$31+(SYNERGIES!$G$24*(1-ASSUMPTIONS!$F$84))*($B25-1)-DEBT!$G$10*(C$23-ASSUMPTIONS!$F$68)*(1-ASSUMPTIONS!$F$84))/PF_IS!$G$49)/ACCR_DIL!$G$6-1 -> 0.10510491 | D25: =((ACCR_DIL!$G$31+(SYNERGIES!$G$24*(1-ASSUMPTIONS!$F$84))*($B25-1)-DEBT!$G$10*(D$23-ASSUMPTIONS!$F$68)*(1-ASSUMPTIONS!$F$84))/PF_IS!$G$49)/ACCR_DIL!$G$6-1 -> 0.10510491 | E25: =((ACCR_DIL!$G$31+(SYNERGIES!$G$24*(1-ASSUMPTIONS!$F$84))*($B25-1)-DEBT!$G$10*(E$23-ASSUMPTIONS!$F$68)*(1-ASSUMPTIONS!$F$84))/PF_IS!$G$49)/ACCR_DIL!$G$6-1 -> 0.10510491 | F25: =((ACCR_DIL!$G$31+(SYNERGIES!$G$24*(1-ASSUMPTIONS!$F$84))*($B25-1)-DEBT!$G$10*(F$23-ASSUMPTIONS!$F$68)*(1-ASSUMPTIONS!$F$84))/PF_IS!$G$49)/ACCR_DIL!$G$6-1 -> 0.10510491 | G25: =((ACCR_DIL!$G$31+(SYNERGIES!$G$24*(1-ASSUMPTIONS!$F$84))*($B25-1)-DEBT!$G$10*(G$23-ASSUMPTIONS!$F$68)*(1-ASSUMPTIONS!$F$84))/PF_IS!$G$49)/ACCR_DIL!$G$6-1 -> 0.10510491
B26: 1 | C26: =((ACCR_DIL!$G$31+(SYNERGIES!$G$24*(1-ASSUMPTIONS!$F$84))*($B26-1)-DEBT!$G$10*(C$23-ASSUMPTIONS!$F$68)*(1-ASSUMPTIONS!$F$84))/PF_IS!$G$49)/ACCR_DIL!$G$6-1 -> 0.13079181 | D26: =((ACCR_DIL!$G$31+(SYNERGIES!$G$24*(1-ASSUMPTIONS!$F$84))*($B26-1)-DEBT!$G$10*(D$23-ASSUMPTIONS!$F$68)*(1-ASSUMPTIONS!$F$84))/PF_IS!$G$49)/ACCR_DIL!$G$6-1 -> 0.13079181 | E26: =((ACCR_DIL!$G$31+(SYNERGIES!$G$24*(1-ASSUMPTIONS!$F$84))*($B26-1)-DEBT!$G$10*(E$23-ASSUMPTIONS!$F$68)*(1-ASSUMPTIONS!$F$84))/PF_IS!$G$49)/ACCR_DIL!$G$6-1 -> 0.13079181 | F26: =((ACCR_DIL!$G$31+(SYNERGIES!$G$24*(1-ASSUMPTIONS!$F$84))*($B26-1)-DEBT!$G$10*(F$23-ASSUMPTIONS!$F$68)*(1-ASSUMPTIONS!$F$84))/PF_IS!$G$49)/ACCR_DIL!$G$6-1 -> 0.13079181 | G26: =((ACCR_DIL!$G$31+(SYNERGIES!$G$24*(1-ASSUMPTIONS!$F$84))*($B26-1)-DEBT!$G$10*(G$23-ASSUMPTIONS!$F$68)*(1-ASSUMPTIONS!$F$84))/PF_IS!$G$49)/ACCR_DIL!$G$6-1 -> 0.13079181
B27: 1.25 | C27: =((ACCR_DIL!$G$31+(SYNERGIES!$G$24*(1-ASSUMPTIONS!$F$84))*($B27-1)-DEBT!$G$10*(C$23-ASSUMPTIONS!$F$68)*(1-ASSUMPTIONS!$F$84))/PF_IS!$G$49)/ACCR_DIL!$G$6-1 -> 0.15647871 | D27: =((ACCR_DIL!$G$31+(SYNERGIES!$G$24*(1-ASSUMPTIONS!$F$84))*($B27-1)-DEBT!$G$10*(D$23-ASSUMPTIONS!$F$68)*(1-ASSUMPTIONS!$F$84))/PF_IS!$G$49)/ACCR_DIL!$G$6-1 -> 0.15647871 | E27: =((ACCR_DIL!$G$31+(SYNERGIES!$G$24*(1-ASSUMPTIONS!$F$84))*($B27-1)-DEBT!$G$10*(E$23-ASSUMPTIONS!$F$68)*(1-ASSUMPTIONS!$F$84))/PF_IS!$G$49)/ACCR_DIL!$G$6-1 -> 0.15647871 | F27: =((ACCR_DIL!$G$31+(SYNERGIES!$G$24*(1-ASSUMPTIONS!$F$84))*($B27-1)-DEBT!$G$10*(F$23-ASSUMPTIONS!$F$68)*(1-ASSUMPTIONS!$F$84))/PF_IS!$G$49)/ACCR_DIL!$G$6-1 -> 0.15647871 | G27: =((ACCR_DIL!$G$31+(SYNERGIES!$G$24*(1-ASSUMPTIONS!$F$84))*($B27-1)-DEBT!$G$10*(G$23-ASSUMPTIONS!$F$68)*(1-ASSUMPTIONS!$F$84))/PF_IS!$G$49)/ACCR_DIL!$G$6-1 -> 0.15647871
B28: 1.5 | C28: =((ACCR_DIL!$G$31+(SYNERGIES!$G$24*(1-ASSUMPTIONS!$F$84))*($B28-1)-DEBT!$G$10*(C$23-ASSUMPTIONS!$F$68)*(1-ASSUMPTIONS!$F$84))/PF_IS!$G$49)/ACCR_DIL!$G$6-1 -> 0.18216561 | D28: =((ACCR_DIL!$G$31+(SYNERGIES!$G$24*(1-ASSUMPTIONS!$F$84))*($B28-1)-DEBT!$G$10*(D$23-ASSUMPTIONS!$F$68)*(1-ASSUMPTIONS!$F$84))/PF_IS!$G$49)/ACCR_DIL!$G$6-1 -> 0.18216561 | E28: =((ACCR_DIL!$G$31+(SYNERGIES!$G$24*(1-ASSUMPTIONS!$F$84))*($B28-1)-DEBT!$G$10*(E$23-ASSUMPTIONS!$F$68)*(1-ASSUMPTIONS!$F$84))/PF_IS!$G$49)/ACCR_DIL!$G$6-1 -> 0.18216561 | F28: =((ACCR_DIL!$G$31+(SYNERGIES!$G$24*(1-ASSUMPTIONS!$F$84))*($B28-1)-DEBT!$G$10*(F$23-ASSUMPTIONS!$F$68)*(1-ASSUMPTIONS!$F$84))/PF_IS!$G$49)/ACCR_DIL!$G$6-1 -> 0.18216561 | G28: =((ACCR_DIL!$G$31+(SYNERGIES!$G$24*(1-ASSUMPTIONS!$F$84))*($B28-1)-DEBT!$G$10*(G$23-ASSUMPTIONS!$F$68)*(1-ASSUMPTIONS!$F$84))/PF_IS!$G$49)/ACCR_DIL!$G$6-1 -> 0.18216561
A29: FY2023E: every column is identical - the financing rate has fully washed out via deleveraging; the matrix collapses to the synergy axis.
A31: 3b · FY2019E Cash A/(D) % (binding year - both drivers interact)
B32: Syn ↓ / Rate → | C32: 0.02 | D32: 0.03 | E32: 0.04 | F32: 0.05 | G32: 0.06
B33: 0.5 | C33: =((ACCR_DIL!$C$31+(SYNERGIES!$C$24*(1-ASSUMPTIONS!$F$84))*($B33-1)-DEBT!$C$10*(C$32-ASSUMPTIONS!$F$68)*(1-ASSUMPTIONS!$F$84))/PF_IS!$C$49)/ACCR_DIL!$C$6-1 -> -0.095535999 | D33: =((ACCR_DIL!$C$31+(SYNERGIES!$C$24*(1-ASSUMPTIONS!$F$84))*($B33-1)-DEBT!$C$10*(D$32-ASSUMPTIONS!$F$68)*(1-ASSUMPTIONS!$F$84))/PF_IS!$C$49)/ACCR_DIL!$C$6-1 -> -0.10722605 | E33: =((ACCR_DIL!$C$31+(SYNERGIES!$C$24*(1-ASSUMPTIONS!$F$84))*($B33-1)-DEBT!$C$10*(E$32-ASSUMPTIONS!$F$68)*(1-ASSUMPTIONS!$F$84))/PF_IS!$C$49)/ACCR_DIL!$C$6-1 -> -0.11891609 | F33: =((ACCR_DIL!$C$31+(SYNERGIES!$C$24*(1-ASSUMPTIONS!$F$84))*($B33-1)-DEBT!$C$10*(F$32-ASSUMPTIONS!$F$68)*(1-ASSUMPTIONS!$F$84))/PF_IS!$C$49)/ACCR_DIL!$C$6-1 -> -0.13060614 | G33: =((ACCR_DIL!$C$31+(SYNERGIES!$C$24*(1-ASSUMPTIONS!$F$84))*($B33-1)-DEBT!$C$10*(G$32-ASSUMPTIONS!$F$68)*(1-ASSUMPTIONS!$F$84))/PF_IS!$C$49)/ACCR_DIL!$C$6-1 -> -0.14229619
B34: 0.75 | C34: =((ACCR_DIL!$C$31+(SYNERGIES!$C$24*(1-ASSUMPTIONS!$F$84))*($B34-1)-DEBT!$C$10*(C$32-ASSUMPTIONS!$F$68)*(1-ASSUMPTIONS!$F$84))/PF_IS!$C$49)/ACCR_DIL!$C$6-1 -> -0.092554301 | D34: =((ACCR_DIL!$C$31+(SYNERGIES!$C$24*(1-ASSUMPTIONS!$F$84))*($B34-1)-DEBT!$C$10*(D$32-ASSUMPTIONS!$F$68)*(1-ASSUMPTIONS!$F$84))/PF_IS!$C$49)/ACCR_DIL!$C$6-1 -> -0.10424435 | E34: =((ACCR_DIL!$C$31+(SYNERGIES!$C$24*(1-ASSUMPTIONS!$F$84))*($B34-1)-DEBT!$C$10*(E$32-ASSUMPTIONS!$F$68)*(1-ASSUMPTIONS!$F$84))/PF_IS!$C$49)/ACCR_DIL!$C$6-1 -> -0.1159344 | F34: =((ACCR_DIL!$C$31+(SYNERGIES!$C$24*(1-ASSUMPTIONS!$F$84))*($B34-1)-DEBT!$C$10*(F$32-ASSUMPTIONS!$F$68)*(1-ASSUMPTIONS!$F$84))/PF_IS!$C$49)/ACCR_DIL!$C$6-1 -> -0.12762444 | G34: =((ACCR_DIL!$C$31+(SYNERGIES!$C$24*(1-ASSUMPTIONS!$F$84))*($B34-1)-DEBT!$C$10*(G$32-ASSUMPTIONS!$F$68)*(1-ASSUMPTIONS!$F$84))/PF_IS!$C$49)/ACCR_DIL!$C$6-1 -> -0.13931449
B35: 1 | C35: =((ACCR_DIL!$C$31+(SYNERGIES!$C$24*(1-ASSUMPTIONS!$F$84))*($B35-1)-DEBT!$C$10*(C$32-ASSUMPTIONS!$F$68)*(1-ASSUMPTIONS!$F$84))/PF_IS!$C$49)/ACCR_DIL!$C$6-1 -> -0.089572602 | D35: =((ACCR_DIL!$C$31+(SYNERGIES!$C$24*(1-ASSUMPTIONS!$F$84))*($B35-1)-DEBT!$C$10*(D$32-ASSUMPTIONS!$F$68)*(1-ASSUMPTIONS!$F$84))/PF_IS!$C$49)/ACCR_DIL!$C$6-1 -> -0.10126265 | E35: =((ACCR_DIL!$C$31+(SYNERGIES!$C$24*(1-ASSUMPTIONS!$F$84))*($B35-1)-DEBT!$C$10*(E$32-ASSUMPTIONS!$F$68)*(1-ASSUMPTIONS!$F$84))/PF_IS!$C$49)/ACCR_DIL!$C$6-1 -> -0.1129527 | F35: =((ACCR_DIL!$C$31+(SYNERGIES!$C$24*(1-ASSUMPTIONS!$F$84))*($B35-1)-DEBT!$C$10*(F$32-ASSUMPTIONS!$F$68)*(1-ASSUMPTIONS!$F$84))/PF_IS!$C$49)/ACCR_DIL!$C$6-1 -> -0.12464274 | G35: =((ACCR_DIL!$C$31+(SYNERGIES!$C$24*(1-ASSUMPTIONS!$F$84))*($B35-1)-DEBT!$C$10*(G$32-ASSUMPTIONS!$F$68)*(1-ASSUMPTIONS!$F$84))/PF_IS!$C$49)/ACCR_DIL!$C$6-1 -> -0.13633279
B36: 1.25 | C36: =((ACCR_DIL!$C$31+(SYNERGIES!$C$24*(1-ASSUMPTIONS!$F$84))*($B36-1)-DEBT!$C$10*(C$32-ASSUMPTIONS!$F$68)*(1-ASSUMPTIONS!$F$84))/PF_IS!$C$49)/ACCR_DIL!$C$6-1 -> -0.086590904 | D36: =((ACCR_DIL!$C$31+(SYNERGIES!$C$24*(1-ASSUMPTIONS!$F$84))*($B36-1)-DEBT!$C$10*(D$32-ASSUMPTIONS!$F$68)*(1-ASSUMPTIONS!$F$84))/PF_IS!$C$49)/ACCR_DIL!$C$6-1 -> -0.098280951 | E36: =((ACCR_DIL!$C$31+(SYNERGIES!$C$24*(1-ASSUMPTIONS!$F$84))*($B36-1)-DEBT!$C$10*(E$32-ASSUMPTIONS!$F$68)*(1-ASSUMPTIONS!$F$84))/PF_IS!$C$49)/ACCR_DIL!$C$6-1 -> -0.109971 | F36: =((ACCR_DIL!$C$31+(SYNERGIES!$C$24*(1-ASSUMPTIONS!$F$84))*($B36-1)-DEBT!$C$10*(F$32-ASSUMPTIONS!$F$68)*(1-ASSUMPTIONS!$F$84))/PF_IS!$C$49)/ACCR_DIL!$C$6-1 -> -0.12166105 | G36: =((ACCR_DIL!$C$31+(SYNERGIES!$C$24*(1-ASSUMPTIONS!$F$84))*($B36-1)-DEBT!$C$10*(G$32-ASSUMPTIONS!$F$68)*(1-ASSUMPTIONS!$F$84))/PF_IS!$C$49)/ACCR_DIL!$C$6-1 -> -0.13335109
B37: 1.5 | C37: =((ACCR_DIL!$C$31+(SYNERGIES!$C$24*(1-ASSUMPTIONS!$F$84))*($B37-1)-DEBT!$C$10*(C$32-ASSUMPTIONS!$F$68)*(1-ASSUMPTIONS!$F$84))/PF_IS!$C$49)/ACCR_DIL!$C$6-1 -> -0.083609205 | D37: =((ACCR_DIL!$C$31+(SYNERGIES!$C$24*(1-ASSUMPTIONS!$F$84))*($B37-1)-DEBT!$C$10*(D$32-ASSUMPTIONS!$F$68)*(1-ASSUMPTIONS!$F$84))/PF_IS!$C$49)/ACCR_DIL!$C$6-1 -> -0.095299252 | E37: =((ACCR_DIL!$C$31+(SYNERGIES!$C$24*(1-ASSUMPTIONS!$F$84))*($B37-1)-DEBT!$C$10*(E$32-ASSUMPTIONS!$F$68)*(1-ASSUMPTIONS!$F$84))/PF_IS!$C$49)/ACCR_DIL!$C$6-1 -> -0.1069893 | F37: =((ACCR_DIL!$C$31+(SYNERGIES!$C$24*(1-ASSUMPTIONS!$F$84))*($B37-1)-DEBT!$C$10*(F$32-ASSUMPTIONS!$F$68)*(1-ASSUMPTIONS!$F$84))/PF_IS!$C$49)/ACCR_DIL!$C$6-1 -> -0.11867935 | G37: =((ACCR_DIL!$C$31+(SYNERGIES!$C$24*(1-ASSUMPTIONS!$F$84))*($B37-1)-DEBT!$C$10*(G$32-ASSUMPTIONS!$F$68)*(1-ASSUMPTIONS!$F$84))/PF_IS!$C$49)/ACCR_DIL!$C$6-1 -> -0.13036939
A39: 4 · VALUE DRIVER RANKING - FY2023E EPS impact ($/sh), ranked
A40: Driver | C40: $/sh | D40: Direction
A41: Fox earnings contribution | C41: =ACCR_DIL!G14 -> 1.0659249 | D41: =IF(C41>0.001,"▲ positive",IF(C41<-0.001,"▼ negative","- neutral")) -> ▲ positive
A42: Cost & revenue synergies (net of integration) | C42: =ACCR_DIL!G15+ACCR_DIL!G16 -> 0.84679666 | D42: =IF(C42>0.001,"▲ positive",IF(C42<-0.001,"▼ negative","- neutral")) -> ▲ positive
A43: Debt paydown / deleveraging benefit | C43: =ACCR_DIL!G18 -> 0.48795811 | D43: =IF(C43>0.001,"▲ positive",IF(C43<-0.001,"▼ negative","- neutral")) -> ▲ positive
A44: Financing costs (interest incurred) | C44: =-DEBT!G30*(1-ASSUMPTIONS!F84)/PF_IS!G49 -> 0 | D44: =IF(C44>0.001,"▲ positive",IF(C44<-0.001,"▼ negative","- neutral")) -> - neutral
A45: Share issuance dilution | C45: =ACCR_DIL!G13 -> -1.4095527 | D45: =IF(C45>0.001,"▲ positive",IF(C45<-0.001,"▼ negative","- neutral")) -> ▼ negative
A46: PPA amortization (non-cash) | C46: =ACCR_DIL!G17 -> -1.4932814 | D46: =IF(C46>0.001,"▲ positive",IF(C46<-0.001,"▼ negative","- neutral")) -> ▼ negative
A47: = Net GAAP accretion / (dilution) | C47: =SUM(C41:C46) -> -0.50215454
A48: memo: ranked largest positive → largest negative (Fox > Synergies > Deleveraging > Financing > Shares > PPA)
A50: 5 · KEY SENSITIVITY CONCLUSIONS
A51: Break-even synergy realization (FY2023E cash A/D = 0) | C51: =1+(ACCR_DIL!$G$6*PF_IS!$G$49-ACCR_DIL!$G$31)/(SYNERGIES!$G$24*(1-ASSUMPTIONS!$F$84)) -> -0.27294261
A52: Break-even new-acq rate (FY2019E cash A/D = 0) | C52: =ASSUMPTIONS!$F$68+(ACCR_DIL!$C$31-ACCR_DIL!$C$6*PF_IS!$C$49)/(DEBT!$C$10*(1-ASSUMPTIONS!$F$84)) -> -0.05662296
A53: • Assumptions that matter most: PPA amortization (−$1.49/sh) and share issuance (−$1.41/sh) dominate the FY2023E bridge - both structural (non-cash / fixed by deal terms), not operating levers. Fox earnings (+$1.07), synergies (+$0.85) and deleveraging (+$0.49) are the offsetting positives.
A54: • Break-even synergy is below 0% - FY2023E is cash-accretive even with zero synergies; synergies enhance but are not required for terminal-year cash accretion.
A55: • Break-even new-acq financing rate is below 0% - even free debt would not make FY2019E cash-accretive; early-year dilution is driven by purchase accounting and share count, not financing cost.
A56: • Conditions for cash accretion: achieved by FY2021E under essentially all tested synergy/financing scenarios. The conclusion is robust - it depends on deleveraging and Fox earnings, both of which hold across the sensitivity ranges, rather than on optimistic synergy or financing assumptions.
A58: AUDIT CHECKS (red = must be ~0)
A59: Synergy base (100%) cash EPS ties to ACCR_DIL (FY23E =0) | C59: =C8-ACCR_DIL!G32 -> 0
A60: Financing base-rate cash EPS ties to ACCR_DIL (FY19E =0) | C60: =(ACCR_DIL!$C$31-DEBT!$C$10*(ASSUMPTIONS!$F$68-ASSUMPTIONS!$F$68)*(1-ASSUMPTIONS!$F$84))/PF_IS!$C$49-ACCR_DIL!C32 -> 0
A61: Value-driver sum ties to GAAP A/(D) (FY23E =0) | C61: =C47-(ACCR_DIL!G7-ACCR_DIL!G6) -> 0
A62: FY23E financing-rate range is invariant (=0) | C62: =DEBT!G10 -> 0
A64: SHEET STATUS | B64: =IF(AND(ABS(C59)<0.01,ABS(C60)<0.01,ABS(C61)<0.01,ABS(C62)<1),"OK","CHECK") -> OK

Sheet OUTPUT
A1: THE WALT DISNEY COMPANY / ACQUISITION OF 21st CENTURY FOX
A2: Merger Model - Executive Summary | $ in millions except per share | all figures linked live to model engine
A4: 1 · TRANSACTION OVERVIEW
A5: Disney acquires the entertainment assets of 21st Century Fox (RemainCo) in a $69.5bn cash-and-stock transaction (closed Mar-2019). Consideration was funded ~51% cash / ~49% new Disney equity; the RSNs were divested and proceeds applied to debt. Double-dummy structure under TWDC Holdco.
A6: Total consideration | C6: =ASSUMPTIONS!B7 -> 69456
A7: Total preliminary goodwill | C7: =PPA!B36 -> 47671
A8: Hulu remeasurement gain (one-time) | C8: =PPA!B34 -> 4669
A9: Pro forma 21CF / Disney ownership | B9: Fox → | C9: ='S&U'!B33 -> 0.16998893 | D9: ='S&U'!B34 -> 0.83001107
A10: Model status | C10: =CONTROL!B23 -> MODEL OK
A12: 2 · DEAL TERMS
A13: Cash consideration | B13: % of total → | C13: =ASSUMPTIONS!B5 -> 35703 | D13: =ASSUMPTIONS!B5/ASSUMPTIONS!B7 -> 0.51403766
A14: Stock consideration | B14: % of total → | C14: =ASSUMPTIONS!B6 -> 33753 | D14: =ASSUMPTIONS!B6/ASSUMPTIONS!B7 -> 0.48596234
A15: New Disney shares issued (mm) | C15: =ASSUMPTIONS!B8 -> 307
A16: Exchange ratio | C16: =ASSUMPTIONS!B11 -> 0.3328
A17: Disney close price (3/19/19) | C17: =ASSUMPTIONS!B9 -> 110
A18: Assumed 21CF debt (book / FV) | B18: FV → | C18: =ASSUMPTIONS!B15 -> 19208 | D18: =ASSUMPTIONS!B16 -> 22800
A20: 3 · SOURCES & USES
A21: Sources | E21: Uses
A22: New Disney equity issued | C22: ='S&U'!B5 -> 33753 | E22: Cash to 21CF holders | G22: ='S&U'!B11 -> 35703
A23: New debt incurred | C23: ='S&U'!B6 -> 35703 | E23: Stock to 21CF holders | G23: ='S&U'!B10 -> 33753
A24: Total sources | C24: ='S&U'!B7 -> 69456 | E24: Total uses | G24: ='S&U'!B12 -> 69456
A26: 4 · SYNERGY SUMMARY
C27: FY2019E | D27: FY2020E | E27: FY2021E | F27: FY2022E | G27: FY2023E
A28: Run-rate cost synergies (target) | C28: =ASSUMPTIONS!F61 -> 2000 | D28: =ASSUMPTIONS!F61 -> 2000 | E28: =ASSUMPTIONS!F61 -> 2000 | F28: =ASSUMPTIONS!F61 -> 2000 | G28: =ASSUMPTIONS!F61 -> 2000
A29: Cost synergies realized | C29: =SYNERGIES!C15 -> 200 | D29: =SYNERGIES!D15 -> 1000 | E29: =SYNERGIES!E15 -> 1800 | F29: =SYNERGIES!F15 -> 2000 | G29: =SYNERGIES!G15 -> 2000
A30: Realization % of run-rate | C30: =SYNERGIES!C15/ASSUMPTIONS!F61 -> 0.1 | D30: =SYNERGIES!D15/ASSUMPTIONS!F61 -> 0.5 | E30: =SYNERGIES!E15/ASSUMPTIONS!F61 -> 0.9 | F30: =SYNERGIES!F15/ASSUMPTIONS!F61 -> 1 | G30: =SYNERGIES!G15/ASSUMPTIONS!F61 -> 1
A31: Costs to achieve (incurred) | C31: =SYNERGIES!C21 -> 560 | D31: =SYNERGIES!D21 -> 560 | E31: =SYNERGIES!E21 -> 280 | F31: =SYNERGIES!F21 -> 0 | G31: =SYNERGIES!G21 -> 0
A32: After-tax synergy impact | C32: =SYNERGIES!C28 -> -273.6 | D32: =SYNERGIES!D28 -> 334.4 | E32: =SYNERGIES!E28 -> 1155.2 | F32: =SYNERGIES!F28 -> 1520 | G32: =SYNERGIES!G28 -> 1520
A34: 5 · DEBT & DELEVERAGING SUMMARY
A35: Total debt at close | C35: =DEBT!B8 -> 38811
C36: FY2019E | D36: FY2020E | E36: FY2021E | F36: FY2022E | G36: FY2023E
A37: Total debt - ending | C37: =DEBT!C24 -> 19396.485 | D37: =DEBT!D24 -> 12164.074 | E37: =DEBT!E24 -> 4112.4839 | F37: =DEBT!F24 -> 0 | G37: =DEBT!G24 -> 0
A38: % of total debt repaid | C38: =1-DEBT!C24/DEBT!B8 -> 0.50023227 | D38: =1-DEBT!D24/DEBT!B8 -> 0.6865818 | E38: =1-DEBT!E24/DEBT!B8 -> 0.89403819 | F38: =1-DEBT!F24/DEBT!B8 -> 1 | G38: =1-DEBT!G24/DEBT!B8 -> 1
A39: Total interest expense | C39: =DEBT!C30 -> 1594.379 | D39: =DEBT!D30 -> 953.70002 | E39: =DEBT!E30 -> 524.84443 | F39: =DEBT!F30 -> 41.749036 | G39: =DEBT!G30 -> 0
A40: Total debt / EBITDA | C40: =DEBT!C42 -> 0.84756593 | D40: =DEBT!D42 -> 0.49593943 | E40: =DEBT!E42 -> 0.15690167 | F40: =DEBT!F42 -> 0 | G40: =DEBT!G42 -> 0
A41: Net debt / EBITDA | C41: =DEBT!C44 -> 0.67277841 | D41: =DEBT!D44 -> 0.3328561 | E41: =DEBT!E44 -> 0.0042915467 | F41: =DEBT!F44 -> -0.14632384 | G41: =DEBT!G44 -> -0.14130512
A43: 6 · ACCRETION / (DILUTION) SUMMARY - GAAP
C44: FY2019E | D44: FY2020E | E44: FY2021E | F44: FY2022E | G44: FY2023E
A45: Disney standalone EPS | C45: =ACCR_DIL!C6 -> 7.099952 | D45: =ACCR_DIL!D6 -> 7.3649556 | E45: =ACCR_DIL!E6 -> 7.6431216 | F45: =ACCR_DIL!F6 -> 7.9350867 | G45: =ACCR_DIL!G6 -> 8.2415217
A46: Pro forma EPS | C46: =ACCR_DIL!C7 -> 4.5303963 | D46: =ACCR_DIL!D7 -> 5.4813704 | E46: =ACCR_DIL!E7 -> 6.4747595 | F46: =ACCR_DIL!F7 -> 7.2512727 | G46: =ACCR_DIL!G7 -> 7.7393672
A47: Accretion / (dilution) - $ | C47: =ACCR_DIL!C8 -> -2.5695557 | D47: =ACCR_DIL!D8 -> -1.8835852 | E47: =ACCR_DIL!E8 -> -1.1683621 | F47: =ACCR_DIL!F8 -> -0.68381398 | G47: =ACCR_DIL!G8 -> -0.50215454
A48: Accretion / (dilution) - % | C48: =ACCR_DIL!C9 -> -0.36191171 | D48: =ACCR_DIL!D9 -> -0.2557497 | E48: =ACCR_DIL!E9 -> -0.15286452 | F48: =ACCR_DIL!F9 -> -0.086175994 | G48: =ACCR_DIL!G9 -> -0.060929833
A50: 7 · CASH EPS SUMMARY (excl. non-cash PPA amortization)
C51: FY2019E | D51: FY2020E | E51: FY2021E | F51: FY2022E | G51: FY2023E
A52: Cash pro forma EPS | C52: =ACCR_DIL!C32 -> 6.3560924 | D52: =ACCR_DIL!D32 -> 7.245662 | E52: =ACCR_DIL!E32 -> 8.1776466 | F52: =ACCR_DIL!F32 -> 8.8927553 | G52: =ACCR_DIL!G32 -> 9.3194453
A53: Cash accretion / (dilution) - $ | C53: =ACCR_DIL!C33 -> -0.74385958 | D53: =ACCR_DIL!D33 -> -0.11929357 | E53: =ACCR_DIL!E33 -> 0.53452501 | F53: =ACCR_DIL!F33 -> 0.95766862 | G53: =ACCR_DIL!G33 -> 1.0779235
A54: Cash accretion / (dilution) - % | C54: =ACCR_DIL!C34 -> -0.10476966 | D54: =ACCR_DIL!D34 -> -0.016197459 | E54: =ACCR_DIL!E34 -> 0.069935431 | F54: =ACCR_DIL!F34 -> 0.12068786 | G54: =ACCR_DIL!G34 -> 0.13079181
A55: GAAP EPS crossover (accretive from) | C55: =IF(ACCR_DIL!C9>0,"FY2019E",IF(ACCR_DIL!D9>0,"FY2020E",IF(ACCR_DIL!E9>0,"FY2021E",IF(ACCR_DIL!F9>0,"FY2022E",IF(ACCR_DIL!G9>0,"FY2023E","beyond FY2023E"))))) -> beyond FY2023E
A56: Cash EPS crossover (accretive from) | C56: =IF(ACCR_DIL!C34>0,"FY2019E",IF(ACCR_DIL!D34>0,"FY2020E",IF(ACCR_DIL!E34>0,"FY2021E",IF(ACCR_DIL!F34>0,"FY2022E",IF(ACCR_DIL!G34>0,"FY2023E","beyond"))))) -> FY2021E
A58: 8 · VALUE CREATION SUMMARY (cumulative; FY2023E = 5-yr total)
C59: FY2019E | D59: FY2020E | E59: FY2021E | F59: FY2022E | G59: FY2023E
A60: Cumulative net synergies, after-tax | C60: =ACCR_DIL!C37 -> -273.6 | D60: =ACCR_DIL!D37 -> 60.8 | E60: =ACCR_DIL!E37 -> 1216 | F60: =ACCR_DIL!F37 -> 2736 | G60: =ACCR_DIL!G37 -> 4256
A61: Cumulative PPA amortization (non-cash) | C61: =ACCR_DIL!C38 -> -3121.3246 | D61: =ACCR_DIL!D38 -> -6132.4281 | E61: =ACCR_DIL!E38 -> -9033.3105 | F61: =ACCR_DIL!F38 -> -11823.972 | G61: =ACCR_DIL!G38 -> -14504.412
A62: Cumulative GAAP A/(D) per share | C62: =ACCR_DIL!C40 -> -2.5695557 | D62: =ACCR_DIL!D40 -> -4.453141 | E62: =ACCR_DIL!E40 -> -5.6215031 | F62: =ACCR_DIL!F40 -> -6.305317 | G62: =ACCR_DIL!G40 -> -6.8074716
A63: Cumulative cash A/(D) per share | C63: =ACCR_DIL!C41 -> -0.74385958 | D63: =ACCR_DIL!D41 -> -0.86315315 | E63: =ACCR_DIL!E41 -> -0.32862815 | F63: =ACCR_DIL!F41 -> 0.62904048 | G63: =ACCR_DIL!G41 -> 1.706964
A65: 9 · KEY CONCLUSIONS
A66: • GAAP-dilutive throughout the explicit forecast (−36% in FY2019E narrowing to −6% by FY2023E). Two structural, largely non-economic drivers explain nearly all of it: ~$1.2–1.4/sh from the 307mm new shares issued to fund the stock consideration, and ~$1.5–1.7/sh of non-cash purchase-accounting (PPA) amortization on the stepped-up intangibles and film assets.
A67: • Cash-accretive from FY2021E. Stripping out the non-cash PPA amortization, the transaction crosses into accretion in year three (+7%) and reaches +13% by FY2023E - the true cash economics are favorable well before GAAP EPS recovers.
A68: • Primary value drivers: (i) Fox earnings contribution (+$0.8–1.1/sh); (ii) cost synergies ramping to the $2.0bn run-rate by FY2022E; and (iii) rapid deleveraging - RSN divestiture proceeds plus cash sweep retire all acquisition and assumed debt by FY2022E, turning financing from a drag into an EPS tailwind.
A69: • Bottom line: a classic large, intangible-heavy stock-and-cash acquisition - optically GAAP-dilutive due to share issuance and purchase accounting, but cash-accretive within three years and deleveraging to net cash, with synergy realization and debt paydown as the core value-creation levers.
A71: AUDIT CHECKS (red = must be ~0)
A72: Consideration ties to S&U (=0) | C72: =C6-'S&U'!B7 -> 0
A73: GAAP A/(D) $ ties to ACCR_DIL (FY19E =0) | C73: =C47-(ACCR_DIL!C7-ACCR_DIL!C6) -> 0
A74: Debt at close ties to S&U + assumed (=0) | C74: =C35-('S&U'!B18+ASSUMPTIONS!B15) -> 0
A75: Goodwill ties (RemainCo + Hulu, =0) | C75: =PPA!B36-(PPA!B22+PPA!B33) -> 0
A76: Cash EPS crossover detected (text non-blank) | C76: =IF(C56="beyond",1,0) -> 0
A78: SHEET STATUS | B78: =IF(AND(ABS(C72)<1,ABS(C73)<0.01,ABS(C74)<1,ABS(C75)<1,C76=0),"OK","CHECK") -> OK
A81: EXECUTIVE CONCLUSION
A82: Transaction - Disney acquires the entertainment assets of 21st Century Fox for $69.5bn (~51% cash / ~49% new equity); closed Mar-2019. Goodwill $47.7bn; pro forma ownership ~83% Disney / ~17% Fox.
A83: Why GAAP-dilutive - EPS-dilutive across the forecast (−36% FY2019E → −6% FY2023E). The dilution is structural, not operational: the 307mm shares issued to fund the equity consideration (~−$1.4/sh) and non-cash purchase-accounting amortization (~−$1.5/sh) together explain essentially all of it.
A84: Why cash-accretive - Stripping the non-cash PPA amortization, cash EPS turns accretive in FY2021E and reaches +13% by FY2023E - the underlying cash economics are favorable well before GAAP EPS recovers.
A85: Crossover timing - GAAP: remains dilutive through FY2023E (crossover beyond the explicit window). Cash: crosses to accretion in FY2021E.
A86: Key value drivers - Fox earnings (+$1.1/sh), cost synergies ramping to a $2.0bn run-rate (+$0.8/sh), and rapid deleveraging - RSN proceeds plus cash sweep retire all acquisition and assumed debt by FY2022E (+$0.5/sh).
A87: Investment conclusion - Strategically compelling and scale-defining. The headline GAAP dilution masks favorable cash economics and a strong deleveraging profile; sensitivity testing confirms FY2023E cash accretion holds even at zero synergies and across a 2–6% financing-rate range. Accretive on the metric that matters within three years.
A89: CHART DATA (linked to model - feeds charts; do not edit)
A90: Year | C90: FY2019E | D90: FY2020E | E90: FY2021E | F90: FY2022E | G90: FY2023E
A91: GAAP A/(D) % | C91: =ACCR_DIL!C9 -> -0.36191171 | D91: =ACCR_DIL!D9 -> -0.2557497 | E91: =ACCR_DIL!E9 -> -0.15286452 | F91: =ACCR_DIL!F9 -> -0.086175994 | G91: =ACCR_DIL!G9 -> -0.060929833
A92: Cash A/(D) % | C92: =ACCR_DIL!C34 -> -0.10476966 | D92: =ACCR_DIL!D34 -> -0.016197459 | E92: =ACCR_DIL!E34 -> 0.069935431 | F92: =ACCR_DIL!F34 -> 0.12068786 | G92: =ACCR_DIL!G34 -> 0.13079181
A93: Synergy realization % | C93: =SYNERGIES!C15/ASSUMPTIONS!$F$61 -> 0.1 | D93: =SYNERGIES!D15/ASSUMPTIONS!$F$61 -> 0.5 | E93: =SYNERGIES!E15/ASSUMPTIONS!$F$61 -> 0.9 | F93: =SYNERGIES!F15/ASSUMPTIONS!$F$61 -> 1 | G93: =SYNERGIES!G15/ASSUMPTIONS!$F$61 -> 1
A95: Debt point | B95: At close | C95: FY2019E | D95: FY2020E | E95: FY2021E | F95: FY2022E | G95: FY2023E
A96: Total debt | B96: =DEBT!B8 -> 38811 | C96: =DEBT!C24 -> 19396.485 | D96: =DEBT!D24 -> 12164.074 | E96: =DEBT!E24 -> 4112.4839 | F96: =DEBT!F24 -> 0 | G96: =DEBT!G24 -> 0
A98: EPS waterfall (FY2023E) | C98: Base | D98: Decrease | E98: Increase | F98: Total | H98: Running
A99: Disney Standalone EPS | C99: 0 | D99: 0 | E99: 0 | F99: =ACCR_DIL!G12 -> 8.2415217 | H99: =ACCR_DIL!G12 -> 8.2415217
A100: (−) Share issuance dilution | C100: =MIN(H99,H100) -> 6.831969 | D100: =MAX(-ACCR_DIL!G13,0) -> 1.4095527 | E100: =MAX(ACCR_DIL!G13,0) -> 0 | F100: 0 | H100: =H99+ACCR_DIL!G13 -> 6.831969
A101: (+) Fox earnings contribution | C101: =MIN(H100,H101) -> 6.831969 | D101: =MAX(-ACCR_DIL!G14,0) -> 0 | E101: =MAX(ACCR_DIL!G14,0) -> 1.0659249 | F101: 0 | H101: =H100+ACCR_DIL!G14 -> 7.8978939
A102: (+) Synergies | C102: =MIN(H101,H102) -> 7.8978939 | D102: =MAX(-ACCR_DIL!G15,0) -> 0 | E102: =MAX(ACCR_DIL!G15,0) -> 0.84679666 | F102: 0 | H102: =H101+ACCR_DIL!G15 -> 8.7446905
A103: (−) Integration costs | C103: =MIN(H102,H103) -> 8.7446905 | D103: =MAX(-ACCR_DIL!G16,0) -> 0 | E103: =MAX(ACCR_DIL!G16,0) -> 0 | F103: 0 | H103: =H102+ACCR_DIL!G16 -> 8.7446905
A104: (−) PPA amortization | C104: =MIN(H103,H104) -> 7.2514091 | D104: =MAX(-ACCR_DIL!G17,0) -> 1.4932814 | E104: =MAX(ACCR_DIL!G17,0) -> 0 | F104: 0 | H104: =H103+ACCR_DIL!G17 -> 7.2514091
A105: (+/−) Financing costs | C105: =MIN(H104,H105) -> 7.2514091 | D105: =MAX(-ACCR_DIL!G18,0) -> 0 | E105: =MAX(ACCR_DIL!G18,0) -> 0.48795811 | F105: 0 | H105: =H104+ACCR_DIL!G18 -> 7.7393672
A106: Pro Forma EPS | C106: 0 | D106: 0 | E106: 0 | F106: =ACCR_DIL!G19 -> 7.7393672 | H106: =H105 -> 7.7393672
