Workbook

Sheet Cover
B2: PROLOGIS, INC. (NYSE: PLD)
B3: Equity Valuation - DCF, NAV & Trading Comparables
B4: Independent analysis - public data only - not investment advice
B7: Prepared by: | C7: Muhammed Sheikh
B8: Date: | C8: 46175
B9: Model version: | C9: v0.1 - skeleton
B10: Valuation basis: | C10: Prologis share unless labeled O&M
B11: Reporting currency: | C11: USD ($ in thousands unless noted)
B13: MODEL STATUS
B14: Master audit flag: | C14: =IF(COUNTIF(Audit!E:E,"ERROR")=0,"MODEL OK","ERRORS PRESENT — see Audit tab") -> MODEL OK
B16: VERSION LOG
B17: Date | C17: Change / session notes

Sheet ReadMe
A1: READ ME - CONVENTIONS & SOURCE INDEX
A3: COLOR CONVENTIONS
A4: Blue font | B4: Hardcoded input typed from a source document. Lives ONLY on Data_Collection.
A5: Black font | B5: Formula calculated within the same tab.
A6: Green font | B6: Link pulling from another tab in this workbook.
A7: Red font | B7: Flag / error / external link (avoid external links entirely).
A8: Peach fill | B8: Pre-filled by assistant from Q1'26 release — VERIFY against filing & replace placeholder periods.
A10: CHECK ROWS | B10: Live IF formulas returning OK/ERROR; ERROR conditionally formatted red. Master flag on Cover.
A11: UNITS | B11: $ in millions unless a row says otherwise. Basis = Prologis share unless labeled O&M.
A12: "n/d" | B12: Not disclosed in filings. Never replace with an estimate.
A14: SOURCE DOCUMENT INDEX (fill file names + dates as you download)
A15: [10-K] | B15: PLD Form 10-K FY2025 — SEC EDGAR CIK 1045609
A16: [10-K24/23] | B16: PLD Form 10-K FY2024 / FY2023
A17: [10-Q] | B17: PLD Form 10-Q Q1 2026
A18: [SUPP] | B18: PLD Supplemental Information Q1 2026 — ir.prologis.com
A19: [ER] | B19: PLD Q1 2026 Earnings Release — 8-K Ex.99.2, filed 2026-04-16
A21: BUILD ORDER | B21: Data_Collection → Historicals → FFO_Recon (must tie) → Drivers/Development/Strategic_Capital/Capital_Deployment/Debt/Share_Count → Audit. Then Assumptions → Model → Scenarios → DCF → NAV → Comps → Summary.

Sheet Data_Collection
A1: PROLOGIS - DATA COLLECTION
A2: ($ in thousands unless noted) | B2: FY2023 | C2: FY2024 | D2: FY2025 | E2: Q1 2026 | F2: Source | G2: Section | H2: Page
A3: GROUP 1: INCOME STATEMENT
A4: Rental revenue | B4: 6818542 | C4: 7514705 | D4: 8158904 | E4: 2125084 | F4: Source: PLD Q4 2025 10-K p.55 (FY23/FY24/FY25); Q1 2026 10Q p.55 (Q1 26).
A5: Strategic capital revenue | B5: 1200232 | C5: 671907 | D5: 592353 | E5: 160812
A6: Development management & other revenue | B6: 4695 | C6: 14998 | D6: 38870 | E6: 11827
A7: Rental expenses | B7: 1624793 | C7: 1765385 | D7: 1964137 | E7: 520283
A8: Strategic capital expenses | B8: 385542 | C8: 291856 | D8: 270517 | E8: 81889
A9: General & administrative | B9: 390406 | C9: 418765 | D9: 469114 | E9: 126890
A10: Depreciation & amortization | B10: 2484891 | C10: 2580519 | D10: 2626028 | E10: 731506
A11: Other expenses | B11: 53354 | C11: 47044 | D11: 46029 | E11: 10123
A12: Gains on dispositions of real estate, net | B12: =462270+161039 -> 623309 | C12: =904136+413743 -> 1317879 | D12: =257731+685831 -> 943562 | E12: 384023
A13: Earnings from unconsolidated entities, net | B13: 307227 | C13: 353623 | D13: 402531 | E13: 93296
A14: Interest expense | B14: -641332 | C14: -863932 | D14: -1002344 | E14: -254286
A15: Interest and other income, net | B15: -243609 | C15: -301042 | D15: -588548 | E15: -118269
A16: Foreign currency & derivative gains (losses), net | B16: 87221 | C16: 208731 | D16: 14763 | E16: 44611
A17: Gains (losses) on early extinguishment of debt, net | B17: 3275 | C17: 536 | D17: -3498 | E17: -1890
A18: Income tax expense | B18: 211038 | C18: 166943 | D18: 204017 | E18: 47971
A19: Net earnings attributable to NCI | B19: 193931 | C19: 216300 | D19: 237068 | E19: 39978
A20: Preferred dividends | B20: 5841 | C20: 5881 | D20: 5882 | E20: 1500
A21: Net earnings attributable to common | B21: 3053373 | C21: 3725754 | D21: 3322349 | E21: 1003337
A22: Weighted Avg Shares – Basic | B22: 924351 | C22: 926172 | D22: 928473 | E22: 952981
A23: Weighted Avg Shares – Diluted | B23: 951791 | C23: 953590 | D23: 956832 | E23: 957561
A25: GROUP 2: BALANCE SHEET
A26: Investments in real estate properties (gross) | B26: 88666575 | C26: 91246176 | D26: 95129356 | E26: 95241445 | F26: Source: PLD Q4 2025 10-K p.55 (FY23/FY24/FY25); Q1 2026 10Q p.55 (Q1 26).
A27: Accumulated depreciation | B27: 10931485 | C27: 12758159 | D27: 14729149 | E27: 15298353
A28: Investments in/advances to unconsolidated entities | B28: 9543970 | C28: 10079448 | D28: 11093936 | E28: 11241723
A29: Assets held for sale or contribution | B29: 461657 | C29: 248511 | D29: 203344 | E29: 499799
A30: Cash and cash equivalents | B30: 530388 | C30: 1318591 | D30: 1145647 | E30: 861144
A31: Other assets | B31: 4749735 | C31: 5194342 | D31: 5881122 | E31: 5587693
A32: Total assets (reported) | B32: 93020840 | C32: 95328099 | D32: 98724256 | E32: 98133451
A33: Debt (carrying value per BS) | B33: 29000501 | C33: 30879263 | D33: 35037073 | E33: 34669592
A34: Accounts payable & accrued expenses | B34: 1766018 | C34: 1769327 | D34: 1963645 | E34: 1681047
A35: Other liabilities | B35: 4430601 | C35: 4063549 | D35: 3969530 | E35: 3834320
A36: Total liabilities (reported) | B36: 35197120 | C36: 36712139 | D36: 40970248 | E36: 40184959
A37: Preferred stock | B37: 63948 | C37: 63948 | D37: 63948 | E37: 63948
A38: Total stockholders' equity (reported) | B38: 53181724 | C38: 53951138 | D38: 53193178 | E38: 53503401
... A40: Total equity (reported) | B40: 57823720 | C40: 58616770 | D40: 57754008 | E40: 57948492
A42: GROUP 3: CASH FLOW
A43: Consolidated net earnings | B43: 3253145 | C43: 3947935 | D43: 3565299 | E43: 1044815 | F43: Source: PLD Q4 2025 10-K p.55 (FY23/FY24/FY25); Q1 2026 10Q p.55 (Q1 26).
A44: Depreciation & amortization (CF) | B44: 2484891 | C44: 2580519 | D44: 2626028 | E44: 731506
A45: Straight-line rent & lease intangible amortization | B45: -613005 | C45: -644606 | D45: -691090 | E45: -165749
A46: Equity-based compensation | B46: 267648 | C46: 231747 | D46: 185466 | E46: 60632
A47: Other operating adjustments (net) | B47: 398440 | C47: 796614 | D47: 131730 | E47: 253373
A48: Cash provided by operating activities | B48: 5373058 | C48: 4912209 | D48: 5008434 | E48: 1288136
A49: Real estate development & capital expenditures | B49: -4092956 | C49: -4092639 | D49: -3678815 | E49: -914336
A50: Real estate acquisitions (investing) | B50: -4195714 | C50: -2327605 | D50: -1800527 | E50: -223053
A51: Proceeds from dispositions & contributions | B51: 1764322 | C51: 3790388 | D51: 2246186 | E51: 624036
A52: Other investing (net) | B52: 104951 | C52: -469201 | D52: -397291 | E52: 112868
A53: Debt issued | B53: 5755096 | C53: 4505830 | D53: 3460904 | E53: 161620
A54: Debt repaid | B54: -272203 | C54: -919481 | D54: -701861 | E54: -686276
A55: Common dividends & unit distributions paid | B55: -3228589 | C55: -3570480 | D55: -3764745 | E55: -1026181
... A60: Net change in cash | B60: 251905 | C60: 788203 | D60: -172944 | E60: -284503
A62: GROUP 4: FFO METRICS
A63: Nareit FFO ($) | B63: 5746152 | C63: 5794599 | D63: 5679525 | E63: 1735404 | F63: Source: PLD Q4 2025 Supp p.8 (FY24/FY25); Q1 2026 Supp p.8 (Q1 26); Q4 2023 Supp p.8 (FY23)
A64: Nareit FFO per diluted share/unit | B64: =B63/B23 -> 6.0371993 | C64: =C63/C23 -> 6.0766147 | D64: =D63/D23 -> 5.9357599 | E64: =E63/E23 -> 1.8123169
A65: Core FFO ($) | B65: 5334250 | C65: 5304939 | D65: 5561300 | E65: 1440493
A66: Core FFO per diluted share/unit | B66: =B65/B23 -> 5.6044342 | C66: =C65/C23 -> 5.5631236 | D66: =D65/D23 -> 5.8122011 | E66: =E65/E23 -> 1.5043355
A67: Core FFO ex-promotes per share | E67: 1.52
A68: Net promote income (expense)
A69: PLD Core FFO adjustment - [label 1 verbatim] | B69: 17619 | C69: -68095 | D69: 125247 | E69: -14269
A70: PLD Core FFO adjustment - [label 2 verbatim] | B70: 17708 | C70: 21161 | D70: 4309 | E70: 190
A71: PLD Core FFO adjustment - [label 3 verbatim] | B71: -3275 | C71: -536 | D71: 3498 | E71: 1890
A73: GROUP 5: AFFO METRICS
A74: AFFO ($) | B74: 4710630 | C74: 4421566 | D74: 4335044 | E74: 1471893 | F74: Source: PLD Q4 2025 Supp p.8 (FY24/FY25); Q1 2026 Supp p.8 (Q1 26); Q4 2023 Supp p.8 (FY23)
A75: Recurring/maintenance capex | B75: -303042 | C75: -386481 | D75: -327355 | E75: -26065
A76: Tenant Improvements & Leasing Commissions | B76: -388814 | C76: -499927 | D76: -562197 | E76: -123816
A77: Straight-line rent adjustment (AFFO basis) | B77: -625356 | C77: -644606 | D77: -691090 | E77: -165749
A78: AFFO Per Diluted Share/Unit | B78: =B74/B23 -> 4.9492273 | C78: =C74/C23 -> 4.6367579 | D78: =D74/D23 -> 4.5306219 | E78: =E74/E23 -> 1.5371271
A79: Dividends declared per share
A81: GROUP 6: SAME-STORE (label basis per row)
A82: SS NOI growth - cash % (PLD share) | B82: 0.085 | C82: 0.045 | D82: 0.063 | E82: 0.066 | F82: Source: PLD Q4 2025 Supp p.12 (FY24/FY25); Q1 2026 Supp p.12 (Q1 26); Q4 2023 Supp p.12(FY23)
A83: SS NOI growth - net effective % (PLD share) | B83: 0.075 | C83: 0.04 | D83: 0.048 | E83: 0.051
A84: SS pool size (M sq ft) | B84: 738498 | C84: 764587 | D84: 773176 | E84: 777055
A85: SS average occupancy % | B85: 0.977 | C85: 0.958 | D85: 0.956 | E85: 0.953
A87: GROUP 7: OCCUPANCY
A88: Average occupancy % - PLD share | B88: 0.977 | C88: 0.958 | D88: 0.956 | E88: 0.953 | F88: Source: PLD Q4 2025 Supp p.12 (FY24/FY25); Q1 2026 Supp p.12 (Q1 26); Q4 2023 Supp p.12(FY23)
A89: Average occupancy % - O&M | B89: 0.976 | C89: 0.959 | D89: 0.958 | E89: 0.953
A90: Period-end occupancy % (O&M) | B90: 0.976 | C90: 0.959 | D90: 0.958 | E90: 0.953
A91: Leased % (if disclosed) | B91: 0.978 | C91: 0.96 | D91: 0.962 | E91: 0.958
A93: GROUP 8: LEASE ROLLOVER
A94: Net effective rent change % | B94: 0.741 | C94: 0.663 | D94: 0.438 | E94: 0.319 | F94: Source: PLD Q4 2025 Supp p.10, 11, 16 (FY24/FY25); Q1 2026 Supp p.10, 11, 16 (Q1 26); Q4 2023 Supp p.10, 11, 16 (FY23)
A95: Cash rent change % | B95: 0.518 | C95: 0.401 | D95: 0.273 | E95: 0.168
A96: Retention % | B96: 0.768 | C96: 0.784 | D96: 0.777 | E96: 0.758
A97: Leases commenced/signed (M sq ft) | B97: 43.65 | C97: 46.491 | D97: 43.764 | E97: 66.722
A98: Weighted avg remaining lease term (yrs) | B98: 4.2 | C98: 4.2 | D98: 4.2 | E98: 4.2
A99: Lease expirations - % of NOI expiring Y1 | B99: 0.091 | C99: 0.091 | D99: 0.103 | E99: 0.069
A100: Lease expirations - % expiring Y2 | B100: 0.12 | C100: 0.135 | D100: 0.148 | E100: 0.147
A101: Lease expirations - % expiring Y3 | B101: 0.139 | C101: 0.151 | D101: 0.146 | E101: 0.147
A102: Lease expirations - % expiring Y4 | B102: 0.148 | C102: 0.143 | D102: 0.136 | E102: 0.14
A103: Lease expirations - % expiring Y5 | B103: 0.146 | C103: 0.134 | D103: 0.133 | E103: 0.133
A105: GROUP 9: MARK-TO-MARKET
A106: Lease MTM % (net effective) | B106: 0.764 | C106: 0.687 | D106: 0.501 | E106: 0.435 | F106: Source: PLD Q4 2025 Supp p.10, 11, 16 (FY24/FY25); Q1 2026 Supp p.10, 11, 16 (Q1 26); Q4 2023 Supp p.10, 11, 16 (FY23)
A107: MTM embedded NOI $ (when quantified) | B107: N/D | C107: N/D | D107: N/D | E107: N/D
A109: GROUP 10: DEVELOPMENT
A110: Dev starts - TEI ($) | B110: 3397 | C110: 1339 | D110: 2956 | E110: 1783 | F110: Source: PLD Q4 2025 Supp p.17, 18, 19 (FY24/FY25); Q1 2026 Supp p.17, 18, 19 (Q1 26); Q4 2023 Supp p.17, 18, 19(FY23)
A111: Dev starts - est. yield % | B111: 0.07 | C111: 0.073 | D111: 0.063 | E111: 0.088
A112: Dev starts - est. margin % | B112: 0.274 | C112: 0.269 | D112: 0.193 | E112: 0.32
A113: Dev starts - est. value creation ($) | B113: 931 | C113: 366 | D113: 569 | E113: 571
A114: Dev starts - % build-to-suit | B114: 0.53 | C114: 0.334 | D114: 0.611 | E114: 0.812
...

Sheet Historicals
A1: HISTORICALS - IS / BS / CF
A2: All cells link (green) to Data_Collection or calculate (black). Zero hardcodes.
A4: ($ in millions unless noted) | B4: FY2023 | C4: FY2024 | D4: FY2025 | E4: Q1 2026
A5: INCOME STATEMENT
A6: Rental revenue | B6: =Data_Collection!B4 -> 6818542 | C6: =Data_Collection!C4 -> 7514705 | D6: =Data_Collection!D4 -> 8158904 | E6: =Data_Collection!E4 -> 2125084
A7: Strategic capital revenue | B7: =Data_Collection!B5 -> 1200232 | C7: =Data_Collection!C5 -> 671907 | D7: =Data_Collection!D5 -> 592353 | E7: =Data_Collection!E5 -> 160812
A8: Development management & other revenue | B8: =Data_Collection!B6 -> 4695 | C8: =Data_Collection!C6 -> 14998 | D8: =Data_Collection!D6 -> 38870 | E8: =Data_Collection!E6 -> 11827
A9: Total revenues | B9: =SUM(B6:B8) -> 8023469 | C9: =SUM(C6:C8) -> 8201610 | D9: =SUM(D6:D8) -> 8790127 | E9: =SUM(E6:E8) -> 2297723
A10: Rental expenses | B10: =-Data_Collection!B7 -> -1624793 | C10: =-Data_Collection!C7 -> -1765385 | D10: =-Data_Collection!D7 -> -1964137 | E10: =-Data_Collection!E7 -> -520283
A11: Strategic capital expenses | B11: =-Data_Collection!B8 -> -385542 | C11: =-Data_Collection!C8 -> -291856 | D11: =-Data_Collection!D8 -> -270517 | E11: =-Data_Collection!E8 -> -81889
A12: General & administrative | B12: =-Data_Collection!B9 -> -390406 | C12: =-Data_Collection!C9 -> -418765 | D12: =-Data_Collection!D9 -> -469114 | E12: =-Data_Collection!E9 -> -126890
A13: Depreciation & amortization | B13: =-Data_Collection!B10 -> -2484891 | C13: =-Data_Collection!C10 -> -2580519 | D13: =-Data_Collection!D10 -> -2626028 | E13: =-Data_Collection!E10 -> -731506
A14: Other expenses | B14: =-Data_Collection!B11 -> -53354 | C14: =-Data_Collection!C11 -> -47044 | D14: =-Data_Collection!D11 -> -46029 | E14: =-Data_Collection!E11 -> -10123
A15: Total expenses | B15: =SUM(B10:B14) -> -4938986 | C15: =SUM(C10:C14) -> -5103569 | D15: =SUM(D10:D14) -> -5375825 | E15: =SUM(E10:E14) -> -1470691
A16: Operating income before gains | B16: =B9+B15 -> 3084483 | C16: =C9+C15 -> 3098041 | D16: =D9+D15 -> 3414302 | E16: =E9+E15 -> 827032
A17: Gains on dispositions of real estate, net | B17: =Data_Collection!B12 -> 623309 | C17: =Data_Collection!C12 -> 1317879 | D17: =Data_Collection!D12 -> 943562 | E17: =Data_Collection!E12 -> 384023
A18: Operating income | B18: =B16+B17 -> 3707792 | C18: =C16+C17 -> 4415920 | D18: =D16+D17 -> 4357864 | E18: =E16+E17 -> 1211055
A19: Earnings from unconsolidated entities, net | B19: =Data_Collection!B13 -> 307227 | C19: =Data_Collection!C13 -> 353623 | D19: =Data_Collection!D13 -> 402531 | E19: =Data_Collection!E13 -> 93296
A20: Interest expense | B20: =Data_Collection!B14 -> -641332 | C20: =Data_Collection!C14 -> -863932 | D20: =Data_Collection!D14 -> -1002344 | E20: =Data_Collection!E14 -> -254286
A21: Interest and other income, net | B21: =Data_Collection!B15 -> -243609 | C21: =Data_Collection!C15 -> -301042 | D21: =Data_Collection!D15 -> -588548 | E21: =Data_Collection!E15 -> -118269
A22: Foreign currency & derivative gains (losses), net | B22: =Data_Collection!B16 -> 87221 | C22: =Data_Collection!C16 -> 208731 | D22: =Data_Collection!D16 -> 14763 | E22: =Data_Collection!E16 -> 44611
A23: Gains (losses) on early extinguishment of debt, net | B23: =Data_Collection!B17 -> 3275 | C23: =Data_Collection!C17 -> 536 | D23: =Data_Collection!D17 -> -3498 | E23: =Data_Collection!E17 -> -1890
A24: Pre-tax earnings | B24: =B18+SUM(B19:B20)+SUM(B22:B23) -> 3464183 | C24: =C18+SUM(C19:C20)+SUM(C22:C23) -> 4114878 | D24: =D18+SUM(D19:D20)+SUM(D22:D23) -> 3769316 | E24: =E18+SUM(E19:E20)+SUM(E22:E23) -> 1092786
A25: Income tax expense | B25: =-Data_Collection!B18 -> -211038 | C25: =-Data_Collection!C18 -> -166943 | D25: =-Data_Collection!D18 -> -204017 | E25: =-Data_Collection!E18 -> -47971
A26: Consolidated net earnings | B26: =B24+B25 -> 3253145 | C26: =C24+C25 -> 3947935 | D26: =D24+D25 -> 3565299 | E26: =E24+E25 -> 1044815
A27: Less: net earnings attributable to NCI | B27: =-Data_Collection!B19 -> -193931 | C27: =-Data_Collection!C19 -> -216300 | D27: =-Data_Collection!D19 -> -237068 | E27: =-Data_Collection!E19 -> -39978
A28: Less: preferred dividends | B28: =-Data_Collection!B20 -> -5841 | C28: =-Data_Collection!C20 -> -5881 | D28: =-Data_Collection!D20 -> -5882 | E28: =-Data_Collection!E20 -> -1500
A29: Net earnings attributable to common | B29: =B26+B27+B28 -> 3053373 | C29: =C26+C27+C28 -> 3725754 | D29: =D26+D27+D28 -> 3322349 | E29: =E26+E27+E28 -> 1003337
A31: MEMO - Property NOI | B31: =B6+B10 -> 5193749 | C31: =C6+C10 -> 5749320 | D31: =D6+D10 -> 6194767 | E31: =E6+E10 -> 1604801
A32: MEMO - NOI margin % | B32: =IF(B6=0,0,B31/B6) -> 0.76170961 | C32: =IF(C6=0,0,C31/C6) -> 0.76507594 | D32: =IF(D6=0,0,D31/D6) -> 0.7592646 | E32: =IF(E6=0,0,E31/E6) -> 0.75517062
A34: BALANCE SHEET
A35: Investments in real estate (gross) | B35: =Data_Collection!B26 -> 88666575 | C35: =Data_Collection!C26 -> 91246176 | D35: =Data_Collection!D26 -> 95129356 | E35: =Data_Collection!E26 -> 95241445
A36: Less: accumulated depreciation | B36: =-Data_Collection!B27 -> -10931485 | C36: =-Data_Collection!C27 -> -12758159 | D36: =-Data_Collection!D27 -> -14729149 | E36: =-Data_Collection!E27 -> -15298353
A37: Net investments in real estate properties | B37: =B35+B36 -> 77735090 | C37: =C35+C36 -> 78488017 | D37: =D35+D36 -> 80400207 | E37: =E35+E36 -> 79943092
A38: Investments in/advances to unconsolidated | B38: =Data_Collection!B28 -> 9543970 | C38: =Data_Collection!C28 -> 10079448 | D38: =Data_Collection!D28 -> 11093936 | E38: =Data_Collection!E28 -> 11241723
A39: Assets held for sale or contribution | B39: =Data_Collection!B29 -> 461657 | C39: =Data_Collection!C29 -> 248511 | D39: =Data_Collection!D29 -> 203344 | E39: =Data_Collection!E29 -> 499799
A40: Net investments in real estate | B40: =B37+B38+B39 -> 87740717 | C40: =C37+C38+C39 -> 88815976 | D40: =D37+D38+D39 -> 91697487 | E40: =E37+E38+E39 -> 91684614
A41: Cash and cash equivalents | B41: =Data_Collection!B30 -> 530388 | C41: =Data_Collection!C30 -> 1318591 | D41: =Data_Collection!D30 -> 1145647 | E41: =Data_Collection!E30 -> 861144
A42: Other assets | B42: =Data_Collection!B31 -> 4749735 | C42: =Data_Collection!C31 -> 5194342 | D42: =Data_Collection!D31 -> 5881122 | E42: =Data_Collection!E31 -> 5587693
A43: TOTAL ASSETS | B43: =B40+B41+B42 -> 93020840 | C43: =C40+C41+C42 -> 95328909 | D43: =D40+D41+D42 -> 98724256 | E43: =E40+E41+E42 -> 98133451
A44: Debt | B44: =Data_Collection!B33 -> 29000501 | C44: =Data_Collection!C33 -> 30879263 | D44: =Data_Collection!D33 -> 35037073 | E44: =Data_Collection!E33 -> 34669592
A45: Accounts payable & accrued | B45: =Data_Collection!B34 -> 1766018 | C45: =Data_Collection!C34 -> 1769327 | D45: =Data_Collection!D34 -> 1963645 | E45: =Data_Collection!E34 -> 1681047
A46: Other liabilities | B46: =Data_Collection!B35 -> 4430601 | C46: =Data_Collection!C35 -> 4063549 | D46: =Data_Collection!D35 -> 3969530 | E46: =Data_Collection!E35 -> 3834320
A47: TOTAL LIABILITIES | B47: =SUM(B44:B46) -> 35197120 | C47: =SUM(C44:C46) -> 36712139 | D47: =SUM(D44:D46) -> 40970248 | E47: =SUM(E44:E46) -> 40184959
A48: Preferred stock | B48: =Data_Collection!B37 -> 63948 | C48: =Data_Collection!C37 -> 63948 | D48: =Data_Collection!D37 -> 63948 | E48: =Data_Collection!E37 -> 63948
A49: Common equity (stockholders' equity) | B49: =Data_Collection!B38 -> 53181724 | C49: =Data_Collection!C38 -> 53951138 | D49: =Data_Collection!D38 -> 53193178 | E49: =Data_Collection!E38 -> 53503401
A50: Noncontrolling interests | B50: =Data_Collection!B39 -> 4641996 | C50: =Data_Collection!C39 -> 4665632 | D50: =Data_Collection!D39 -> 4560830 | E50: =Data_Collection!E39 -> 4445091
A51: TOTAL EQUITY | B51: =B49+B50 -> 57823720 | C51: =C49+C50 -> 58616770 | D51: =D49+D50 -> 57754008 | E51: =E49+E50 -> 57948492
A52: CHECK: Assets − (Liab + Equity) | B52: =B43-(B47+B51) -> 0 | C52: =C43-(C47+C51) -> 0 | D52: =D43-(D47+D51) -> 0 | E52: =E43-(E47+E51) -> 0
A54: CASH FLOW
A55: Consolidated net earnings | B55: =Data_Collection!B43 -> 3253145 | C55: =Data_Collection!C43 -> 3947935 | D55: =Data_Collection!D43 -> 3565299 | E55: =Data_Collection!E43 -> 1044815
A56: Depreciation & amortization | B56: =Data_Collection!B44 -> 2484891 | C56: =Data_Collection!C44 -> 2580519 | D56: =Data_Collection!D44 -> 2626028 | E56: =Data_Collection!E44 -> 731506
A57: Straight-line rent & lease intangible amort. | B57: =Data_Collection!B45 -> -613005 | C57: =Data_Collection!C45 -> -644606 | D57: =Data_Collection!D45 -> -691090 | E57: =Data_Collection!E45 -> -165749
A58: Equity-based compensation | B58: =Data_Collection!B46 -> 267648 | C58: =Data_Collection!C46 -> 231747 | D58: =Data_Collection!D46 -> 185466 | E58: =Data_Collection!E46 -> 60632
A59: Other operating adjustments (net) | B59: =Data_Collection!B47 -> 398440 | C59: =Data_Collection!C47 -> 796614 | D59: =Data_Collection!D47 -> 131730 | E59: =Data_Collection!E47 -> 253373
A60: Cash from operating activities | B60: =Data_Collection!B48 -> 5373058 | C60: =Data_Collection!C48 -> 4912209 | D60: =Data_Collection!D48 -> 5008434 | E60: =Data_Collection!E48 -> 1288136
A61: Development & capital expenditures | B61: =Data_Collection!B49 -> -4092956 | C61: =Data_Collection!C49 -> -4092639 | D61: =Data_Collection!D49 -> -3678815 | E61: =Data_Collection!E49 -> -914336
A62: Real estate acquisitions | B62: =Data_Collection!B50 -> -4195714 | C62: =Data_Collection!C50 -> -2327605 | D62: =Data_Collection!D50 -> -1800527 | E62: =Data_Collection!E50 -> -223053
A63: Proceeds from dispositions & contributions | B63: =Data_Collection!B51 -> 1764322 | C63: =Data_Collection!C51 -> 3790388 | D63: =Data_Collection!D51 -> 2246186 | E63: =Data_Collection!E51 -> 624036
A64: Other investing (net) | B64: =Data_Collection!B52 -> 104951 | C64: =Data_Collection!C52 -> -469201 | D64: =Data_Collection!D52 -> -397291 | E64: =Data_Collection!E52 -> 112868
A65: Cash from investing activities | B65: =SUM(B61:B64) -> -6419397 | C65: =SUM(C61:C64) -> -3099057 | D65: =SUM(D61:D64) -> -3630447 | E65: =SUM(E61:E64) -> -400485
A66: Debt issued | B66: =Data_Collection!B53 -> 5755096 | C66: =Data_Collection!C53 -> 4505830 | D66: =Data_Collection!D53 -> 3460904 | E66: =Data_Collection!E53 -> 161620
A67: Debt repaid | B67: =Data_Collection!B54 -> -272203 | C67: =Data_Collection!C54 -> -919481 | D67: =Data_Collection!D54 -> -701861 | E67: =Data_Collection!E54 -> -686276
A68: Dividends & unit distributions paid | B68: =Data_Collection!B55 -> -3228589 | C68: =Data_Collection!C55 -> -3570480 | D68: =Data_Collection!D55 -> -3764745 | E68: =Data_Collection!E55 -> -1026181
A69: Equity issuance, net | B69: =Data_Collection!B56 -> -153003 | C69: =Data_Collection!C56 -> -63142 | D69: =Data_Collection!D56 -> -97598 | E69: =Data_Collection!E56 -> -83556
A70: NCI contributions/(distributions), net | B70: =Data_Collection!B57 -> -213943 | C70: =Data_Collection!C57 -> -222607 | D70: =Data_Collection!D57 -> -256402 | E70: =Data_Collection!E57 -> -41796
A71: Other financing (net) | B71: =Data_Collection!B58 -> -567076 | C71: =Data_Collection!C58 -> -730077 | D71: =Data_Collection!D58 -> -203917 | E71: =Data_Collection!E58 -> 517779
A72: Cash from financing activities | B72: =SUM(B66:B71) -> 1320282 | C72: =SUM(C66:C71) -> -999957 | D72: =SUM(D66:D71) -> -1563619 | E72: =SUM(E66:E71) -> -1158410
A73: FX effect on cash | B73: =Data_Collection!B59 -> -22038 | C73: =Data_Collection!C59 -> -24992 | D73: =Data_Collection!D59 -> 12688 | E73: =Data_Collection!E59 -> -13744
A74: Net change in cash | B74: =B60+B65+B72+B73 -> 251905 | C74: =C60+C65+C72+C73 -> 788203 | D74: =D60+D65+D72+D73 -> -172944 | E74: =E60+E65+E72+E73 -> -284503
A75: CHECK: CF net change vs reported (Data_Collection) | B75: =B74-Data_Collection!B60 -> 0 | C75: =C74-Data_Collection!C60 -> 0 | D75: =D74-Data_Collection!D60 -> 0 | E75: =E74-Data_Collection!E60 -> 0

Sheet FFO_Recon
A1: FFO / CORE FFO / AFFO RECONCILIATION
A3: ($ in thousands; per-share in $) | B3: FY2023 | C3: FY2024 | D3: FY2025 | E3: Q1 2026
A4: NAREIT FFO
A5: Net earnings attributable to common | B5: =Data_Collection!B168 -> 3053373 | C5: =Data_Collection!C168 -> 3725754 | D5: =Data_Collection!D168 -> 3322349 | E5: =Data_Collection!E168 -> 980476
A6: + Real estate related depreciation & amortization | B6: =Data_Collection!B169 -> 2433610 | C6: =Data_Collection!C169 -> 2504001 | D6: =Data_Collection!D169 -> 2538805 | E6: =Data_Collection!E169 -> 705550
A7: − Gains on other dispositions of RE, net of tax | B7: =Data_Collection!B170 -> -157940 | C7: =Data_Collection!C170 -> -899270 | D7: =Data_Collection!D170 -> -684854 | E7: =Data_Collection!E170 -> -91040
A8: ± Reconciling items attributable to NCI | B8: =Data_Collection!B171 -> -38246 | C8: =Data_Collection!C171 -> -31334 | D8: =Data_Collection!D171 -> -47819 | E8: =Data_Collection!E171 -> -10737
A9: + Our prop. share of adjustments - unconsolidated | B9: =Data_Collection!B172 -> 455355 | C9: =Data_Collection!C172 -> 495448 | D9: =Data_Collection!D172 -> 551044 | E9: =Data_Collection!E172 -> 151155
A10: NAREIT FFO | B10: =SUM(B5:B9) -> 5746152 | C10: =SUM(C5:C9) -> 5794599 | D10: =SUM(D5:D9) -> 5679525 | E10: =SUM(E5:E9) -> 1735404
A11: CHECK: vs reported NAREIT FFO | B11: =IF(Data_Collection!B63="","n/a",IF(ABS(B10-Data_Collection!B63)<1,"OK","ERROR")) -> OK | C11: =IF(Data_Collection!C63="","n/a",IF(ABS(C10-Data_Collection!C63)<1,"OK","ERROR")) -> OK | D11: =IF(Data_Collection!D63="","n/a",IF(ABS(D10-Data_Collection!D63)<1,"OK","ERROR")) -> OK | E11: =IF(Data_Collection!E63="","n/a",IF(ABS(E10-Data_Collection!E63)<1,"OK","ERROR")) -> OK
A13: FFO, as modified by Prologis
A14: NAREIT FFO (carryforward) | B14: =B10 -> 5746152 | C14: =C10 -> 5794599 | D14: =D10 -> 5679525 | E14: =E10 -> 1735404
A15: ± Unrealized FX, derivative & other (gains) losses, net | B15: =Data_Collection!B173 -> 17619 | C15: =Data_Collection!C173 -> -68095 | D15: =Data_Collection!D173 -> 125247 | E15: =Data_Collection!E173 -> -14269
A16: ± Deferred income tax expense (benefit) | B16: =Data_Collection!B174 -> 6705 | C16: =Data_Collection!C174 -> 21161 | D16: =Data_Collection!D174 -> 4309 | E16: =Data_Collection!E174 -> 190
A17: ± Adjustments related to NCI | B17: =Data_Collection!B175 -> 403 | C17: =Data_Collection!C175 -> 0 | D17: =Data_Collection!D175 -> -728 | E17: =Data_Collection!E175 -> 712
A18: ± Our prop. share of adjustments - unconsolidated | B18: =Data_Collection!B176 -> -11224 | C18: =Data_Collection!C176 -> -7038 | D18: =Data_Collection!D176 -> -29094 | E18: =Data_Collection!E176 -> -725
A19: FFO, as modified by Prologis | B19: =SUM(B14:B18) -> 5759655 | C19: =SUM(C14:C18) -> 5740627 | D19: =SUM(D14:D18) -> 5779259 | E19: =SUM(E14:E18) -> 1721312
A20: CHECK: vs reported FFO as modified | B20: =IF(Data_Collection!B191="","n/a",IF(ABS(B19-Data_Collection!B191)<1,"OK","ERROR")) -> OK | C20: =IF(Data_Collection!C191="","n/a",IF(ABS(C19-Data_Collection!C191)<1,"OK","ERROR")) -> OK | D20: =IF(Data_Collection!D191="","n/a",IF(ABS(D19-Data_Collection!D191)<1,"OK","ERROR")) -> OK | E20: =IF(Data_Collection!E191="","n/a",IF(ABS(E19-Data_Collection!E191)<1,"OK","ERROR")) -> OK
A21: Core FFO
A22: FFO, as modified by Prologis (carryforward) | B22: =B19 -> 5759655 | C22: =C19 -> 5740627 | D22: =D19 -> 5779259 | E22: =E19 -> 1721312
A23: − Gains on dispositions of dev properties & land, net | B23: =Data_Collection!B177 -> -462270 | C23: =Data_Collection!C177 -> -413743 | D23: =Data_Collection!D177 -> -257731 | E23: =Data_Collection!E177 -> -292983
A24: ± Current income tax on dispositions | B24: =Data_Collection!B178 -> 36125 | C24: =Data_Collection!C178 -> 24876 | D24: =Data_Collection!D178 -> 25738 | E24: =Data_Collection!E178 -> 1302
A25: ± (Gains) losses on early extinguishment of debt | B25: =Data_Collection!B179 -> -3275 | C25: =Data_Collection!C179 -> -536 | D25: =Data_Collection!D179 -> 3498 | E25: =Data_Collection!E179 -> 1890
A26: ± Adjustments related to NCI | B26: =Data_Collection!B180 -> 9359 | C26: =Data_Collection!C180 -> 6244 | D26: =Data_Collection!D180 -> 14944 | E26: =Data_Collection!E180 -> 271
A27: ± Our prop. share of adjustments - unconsolidated | B27: =Data_Collection!B181 -> -5344 | C27: =Data_Collection!C181 -> -52529 | D27: =Data_Collection!D181 -> -4408 | E27: =Data_Collection!E181 -> 8701
A28: Core FFO | B28: =SUM(B22:B27) -> 5334250 | C28: =SUM(C22:C27) -> 5304939 | D28: =SUM(D22:D27) -> 5561300 | E28: =SUM(E22:E27) -> 1440493
A29: CHECK: vs reported Core FFO ($) | B29: =IF(Data_Collection!B65="","n/a",IF(ABS(B28-Data_Collection!B65)<1,"OK","ERROR")) -> OK | C29: =IF(Data_Collection!C65="","n/a",IF(ABS(C28-Data_Collection!C65)<1,"OK","ERROR")) -> OK | D29: =IF(Data_Collection!D65="","n/a",IF(ABS(D28-Data_Collection!D65)<1,"OK","ERROR")) -> OK | E29: =IF(Data_Collection!E65="","n/a",IF(ABS(E28-Data_Collection!E65)<1,"OK","ERROR")) -> OK
A30: Core FFO per share | B30: =B28/1000/Share_Count!B8 -> 5.6020269 | C30: =C28/1000/Share_Count!C8 -> 5.5601499 | D30: =D28/1000/Share_Count!D8 -> 5.8099666 | E30: =E28/1000/Share_Count!E8 -> 1.5000448
A31: CHECK: vs reported Core FFO/share (±$0.005) | B31: =IF(Data_Collection!B66="","n/a",IF(ABS(B30-Data_Collection!B66)<0.005,"OK","ERROR")) -> OK | C31: =IF(Data_Collection!C66="","n/a",IF(ABS(C30-Data_Collection!C66)<0.005,"OK","ERROR")) -> OK | D31: =IF(Data_Collection!D66="","n/a",IF(ABS(D30-Data_Collection!D66)<0.005,"OK","ERROR")) -> OK | E31: =IF(Data_Collection!E66="","n/a",IF(ABS(E30-Data_Collection!E66)<0.005,"OK","ERROR")) -> OK
A32: MEMO: Net promote income (expense) | B32: =Data_Collection!B130 -> 478944 | C32: =Data_Collection!C130 -> 31714 | D32: =Data_Collection!D130 -> -48960 | E32: =Data_Collection!E130 -> -50448
A34: AFFO
A35: Core FFO (carryforward) | B35: =B28 -> 5334250 | C35: =C28 -> 5304939 | D35: =D28 -> 5561300 | E35: =E28 -> 1440493
A36: + Gains on disp dev properties & land (add back) | B36: =Data_Collection!B182 -> 462270 | C36: =Data_Collection!C182 -> 413743 | D36: =Data_Collection!D182 -> 257731 | E36: =Data_Collection!E182 -> 292983
A37: − Current income tax on dispositions | B37: =Data_Collection!B183 -> -36125 | C37: =Data_Collection!C183 -> -24876 | D37: =Data_Collection!D183 -> -25738 | E37: =Data_Collection!E183 -> -1302
A38: − Straight-line rents & lease intangible amort. | B38: =Data_Collection!B184 -> -625356 | C38: =Data_Collection!C184 -> -644606 | D38: =Data_Collection!D184 -> -691090 | E38: =Data_Collection!E184 -> -165749
A39: − Property improvements | B39: =Data_Collection!B185 -> -303042 | C39: =Data_Collection!C185 -> -386481 | D39: =Data_Collection!D185 -> -327355 | E39: =Data_Collection!E185 -> -26065
A40: − Turnover costs (TI + LC) | B40: =Data_Collection!B186 -> -388814 | C40: =Data_Collection!C186 -> -499927 | D40: =Data_Collection!D186 -> -562197 | E40: =Data_Collection!E186 -> -123816
A41: + Amort of debt disc/financing/mgmt contracts | B41: =Data_Collection!B187 -> 76294 | C41: =Data_Collection!C187 -> 80028 | D41: =Data_Collection!D187 -> 90668 | E41: =Data_Collection!E187 -> 21400
A42: + Stock compensation amortization | B42: =Data_Collection!B188 -> 267648 | C42: =Data_Collection!C188 -> 231747 | D42: =Data_Collection!D188 -> 185466 | E42: =Data_Collection!E188 -> 60632
A43: ± Adjustments related to NCI | B43: =Data_Collection!B189 -> 48049 | C43: =Data_Collection!C189 -> 53432 | D43: =Data_Collection!D189 -> 66005 | E43: =Data_Collection!E189 -> 19628
A44: ± Our prop. share of adjustments - unconsolidated | B44: =Data_Collection!B190 -> -124544 | C44: =Data_Collection!C190 -> -106433 | D44: =Data_Collection!D190 -> -219746 | E44: =Data_Collection!E190 -> -46311
A45: AFFO | B45: =SUM(B35:B44) -> 4710630 | C45: =SUM(C35:C44) -> 4421566 | D45: =SUM(D35:D44) -> 4335044 | E45: =SUM(E35:E44) -> 1471893
A46: CHECK: vs reported AFFO | B46: =IF(Data_Collection!B74="","n/a",IF(ABS(B45-Data_Collection!B74)<1,"OK","ERROR")) -> OK | C46: =IF(Data_Collection!C74="","n/a",IF(ABS(C45-Data_Collection!C74)<1,"OK","ERROR")) -> OK | D46: =IF(Data_Collection!D74="","n/a",IF(ABS(D45-Data_Collection!D74)<1,"OK","ERROR")) -> OK | E46: =IF(Data_Collection!E74="","n/a",IF(ABS(E45-Data_Collection!E74)<1,"OK","ERROR")) -> OK
A47: MEMO: AFFO payout ratio

Sheet Drivers
A1: OPERATING DRIVERS
A2: Green = link, blue = input, black = calc.
A4: ($ in millions unless noted) | B4: FY2023 | C4: FY2024 | D4: FY2025 | E4: Q1 2026
A5: OCCUPANCY
A6: Average occupancy % - PLD share | B6: =Data_Collection!B88 -> 0.977 | C6: =Data_Collection!C88 -> 0.958 | D6: =Data_Collection!D88 -> 0.956 | E6: =Data_Collection!E88 -> 0.953
A7: Average occupancy % - O&M | B7: =Data_Collection!B89 -> 0.976 | C7: =Data_Collection!C89 -> 0.959 | D7: =Data_Collection!D89 -> 0.958 | E7: =Data_Collection!E89 -> 0.953
A8: Period-end occupancy % (O&M) | B8: =Data_Collection!B90 -> 0.976 | C8: =Data_Collection!C90 -> 0.959 | D8: =Data_Collection!D90 -> 0.958 | E8: =Data_Collection!E90 -> 0.953
A9: Leased % (if disclosed) | B9: =Data_Collection!B91 -> 0.978 | C9: =Data_Collection!C91 -> 0.96 | D9: =Data_Collection!D91 -> 0.962 | E9: =Data_Collection!E91 -> 0.958
A11: SAME-STORE NOI
A12: SS NOI growth - cash % | B12: =Data_Collection!B82 -> 0.085 | C12: =Data_Collection!C82 -> 0.045 | D12: =Data_Collection!D82 -> 0.063 | E12: =Data_Collection!E82 -> 0.066
A13: SS NOI growth - net effective % | B13: =Data_Collection!B83 -> 0.075 | C13: =Data_Collection!C83 -> 0.04 | D13: =Data_Collection!D83 -> 0.048 | E13: =Data_Collection!E83 -> 0.051
A14: SS pool size (M sq ft) | B14: =Data_Collection!B84 -> 738498 | C14: =Data_Collection!C84 -> 764587 | D14: =Data_Collection!D84 -> 773176 | E14: =Data_Collection!E84 -> 777055
A16: RENT CHANGE ON ROLLOVER
A17: Net effective rent change % | B17: =Data_Collection!B94 -> 0.741 | C17: =Data_Collection!C94 -> 0.663 | D17: =Data_Collection!D94 -> 0.438 | E17: =Data_Collection!E94 -> 0.319
A18: Cash rent change % | B18: =Data_Collection!B95 -> 0.518 | C18: =Data_Collection!C95 -> 0.401 | D18: =Data_Collection!D95 -> 0.273 | E18: =Data_Collection!E95 -> 0.168
A19: Retention % | B19: =Data_Collection!B96 -> 0.768 | C19: =Data_Collection!C96 -> 0.784 | D19: =Data_Collection!D96 -> 0.777 | E19: =Data_Collection!E96 -> 0.758
A20: Leases commenced/signed (M sq ft) | B20: =Data_Collection!B97 -> 43.65 | C20: =Data_Collection!C97 -> 46.491 | D20: =Data_Collection!D97 -> 43.764 | E20: =Data_Collection!E97 -> 66.722
A22: LEASE EXPIRATION SCHEDULE (forward, annual)
A23: % of NOI expiring Y1 | B23: =Data_Collection!B99 -> 0.091 | C23: =Data_Collection!C99 -> 0.091 | D23: =Data_Collection!D99 -> 0.103 | E23: =Data_Collection!E99 -> 0.069
A24: % expiring Y2 | B24: =Data_Collection!B100 -> 0.12 | C24: =Data_Collection!C100 -> 0.135 | D24: =Data_Collection!D100 -> 0.148 | E24: =Data_Collection!E100 -> 0.147
A25: % expiring Y3 | B25: =Data_Collection!B101 -> 0.139 | C25: =Data_Collection!C101 -> 0.151 | D25: =Data_Collection!D101 -> 0.146 | E25: =Data_Collection!E101 -> 0.147
A26: % expiring Y4 | B26: =Data_Collection!B102 -> 0.148 | C26: =Data_Collection!C102 -> 0.143 | D26: =Data_Collection!D102 -> 0.136 | E26: =Data_Collection!E102 -> 0.14
A27: % expiring Y5 | B27: =Data_Collection!B103 -> 0.146 | C27: =Data_Collection!C103 -> 0.134 | D27: =Data_Collection!D103 -> 0.133 | E27: =Data_Collection!E103 -> 0.133
A29: MARK-TO-MARKET
A30: Lease MTM % (net effective) | B30: =Data_Collection!B106 -> 0.764 | C30: =Data_Collection!C106 -> 0.687 | D30: =Data_Collection!D106 -> 0.501 | E30: =Data_Collection!E106 -> 0.435
A31: MTM embedded NOI $ | B31: =Data_Collection!B107 -> N/D | C31: =Data_Collection!C107 -> N/D | D31: =Data_Collection!D107 -> N/D | E31: =Data_Collection!E107 -> N/D
A33: NOTE: PLD same-store definition (paste verbatim) →

Sheet Development
A1: DEVELOPMENT PIPELINE
A2: Green = link, blue = input, black = calc.
A4: ($ in millions unless noted) | B4: FY2023 | C4: FY2024 | D4: FY2025 | E4: Q1 2026
A5: TOTAL DEVELOPMENT
A6: Starts - TEI ($) | B6: =Data_Collection!B110 -> 3397 | C6: =Data_Collection!C110 -> 1339 | D6: =Data_Collection!D110 -> 2956 | E6: =Data_Collection!E110 -> 1783
A7: Starts - est. yield % | B7: =Data_Collection!B111 -> 0.07 | C7: =Data_Collection!C111 -> 0.073 | D7: =Data_Collection!D111 -> 0.063 | E7: =Data_Collection!E111 -> 0.088
A8: Starts - est. margin % | B8: =Data_Collection!B112 -> 0.274 | C8: =Data_Collection!C112 -> 0.269 | D8: =Data_Collection!D112 -> 0.193 | E8: =Data_Collection!E112 -> 0.32
A9: Starts - est. value creation ($) | B9: =Data_Collection!B113 -> 931 | C9: =Data_Collection!C113 -> 366 | D9: =Data_Collection!D113 -> 569 | E9: =Data_Collection!E113 -> 571
A10: Starts - % build-to-suit | B10: =Data_Collection!B114 -> 0.53 | C10: =Data_Collection!C114 -> 0.334 | D10: =Data_Collection!D114 -> 0.611 | E10: =Data_Collection!E114 -> 0.812
A12: STREAM SPLIT
A13: Data center starts - TEI ($) | B13: =Data_Collection!B115 -> N/D | C13: =Data_Collection!C115 -> N/D | D13: =Data_Collection!D115 -> N/D | E13: =Data_Collection!E115 -> 1300
A14: Logistics starts - TEI ($) | B14: =B6-B10 -> 3396.47 | C14: =C6-C10 -> 1338.666 | D14: =D6-D10 -> 2955.389 | E14: =E6-E10 -> 1782.188
A15: DC % of total starts | B15: =IF(B6=0,0,B10/B6) -> 0.00015602002 | C15: =IF(C6=0,0,C10/C6) -> 0.00024943988 | D15: =IF(D6=0,0,D10/D6) -> 0.00020669824 | E15: =IF(E6=0,0,E10/E6) -> 0.00045541223
A17: STABILIZATIONS
A18: Stabilizations - TEI ($) | B18: =Data_Collection!B116 -> 3151 | C18: =Data_Collection!C116 -> 4168 | D18: =Data_Collection!D116 -> 2260 | E18: =Data_Collection!E116 -> 1113
A19: Stabilizations - est. yield % | B19: =Data_Collection!B117 -> 0.063 | C19: =Data_Collection!C117 -> 0.061 | D19: =Data_Collection!D117 -> 0.067 | E19: =Data_Collection!E117 -> 0.076
A20: Stabilizations - est. margin % | B20: =Data_Collection!B118 -> 0.291 | C20: =Data_Collection!C118 -> 0.185 | D20: =Data_Collection!D118 -> 0.251 | E20: =Data_Collection!E118 -> 0.348
A21: Stabilizations - est. value creation ($) | B21: =Data_Collection!B119 -> 917 | C21: =Data_Collection!C119 -> 773 | D21: =Data_Collection!D119 -> 568 | E21: =Data_Collection!E119 -> 387
A23: PIPELINE & LAND
A24: CIP balance ($) | B24: =Data_Collection!B120 -> 7850 | C24: =Data_Collection!C120 -> 4712 | D24: =Data_Collection!D120 -> 5126 | E24: =Data_Collection!E120 -> 5491
A25: CIP - % leased | B25: =Data_Collection!B121 -> 0.372 | C25: =Data_Collection!C121 -> 0.332 | D25: =Data_Collection!D121 -> 0.548 | E25: =Data_Collection!E121 -> 0.475
A26: Land bank - book value ($) | B26: =Data_Collection!B122 -> 3814 | C26: =Data_Collection!C122 -> 4485 | D26: =Data_Collection!D122 -> 4979 | E26: =Data_Collection!E122 -> 4799
A27: Land bank - buildout TEI capacity ($) | B27: =Data_Collection!B123 -> 37000 | C27: =Data_Collection!C123 -> 38300 | D27: =Data_Collection!D123 -> 39000 | E27: =Data_Collection!E123 -> 38000
A29: DERIVED HISTORY
A30: Realized value-creation margin % (VC ÷ TEI) | B30: =IF(B16=0,0,B19/B16) -> 0 | C30: =IF(C16=0,0,C19/C16) -> 0 | D30: =IF(D16=0,0,D19/D16) -> 0 | E30: =IF(E16=0,0,E19/E16) -> 0

Sheet Strategic_Capital
A1: STRATEGIC CAPITAL
A2: Green = link, blue = input, black = calc.
A4: ($ in millions unless noted) | B4: FY2023 | C4: FY2024 | D4: FY2025 | E4: Q1 2026
A5: AUM ($B)
A6: Gross AUM | B6: =Data_Collection!B126 -> 219 | C6: =Data_Collection!C126 -> 198 | D6: =Data_Collection!D126 -> 230 | E6: =Data_Collection!E126 -> 235
A7: Prologis-share AUM | B7: =Data_Collection!B127 -> 159 | C7: =Data_Collection!C127 -> 136 | D7: =Data_Collection!D127 -> 162 | E7: =Data_Collection!E127 -> 166
A8: Third-party AUM | B8: =B6-B7 -> 60 | C8: =C6-C7 -> 62 | D8: =D6-D7 -> 68 | E8: =E6-E7 -> 69
A10: FEE REVENUE ($)
A11: Recurring asset management fees | B11: =Data_Collection!B128 -> 327456 | C11: =Data_Collection!C128 -> 347540 | D11: =Data_Collection!D128 -> 374044 | E11: =Data_Collection!E128 -> 379020
A12: Transactional fees | B12: =Data_Collection!B129 -> 31801 | C12: =Data_Collection!C129 -> 29126 | D12: =Data_Collection!D129 -> 32512 | E12: =Data_Collection!E129 -> 37142
A13: Total strategic capital revenue | B13: =B11+B12 -> 359257 | C13: =C11+C12 -> 376666 | D13: =D11+D12 -> 406556 | E13: =E11+E12 -> 416162
A14: Strategic capital expenses | B14: =Data_Collection!B131 -> 385542 | C14: =Data_Collection!C131 -> 291856 | D14: =Data_Collection!D131 -> 270517 | E14: =Data_Collection!E131 -> 81889
A16: PROMOTES ($)
A17: Net promote income (expense) | B17: =Data_Collection!B130 -> 478944 | C17: =Data_Collection!C130 -> 31714 | D17: =Data_Collection!D130 -> -48960 | E17: =Data_Collection!E130 -> -50448
A19: CO-INVESTMENT
A20: Contributions to ventures ($) | B20: =Data_Collection!B132 -> 1253395 | C20: =Data_Collection!C132 -> 2306446 | D20: =Data_Collection!D132 -> 1042681 | E20: =Data_Collection!E132 -> 339404
A21: PLD share of venture debt ($) | B21: =Data_Collection!B133 -> 3613882 | C21: =Data_Collection!C133 -> 4653326 | D21: =Data_Collection!D133 -> 5329877 | E21: =Data_Collection!E133 -> 5429782
A22: Effective fee rate (fees ÷ avg 3rd-party AUM) | B22: =IF(B8=0,0,(B11)/(B8*1000)) -> 5.4576 | C22: =IF(C8=0,0,(C11)/(C8*1000)) -> 5.6054839 | D22: =IF(D8=0,0,(D11)/(D8*1000)) -> 5.5006471 | E22: =IF(E8=0,0,(E11)/(E8*1000)) -> 5.4930435

Sheet Capital_Deployment
A1: CAPITAL DEPLOYMENT
A2: Green = link, blue = input, black = calc.
A4: ($ in millions unless noted) | B4: FY2023 | C4: FY2024 | D4: FY2025 | E4: Q1 2026
A5: ACQUISITIONS
A6: Acquisitions ($) | B6: =Data_Collection!B136 -> 732636 | C6: =Data_Collection!C136 -> 1916744 | D6: =Data_Collection!D136 -> 1710000 | E6: =Data_Collection!E136 -> 267930
A7: Acquisitions - wtd avg stabilized cap rate % | B7: =Data_Collection!B137 -> 0.054 | C7: =Data_Collection!C137 -> 0.051 | D7: =Data_Collection!D137 -> 0.047 | E7: =Data_Collection!E137 -> 0.047
A9: DISPOSITIONS & CONTRIBUTIONS [NAV ANCHOR]
A10: Dispositions + contributions ($) | B10: =Data_Collection!B138 -> 1607994 | C10: =Data_Collection!C138 -> 3984920 | D10: =Data_Collection!D138 -> 2170174 | E10: =Data_Collection!E138 -> 676426
A11: Disposition cap rate % [NAV ANCHOR] | B11: =Data_Collection!B139 -> 0.045 | C11: =Data_Collection!C139 -> 0.048 | D11: =Data_Collection!D139 -> 0.049 | E11: =Data_Collection!E139 -> 0.051

Sheet Debt
A1: DEBT SCHEDULE
A2: Green = link, blue = input, black = calc.
A4: ($ in millions unless noted) | B4: FY2023 | C4: FY2024 | D4: FY2025 | E4: Q1 2026
A5: INSTRUMENT DETAIL (one row per note series — fill from 10-K debt footnote)
A6: [Instrument 1 - principal]
A7: [Instrument 2 - principal]
A8: [Instrument 3 - principal]
A10: PORTFOLIO STATS (quarterly)
A11: Wtd avg interest rate % (PLD share) | B11: =Data_Collection!B144 -> 0.03 | C11: =Data_Collection!C144 -> 0.032 | D11: =Data_Collection!D144 -> 0.033 | E11: =Data_Collection!E144 -> 0.033
A12: Wtd avg remaining term (yrs) | B12: =Data_Collection!B145 -> 9.1 | C12: =Data_Collection!C145 -> 9 | D12: =Data_Collection!D145 -> 8.2 | E12: =Data_Collection!E145 -> 8.1
A13: % fixed-rate | B13: =Data_Collection!B146 -> 0.91 | C13: =Data_Collection!C146 -> 0.952 | D13: =Data_Collection!D146 -> 0.962 | E13: =Data_Collection!E146 -> 0.954
A14: % secured (of gross RE assets) | B14: =Data_Collection!B147 -> 0.006 | C14: =Data_Collection!C147 -> 0.005 | D14: =Data_Collection!D147 -> 0.003 | E14: =Data_Collection!E147 -> 0.004
A15: Debt / Adjusted EBITDA (x) | B15: =Data_Collection!B148 -> 4.6 | C15: =Data_Collection!C148 -> 4.6 | D15: =Data_Collection!D148 -> 5.3 | E15: =Data_Collection!E148 -> 4.8
A16: Fixed charge coverage (x) | B16: =Data_Collection!B149 -> 7.9 | C16: =Data_Collection!C149 -> 6.8 | D16: =Data_Collection!D149 -> 5.9 | E16: =Data_Collection!E149 -> 6.4
A17: Available liquidity ($) | B17: =Data_Collection!B152 -> 6000 | C17: =Data_Collection!C152 -> 7400 | D17: =Data_Collection!D152 -> 7600 | E17: =Data_Collection!E152 -> 6700
A19: NEW ISSUANCE SERIES (cost-of-debt input for WACC)
A20: New issuance during period ($) | B20: =Data_Collection!B150 -> 5755 | C20: =Data_Collection!C150 -> 4506 | D20: =Data_Collection!D150 -> 3461 | E20: =Data_Collection!E150 -> 162
A21: New issuance - wtd avg rate % | B21: =Data_Collection!B151 -> 0.047 | C21: =Data_Collection!C151 -> 0.048 | D21: =Data_Collection!D151 -> 0.042 | E21: =Data_Collection!E151 -> 0.037
A23: HEDGE BLOCK
A24: FX hedge notional - EUR ($)
A25: FX hedge notional - GBP ($)
A26: FX hedge notional - JPY ($)
A27: % forecasted earnings USD-or-hedged (note)

Sheet Share_Count
A1: SHARE COUNT
A2: The cardinal rule: Core FFO per-share math uses the units-inclusive Core FFO basis, NOT the EPS basis.
A4: ($ in millions unless noted) | B4: FY2023 | C4: FY2024 | D4: FY2025 | E4: Q1 2026
A5: SHARE COUNTS (M)
A6: Common shares outstanding (period-end) | B6: =Data_Collection!B155 -> 924.4 | C6: =Data_Collection!C155 -> 926.3 | D6: =Data_Collection!D155 -> 929.2 | E6: =Data_Collection!E155 -> 932.3
A7: Wtd avg diluted - EPS basis | B7: =Data_Collection!B156 -> 951.8 | C7: =Data_Collection!C156 -> 953.6 | D7: =Data_Collection!D156 -> 956.8 | E7: =Data_Collection!E156 -> 957.6
A8: Wtd avg shares/units - Core FFO basis | B8: =Data_Collection!B157 -> 952.2 | C8: =Data_Collection!C157 -> 954.1 | D8: =Data_Collection!D157 -> 957.2 | E8: =Data_Collection!E157 -> 960.3
A9: OP/LP units outstanding | B9: =Data_Collection!B158 -> 23.3 | C9: =Data_Collection!C158 -> 23.4 | D9: =Data_Collection!D158 -> 22.1 | E9: =Data_Collection!E158 -> 20
A10: Core FFO basis − EPS basis (units bridge) | B10: =B8-B7 -> 0.4 | C10: =C8-C7 -> 0.5 | D10: =D8-D7 -> 0.4 | E10: =E8-E7 -> 2.7
A11: CHECK: Core FFO basis ≥ EPS basis | B11: =IF(B8="","n/a",IF(B8>=B7,"OK","ERROR")) -> OK | C11: =IF(C8="","n/a",IF(C8>=C7,"OK","ERROR")) -> OK | D11: =IF(D8="","n/a",IF(D8>=D7,"OK","ERROR")) -> OK | E11: =IF(E8="","n/a",IF(E8>=E7,"OK","ERROR")) -> OK
A13: ISSUANCE ACTIVITY
A14: ATM issuance ($) | B14: =Data_Collection!B159 -> 0 | C14: =Data_Collection!C159 -> 0 | D14: =Data_Collection!D159 -> 0 | E14: =Data_Collection!E159 -> 0
A15: ATM issuance (shares) | B15: =Data_Collection!B160 -> 0 | C15: =Data_Collection!C160 -> 0 | D15: =Data_Collection!D160 -> 0 | E15: =Data_Collection!E160 -> 0

Sheet Audit
A1: AUDIT - MODEL HEALTH
A2: Each check returns OK/ERROR. ERROR = model is wrong. Master flag on Cover reads column E.
A4: # | B4: Check | C4: Category | D4: References | E4: Status
A5: 1 | B5: Balance sheet balances (all periods) | C5: Balance sheet | D5: Historicals check row 52 | E5: =IF(SUMPRODUCT(ABS(Historicals!B52:E52))<4,"OK","ERROR") -> OK
A6: 2 | B6: Nareit FFO ties to reported | C6: FFO | D6: FFO_Recon row 12 | E6: =IF(COUNTIF(FFO_Recon!B11:E11,"ERROR")=0,"OK","ERROR") -> OK
A7: 3 | B7: Core FFO/share ties to reported | C7: FFO | D7: FFO_Recon row 32 | E7: =IF(COUNTIF(FFO_Recon!B31:E31,"ERROR")=0,"OK","ERROR") -> OK
A8: 4 | B8: AFFO ties to reported | C8: AFFO | D8: FFO_Recon row 47 | E8: =IF(COUNTIF(FFO_Recon!B46:E46,"ERROR")=0,"OK","ERROR") -> OK
A9: 5 | B9: Core FFO share count ≥ EPS share count | C9: Share count | D9: Share_Count row 11 | E9: =IF(COUNTIF(Share_Count!B11:E11,"ERROR")=0,"OK","ERROR") -> OK
A10: 6 | B10: Debt schedule ties to balance sheet | C10: Debt | D10: Debt tab - wire instrument sum to Historicals debt line | E10: =IF(Debt!B6="","PENDING","REVIEW") -> PENDING
A11: 7 | B11: No hardcodes outside Data_Collection | C11: Hygiene | D11: Manual color audit each session | E11: =IF(1=1,"MANUAL","") -> MANUAL
A12: 8 | B12: Every filled Data_Collection row has a source | C12: Hygiene | D12: Manual review | E12: =IF(1=1,"MANUAL","") -> MANUAL

Sheet Assumptions
A1: PROLOGIS (PLD) - FORECAST ASSUMPTIONS
A2: Scenario-driven inputs for the 5-year forecast. Blue = input (you set). Green = historical reference link. ACTIVE column resolves the chosen case via the scenario switch and is the ONLY column the Model tab reads.
A4: SCENARIO SWITCH | U4: 1
A5: Active scenario (1 = Base, 2 = Bull, 3 = Bear) | B5: 1 | G5: Change this one cell to flip the whole model. Forecast Model reads only the ACTIVE column (E-equivalent resolver per row). | U5: 2
A6: Active scenario name | B6: =CHOOSE($B$5,"BASE","BULL","BEAR") -> BASE | U6: 3
A8: Assumption | B8: Hist. ref. | C8: Base | D8: Bull | E8: Bear | F8: ACTIVE | G8: Source / rationale
A9: 1 · OPERATING ASSUMPTIONS (same-store NOI engine)
A10: Average occupancy % - PLD share | B10: =Drivers!D6 -> 0.956 | C10: 0.953 | D10: 0.957 | E10: 0.935 | F10: =CHOOSE($B$5,C10,D10,E10) -> 0.953 | G10: Hist = FY2025. Base: hold guided 95.0–95.75% band then flat. Bull: upper band. Bear: 150–250bps erosion (recession proxy). Lever 2.
A11: Market rent growth - Y1 (annual) | B11: N/A | C11: 0.03 | D11: 0.06 | E11: -0.01 | F11: =CHOOSE($B$5,C11,D11,E11) -> 0.03 | G11: Lever 1. Base: modest mean-reverting. Bull: supply-trough re-accel. Bear: renewed declines. Largest compounding effect on SS NOI.
A12: Market rent growth - terminal (Y5) | B12: N/A | C12: 0.035 | D12: 0.055 | E12: 0.01 | F12: =CHOOSE($B$5,C12,D12,E12) -> 0.035 | G12: Path glides Y1→Y5; set endpoints here, interpolate in Model. Keep bull below boom-era peaks.
A13: Contractual escalators (in-place) | B13: N/A | C13: 0.04 | D13: 0.045 | E13: 0.035 | F13: =CHOOSE($B$5,C13,D13,E13) -> 0.04 | G13: Embedded annual bumps on in-place leases — the floor under SS NOI. Tight band; not a recession lever.
A14: SS NOI growth - sanity ceiling (cash) | B14: =Drivers!D12 -> 0.063 | G14: Hist = FY2025 cash SS NOI +6.3%. Reference only; SS NOI growth is an OUTPUT of the Model bridge, not an input here.
A15: Operating expense ratio (rental) | B15: N/A | C15: 0.245 | D15: 0.24 | E15: 0.255 | F15: =CHOOSE($B$5,C15,D15,E15) -> 0.245 | G15: Rental exp ÷ rental rev. Used to gross NOI up to revenue. Hist ~24% (Historicals). Slight scenario flex on margin.
A17: 2 · LEASING ASSUMPTIONS (rollover / mark-to-market runway)
A18: Net effective rent change on rollover - Y1 | B18: =Drivers!D17 -> 0.438 | C18: 0.3 | D18: 0.4 | E18: 0.18 | F18: =CHOOSE($B$5,C18,D18,E18) -> 0.3 | G18: Hist = FY2025 +43.8%. Base decays from here (MTM is a depleting stock). Lever 3.
A19: Rollover spread - terminal (Y5) | B19: N/A | C19: 0.1 | D19: 0.22 | E19: 0.03 | F19: =CHOOSE($B$5,C19,D19,E19) -> 0.1 | G19: Decay endpoint. If market rents flat, spread converges to escalator levels. Constant 30%+ forever = classic bull error.
A20: Annual MTM realization (% pool rolling) | B20: =Drivers!D23 -> 0.103 | C20: 0.13 | D20: 0.15 | E20: 0.11 | F20: =CHOOSE($B$5,C20,D20,E20) -> 0.13 | G20: Hist = FY2025 % NOI expiring Y1 (~10.3%). % of pool that reprices each year, from lease-expiry schedule.
A21: Retention % | B21: =Drivers!D19 -> 0.777 | C21: 0.77 | D21: 0.8 | E21: 0.72 | F21: =CHOOSE($B$5,C21,D21,E21) -> 0.77 | G21: Hist = FY2025 77.7%. Higher retention lowers downtime/turnover cost; bear leaks.
A22: Embedded MTM stock (net effective) | B22: =Drivers!D30 -> 0.501 | C22: 0.5 | D22: 0.5 | E22: 0.5 | F22: =CHOOSE($B$5,C22,D22,E22) -> 0.5 | G22: Hist = FY2025 lease MTM 50.1%. Starting embedded upside that depletes as leases roll; decay path set above.
A24: 3 · DEVELOPMENT ASSUMPTIONS (Approach B - logistics + data centers as separate streams)
A25: Logistics starts - TEI Y1 ($mm) | B25: =Drivers!D14/1000 -> 773.176 | C25: 4000 | D25: 5500 | E25: 2500 | F25: =CHOOSE($B$5,C25,D25,E25) -> 4000 | G25: Hist = FY2025 logistics starts. Base: guidance yr1 ($3.5–4.5B PLD share) then policy. Lever 4. (units $mm)
A26: Logistics starts - annual growth | B26: N/A | C26: 0.05 | D26: 0.12 | E26: -0.2 | F26: =CHOOSE($B$5,C26,D26,E26) -> 0.05 | G26: Years 2–5 growth off Y1. Bear sharply curtails. Drives delivered NOI + AUM feed.
A27: Logistics - stabilized yield on cost | B27: =Development!D19 -> 0.067 | C27: 0.065 | D27: 0.075 | E27: 0.055 | F27: =CHOOSE($B$5,C27,D27,E27) -> 0.065 | G27: Hist ref = FY2025 stabilization yield 6.7%. Lever 5 (value-creation engine).
A28: Logistics - value-creation margin | B28: =Development!D20 -> 0.251 | C28: 0.2 | D28: 0.3 | E28: 0.05 | F28: =CHOOSE($B$5,C28,D28,E28) -> 0.2 | G28: Hist = FY2025 stabilization margin 25.1%. "Is development worth anything" in one cell. Bear compresses toward zero.
A29: Data center starts - TEI Y1 ($mm) | B29: =Development!E13 -> 1300 | C29: 1300 | D29: 2500 | E29: 500 | F29: =CHOOSE($B$5,C29,D29,E29) -> 1300 | G29: Hist = Q1 2026 DC starts $1.3B (first disclosed). Separate stream: longer build, ~100% BTS, higher TEI/project.
A30: Data center - annual growth | B30: N/A | C30: 0.1 | D30: 0.25 | E30: -0.3 | F30: =CHOOSE($B$5,C30,D30,E30) -> 0.1 | G30: DC pivot accel in bull; capital-hungry & competitive in bear. Inference-based (limited disclosure).
A31: Data center - stabilized yield on cost | B31: N/A | C31: 0.08 | D31: 0.09 | E31: 0.065 | F31: =CHOOSE($B$5,C31,D31,E31) -> 0.08 | G31: Q1 2026 starts yield 8.8% (blended). DC carries different economics; footnote mix-shift risk.
A32: Data center - value-creation margin | B32: N/A | C32: 0.25 | D32: 0.35 | E32: 0.1 | F32: =CHOOSE($B$5,C32,D32,E32) -> 0.25 | G32: Higher than logistics on BTS de-risking; bear imports compressed post-2022 logistics margins as caution.
A33: Stabilization lag (quarters, both streams) | B33: N/A | C33: 6 | D33: 5 | E33: 7 | F33: =CHOOSE($B$5,C33,D33,E33) -> 6 | G33: Quarters from start to NOI in operating pool. DC longer than logistics in practice — simplify to one lag, footnote.
A34: Development → contribution share (AUM feed) | B34: N/A | C34: 0.4 | D34: 0.5 | E34: 0.2 | F34: =CHOOSE($B$5,C34,D34,E34) -> 0.4 | G34: % of stabilized TEI contributed to ventures (the conveyor exit ramp into Strategic Capital AUM).
A36: 4 · STRATEGIC CAPITAL ASSUMPTIONS (fee + promote engine)
A37: Effective fee rate (bps of 3rd-party AUM) | B37: =Strategic_Capital!D22 -> 5.5006471 | C37: 0.0055 | D37: 0.0058 | E37: 0.005 | F37: =CHOOSE($B$5,C37,D37,E37) -> 0.0055 | G37: Hist = FY2025 ~55bps (fees ÷ avg 3rd-party AUM). Trailing 3yr, held ~flat. Mix-shift risk footnoted, not modeled.
A38: Third-party AUM growth (annual) | B38: N/A | C38: 0.05 | D38: 0.1 | E38: -0.05 | F38: =CHOOSE($B$5,C38,D38,E38) -> 0.05 | G38: Contribution-driven base. Bull: new vehicle wins ($2.8B Q1 JVs). Bear: net outflows + negative marks. Lever 6.
A39: Transactional fee growth | B39: N/A | C39: 0.03 | D39: 0.08 | E39: -0.1 | F39: =CHOOSE($B$5,C39,D39,E39) -> 0.03 | G39: Tied to deployment pace; lumpier than recurring fees.
A40: Net promote income - FY2026 ($mm) | B40: =Strategic_Capital!D17/1000 -> -48.96 | C40: -50 | D40: -50 | E40: -50 | F40: =CHOOSE($B$5,C40,D40,E40) -> -50 | G40: Hist = FY2025 net promote $(49)M. Base = guided FY26 $(50)M. All cases anchor yr1 to guidance. Lever 8.
A41: Net promote - FY2027+ ($mm/yr) | B41: N/A | C41: 0 | D41: 150 | E41: -50 | F41: =CHOOSE($B$5,C41,D41,E41) -> 0 | G41: Base = ZERO (honest expectation; unforecastable timing — say so loudly). Bull: modest positive. Bear: recurring expense. Asymmetry display.
A42: Strategic capital expense ratio | B42: N/A | C42: 0.55 | D42: 0.52 | E42: 0.58 | F42: =CHOOSE($B$5,C42,D42,E42) -> 0.55 | G42: SC expenses ÷ recurring+transactional fees. Drives FRE margin. Hist noisy (promote-comp timing).
A44: 5 · CAPITAL STRUCTURE ASSUMPTIONS (debt ladder + leverage policy)
A45: New-issue debt cost (all-in %) | B45: =Debt!D21 -> 0.042 | C45: 0.05 | D45: 0.0425 | E45: 0.06 | F45: =CHOOSE($B$5,C45,D45,E45) -> 0.05 | G45: Hist = FY2025 new-issue 4.2%. Base: current curve + spread. Bull: −75bps. Bear: +100bps. Lever 7 (refi drag).
A46: Leverage policy - Net debt / Adj. EBITDA | B46: =Debt!D15 -> 5.3 | C46: 4.8 | D46: 4.5 | E46: 5.5 | F46: =CHOOSE($B$5,C46,D46,E46) -> 4.8 | G46: Hist = FY2025 5.3x (Q1 4.8x). Target band 4.5–5.0x. Incremental debt sized to hold this roughly constant.
A47: Wtd-avg refi rate on maturities (%) | B47: =Debt!D11 -> 0.033 | C47: 0.045 | D47: 0.04 | E47: 0.055 | F47: =CHOOSE($B$5,C47,D47,E47) -> 0.045 | G47: Legacy coupon ~3.3% below new-issue → every refi year a small FFO headwind. Mechanical ladder, not a debate.
A48: % of new funding from debt (waterfall) | B48: N/A | C48: 0.6 | D48: 0.5 | E48: 0.7 | F48: =CHOOSE($B$5,C48,D48,E48) -> 0.6 | G48: Funding waterfall: retained AFFO → disposition proceeds → debt → ATM equity. % debt vs equity of the residual gap.
A49: Disposition / contribution cap rate % | B49: =Capital_Deployment!D11 -> 0.049 | C49: 0.05 | D49: 0.045 | E49: 0.058 | F49: =CHOOSE($B$5,C49,D49,E49) -> 0.05 | G49: Hist = FY2025 disp cap 4.9% [NAV anchor]. Bear: cap-rate shock widens. Also feeds AUM marks.
A51: 6 · SHARE COUNT ASSUMPTIONS (dilution + ATM residual)
A52: Starting diluted Core FFO share basis (M) | B52: =Share_Count!D8 -> 957.2 | F52: =CHOOSE($B$5,C52,D52,E52) -> 0 | G52: Hist = FY2025 957.2M (Core FFO basis — the cardinal per-share denominator). Forecast grows from here.
A53: Equity-comp share creep (annual %) | B53: N/A | C53: 0.003 | D53: 0.003 | E53: 0.004 | F53: =CHOOSE($B$5,C53,D53,E53) -> 0.003 | G53: Trailing-avg dilution from equity awards. Small, mechanical; slightly higher in bear (comp issued in down tape).
A54: ATM issuance pace ceiling ($mm/yr) | B54: N/A | C54: 1500 | D54: 2500 | E54: 500 | F54: =CHOOSE($B$5,C54,D54,E54) -> 1500 | G54: ATM modeled as funding-gap RESIDUAL with a historical-pace cap. Never issue equity the waterfall does not require.
A55: OP/LP unit conversion (annual %) | B55: =Share_Count!D9 -> 22.1 | C55: 0 | D55: 0 | E55: 0 | F55: =CHOOSE($B$5,C55,D55,E55) -> 0 | G55: Hist = 22.1M units outstanding FY2025. Conversions move units→shares (denominator-neutral on Core basis); hold flat.
A57: 7 · VALUATION ASSUMPTIONS (placeholders - keyed to same switch; populated in DCF/NAV/Comps phases)
A58: Dividend payout ratio (% of AFFO) | B58: =-Data_Collection!D55/Data_Collection!D74 -> 0.86844447 | C58: 0.87 | D58: 0.85 | E58: 0.92 | F58: =CHOOSE($B$5,C58,D58,E58) -> 0.87 | G58: Hist = FY2025 common div ÷ AFFO. Dividends are an OUTPUT of earnings × payout, with REIT min-distribution floor. Not an independent growth input.
A59: WACC / discount rate | B59: N/A | C59: 0.075 | D59: 0.07 | E59: 0.085 | F59: =CHOOSE($B$5,C59,D59,E59) -> 0.075 | G59: Phase 5 (DCF). Listed for completeness; bear world = higher rate AND weaker rents (correlated, never one alone).
A60: Exit / terminal cap rate | B60: N/A | C60: 0.05 | D60: 0.045 | E60: 0.06 | F60: =CHOOSE($B$5,C60,D60,E60) -> 0.05 | G60: Phase 5 terminal value. Keyed to switch so scenarios stay internally consistent.
A61: NAV cap rate (blended operating) | B61: =Capital_Deployment!D11 -> 0.049 | C61: 0.05 | D61: 0.045 | E61: 0.058 | F61: =CHOOSE($B$5,C61,D61,E61) -> 0.05 | G61: Phase 6 (NAV). Anchored to disposition cap rate evidence; bear marks assets down.
A62: Terminal growth (perpetuity) | B62: N/A | C62: 0.025 | D62: 0.03 | E62: 0.015 | F62: =CHOOSE($B$5,C62,D62,E62) -> 0.025 | G62: Phase 5 Gordon growth, if used. Bounded by long-run rent/inflation; not a free variable.
A64: NOTE: Only the 8 levers in §1–§5 move across cases (Phase 4 §7). Everything else is held identical so scenario deltas are attributable. Valuation §7 rates key off the SAME switch in Phases 5–6. Every input carries a source/rationale in column G.

Sheet Model
A1: PROLOGIS (PLD) - 5 YEAR INTEGRATED FORECAST
A2: Driven entirely by Assumptions!ACTIVE column (col F) - flip Assumptions!B5 to reprice every line. FY2025 (col B) = actual anchor (green links). Forecast FY2026–FY2030 (cols C–G).
A4: ($ in thousands) | B4: FY2025A | C4: FY2026E | D4: FY2027E | E4: FY2028E | F4: FY2029E | G4: FY2030E | H4: ="Scenario: "&Assumptions!B6 -> Scenario: BASE
A5: 1 · OPERATING FORECAST
A6: Average occupancy % - PLD share | B6: =Drivers!D6 -> 0.956 | C6: =Assumptions!$F$10 -> 0.953 | D6: =Assumptions!$F$10 -> 0.953 | E6: =Assumptions!$F$10 -> 0.953 | F6: =Assumptions!$F$10 -> 0.953 | G6: =Assumptions!$F$10 -> 0.953 | H6: Held at ACTIVE occupancy (level). Assumptions r10. Lever 2.
A7: Occupancy delta vs prior (bps→%) | B7: ="" | C7: =C6-B6 -> -0.003 | D7: =D6-C6 -> 0 | E7: =E6-D6 -> 0 | F7: =F6-E6 -> 0 | G7: =G6-F6 -> 0 | H7: Year-over-year occupancy change → SS NOI contribution.
A8: Market rent growth (glide Y1→terminal) | B8: ="" | C8: =Assumptions!$F$11 -> 0.03 | D8: =Assumptions!$F$11+(Assumptions!$F$12-Assumptions!$F$11)*1/4 -> 0.03125 | E8: =Assumptions!$F$11+(Assumptions!$F$12-Assumptions!$F$11)*2/4 -> 0.0325 | F8: =Assumptions!$F$11+(Assumptions!$F$12-Assumptions!$F$11)*3/4 -> 0.03375 | G8: =Assumptions!$F$12 -> 0.035 | H8: Linear glide: Y1 (Assump r11) → Y5 terminal (r12). Lever 1.
A9: Contractual escalators (in-place) | B9: ="" | C9: =Assumptions!$F$13 -> 0.04 | D9: =Assumptions!$F$13 -> 0.04 | E9: =Assumptions!$F$13 -> 0.04 | F9: =Assumptions!$F$13 -> 0.04 | G9: =Assumptions!$F$13 -> 0.04 | H9: Embedded annual bumps. Assumptions r13. Floor under SS NOI.
A10: Rollover spread (decaying Y1→terminal) | B10: =Drivers!D17 -> 0.438 | C10: =Assumptions!$F$18 -> 0.3 | D10: =Assumptions!$F$18+(Assumptions!$F$19-Assumptions!$F$18)*1/4 -> 0.25 | E10: =Assumptions!$F$18+(Assumptions!$F$19-Assumptions!$F$18)*2/4 -> 0.2 | F10: =Assumptions!$F$18+(Assumptions!$F$19-Assumptions!$F$18)*3/4 -> 0.15 | G10: =Assumptions!$F$19 -> 0.1 | H10: MTM stock depletes: spread glides Y1 (r18) → terminal (r19). Lever 3.
A11: MTM realization (% pool rolling) | B11: =Drivers!D23 -> 0.103 | C11: =Assumptions!$F$20 -> 0.13 | D11: =Assumptions!$F$20 -> 0.13 | E11: =Assumptions!$F$20 -> 0.13 | F11: =Assumptions!$F$20 -> 0.13 | G11: =Assumptions!$F$20 -> 0.13 | H11: % of pool repricing each year. Assumptions r20.
A12: Rollover NOI contribution | B12: ="" | C12: =C10*C11 -> 0.039 | D12: =D10*D11 -> 0.0325 | E12: =E10*E11 -> 0.026 | F12: =F10*F11 -> 0.0195 | G12: =G10*G11 -> 0.013 | H12: rollover spread × % pool rolling. The contracted-growth runway.
A13: Same-store NOI growth % | B13: =Drivers!D12 -> 0.063 | C13: =C9+C7+C12 -> 0.076 | D13: =D9+D7+D12 -> 0.0725 | E13: =E9+E7+E12 -> 0.066 | F13: =F9+F7+F12 -> 0.0595 | G13: =G9+G7+G12 -> 0.053 | H13: escalators + occupancy delta + rollover contribution. output of the bridge.
A15: Property NOI | B15: =Historicals!D31 -> 6194767 | C15: =B15*(1+C13) -> 6665569.3 | D15: =C15*(1+D13) -> 7148823.1 | E15: =D15*(1+E13) -> 7620645.4 | F15: =E15*(1+F13) -> 8074073.8 | G15: =F15*(1+G13) -> 8501999.7 | H15: Same-store base compounds at SS NOI growth. Development NOI added below (rDEV).
A16: Operating expense ratio | B16: =-Historicals!D10/Historicals!D6 -> 0.2407354 | C16: =Assumptions!$F$15 -> 0.245 | D16: =Assumptions!$F$15 -> 0.245 | E16: =Assumptions!$F$15 -> 0.245 | F16: =Assumptions!$F$15 -> 0.245 | G16: =Assumptions!$F$15 -> 0.245 | H16: Assumptions r15. Rental exp ÷ rental rev.
A17: Rental revenue | B17: =Historicals!D6 -> 8158904 | C17: =C36/(1-C16) -> 8966571.4 | D17: =D36/(1-D16) -> 10088762 | E17: =E36/(1-E16) -> 11226805 | F17: =F36/(1-F16) -> 12373716 | G17: =G36/(1-G16) -> 13522501 | H17: total property noi (R36) ÷ (1 − opex ratio). Revenue is an OUTPUT.
A18: Rental expenses | B18: =Historicals!D10 -> -1964137 | C18: =-(C17-C36) -> -2196810 | D18: =-(D17-D36) -> -2471746.6 | E18: =-(E17-E36) -> -2750567.1 | F18: =-(F17-F36) -> -3031560.5 | G18: =-(G17-G36) -> -3313012.8 | H18: −(rental revenue − Property NOI).
A20: 2 · DEVELOPMENT FORECAST (Approach B - two streams; $mm except NOI in $000s)
A21: LOGISTICS
A22: Logistics starts - TEI ($mm) | B22: =Development!D14/1000 -> 2.955389 | C22: =Assumptions!$F$25 -> 4000 | D22: =C22*(1+Assumptions!$F$26) -> 4200 | E22: =D22*(1+Assumptions!$F$26) -> 4410 | F22: =E22*(1+Assumptions!$F$26) -> 4630.5 | G22: =F22*(1+Assumptions!$F$26) -> 4862.025 | H22: Y1 = Assump r25 (guidance); grows at r26. Lever 4. $mm.
A23: Logistics - stabilized yield on cost | B23: =Development!D19 -> 0.067 | C23: =Assumptions!$F$27 -> 0.065 | D23: =Assumptions!$F$27 -> 0.065 | E23: =Assumptions!$F$27 -> 0.065 | F23: =Assumptions!$F$27 -> 0.065 | G23: =Assumptions!$F$27 -> 0.065 | H23: Assumptions r27.
A24: Logistics - value-creation margin | B24: =Development!D20 -> 0.251 | C24: =Assumptions!$F$28 -> 0.2 | D24: =Assumptions!$F$28 -> 0.2 | E24: =Assumptions!$F$28 -> 0.2 | F24: =Assumptions!$F$28 -> 0.2 | G24: =Assumptions!$F$28 -> 0.2 | H24: Assumptions r28. Lever 5.
A25: Logistics stabilizations - TEI ($mm) | B25: =Development!D18 -> 2260 | C25: =B22 -> 2.955389 | D25: =C22 -> 4000 | E25: =D22 -> 4200 | F25: =E22 -> 4410 | G25: =F22 -> 4630.5 | H25: prior-year starts (≈6-qtr lag, Assump r33, simplified to 1yr in annual cols - see Notes).)
A26: Logistics delivered NOI ($000s) | B26: ="" | C26: =C25*1000*C23 -> 192.10029 | D26: =D25*1000*D23 -> 260000 | E26: =E25*1000*E23 -> 273000 | F26: =F25*1000*F23 -> 286650 | G26: =G25*1000*G23 -> 300982.5 | H26: stabilized tei × yield, ×1000 to $000s.
A27: DATA CENTERS
A28: DC starts - TEI ($mm) | B28: =Development!E13 -> 1300 | C28: =Assumptions!$F$29 -> 1300 | D28: =C28*(1+Assumptions!$F$30) -> 1430 | E28: =D28*(1+Assumptions!$F$30) -> 1573 | F28: =E28*(1+Assumptions!$F$30) -> 1730.3 | G28: =F28*(1+Assumptions!$F$30) -> 1903.33 | H28: Y1 = Assump r29; grows at r30. Separate stream.
A29: DC - stabilized yield on cost | B29: ="" | C29: =Assumptions!$F$31 -> 0.08 | D29: =Assumptions!$F$31 -> 0.08 | E29: =Assumptions!$F$31 -> 0.08 | F29: =Assumptions!$F$31 -> 0.08 | G29: =Assumptions!$F$31 -> 0.08 | H29: Assumptions r31.
A30: DC - value-creation margin | B30: ="" | C30: =Assumptions!$F$32 -> 0.25 | D30: =Assumptions!$F$32 -> 0.25 | E30: =Assumptions!$F$32 -> 0.25 | F30: =Assumptions!$F$32 -> 0.25 | G30: =Assumptions!$F$32 -> 0.25 | H30: Assumptions r32.
A31: DC stabilizations - TEI ($mm) | B31: ="" | C31: =B28 -> 1300 | D31: =C28 -> 1300 | E31: =D28 -> 1430 | F31: =E28 -> 1573 | G31: =F28 -> 1730.3 | H31: prior-year dc starts (longer build in reality - see Notes).)
A32: DC delivered NOI ($000s) | B32: ="" | C32: =C31*1000*C29 -> 104000 | D32: =D31*1000*D29 -> 104000 | E32: =E31*1000*E29 -> 114400 | F32: =F31*1000*F29 -> 125840 | G32: =G31*1000*G29 -> 138424 | H32: stabilized tei × yield, ×1000.
A33: Total development NOI delivered (cumulative) | B33: ="" | C33: =C26+C32 -> 104192.1 | D33: =C33+D26+D32 -> 468192.1 | E33: =D33+E26+E32 -> 855592.1 | F33: =E33+F26+F32 -> 1268082.1 | G33: =F33+G26+G32 -> 1707488.6 | H33: Cumulative NOI from stabilized developments entering the operating pool.
A34: Stabilized TEI → contributions (AUM feed, $mm) | B34: ="" | C34: =(C25+C31)*Assumptions!$F$34 -> 521.18216 | D34: =(D25+D31)*Assumptions!$F$34 -> 2120 | E34: =(E25+E31)*Assumptions!$F$34 -> 2252 | F34: =(F25+F31)*Assumptions!$F$34 -> 2393.2 | G34: =(G25+G31)*Assumptions!$F$34 -> 2544.32 | H34: stabilized tei × contribution share (Assump r34). Feeds Strategic Capital + Deployment.
A36: TOTAL PROPERTY NOI (same-store + development) | B36: =Historicals!D31 -> 6194767 | C36: =C15+C33 -> 6769761.4 | D36: =D15+D33 -> 7617015.2 | E36: =E15+E33 -> 8476237.5 | F36: =F15+F33 -> 9342155.9 | G36: =G15+G33 -> 10209488 | H36: Same-store NOI (r15) + cumulative development NOI (r33).
A38: 3 · STRATEGIC CAPITAL FORECAST (AUM in $B; fees/promotes in $000s)
A39: Third-party AUM ($B) | B39: =Strategic_Capital!D8 -> 68 | C39: =B39*(1+Assumptions!$F$38) -> 71.4 | D39: =C39*(1+Assumptions!$F$38) -> 74.97 | E39: =D39*(1+Assumptions!$F$38) -> 78.7185 | F39: =E39*(1+Assumptions!$F$38) -> 82.654425 | G39: =F39*(1+Assumptions!$F$38) -> 86.787146 | H39: Grows at Assump r38 (contribution-driven). Lever 6.
A40: Gross AUM ($B) | B40: =Strategic_Capital!D6 -> 230 | C40: =B40*(1+Assumptions!$F$38) -> 241.5 | D40: =C40*(1+Assumptions!$F$38) -> 253.575 | E40: =D40*(1+Assumptions!$F$38) -> 266.25375 | F40: =E40*(1+Assumptions!$F$38) -> 279.56644 | G40: =F40*(1+Assumptions!$F$38) -> 293.54476 | H40: Tracks 3rd-party AUM growth.
A41: Avg 3rd-party AUM ($B) | B41: ="" | C41: =(B39+C39)/2 -> 69.7 | D41: =(C39+D39)/2 -> 73.185 | E41: =(D39+E39)/2 -> 76.84425 | F41: =(E39+F39)/2 -> 80.686463 | G41: =(F39+G39)/2 -> 84.720786 | H41: Average of opening/closing for fee calc.
A42: Recurring fee revenue ($000s) | B42: =Strategic_Capital!D11 -> 374044 | C42: =C41*1000000*Assumptions!$F$37 -> 383350 | D42: =D41*1000000*Assumptions!$F$37 -> 402517.5 | E42: =E41*1000000*Assumptions!$F$37 -> 422643.38 | F42: =F41*1000000*Assumptions!$F$37 -> 443775.54 | G42: =G41*1000000*Assumptions!$F$37 -> 465964.32 | H42: avg 3rd-party aum ($b→$000s) × effective fee rate (Assump r37).)
A43: Transactional fees ($000s) | B43: =Strategic_Capital!D12 -> 32512 | C43: =B43*(1+Assumptions!$F$39) -> 33487.36 | D43: =C43*(1+Assumptions!$F$39) -> 34491.981 | E43: =D43*(1+Assumptions!$F$39) -> 35526.74 | F43: =E43*(1+Assumptions!$F$39) -> 36592.542 | G43: =F43*(1+Assumptions!$F$39) -> 37690.319 | H43: Grows at Assump r39; tied to deployment pace.
A44: Strategic capital expenses ($000s) | B44: =Historicals!D11 -> -270517 | C44: =-(C42+C43)*Assumptions!$F$42 -> -229260.55 | D44: =-(D42+D43)*Assumptions!$F$42 -> -240355.21 | E44: =-(E42+E43)*Assumptions!$F$42 -> -251993.56 | F44: =-(F42+F43)*Assumptions!$F$42 -> -264202.45 | G44: =-(G42+G43)*Assumptions!$F$42 -> -277010.05 | H44: −(recurring+transactional fees) × expense ratio (Assump r42).
A45: Net promote income (expense) ($000s) | B45: =Strategic_Capital!D17 -> -48960 | C45: =Assumptions!$F$40*1000 -> -50000 | D45: =Assumptions!$F$41*1000 -> 0 | E45: =Assumptions!$F$41*1000 -> 0 | F45: =Assumptions!$F$41*1000 -> 0 | G45: =Assumptions!$F$41*1000 -> 0 | H45: KEPT SEPARATE. FY26 = Assump r40 (guided); FY27+ = r41. Base FY27+ = 0. Lever 8. ×1000 to $000s.
A46: Fee-related earnings (FRE) ($000s) | B46: ="" | C46: =C42+C43+C44 -> 187576.81 | D46: =D42+D43+D44 -> 196654.27 | E46: =E42+E43+E44 -> 206176.55 | F46: =F42+F43+F44 -> 216165.64 | G46: =G42+G43+G44 -> 226644.59 | H46: recurring + transactional fees − SC expenses (ex-promote).
A47: 4 · CAPITAL DEPLOYMENT FORECAST ($mm)
A48: Acquisitions ($mm) | B48: =Capital_Deployment!D6/1000 -> 1710 | C48: =B48*(1+Assumptions!$F$38) -> 1795.5 | D48: =C48*(1+Assumptions!$F$38) -> 1885.275 | E48: =D48*(1+Assumptions!$F$38) -> 1979.5388 | F48: =E48*(1+Assumptions!$F$38) -> 2078.5157 | G48: =F48*(1+Assumptions!$F$38) -> 2182.4415 | H48: Held at policy pace, grows with AUM (Assump r38). $mm.
A49: Dispositions + contributions ($mm) | B49: =Capital_Deployment!D10/1000 -> 2170.174 | C49: =C34 -> 521.18216 | D49: =D34 -> 2120 | E49: =E34 -> 2252 | F49: =F34 -> 2393.2 | G49: =G34 -> 2544.32 | H49: development conveyor contributions (R34) - consistent with Strategic Capital AUM feed.
A50: Disposition cap rate % | B50: =Capital_Deployment!D11 -> 0.049 | C50: =Assumptions!$F$49 -> 0.05 | D50: =Assumptions!$F$49 -> 0.05 | E50: =Assumptions!$F$49 -> 0.05 | F50: =Assumptions!$F$49 -> 0.05 | G50: =Assumptions!$F$49 -> 0.05 | H50: Assumptions r49 [NAV anchor].
A52: 5 · CORPORATE & FFO BUILD ($000s)
A53: General & administrative | B53: =Historicals!D12 -> -469114 | C53: =B53*(1+Assumptions!$F$13) -> -487878.56 | D53: =C53*(1+Assumptions!$F$13) -> -507393.7 | E53: =D53*(1+Assumptions!$F$13) -> -527689.45 | F53: =E53*(1+Assumptions!$F$13) -> -548797.03 | G53: =F53*(1+Assumptions!$F$13) -> -570748.91 | H53: Grows at escalator rate (Assump r13) as G&A proxy. Flag: simplifying assumption.
A54: Earnings from unconsolidated entities, net | B54: =Historicals!D19 -> 402531 | C54: =B54*(1+Assumptions!$F$38) -> 422657.55 | D54: =B54*(1+Assumptions!$F$38) -> 422657.55 | E54: =B54*(1+Assumptions!$F$38) -> 422657.55 | F54: =B54*(1+Assumptions!$F$38) -> 422657.55 | G54: =B54*(1+Assumptions!$F$38) -> 422657.55 | H54: Grows with AUM (Assump r38) as JV-earnings proxy.
A55: Preferred dividends | B55: =-Data_Collection!D20 -> -5882 | C55: =B55 -> -5882 | D55: =B55 -> -5882 | E55: =B55 -> -5882 | F55: =B55 -> -5882 | G55: =B55 -> -5882 | H55: Held flat (small, fixed).
A56: Adjusted EBITDA (proxy) | B56: =Historicals!D31+Strategic_Capital!D13+Historicals!D11+Historicals!D12 -> 5861692 | C56: =C36+C46+C53+C54 -> 6892117.2 | D56: =D36+D46+D53+D54 -> 7728933.3 | E56: =E36+E46+E53+E54 -> 8577382.1 | F56: =F36+F46+F53+F54 -> 9432182 | G56: =G36+G46+G53+G54 -> 10288042 | H56: NOI + FRE − G&A + JV earnings. Used for Debt/EBITDA. Proxy - see Notes.
A57: 6 · DEBT FORECAST - FUNDING WATERFALL ($000s unless noted)
A58: Funding uses: dev + acquisitions ($000s) | B58: ="" | C58: =(C22+C28+C48)*1000 -> 7095500 | D58: =(D22+D28+D48)*1000 -> 7515275 | E58: =(E22+E28+E48)*1000 -> 7962538.8 | F58: =(F22+F28+F48)*1000 -> 8439315.7 | G58: =(G22+G28+G48)*1000 -> 8947796.5 | H58: Logistics + DC starts + acquisitions ($mm→$000s).
A59: Source 1: Retained AFFO (after dividends) | B59: ="" | C59: =B76+B78 -> 570299 | D59: =C76+C78 -> 569562.06 | E59: =D76+D78 -> 648563.2 | F59: =E76+E78 -> 724621.46 | G59: =F76+F78 -> 800825.93 | H59: AFFO − common dividends. Filled from FFO block.
A60: Source 2: Disposition/contribution proceeds | B60: ="" | C60: =C49*1000 -> 521182.16 | D60: =D49*1000 -> 2120000 | E60: =E49*1000 -> 2252000 | F60: =F49*1000 -> 2393200 | G60: =G49*1000 -> 2544320 | H60: Dispositions+contributions ($mm→$000s).
A61: Source 3: Debt issuance (to hold leverage) | B61: ="" | C61: =MAX(0,(C58-C59-C60))*Assumptions!$F$48 -> 3602411.3 | D61: =MAX(0,(D58-D59-D60))*Assumptions!$F$48 -> 2895427.8 | E61: =MAX(0,(E58-E59-E60))*Assumptions!$F$48 -> 3037185.3 | F61: =MAX(0,(F58-F59-F60))*Assumptions!$F$48 -> 3192896.5 | G61: =MAX(0,(G58-G59-G60))*Assumptions!$F$48 -> 3361590.3 | H61: % of residual gap funded by debt (assump R48). filled after retained affo.
A62: Source 4: ATM equity (residual) | B62: ="" | C62: =MIN(MAX(0,(C58-C59-C60)-C61),Assumptions!$F$54*1000) -> 1500000 | D62: =MIN(MAX(0,(D58-D59-D60)-D61),Assumptions!$F$54*1000) -> 1500000 | E62: =MIN(MAX(0,(E58-E59-E60)-E61),Assumptions!$F$54*1000) -> 1500000 | F62: =MIN(MAX(0,(F58-F59-F60)-F61),Assumptions!$F$54*1000) -> 1500000 | G62: =MIN(MAX(0,(G58-G59-G60)-G61),Assumptions!$F$54*1000) -> 1500000 | H62: Residual funding gap, capped at ATM ceiling (Assump r54). Filled below.
A63: Debt balance (period-end) | B63: =Data_Collection!D33 -> 35037073 | C63: =B63+C61 -> 38639484 | D63: =C63+D61 -> 41534912 | E63: =D63+E61 -> 44572097 | F63: =E63+F61 -> 47764994 | G63: =F63+G61 -> 51126584 | H63: Prior balance + net debt issuance. Anchor = FY25 BS debt $35.0B.
A64: Interest expense | B64: =Historicals!D20 -> -1002344 | C64: =-((B63+C63)/2)*Debt!D11 -> -1215663.2 | D64: =-((C63+D63)/2)*Debt!D11 -> -1322877.5 | E64: =-((D63+E63)/2)*Debt!D11 -> -1420765.7 | F64: =-((E63+F63)/2)*Debt!D11 -> -1523562 | G64: =-((F63+G63)/2)*Debt!D11 -> -1631711 | H64: avg debt balance × wtd-avg rate (Debt!D12). New-issue cost (Assump r45) applies to increments - see Notes.
A65: Debt / Adjusted EBITDA (x) | B65: =Debt!D15 -> 5.3 | C65: =C63/C56 -> 5.6063301 | D65: =D63/D56 -> 5.3739514 | E65: =E63/E56 -> 5.1964687 | F65: =F63/F56 -> 5.064045 | G65: =G63/G56 -> 4.9695157 | H65: Leverage check vs target (Assump r46 = 4.8x).
A67: 7 · SHARE COUNT FORECAST (millions; Core FFO denominator)
A68: Core FFO diluted share/unit basis (M) | B68: =Share_Count!D8 -> 957.2 | C68: =B68*(1+Assumptions!$F$53)+C62/1000/Data_Collection!$D$163 -> 971.82156 | D68: =C68*(1+Assumptions!$F$53)+D62/1000/Data_Collection!$D$163 -> 986.48699 | E68: =D68*(1+Assumptions!$F$53)+E62/1000/Data_Collection!$D$163 -> 1001.1964 | F68: =E68*(1+Assumptions!$F$53)+F62/1000/Data_Collection!$D$163 -> 1015.95 | G68: =F68*(1+Assumptions!$F$53)+G62/1000/Data_Collection!$D$163 -> 1030.7478 | H68: Prior × (1+equity-comp creep, Assump r53) + ATM shares (ATM$ ÷ price). Separate Core FFO denominator.
A69: o/w equity-comp dilution (M) | B69: ="" | C69: =B68*Assumptions!$F$53 -> 2.8716 | D69: =C68*Assumptions!$F$53 -> 2.9154647 | E69: =D68*Assumptions!$F$53 -> 2.959461 | F69: =E68*Assumptions!$F$53 -> 3.0035892 | G69: =F68*Assumptions!$F$53 -> 3.0478499 | H69: Assumptions r53.
A70: o/w ATM dilution (M) | B70: ="" | C70: =C62/1000/Data_Collection!$D$163 -> 11.749961 | D70: =D62/1000/Data_Collection!$D$163 -> 11.749961 | E70: =E62/1000/Data_Collection!$D$163 -> 11.749961 | F70: =F62/1000/Data_Collection!$D$163 -> 11.749961 | G70: =G62/1000/Data_Collection!$D$163 -> 11.749961 | H70: ATM $ ÷ share price (Data_Collection r165).
A71: 8 · FFO FORECAST ($000s except per-share)
A72: Core FFO | B72: =FFO_Recon!D28 -> 5561300 | C72: =C36+C46+C45+C53+C64+C54+C55 -> 5620572 | D72: =D36+D46+D45+D53+D64+D54+D55 -> 6400173.7 | E72: =E36+E46+E45+E53+E64+E54+E55 -> 7150734.5 | F72: =F36+F46+F45+F53+F64+F54+F55 -> 7902738 | G72: =G36+G46+G45+G53+G64+G54+G55 -> 8650448.5 | H72: noi + fre + net promote − G&A − interest + JV earnings − preferred. (G&A/int/pref carry signs.)
A73: Core FFO per share | B73: =FFO_Recon!D30 -> 5.8099666 | C73: =C72/1000/C68 -> 5.7835432 | D73: =D72/1000/D68 -> 6.4878441 | E73: =E72/1000/E68 -> 7.1421895 | F73: =F72/1000/F68 -> 7.7786686 | G73: =G72/1000/G68 -> 8.3924009 | H73: core ffo ÷ Core FFO share basis. The headline per-share metric.
A74: Core FFO/share ex-promotes | B74: ="" | C74: =(C72-C45)/1000/C68 -> 5.834993 | D74: =(D72-D45)/1000/D68 -> 6.4878441 | E74: =(E72-E45)/1000/E68 -> 7.1421895 | F74: =(F72-F45)/1000/F68 -> 7.7786686 | G74: =(G72-G45)/1000/G68 -> 8.3924009 | H74: Strips net promote - how PLD now guides.
A75: NAREIT FFO | B75: =FFO_Recon!D10 -> 5679525 | C75: =C72*(FFO_Recon!$D$10/FFO_Recon!$D$28) -> 5740057 | D75: =D72*(FFO_Recon!$D$10/FFO_Recon!$D$28) -> 6536232 | E75: =E72*(FFO_Recon!$D$10/FFO_Recon!$D$28) -> 7302748.5 | F75: =F72*(FFO_Recon!$D$10/FFO_Recon!$D$28) -> 8070738.5 | G75: =G72*(FFO_Recon!$D$10/FFO_Recon!$D$28) -> 8834344.2 | H75: core ffo × historical NAREIT/Core ratio (FY25). Forecast simplification - see Notes.
A76: AFFO | B76: =FFO_Recon!D45 -> 4335044 | C76: =C72*(FFO_Recon!$D$45/FFO_Recon!$D$28) -> 4381246.6 | D76: =D72*(FFO_Recon!$D$45/FFO_Recon!$D$28) -> 4988947.7 | E76: =E72*(FFO_Recon!$D$45/FFO_Recon!$D$28) -> 5574011.2 | F76: =F72*(FFO_Recon!$D$45/FFO_Recon!$D$28) -> 6160199.4 | G76: =G72*(FFO_Recon!$D$45/FFO_Recon!$D$28) -> 6743041.2 | H76: core ffo × historical AFFO/Core ratio (FY25 ~78%). Forecast simplification - see Notes.
A77: AFFO per share | B77: =FFO_Recon!D45/1000/Share_Count!D8 -> 4.5288801 | C77: =C76/1000/C68 -> 4.508283 | D77: =D76/1000/D68 -> 5.0572869 | E77: =E76/1000/E68 -> 5.5673504 | F77: =F76/1000/F68 -> 6.0634871 | G77: =G76/1000/G68 -> 6.5418926 | H77: affo ÷ Core FFO share basis.
A78: Common dividends & distributions | B78: =Data_Collection!D55 -> -3764745 | C78: =-C76*Assumptions!$F$58 -> -3811684.6 | D78: =-D76*Assumptions!$F$58 -> -4340384.5 | E78: =-E76*Assumptions!$F$58 -> -4849389.8 | F78: =-F76*Assumptions!$F$58 -> -5359373.5 | G78: =-G76*Assumptions!$F$58 -> -5866445.8 | H78: −AFFO × payout ratio (Assump r58). Dividend is an OUTPUT.
A81: NOTES & FLAGGED MODELING ASSUMPTIONS
A82: 1. Stabilization lag: Assumptions r33 = 6 quarters (~1.5yr). In annual columns this is simplified to a 1-year lag (stabilizations = prior-year starts). Refine to fractional-year split if quarterly granularity is added.
A83: 2. Development NOI is cumulative: each year stabilized TEI x yield is added to a running pool. No decay/disposition of stabilized assets is modeled within the 5-yr window (conservative - assets season into same-store but are not double-counted because same-store grows only at SS NOI%).
A84: 3. NAREIT FFO and AFFO are forecast as Core FFO x the FY2025 historical ratio (NAREIT/Core ~1.02; AFFO/Core ~0.78). This holds the bridge mix constant. Acceptable for a 5-yr outlook; for precision, project each AFFO non-cash line (straight-line rent, TI/LC, stock comp) off NOI/leasing drivers.
A85: 4. Adjusted EBITDA is a proxy (NOI + FRE - G&A + JV earnings); it excludes some non-cash add-backs in the official Adjusted EBITDA reconciliation. Sufficient for the Debt/EBITDA leverage check; not a substitute for the full reconciliation.
A86: 5. Interest expense uses the blended historical wtd-avg rate (Debt!D12) on the average balance. The new-issue cost (Assumptions r45) and refi rate (r47) are available levers but are not yet applied incrementally to new vs. maturing debt - refine with a maturity ladder (Debt tab instrument detail is still a stub).
A87: 6. G&A and JV earnings are grown by simple proxies (escalator and AUM growth respectively) - flag for refinement.
A88: 7. CIRCULARITY: the funding waterfall (interest -> Core FFO -> AFFO -> retained AFFO -> debt issuance -> debt balance -> interest) is a genuine loop. If your Excel shows 0s or a circular warning, enable iterative calculation (File > Options > Formulas > Enable iterative calculation, 100 iters, 0.001). LibreOffice/this recalc engine resolves it iteratively.
A89: 8. Dividends are an OUTPUT (AFFO x payout ratio, Assumptions r58), not an input. REIT minimum-distribution floor not separately enforced - add if payout assumption falls below ~90% of taxable income.
A90: 9. Acquisitions grown with AUM as a policy proxy; dispositions/contributions tied to the development conveyor for internal consistency with Strategic Capital AUM growth.

Sheet DCF
A1: PROLOGIS (PLD) - DISCOUNTED CASH FLOW (DCF)
A2: Equity DCF on AFFO. AFFO is a levered (post-interest) cash flow, so its present value IS equity value - no debt is subtracted (that would double-count leverage); Enterprise Value is shown as a derived reconciliation. Discount rate & terminal growth link to Assumptions and flex with the scenario switch. $ in thousands unless noted.
A3: ($ in thousands) | B3: FY2026E | C3: FY2027E | D3: FY2028E | E3: FY2029E | F3: FY2030E | G3: Total / Term.
A4: 1 · DISCOUNT RATE & TERMINAL ASSUMPTIONS (linked from Assumptions)
A5: Equity discount rate (Assumptions r59) | B5: =Assumptions!F59 -> 0.075 | H5: Linked to Assumptions r59 (ACTIVE, switch-driven; Base 7.50% / Bull 7.00% / Bear 8.50%). Scoped there as "WACC/discount rate"; used here as the EQUITY discount rate for the levered AFFO stream. For a pure cost-of-equity one would typically set this ~100bps above WACC - adjustable in Assumptions.
A6: Terminal growth g (Assumptions r62) | B6: =Assumptions!F62 -> 0.025 | H6: Linked to Assumptions r62 (Base 2.5% / Bull 3.0% / Bear 1.5%). Bounded by long-run rent/inflation; g ≤ inflation+1%.
A7: Spread (discount rate − g) | B7: =B5-B6 -> 0.05
A8: Memo: 10- yr UST risk- free (Data_Collection) | B8: =Data_Collection!E164 -> 0.0449
A9: Memo: exit/terminal cap rate (Assumptions r60) | B9: =Assumptions!F60 -> 0.05
A10: 2 · FORECAST CASH FLOWS (from Model FY2026–FY2030)
A11: AFFO - PRIMARY cash- flow stream | B11: =Model!C76 -> 4381246.6 | C11: =Model!D76 -> 4988947.7 | D11: =Model!E76 -> 5574011.2 | E11: =Model!F76 -> 6160199.4 | F11: =Model!G76 -> 6743041.2 | H11: Green link to Model r76. AFFO = cash earnings to common+OP-unit holders after recurring capex and TI/LC. The equity claim.
A12: AFFO per share ($) | B12: =Model!C77 -> 4.508283 | C12: =Model!D77 -> 5.0572869 | D12: =Model!E77 -> 5.5673504 | E12: =Model!F77 -> 6.0634871 | F12: =Model!G77 -> 6.5418926
A13: Core FFO - cross- check stream | B13: =Model!C72 -> 5620572 | C13: =Model!D72 -> 6400173.7 | D13: =Model!E72 -> 7150734.5 | E13: =Model!F72 -> 7902738 | F13: =Model!G72 -> 8650448.5 | H13: Core FFO includes non-cash items AFFO removes (straight-line rent, etc.); used only as an upper-bound cross-check (Section 6).
A14: Core FFO per share ($) | B14: =Model!C73 -> 5.7835432 | C14: =Model!D73 -> 6.4878441 | D14: =Model!E73 -> 7.1421895 | E14: =Model!F73 -> 7.7786686 | F14: =Model!G73 -> 8.3924009
A15: 3 · DISCOUNT FACTORS & PV OF EXPLICIT AFFO (end- of- year convention)
A16: Period (t, years) | B16: 1 | C16: 2 | D16: 3 | E16: 4 | F16: 5
A17: Discount factor = 1/(1+r)^t | B17: =1/(1+$B$5)^B16 -> 0.93023256 | C17: =1/(1+$B$5)^C16 -> 0.86533261 | D17: =1/(1+$B$5)^D16 -> 0.80496057 | E17: =1/(1+$B$5)^E16 -> 0.74880053 | F17: =1/(1+$B$5)^F16 -> 0.69655863
A18: PV of AFFO ($000s) | B18: =B11*B17 -> 4075578.3 | C18: =C11*C17 -> 4317099.1 | D18: =D11*D17 -> 4486859.2 | E18: =E11*E17 -> 4612760.6 | F18: =F11*F17 -> 4696923.5 | G18: =SUM(B18:F18) -> 22189221 | H18: Each year: AFFO × discount factor. Total (col G) = PV of the explicit 5-year AFFO stream.
A20: 4 · TERMINAL VALUE - GORDON GROWTH
A21: Terminal- year AFFO (FY2030) | B21: =F11 -> 6743041.2
A22: Terminal AFFO × (1+g) | B22: =B21*(1+$B$6) -> 6911617.2
A23: Terminal value = AFFO₍FY30₎×(1+g)/(r−g) | B23: =B22/($B$5-$B$6) -> 1.3823234e+08 | H23: Gordon-growth perpetuity at the end of FY2030 (undiscounted).
A24: Discount factor at t = 5 | B24: =F17 -> 0.69655863
A25: PV of terminal value ($000s) | B25: =B23*B24 -> 96286932
A26: Memo: implied terminal AFFO multiple (TV ÷ AFFO₍FY30₎) | B26: =B23/B21 -> 20.5 | H26: Equals 1/(r−g) applied to forward AFFO. Sanity-check vs where quality REITs trade on AFFO.
A28: 5 · DCF VALUATION
A29: PV of explicit AFFO (FY2026–2030) | B29: =G18 -> 22189221
A30: + PV of terminal value | B30: =B25 -> 96286932
A31: EQUITY VALUE ($000s) | B31: =B29+B30 -> 1.1847615e+08 | H31: PV of the AFFO (equity) stream + PV of terminal value. AFFO accrues to equity, so this is equity value directly - NO debt subtraction.
A32: ÷ Core FFO share/unit count (M) | B32: =Share_Count!D8 -> 957.2
A33: DCF VALUE PER SHARE ($) | B33: =B31/1000/B32 -> 123.77367
A34: Memo: TV as % of equity value | B34: =B30/B31 -> 0.8127115
A35: Implied ENTERPRISE VALUE (reconciliation) | B35: =B31+(Data_Collection!E33-Data_Collection!E143)+Data_Collection!E37+Data_Collection!E39-Data_Collection!E30 -> 1.5731903e+08 | H35: Derived: Equity + net debt (face − cash) + preferred + NCI. EV is reconciled FROM equity because AFFO is an equity stream (the reverse of an unlevered-FCF DCF).
A36: Current share price ($) | B36: =NAV!B79 -> 145 | H36: Linked to the current-price input already on the NAV tab (single source).
A37: Implied upside / (downside) to DCF value | B37: =B33/B36-1 -> -0.14638851
A39: 6 · CORE FFO CROSS- CHECK (secondary; upper bound)
A40: PV of explicit Core FFO ($000s) | B40: =SUMPRODUCT(B13:F13,B17:F17) -> 28465896
A41: Terminal value on Core FFO | B41: =F13*(1+$B$6)/($B$5-$B$6) -> 1.7733419e+08
A42: + PV terminal (Core FFO) | B42: =B41*F17 -> 1.2352366e+08
A43: Equity value - Core FFO basis ($000s) | B43: =B40+B42 -> 1.5198956e+08
A44: Per share - Core FFO basis ($) | B44: =B43/1000/B32 -> 158.78558 | H44: Core FFO is pre-recurring-capex, so this overstates distributable cash → an upper bound. AFFO (Section 5) is the primary DCF output.
A46: 7 · SENSITIVITY - DCF/share ($): discount rate (down) × terminal growth (across)
A47: r ↓ \ g → | B47: 0.015 | C47: 0.02 | D47: 0.025 | E47: 0.03 | F47: 0.035
A48: 0.065 | B48: =($B$11/(1+$A48)^1+$C$11/(1+$A48)^2+$D$11/(1+$A48)^3+$E$11/(1+$A48)^4+$F$11/(1+$A48)^5+($F$11*(1+B$47)/($A48-B$47))/(1+$A48)^5)/1000/$B$32 -> 128.23416 | C48: =($B$11/(1+$A48)^1+$C$11/(1+$A48)^2+$D$11/(1+$A48)^3+$E$11/(1+$A48)^4+$F$11/(1+$A48)^5+($F$11*(1+C$47)/($A48-C$47))/(1+$A48)^5)/1000/$B$32 -> 140.4028 | D48: =($B$11/(1+$A48)^1+$C$11/(1+$A48)^2+$D$11/(1+$A48)^3+$E$11/(1+$A48)^4+$F$11/(1+$A48)^5+($F$11*(1+D$47)/($A48-D$47))/(1+$A48)^5)/1000/$B$32 -> 155.61361 | E48: =($B$11/(1+$A48)^1+$C$11/(1+$A48)^2+$D$11/(1+$A48)^3+$E$11/(1+$A48)^4+$F$11/(1+$A48)^5+($F$11*(1+E$47)/($A48-E$47))/(1+$A48)^5)/1000/$B$32 -> 175.17036 | F48: =($B$11/(1+$A48)^1+$C$11/(1+$A48)^2+$D$11/(1+$A48)^3+$E$11/(1+$A48)^4+$F$11/(1+$A48)^5+($F$11*(1+F$47)/($A48-F$47))/(1+$A48)^5)/1000/$B$32 -> 201.24602 | H48: Each cell re-runs the full AFFO DCF at that discount rate (row) and terminal growth (column). Center cell (7.50% × 2.5%) reconciles to the DCF/share above.
A49: 0.07 | B49: =($B$11/(1+$A49)^1+$C$11/(1+$A49)^2+$D$11/(1+$A49)^3+$E$11/(1+$A49)^4+$F$11/(1+$A49)^5+($F$11*(1+B$47)/($A49-B$47))/(1+$A49)^5)/1000/$B$32 -> 116.20699 | C49: =($B$11/(1+$A49)^1+$C$11/(1+$A49)^2+$D$11/(1+$A49)^3+$E$11/(1+$A49)^4+$F$11/(1+$A49)^5+($F$11*(1+C$47)/($A49-C$47))/(1+$A49)^5)/1000/$B$32 -> 125.97835 | D49: =($B$11/(1+$A49)^1+$C$11/(1+$A49)^2+$D$11/(1+$A49)^3+$E$11/(1+$A49)^4+$F$11/(1+$A49)^5+($F$11*(1+D$47)/($A49-D$47))/(1+$A49)^5)/1000/$B$32 -> 137.92113 | E49: =($B$11/(1+$A49)^1+$C$11/(1+$A49)^2+$D$11/(1+$A49)^3+$E$11/(1+$A49)^4+$F$11/(1+$A49)^5+($F$11*(1+E$47)/($A49-E$47))/(1+$A49)^5)/1000/$B$32 -> 152.84961 | F49: =($B$11/(1+$A49)^1+$C$11/(1+$A49)^2+$D$11/(1+$A49)^3+$E$11/(1+$A49)^4+$F$11/(1+$A49)^5+($F$11*(1+F$47)/($A49-F$47))/(1+$A49)^5)/1000/$B$32 -> 172.04337
A50: 0.075 | B50: =($B$11/(1+$A50)^1+$C$11/(1+$A50)^2+$D$11/(1+$A50)^3+$E$11/(1+$A50)^4+$F$11/(1+$A50)^5+($F$11*(1+B$47)/($A50-B$47))/(1+$A50)^5)/1000/$B$32 -> 106.19046 | C50: =($B$11/(1+$A50)^1+$C$11/(1+$A50)^2+$D$11/(1+$A50)^3+$E$11/(1+$A50)^4+$F$11/(1+$A50)^5+($F$11*(1+C$47)/($A50-C$47))/(1+$A50)^5)/1000/$B$32 -> 114.18283 | D50: =($B$11/(1+$A50)^1+$C$11/(1+$A50)^2+$D$11/(1+$A50)^3+$E$11/(1+$A50)^4+$F$11/(1+$A50)^5+($F$11*(1+D$47)/($A50-D$47))/(1+$A50)^5)/1000/$B$32 -> 123.77367 | E50: =($B$11/(1+$A50)^1+$C$11/(1+$A50)^2+$D$11/(1+$A50)^3+$E$11/(1+$A50)^4+$F$11/(1+$A50)^5+($F$11*(1+E$47)/($A50-E$47))/(1+$A50)^5)/1000/$B$32 -> 135.4958 | F50: =($B$11/(1+$A50)^1+$C$11/(1+$A50)^2+$D$11/(1+$A50)^3+$E$11/(1+$A50)^4+$F$11/(1+$A50)^5+($F$11*(1+F$47)/($A50-F$47))/(1+$A50)^5)/1000/$B$32 -> 150.14847
A51: 0.08 | B51: =($B$11/(1+$A51)^1+$C$11/(1+$A51)^2+$D$11/(1+$A51)^3+$E$11/(1+$A51)^4+$F$11/(1+$A51)^5+($F$11*(1+B$47)/($A51-B$47))/(1+$A51)^5)/1000/$B$32 -> 97.720456 | C51: =($B$11/(1+$A51)^1+$C$11/(1+$A51)^2+$D$11/(1+$A51)^3+$E$11/(1+$A51)^4+$F$11/(1+$A51)^5+($F$11*(1+C$47)/($A51-C$47))/(1+$A51)^5)/1000/$B$32 -> 104.35886 | D51: =($B$11/(1+$A51)^1+$C$11/(1+$A51)^2+$D$11/(1+$A51)^3+$E$11/(1+$A51)^4+$F$11/(1+$A51)^5+($F$11*(1+D$47)/($A51-D$47))/(1+$A51)^5)/1000/$B$32 -> 112.20424 | E51: =($B$11/(1+$A51)^1+$C$11/(1+$A51)^2+$D$11/(1+$A51)^3+$E$11/(1+$A51)^4+$F$11/(1+$A51)^5+($F$11*(1+E$47)/($A51-E$47))/(1+$A51)^5)/1000/$B$32 -> 121.6187 | F51: =($B$11/(1+$A51)^1+$C$11/(1+$A51)^2+$D$11/(1+$A51)^3+$E$11/(1+$A51)^4+$F$11/(1+$A51)^5+($F$11*(1+F$47)/($A51-F$47))/(1+$A51)^5)/1000/$B$32 -> 133.12526
A52: 0.085 | B52: =($B$11/(1+$A52)^1+$C$11/(1+$A52)^2+$D$11/(1+$A52)^3+$E$11/(1+$A52)^4+$F$11/(1+$A52)^5+($F$11*(1+B$47)/($A52-B$47))/(1+$A52)^5)/1000/$B$32 -> 90.465449 | C52: =($B$11/(1+$A52)^1+$C$11/(1+$A52)^2+$D$11/(1+$A52)^3+$E$11/(1+$A52)^4+$F$11/(1+$A52)^5+($F$11*(1+C$47)/($A52-C$47))/(1+$A52)^5)/1000/$B$32 -> 96.051344 | D52: =($B$11/(1+$A52)^1+$C$11/(1+$A52)^2+$D$11/(1+$A52)^3+$E$11/(1+$A52)^4+$F$11/(1+$A52)^5+($F$11*(1+D$47)/($A52-D$47))/(1+$A52)^5)/1000/$B$32 -> 102.56822 | E52: =($B$11/(1+$A52)^1+$C$11/(1+$A52)^2+$D$11/(1+$A52)^3+$E$11/(1+$A52)^4+$F$11/(1+$A52)^5+($F$11*(1+E$47)/($A52-E$47))/(1+$A52)^5)/1000/$B$32 -> 110.26999 | F52: =($B$11/(1+$A52)^1+$C$11/(1+$A52)^2+$D$11/(1+$A52)^3+$E$11/(1+$A52)^4+$F$11/(1+$A52)^5+($F$11*(1+F$47)/($A52-F$47))/(1+$A52)^5)/1000/$B$32 -> 119.5121
A55: METHODOLOGY & KEY ASSUMPTIONS
A56: 1 · Cash flow = AFFO (levered/equity). AFFO is post-interest cash earnings to common + OP-unit holders, after recurring capex and TI/LC - the closest REIT analog to free cash flow to equity. Discounting it gives EQUITY value directly. Core FFO (Section 6) is a pre-capex upper-bound cross-check.
A57: 2 · Discount rate (Assumptions r59, switch-linked). Applied as the equity discount rate. It is labelled "WACC/discount rate" in Assumptions and is on the low side for a pure cost of equity; because AFFO is levered, the result is equity value, so NO debt is subtracted. Enterprise Value is reconciled FROM equity (Section 5).
A58: 3 · Terminal value - Gordon growth. TV = AFFO₍FY30₎ × (1+g) / (r − g), with g from Assumptions r62 (Base 2.5%, bounded by inflation+1%). Discounted at the t=5 factor. TV is a large share of value (memo r35) - typical for a low-rate growing perpetuity; the sensitivity table stresses both r and g.
A59: 4 · Discounting. End-of-year convention, t = 1…5 for FY2026–FY2030. A mid-year convention would lift value modestly; flagged as an option, not applied.
A60: 5 · Share count. Units-inclusive Core FFO basis (957.2M, Share_Count r8) - consistent with the NAV and the Model per-share denominator. A current snapshot, not forecast-grown.
A61: 6 · EV reconciliation. Implied EV = Equity + net debt (face − cash) + preferred + NCI. JV economics are already inside AFFO (unconsolidated earnings flow through Core FFO), so no separate JV add-back.
A62: 7 · Scenario behaviour. Discount rate, terminal growth and the AFFO stream itself all key off Assumptions!B5 (the AFFO feed reads the Model ACTIVE column). The DCF therefore reprices when the switch is flipped; the reference state is Base.

Sheet NAV
A1: PROLOGIS (PLD) - NET ASSET VALUE (NAV)
A2: Sum-of-the-parts on a Prologis-share economic basis. Bull/Bear columns flex operating NOI (captured from the Model), cap rate and development margins / FRE multiple; CIP, land and FRE are held at snapshot levels across cases. Balance sheet as of Q1 2026.
A3: ⚠ Reference state = BASE (Assumptions!B5 = 1). The Base column's NOI (r7/r8) and FRE (r35) link to the ACTIVE scenario, so keep the switch on Base when reading this tab; Bull/Bear NOI are static captures (r7/r8, blue). Switch-independent three-scenario assembly is the Scenarios tab's role (next phase).
A4: ($ in thousands unless noted) | B4: Base | C4: Bull | D4: Bear | E4: Source / methodology
A5: 1 · STABILIZED NOI (Section 1)
A6: Stabilized forecast year selected | B6: FY2026E | C6: FY2026E | D6: FY2026E | E6: Forward / NTM year. Nearest forward period: rents are already marked toward market via the FY2026 bridge and occupancy sits at the stabilized ~95.3% level in the model, so minimal normalization is required. Standard forward-NOI NAV convention.
A7: Model FY2026E total property NOI (same-store + dev) | B7: =Model!C36 -> 6769761.4 | C7: 6968634 | D7: 6488812.7 | E7: Base (B7) is a live link to Model r36. Bull/Bear (C7/D7) are Model total NOI CAPTURED manually under switch=2/3 (values verified to match the Model exactly). Blue = static input: they will NOT auto-update if Model assumptions change. Live three-scenario capture belongs in the Scenarios tab (next phase).
A8: Less: development-delivered NOI (valued separately, Sec 3) | B8: =-Model!C33 -> -104192.1 | C8: -117221.65 | D8: -84662.546 | E8: Base (B8) live-links Model r33. Bull/Bear (C8/D8) are the matching manually-captured development-NOI values (static; see r7 note).
A9: Stabilized operating NOI (forward FY2026E) | B9: =B7+B8 -> 6665569.3 | C9: =C7+C8 -> 6851412.3 | D9: =D7+D8 -> 6404150.1 | E9: Standing-portfolio forward NOI (consolidated). Held constant across the three valuation cases (see Validation).
A11: 2 · REAL ESTATE PORTFOLIO VALUE (Section 2)
A12: NAV cap rate (blended operating) | B12: =Assumptions!C61 -> 0.05 | C12: =Assumptions!D61 -> 0.045 | D12: =Assumptions!E61 -> 0.058 | E12: Linked to Assumptions r61. Anchored to FY2025 disposition cap evidence 4.9–5.1%. Base 5.00% / Bull 4.50% / Bear 5.80%.
A13: Gross real estate value (= Stabilized NOI ÷ cap rate) | B13: =B$9/B12 -> 1.3331139e+08 | C13: =C$9/C12 -> 1.5225361e+08 | D13: =D$9/D12 -> 1.1041638e+08 | E13: Direct capitalization of forward stabilized NOI. The single largest NAV component and the dominant value driver.
A15: 3 · DEVELOPMENT VALUE (in-process pipeline; cost + value-creation, Section 3)
A16: Total construction-in-progress (CIP), Q1 2026 | B16: =Data_Collection!E120*1000 -> 5491000 | C16: =B16 -> 5491000 | D16: =B16 -> 5491000 | E16: Supplemental CIP balance $5,491M (Q1 2026), $mm→$000s. The IN-PROCESS book as of the valuation date — NOT forecast future starts (those are future activity, captured in the DCF, never in a snapshot NAV).
A17: DC share of CIP (estimate) | B17: 0.3 | C17: =B17 -> 0.3 | D17: =B17 -> 0.3 | E17: NAV-local estimate. Q1 2026 data-center starts were ~73% of new starts, but CIP is a multi-year accumulated stock; 30% is a reasoned mid-point. Adjustable. Split held across cases (the data does not disclose a CIP logistics/DC split).
A18: Margin realization on in-process pipeline | B18: 0.5 | C18: =B18 -> 0.5 | D18: =B18 -> 0.5 | E18: Fraction of projected value-creation margin recognized now, given mid-construction and ~47.5% pre-leasing (CIP %-leased, Q1 2026). Full margin is earned only at stabilization. Held across cases.
A19: LOGISTICS
A20: Logistics CIP | B20: =B16*(1-B17) -> 3843700 | C20: =B20 -> 3843700 | D20: =B20 -> 3843700
A21: Logistics value-creation margin | B21: =Assumptions!C28 -> 0.2 | C21: =Assumptions!D28 -> 0.3 | D21: =Assumptions!E28 -> 0.05 | E21: Assumptions r28. Base 20% / Bull 30% / Bear 5%.
A22: Logistics development value | B22: =B20*(1+B21*$B$18) -> 4228070 | C22: =B20*(1+C21*$B$18) -> 4420255 | D22: =B20*(1+D21*$B$18) -> 3939792.5 | E22: Logistics CIP × (1 + margin × realization).
A23: DATA CENTERS
A24: Data center CIP | B24: =B16*B17 -> 1647300 | C24: =B24 -> 1647300 | D24: =B24 -> 1647300
A25: Data center value-creation margin | B25: =Assumptions!C32 -> 0.25 | C25: =Assumptions!D32 -> 0.35 | D25: =Assumptions!E32 -> 0.1 | E25: Assumptions r32. Base 25% / Bull 35% / Bear 10%.
A26: Data center development value | B26: =B24*(1+B25*$B$18) -> 1853212.5 | C26: =B24*(1+C25*$B$18) -> 1935577.5 | D26: =B24*(1+D25*$B$18) -> 1729665 | E26: DC CIP × (1 + margin × realization).
A27: Total development value | B27: =B22+B26 -> 6081282.5 | C27: =C22+C26 -> 6355832.5 | D27: =D22+D26 -> 5669457.5
A29: 4 · LAND BANK (Section 4)
A30: Land bank book value, Q1 2026 | B30: =Data_Collection!E122*1000 -> 4799000 | C30: =B30 -> 4799000 | D30: =B30 -> 4799000 | E30: Supplemental land book $4,799M (Q1 2026), $mm→$000s. Carried at lower-of-cost. Buildout TEI capacity ~$38B (r125) is embedded option value NOT marked here — upside, deliberately excluded from base.
A31: Mark vs book | B31: 1 | C31: =B31 -> 1 | D31: =B31 -> 1 | E31: Held at book (conservative). Adjustable.
A32: Land bank value | B32: =B30*B31 -> 4799000 | C32: =B32 -> 4799000 | D32: =B32 -> 4799000 | E32: Held across cases at book.
A34: 5 · STRATEGIC CAPITAL PLATFORM (FRE multiple, Section 5)
A35: Forward fee-related earnings (FRE), ex-promotes | B35: =Model!C46 -> 187576.81 | C35: 215631.82 | D35: 151519.54 | E35: Model FY2026E FRE = recurring + transactional fees − strategic-capital expenses (Model r46). Promotes EXCLUDED (base case = $0 FY27+). Held across cases.
A36: FRE multiple (asset-manager basis) | B36: 13 | C36: 16 | D36: 9 | E36: NAV-local input. Listed alternative-asset / real-asset platform managers trade ~10–18× FRE; the PLD platform is sticky, real-asset-backed and growing. Base 13× / Bull 16× / Bear 9×.
A37: Strategic capital platform value | B37: =B35*B36 -> 2438498.6 | C37: =C35*C36 -> 3450109.1 | D37: =D35*D36 -> 1363675.8
A39: 6 · ENTERPRISE NAV (Section 6)
A40: Stabilized real estate (Sec 2) | B40: =B13 -> 1.3331139e+08 | C40: =C13 -> 1.5225361e+08 | D40: =D13 -> 1.1041638e+08
A41: + Development pipeline (Sec 3) | B41: =B27 -> 6081282.5 | C41: =C27 -> 6355832.5 | D41: =D27 -> 5669457.5
A42: + Land bank (Sec 4) | B42: =B32 -> 4799000 | C42: =C32 -> 4799000 | D42: =D32 -> 4799000
A43: + Strategic capital platform (Sec 5) | B43: =B37 -> 2438498.6 | C43: =C37 -> 3450109.1 | D43: =D37 -> 1363675.8
A44: GROSS ASSET VALUE (GAV) | B44: =SUM(B40:B43) -> 1.4663017e+08 | C44: =SUM(C40:C43) -> 1.6685855e+08 | D44: =SUM(D40:D43) -> 1.2224851e+08
A45: + Cash & equivalents | B45: =Data_Collection!E30 -> 861144 | C45: =B45 -> 861144 | D45: =B45 -> 861144 | E45: Q1 2026 balance sheet.
A46: + Co-investments in unconsolidated ventures (carrying) | B46: =Data_Collection!E28 -> 11241723 | C46: =B46 -> 11241723 | D46: =B46 -> 11241723 | E46: PLD-share JV equity at carrying (equity-method, depreciated) — conservative vs a JV look-through NAV. The operating NOI above is consolidated, so JV economics are added HERE, not in Section 2.
A47: + Net other assets / (liabilities) | B47: =Data_Collection!E31-Data_Collection!E35-Data_Collection!E34 -> 72326 | C47: =B47 -> 72326 | D47: =B47 -> 72326 | E47: Other assets − other liabilities − accounts payable (working-capital net). Immaterial.
A48: − Debt at face | B48: =-(Data_Collection!E33-Data_Collection!E143) -> -35194978 | C48: =B48 -> -35194978 | D48: =B48 -> -35194978 | E48: Consolidated debt at face = carrying $34.67B + unamortized discount/issuance costs $0.53B = $35.19B (Q1 2026).
A49: − Preferred equity | B49: =-Data_Collection!E37 -> -63948 | C49: =B49 -> -63948 | D49: =B49 -> -63948
A50: − Noncontrolling interests | B50: =-Data_Collection!E39 -> -4445091 | C50: =B50 -> -4445091 | D50: =B50 -> -4445091 | E50: Minority share of consolidated equity. Deducted because the NOI feed is consolidated (includes minority-owned property NOI); this reconciles the consolidated valuation to a Prologis-share equity NAV.
A51: EQUITY NAV | B51: =B44+SUM(B45:B50) -> 1.1910134e+08 | C51: =C44+SUM(C45:C50) -> 1.3932972e+08 | D51: =D44+SUM(D45:D50) -> 94719691
A52: Memo: Equity NAV ($B) | B52: =B51/1000000 -> 119.10134 | C52: =C51/1000000 -> 139.32972 | D52: =D51/1000000 -> 94.719691
A53: ÷ Core FFO share/unit count (M) | B53: =Share_Count!D8 -> 957.2 | C53: =B53 -> 957.2 | D53: =B53 -> 957.2 | E53: Units-inclusive Core FFO basis (957.2M) per instruction. Snapshot count — not forecast-grown.
A54: NAV PER SHARE ($) | B54: =B51/1000/B53 -> 124.42681 | C54: =C51/1000/C53 -> 145.55968 | D54: =D51/1000/D53 -> 98.954963 | E54: Equity NAV ($000s) ÷ 1000 → $mm, ÷ share count (M) = $ / share.
A56: 7 · SENSITIVITY ANALYSIS (NAV per share, Section 7)
A57: Non-RE NAV held at Base ($000s) | B57: =B51-B13 -> -14210043 | C57: =C51-C13 -> -12923882 | D57: =D51-D13 -> -15696691 | E57: Equity NAV less stabilized real estate = development + land + strategic capital + cash + co-invest + net other − debt − preferred − NCI, all at Base. RE value is the variable in Table A.
A58: Non-RE, non-SC NAV held at Base ($000s) | B58: =B57-B37 -> -16648542 | C58: =C57-C37 -> -16373991 | D58: =D57-D37 -> -17060366 | E58: As above, also excluding the strategic-capital platform — which is the variable in Table B.
A60: Table A — NAV/share ($): cap rate (down) × stabilized NOI (across)
A61: Cap ↓ \ NOI → | B61: =B9*0.9 -> 5999012.4 | C61: =B9*0.95 -> 6332290.8 | D61: =B9*1 -> 6665569.3 | E61: =B9*1.05 -> 6998847.8 | F61: =B9*1.1 -> 7332126.2
A62: 0.045 | B62: =(B$61/$A62+$B$57)/1000/$B$53 -> 124.42681 | C62: =(C$61/$A62+$B$57)/1000/$B$53 -> 132.16416 | D62: =(D$61/$A62+$B$57)/1000/$B$53 -> 139.9015 | E62: =(E$61/$A62+$B$57)/1000/$B$53 -> 147.63885 | F62: =(F$61/$A62+$B$57)/1000/$B$53 -> 155.3762
A63: 0.05 | B63: =(B$61/$A63+$B$57)/1000/$B$53 -> 110.49959 | C63: =(C$61/$A63+$B$57)/1000/$B$53 -> 117.4632 | D63: =(D$61/$A63+$B$57)/1000/$B$53 -> 124.42681 | E63: =(E$61/$A63+$B$57)/1000/$B$53 -> 131.39042 | F63: =(F$61/$A63+$B$57)/1000/$B$53 -> 138.35403
A64: 0.055 | B64: =(B$61/$A64+$B$57)/1000/$B$53 -> 99.104585 | C64: =(C$61/$A64+$B$57)/1000/$B$53 -> 105.43514 | D64: =(D$61/$A64+$B$57)/1000/$B$53 -> 111.7657 | E64: =(E$61/$A64+$B$57)/1000/$B$53 -> 118.09625 | F64: =(F$61/$A64+$B$57)/1000/$B$53 -> 124.42681
A65: 0.058 | B65: =(B$61/$A65+$B$57)/1000/$B$53 -> 93.210619 | C65: =(C$61/$A65+$B$57)/1000/$B$53 -> 99.213733 | D65: =(D$61/$A65+$B$57)/1000/$B$53 -> 105.21685 | E65: =(E$61/$A65+$B$57)/1000/$B$53 -> 111.21996 | F65: =(F$61/$A65+$B$57)/1000/$B$53 -> 117.22307
A66: 0.06 | B66: =(B$61/$A66+$B$57)/1000/$B$53 -> 89.608751 | C66: =(C$61/$A66+$B$57)/1000/$B$53 -> 95.411761 | D66: =(D$61/$A66+$B$57)/1000/$B$53 -> 101.21477 | E66: =(E$61/$A66+$B$57)/1000/$B$53 -> 107.01778 | F66: =(F$61/$A66+$B$57)/1000/$B$53 -> 112.82079
A68: Table B — NAV/share ($): cap rate (down) × strategic-capital platform value (across)
A69: Cap ↓ \ SC val → | B69: =B35*9 -> 1688191.3 | C69: =B35*11 -> 2063344.9 | D69: =B35*13 -> 2438498.6 | E69: =B35*15 -> 2813652.2 | F69: =B35*17 -> 3188805.8
A70: 0.045 | B70: =($B$9/$A70+$B$58+B$69)/1000/$B$53 -> 139.11765 | C70: =($B$9/$A70+$B$58+C$69)/1000/$B$53 -> 139.50958 | D70: =($B$9/$A70+$B$58+D$69)/1000/$B$53 -> 139.9015 | E70: =($B$9/$A70+$B$58+E$69)/1000/$B$53 -> 140.29343 | F70: =($B$9/$A70+$B$58+F$69)/1000/$B$53 -> 140.68536
A71: 0.05 | B71: =($B$9/$A71+$B$58+B$69)/1000/$B$53 -> 123.64295 | C71: =($B$9/$A71+$B$58+C$69)/1000/$B$53 -> 124.03488 | D71: =($B$9/$A71+$B$58+D$69)/1000/$B$53 -> 124.42681 | E71: =($B$9/$A71+$B$58+E$69)/1000/$B$53 -> 124.81874 | F71: =($B$9/$A71+$B$58+F$69)/1000/$B$53 -> 125.21067
A72: 0.055 | B72: =($B$9/$A72+$B$58+B$69)/1000/$B$53 -> 110.98184 | C72: =($B$9/$A72+$B$58+C$69)/1000/$B$53 -> 111.37377 | D72: =($B$9/$A72+$B$58+D$69)/1000/$B$53 -> 111.7657 | E72: =($B$9/$A72+$B$58+E$69)/1000/$B$53 -> 112.15763 | F72: =($B$9/$A72+$B$58+F$69)/1000/$B$53 -> 112.54955
A73: 0.058 | B73: =($B$9/$A73+$B$58+B$69)/1000/$B$53 -> 104.43299 | C73: =($B$9/$A73+$B$58+C$69)/1000/$B$53 -> 104.82492 | D73: =($B$9/$A73+$B$58+D$69)/1000/$B$53 -> 105.21685 | E73: =($B$9/$A73+$B$58+E$69)/1000/$B$53 -> 105.60877 | F73: =($B$9/$A73+$B$58+F$69)/1000/$B$53 -> 106.0007
A74: 0.06 | B74: =($B$9/$A74+$B$58+B$69)/1000/$B$53 -> 100.43091 | C74: =($B$9/$A74+$B$58+C$69)/1000/$B$53 -> 100.82284 | D74: =($B$9/$A74+$B$58+D$69)/1000/$B$53 -> 101.21477 | E74: =($B$9/$A74+$B$58+E$69)/1000/$B$53 -> 101.6067 | F74: =($B$9/$A74+$B$58+F$69)/1000/$B$53 -> 101.99863
A75: Tables hold non-varying components at Base; row = NAV cap rate, columns = the swept variable. Center cell of each table reconciles exactly to Base NAV/share.
A76: 8 · OUTPUT SUMMARY & VALIDATION (Section 8)
A77: Output | B77: Base | C77: Bull | D77: Bear
A78: NAV per share ($) | B78: =B54 -> 124.42681 | C78: =C54 -> 145.55968 | D78: =D54 -> 98.954963
A79: Current share price ($) | B79: 145 | C79: =B79 -> 145 | D79: =B79 -> 145 | E79: Live ≈ $143–149 (mid-June 2026; Yahoo Finance / Investing.com ~$148.7, intraday quotes ~$141–143). Adjustable blue input. Workbook Q1 2026 snapshot = $132 (Data_Collection r165, shown below).
A80: Premium / (discount) to NAV | B80: =B79/B78-1 -> 0.1653437 | C80: =C79/C78-1 -> -0.0038450112 | D80: =D79/D78-1 -> 0.46531306 | E80: Price ÷ NAV − 1. Positive = market premium to NAV.
A81: Implied upside / (downside) to NAV | B81: =B78/B79-1 -> -0.14188407 | C81: =C78/C79-1 -> 0.0038598523 | D81: =D78/D79-1 -> -0.31755198 | E81: NAV ÷ price − 1. Positive = NAV above the current price (upside).
A83: Memo: workbook snapshot price (Q1 2026, $) | B83: =Data_Collection!E163 -> 132.18 | C83: =B83 -> 132.18 | D83: =B83 -> 132.18
A84: Premium/(discount) vs snapshot price | B84: =B83/B78-1 -> 0.062311246 | C84: =B83/C78-1 -> -0.091918852 | D84: =B83/D78-1 -> 0.33575917
A85: Memo: stabilized NOI ÷ GAV (blended asset yield) | B85: =B9/B44 -> 0.045458376 | C85: =C9/C44 -> 0.0410612 | D85: =D9/D44 -> 0.052386323 | E85: Blended yield on gross assets (below the 5.0% RE cap because GAV includes non-income land, in-process development and the fee platform). A coherence check, not a pure cap rate.
A86: Memo: stabilized RE value per sq ft ($/sf) | B86: =B13/Data_Collection!D84 -> 172.42049 | C86: =C13/Data_Collection!D84 -> 196.91973 | D86: =D13/Data_Collection!D84 -> 142.80886 | E86: Base RE value ÷ same-store operating pool (Data_Collection r86, ~773M sf). Sanity vs prime-logistics replacement cost.
A88: VALIDATION & KEY DRIVERS
A89: 1 · Is the NAV reasonable? Base NAV ≈ B54; range Bear (D54) – Bull (C54). Implied value/sf (~$172, r86) sits within prime-logistics replacement cost and the blended GAV yield (~4.6%, r85) is consistent with a high-quality global industrial portfolio. The build is deliberately conservative: JV interests at carrying (depreciated equity value), land at book (≈$38B buildout option excluded), and NO value for future (post-snapshot) development starts. So if anything the snapshot NAV is understated.
A90: 2 · Premium or discount? At ~$145 (mid-June 2026) PLD trades at a PREMIUM to NAV -roughly +17% to Base and ~+3% to Bull (r80). Against the workbook’s Q1 2026 snapshot price ($132) the premium is ~+6% (r84). PLD has historically commanded an NAV premium for its development engine, fee platform and balance-sheet quality; +17% to a conservative Base is toward the upper end of that range and is the central debate -is the market paying for data-center / development optionality this snapshot NAV intentionally omits?
A91: 3 · Which assumptions drive the valuation? The NAV cap rate and stabilized NOI dominate. Table A shows roughly $6–7 of NAV/share per 25 bps of cap rate and per ~5% of NOI -together they explain almost the entire spread. The strategic-capital multiple and development margin are second-order: Table B shows a full 2× swing in the FRE multiple moves NAV well under $1/share. Challenge should focus on the operating cap rate applied to forward NOI.
A92: Scenario design. Three full scenarios: Bull/Bear flex operating NOI (Section 1, captured from the Model under switch=2/3), the NAV cap rate (Assumptions r61), development margins (r28/r32) and the FRE multiple (r36). CIP, land and FRE are held at snapshot levels (the NAV values today's in-process book and platform, not forward activity). NOTE: the Bull/Bear NOI in C7/D7/C8/D8 are static manual captures (blue), so they do not auto-update with Model changes and trip the "no hardcodes outside Data_Collection" hygiene rule -the live three-scenario engine belongs in the Scenarios tab. The Base column remains fully linked to the live forecast.
A93: Tie-back & integrity. Stabilized NOI and FRE link to Model FY2026E (which reads the Assumptions ACTIVE column); cap rates and development margins link to Assumptions; the balance sheet links to Data_Collection (Q1 2026); share count links to Share_Count. No NAV output is hardcoded. The NAV is a downstream consumer only -it feeds nothing back into the forecast -so it introduces no new circularity.

Sheet Comps
A1: PROLOGIS (PLD) - TRADING COMPARABLES
A2: Logistics-REIT peer group. $ in billions except per-share & ratios. Forward (2026E) multiples. Blue = sourced/estimated input; black = calculation; green = link to this model (PLD row & implied value). See notes for sourcing.
A3: ⚠ Live peer prices showed provider/date dispersion (treated as ~mid-June 2026 estimates, adjustable). The implied-value conclusion rests on RELATIVE multiples, robust to absolute price level. PLD price links to NAV for model consistency. EBITDA / cap-rate figures are estimates.
A4: Peer AFFO/FFO ratio (applied to peer Core FFO): | B4: 0.9 | D4: Single transparent ratio. Pure-play landlords convert FFO→AFFO higher than PLD (whose model AFFO/FFO is ~78% due to development capex).
A5: Company | B5: Ticker | C5: Price ($) | D5: Shares (M) | E5: Mkt cap ($B) | F5: Net debt+pref ($B) | G5: EV ($B) | H5: EBITDA ($B) | I5: Net debt/ EBITDA | J5: Div/sh | K5: Div yield | L5: Core FFO/sh | M5: AFFO/sh | N5: P/Core FFO | O5: P/AFFO | P5: EV/ EBITDA | Q5: Impl. cap rate
A6: Prologis | B6: PLD | C6: =NAV!B79 -> 145 | D6: =Data_Collection!E155 -> 932.3 | E6: =C6*D6/1000 -> 135.1835 | F6: =(Data_Collection!E33-Data_Collection!E143-Data_Collection!E30+Data_Collection!E37)/1000000 -> 34.397782 | G6: =E6+F6 -> 169.58128 | H6: =Model!C56/1000000 -> 6.8921172 | I6: =F6/H6 -> 4.9908876 | J6: 4.28 | K6: =J6/C6 -> 0.029517241 | L6: =Model!C73 -> 5.7835432 | M6: =Model!C77 -> 4.508283 | N6: =C6/L6 -> 25.071136 | O6: =C6/M6 -> 32.163021 | P6: =G6/H6 -> 24.605107 | Q6: 0.05
A7: Rexford | B7: REXR | C7: 35 | D7: 229 | E7: =C7*D7/1000 -> 8.015 | F7: 3.45 | G7: =E7+F7 -> 11.465 | H7: 0.75 | I7: =F7/H7 -> 4.6 | J7: 1.74 | K7: =J7/C7 -> 0.049714286 | L7: 2.4 | M7: =L7*$B$4 -> 2.16 | N7: =C7/L7 -> 14.583333 | O7: =C7/M7 -> 16.203704 | P7: =G7/H7 -> 15.286667 | Q7: 0.055
A8: EastGroup | B8: EGP | C8: 205 | D8: 53.8 | E8: =C8*D8/1000 -> 11.029 | F8: 1.8 | G8: =E8+F8 -> 12.829 | H8: 0.6 | I8: =F8/H8 -> 3 | J8: 6.2 | K8: =J8/C8 -> 0.030243902 | L8: 9.56 | M8: =L8*$B$4 -> 8.604 | N8: =C8/L8 -> 21.443515 | O8: =C8/M8 -> 23.826127 | P8: =G8/H8 -> 21.381667 | Q8: 0.05
A9: First Industrial | B9: FR | C9: 58 | D9: 135 | E9: =C9*D9/1000 -> 7.83 | F9: 2.2 | G9: =E9+F9 -> 10.03 | H9: 0.49 | I9: =F9/H9 -> 4.4897959 | J9: 2 | K9: =J9/C9 -> 0.034482759 | L9: 3.14 | M9: =L9*$B$4 -> 2.826 | N9: =C9/L9 -> 18.471338 | O9: =C9/M9 -> 20.523708 | P9: =G9/H9 -> 20.469388 | Q9: 0.055
A10: Terreno | B10: TRNO | C10: 60 | D10: 105.7 | E10: =C10*D10/1000 -> 6.342 | F10: 0.95 | G10: =E10+F10 -> 7.292 | H10: 0.42 | I10: =F10/H10 -> 2.2619048 | J10: 2.08 | K10: =J10/C10 -> 0.034666667 | L10: 2.7 | M10: =L10*$B$4 -> 2.43 | N10: =C10/L10 -> 22.222222 | O10: =C10/M10 -> 24.691358 | P10: =G10/H10 -> 17.361905 | Q10: 0.0525
A11: STAG Industrial | B11: STAG | C11: 37 | D11: 198 | E11: =C11*D11/1000 -> 7.326 | F11: 3.2 | G11: =E11+F11 -> 10.526 | H11: 0.636 | I11: =F11/H11 -> 5.0314465 | J11: 1.49 | K11: =J11/C11 -> 0.04027027 | L11: 2.62 | M11: =L11*$B$4 -> 2.358 | N11: =C11/L11 -> 14.122137 | O11: =C11/M11 -> 15.691264 | P11: =G11/H11 -> 16.550314 | Q11: 0.06
A13: SUMMARY STATISTICS — peer set (REXR, EGP, FR, TRNO, STAG; excludes PLD)
A14: Mean | I14: =AVERAGE(I7:I11) -> 3.8766294 | K14: =AVERAGE(K7:K11) -> 0.037875577 | N14: =AVERAGE(N7:N11) -> 18.168509 | O14: =AVERAGE(O7:O11) -> 20.187232 | P14: =AVERAGE(P7:P11) -> 18.209988 | Q14: =AVERAGE(Q7:Q11) -> 0.0545
A15: Median | I15: =MEDIAN(I7:I11) -> 4.4897959 | K15: =MEDIAN(K7:K11) -> 0.034666667 | N15: =MEDIAN(N7:N11) -> 18.471338 | O15: =MEDIAN(O7:O11) -> 20.523708 | P15: =MEDIAN(P7:P11) -> 17.361905 | Q15: =MEDIAN(Q7:Q11) -> 0.055
A16: High | I16: =MAX(I7:I11) -> 5.0314465 | K16: =MAX(K7:K11) -> 0.049714286 | N16: =MAX(N7:N11) -> 22.222222 | O16: =MAX(O7:O11) -> 24.691358 | P16: =MAX(P7:P11) -> 21.381667 | Q16: =MAX(Q7:Q11) -> 0.06
A17: Low | I17: =MIN(I7:I11) -> 2.2619048 | K17: =MIN(K7:K11) -> 0.030243902 | N17: =MIN(N7:N11) -> 14.122137 | O17: =MIN(O7:O11) -> 15.691264 | P17: =MIN(P7:P11) -> 15.286667 | Q17: =MIN(Q7:Q11) -> 0.05
A18: PLD (subject) | I18: =I6 -> 4.9908876 | K18: =K6 -> 0.029517241 | N18: =N6 -> 25.071136 | O18: =O6 -> 32.163021 | P18: =P6 -> 24.605107 | Q18: =Q6 -> 0.05
A20: PLD IMPLIED VALUATION — peer median multiples applied to PLD forward metrics
A21: Method | B21: Peer median × | C21: PLD metric | D21: Implied $/sh | E21: vs current price
A22: Median P/Core FFO × PLD Core FFO/sh | B22: =N15 -> 18.471338 | C22: =L6 -> 5.7835432 | D22: =B22*C22 -> 106.82978 | E22: =D22/C6-1 -> -0.2632429 | F22: Implied = peer-median multiple × PLD forward per-share metric. "vs price" = implied ÷ current − 1 (negative = PLD trades above where peer multiples imply).
A23: Median P/AFFO × PLD AFFO/sh | B23: =O15 -> 20.523708 | C23: =M6 -> 4.508283 | D23: =B23*C23 -> 92.526686 | E23: =D23/C6-1 -> -0.36188492
A24: Implied PLD value range (low–high of the two methods) | D24: =TEXT(MIN(D22:D23),"$0.00")&" - "&TEXT(MAX(D22:D23),"$0.00") -> $92.53 - $106.83
A25: Current PLD price ($) | D25: =C6 -> 145
A27: VALUATION CONCLUSION — PLD vs peer median
A28: Multiple | B28: PLD (current) | C28: Peer median | D28: PLD premium/(disc)
A29: P/Core FFO | B29: =N6 -> 25.071136 | C29: =N15 -> 18.471338 | D29: =N6/N15-1 -> 0.35729944
A30: P/AFFO | B30: =O6 -> 32.163021 | C30: =O15 -> 20.523708 | D30: =O6/O15-1 -> 0.56711546
A31: EV/EBITDA | B31: =P6 -> 24.605107 | C31: =P15 -> 17.361905 | D31: =P6/P15-1 -> 0.41718939
A32: Net debt/EBITDA | B32: =I6 -> 4.9908876 | C32: =I15 -> 4.4897959 | D32: =I6/I15-1 -> 0.11160678
A33: Dividend yield | B33: =K6 -> 0.029517241 | C33: =K15 -> 0.034666667 | D33: =K6/K15-1 -> -0.14854111
A35: KEY OBSERVATIONS
A36: 1 · PLD trades at a clear premium to the logistics peer group. On forward P/Core FFO and P/AFFO, PLD sits above the peer median (row 29–30). Applying peer-median multiples to PLD's own forward metrics implies a value (row 24) BELOW the current price -i.e., the market pays a premium for PLD vs the group. This is the expected result for the sector bellwether and is consistent with the NAV and DCF, which also sit below price.
A37: 2 · The implied "value" is a relative-positioning read, not a target. It answers "what would PLD be worth at peer multiples?" PLD's scale, global platform, strategic-capital franchise and data-center optionality justify a premium that pure-play domestic peers do not carry; a literal peer-multiple target understates PLD.
A38: 3 · P/Core FFO is the cleaner cross-company multiple. The P/AFFO comparison is distorted because PLD's AFFO/FFO ratio (~78%, heavy development capex) is lower than the ~90% assumed for pure-play peers, mechanically lowering PLD's implied P/AFFO value. Weight the P/Core FFO read accordingly.
A39: 4 · Within the group, multiples disperse with quality/market. EGP and TRNO (Sunbelt / coastal infill, low leverage) screen richest; REXR and STAG (SoCal repositioning / secondary markets) screen cheapest. PLD's premium to the median is widest on P/Core FFO.
A40: 5 · Leverage & yield context. PLD's net debt/EBITDA (~5.0x) is around the peer median; its dividend yield is below the peer median, another premium signal. EV/EBITDA and implied cap rates are indicative estimates (peer EBITDA not separately sourced) and should be read as directional.
A42: SOURCES & METHODOLOGY
A43: Prices ~mid-June 2026 (Yahoo / Investing.com / Google Finance / macrotrends / wallstreetzen); cross-provider dispersion noted, treated as blue inputs. PLD price links to NAV!B79. 2026E Core FFO/sh = FY2026 guidance midpoints: EGP $9.56 ($9.46–9.66), FR $3.14 ($3.09–3.19 ex-advisory), STAG $2.62 ($2.60–2.64), REXR ~$2.40, TRNO ~$2.70 (consensus). PLD Core FFO/sh & AFFO/sh link to Model FY2026E (r73/r77).
A44: AFFO (peers) = Core FFO × 90% (cell B4). Net debt+pref, EBITDA and implied cap rates are estimates (sourced leverage where available: EGP 3.0x, STAG 5.0x net debt/EBITDA). Statistics span the 5 peers, excluding PLD. Implied value applies peer MEDIAN P/Core FFO and P/AFFO to PLD's forward metrics.

Sheet Football_Field
A1: PROLOGIS (PLD) — FOOTBALL FIELD (VALUATION SUMMARY)
A2: Per-share value ranges by methodology, with the current market price. All values link to NAV, DCF and Comps. NAV = scenario range (Bear/Base/Bull). DCF = discount-rate band (7.0–8.5% WACC, g 2.5%). Comps = P/AFFO–P/Core FFO implied range.
A4: 1 · VALUATION RANGES ($/share)
A5: Methodology | B5: Low | C5: Base / mid | D5: High | E5: Midpoint | F5: Range ($) | I5: Category | J5: Offset | K5: Range
A6: NAV (sum-of-parts) | B6: =NAV!D54 -> 98.954963 | C6: =NAV!B54 -> 124.42681 | D6: =NAV!C54 -> 145.55968 | E6: =(B6+D6)/2 -> 122.25732 | F6: =D6-B6 -> 46.604715 | G6: NAV Bear / Base / Bull (NAV!D54/B54/C54). | I6: Trading comps | J6: =B8 -> 92.526686 | K6: =D8-B8 -> 14.303093
A7: DCF (AFFO equity) | B7: =DCF!D52 -> 102.56822 | C7: =DCF!B33 -> 123.77367 | D7: =DCF!D49 -> 137.92113 | E7: =(B7+D7)/2 -> 120.24468 | F7: =D7-B7 -> 35.352913 | G7: DCF at bear/bull WACC (8.5%/7.0%), terminal g 2.5% (DCF!D53/D50); base DCF!B34. | I7: DCF (AFFO equity) | J7: =B7 -> 102.56822 | K7: =D7-B7 -> 35.352913
A8: Trading comps | B8: =Comps!D23 -> 92.526686 | C8: =(B8+D8)/2 -> 99.678233 | D8: =Comps!D22 -> 106.82978 | E8: =(B8+D8)/2 -> 99.678233 | F8: =D8-B8 -> 14.303093 | G8: Comps implied: P/AFFO (low) – P/Core FFO (high) (Comps!D23/D22). | I8: NAV (sum-of-parts) | J8: =B6 -> 98.954963 | K8: =D6-B6 -> 46.604715
A9: Current share price | C9: =NAV!B79 -> 145 | G9: Linked to NAV!B79 (model-consistent current price). | I9: ◄ Current price | J9: =C9-0.4 -> 144.6 | K9: =0.8 -> 0.8
A15: 2 · VALUATION SUMMARY
A16: Metric | B16: Value
A17: Overall low (min across methods) | B17: =MIN(B6:B8) -> 92.526686
A18: Overall high (max across methods) | B18: =MAX(D6:D8) -> 145.55968
A19: Blended midpoint (avg of method midpoints) | B19: =AVERAGE(E6:E8) -> 114.06008
A20: Current share price | B20: =C9 -> 145
A21: Price vs blended midpoint | B21: =C9/B19-1 -> 0.27125988
A22: Price vs NAV base / DCF base / comps mid | B22: =C9/C6-1 -> 0.1653437 | C22: =C9/C7-1 -> 0.17149313 | D22: =C9/E8-1 -> 0.45468069 | E22: Premium of price to: NAV base, DCF base, comps midpoint.
A24: KEY OBSERVATIONS
A25: 1 · The three methodologies converge tightly on intrinsic value. NAV base (~$124), DCF base (~$124) and the comps midpoint (~$100) cluster in the ~$100–124 zone; the blended midpoint sits near $115. Independent approaches triangulating this closely is a strong signal.
A26: 2 · The market price sits at or above the top of every range. At $145 PLD trades above NAV bull, above the DCF bull-WACC high, and well above the comps-implied range -a consistent premium across all three lenses.
A27: 3 · The premium is the thesis, not a mispricing flag. PLD's scale, global platform, strategic-capital franchise and data-center / development optionality justify a premium that the asset-, cash-flow- and peer-based methods do not fully capture. The football field frames how much premium the market is paying.
A28: 4 · Comps anchors the low end; NAV/DCF anchor the center. Trading comps screen PLD cheapest (it is priced richer than peers); NAV and DCF -which capture PLD-specific platform value -sit higher and should carry more weight in the final view.

Sheet Scenarios
A1: PROLOGIS (PLD) - SCENARIO SUMMARY (EXECUTIVE VIEW)
A2: Base / Bull / Bear via the Assumptions scenario switch. Base column, NAV/share and all drivers link live. Single-scenario outputs (operating, DCF, comps) for Bull/Bear are MODEL-DERIVED CAPTURES (blue) -the model computes one scenario at a time. $ in thousands except per-share.
A3: ⚠ Reference state = Base (Assumptions!B5 = 1). Bull/Bear captures were produced by running the model under each switch setting; refresh them if the model changes. Green = live link; blue = model-derived capture; black = calculation.
A4: Metric | B4: Base | C4: Bull | D4: Bear | E4: Source / note
A5: 1 · OPERATING SUMMARY -FY2030E | G5: Scenario | H5: NAV/share | I5: DCF/share | J5: Current price
A6: Revenue ($000s) | B6: =Model!G17 -> 13522501 | C6: 17092091 | D6: 10999577 | E6: Base links Model FY2030 (col G); Bull/Bear captured at switch=2/3. | G6: Bear | H6: =D14 -> 98.954963 | I6: =D15 -> 71.219035 | J6: =$B$20 -> 145
A7: Total property NOI ($000s) | B7: =Model!G36 -> 10209488 | C7: 12989989 | D7: 8194685.2 | G7: Base | H7: =B14 -> 124.42681 | I7: =B15 -> 123.77367 | J7: =$B$20 -> 145
A8: Core FFO ($000s) | B8: =Model!G72 -> 8650448.5 | C8: 11556664 | D8: 6642837 | G8: Bull | H8: =C14 -> 145.55968 | I8: =C15 -> 200.99564 | J8: =$B$20 -> 145
A9: AFFO ($000s) | B9: =Model!G76 -> 6743041.2 | C9: 9008441.7 | D9: 5178104.1
A10: Core FFO / share ($) | B10: =Model!G73 -> 8.3924009 | C10: 10.799107 | D10: 6.6679195 | E10: Core FFO/share — Bull $10.80 / Bear $6.67 vs Base $8.40 shows the operating spread.
A11: AFFO / share ($) | B11: =Model!G77 -> 6.5418926 | C11: 8.4179242 | D11: 5.197656
A13: 2 · VALUATION SUMMARY ($/share)
A14: NAV / share | B14: =NAV!B54 -> 124.42681 | C14: =NAV!C54 -> 145.55968 | D14: =NAV!D54 -> 98.954963 | E14: Dynamic — NAV tab already carries Base/Bull/Bear columns (NAV!B54/C54/D54).
A15: DCF / share | B15: =DCF!B33 -> 123.77367 | C15: 200.99564 | D15: 71.219035 | E15: Bull DCF is amplified by the terminal r−g spread (7.0% WACC, 3.0% g) → read with caution; NAV bull is the firmer anchor.
A16: Trading comps value | B16: =(Comps!D22+Comps!D23)/2 -> 99.678233 | C16: 102.99178 | D16: 94.278759 | E16: Midpoint of P/Core FFO & P/AFFO implied (Comps!D22/D23). Near-term-driven, so it varies little across cases.
A17: Football Field midpoint | B17: =AVERAGE(B14:B16) -> 115.95957 | C17: =AVERAGE(C14:C16) -> 149.84903 | D17: =AVERAGE(D14:D16) -> 88.150919 | E17: Blended midpoint = average of NAV, DCF and comps for each scenario.
A19: 3 · RETURN FRAMEWORK (vs current share price)
A20: Current share price ($) | B20: =NAV!B79 -> 145 | C20: =B20 -> 145 | D20: =B20 -> 145
A21: Upside / (downside) to NAV | B21: =B14/B20-1 -> -0.14188407 | C21: =C14/C20-1 -> 0.0038598523 | D21: =D14/D20-1 -> -0.31755198 | E21: Each scenario value ÷ current price − 1. Positive = value above price (upside).
A22: Upside / (downside) to DCF | B22: =B15/B20-1 -> -0.14638851 | C22: =C15/C20-1 -> 0.38617682 | D22: =D15/D20-1 -> -0.50883424
A23: Upside / (downside) to blended | B23: =B17/B20-1 -> -0.20027883 | C23: =C17/C20-1 -> 0.033441609 | D23: =D17/D20-1 -> -0.39206263
A25: 4 · SCENARIO DRIVERS (linked to Assumptions)
A26: Operating
A27: Average occupancy % | B27: =Assumptions!C10 -> 0.953 | C27: =Assumptions!D10 -> 0.957 | D27: =Assumptions!E10 -> 0.935
A28: Market rent growth (Y1) | B28: =Assumptions!C11 -> 0.03 | C28: =Assumptions!D11 -> 0.06 | D28: =Assumptions!E11 -> -0.01
A29: Retention % | B29: =Assumptions!C21 -> 0.77 | C29: =Assumptions!D21 -> 0.8 | D29: =Assumptions!E21 -> 0.72
A30: MTM realization % | B30: =Assumptions!C20 -> 0.13 | C30: =Assumptions!D20 -> 0.15 | D30: =Assumptions!E20 -> 0.11
A31: Development
A32: Logistics starts -TEI Y1 ($mm) | B32: =Assumptions!C25 -> 4000 | C32: =Assumptions!D25 -> 5500 | D32: =Assumptions!E25 -> 2500
A33: Data-center starts -TEI Y1 ($mm) | B33: =Assumptions!C29 -> 1300 | C33: =Assumptions!D29 -> 2500 | D33: =Assumptions!E29 -> 500
A34: Logistics stabilized yield | B34: =Assumptions!C27 -> 0.065 | C34: =Assumptions!D27 -> 0.075 | D34: =Assumptions!E27 -> 0.055
A35: Data-center stabilized yield | B35: =Assumptions!C31 -> 0.08 | C35: =Assumptions!D31 -> 0.09 | D35: =Assumptions!E31 -> 0.065
A36: Capital structure
A37: New-issue debt cost | B37: =Assumptions!C45 -> 0.05 | C37: =Assumptions!D45 -> 0.0425 | D37: =Assumptions!E45 -> 0.06
A38: Leverage (net debt / EBITDA) | B38: =Assumptions!C46 -> 4.8 | C38: =Assumptions!D46 -> 4.5 | D38: =Assumptions!E46 -> 5.5
A39: Valuation
A40: NAV cap rate | B40: =Assumptions!C61 -> 0.05 | C40: =Assumptions!D61 -> 0.045 | D40: =Assumptions!E61 -> 0.058
A41: Discount rate (WACC) | B41: =Assumptions!C59 -> 0.075 | C41: =Assumptions!D59 -> 0.07 | D41: =Assumptions!E59 -> 0.085
A42: Terminal growth | B42: =Assumptions!C62 -> 0.025 | C42: =Assumptions!D62 -> 0.03 | D42: =Assumptions!E62 -> 0.015
A44: 5 · EXECUTIVE TAKEAWAYS
A45: BASE | B45: Outcome: ~5% same-store NOI growth, FY2030 Core FFO/share ~$8.40 (≈8%/yr). Valuation: NAV ≈ $124, DCF ≈ $124 -intrinsic value clusters ~$124; price (~$145) sits at a ~17% premium.
A46: BULL | B46: Outcome: stronger rents/leasing + heavier accretive development; FY2030 Core FFO/share ~$10.80. Valuation: NAV ≈ $146 (≈ current price); DCF screens far higher but is terminal-value-sensitive. Bull justifies today's price.
A47: BEAR | B47: Outcome: rent declines, weaker leasing, higher cap/discount rates; FY2030 Core FFO/share ~$6.67. Valuation: NAV ≈ $99, DCF ≈ $71 -~20–50% downside from price. Quantifies the premium's downside risk.
A49: 6 · VISUALIZATION — NAV/share, DCF/share & current price by scenario
A68: NOTES & METHODOLOGY
A69: Architecture: the Model computes one scenario at a time via Assumptions!B5. NAV/share and all drivers carry native Base/Bull/Bear columns and link live. Operating, DCF and comps outputs are single-scenario, so their Bull/Bear values are MODEL-DERIVED CAPTURES (run the model at switch=2/3, read the output). These are computed values, not manual inputs; the Base column links live. Refresh captures if Model/Assumptions change.
A70: DCF caution: the Bull DCF (~$201) stacks lower discount (7.0%), higher terminal growth (3.0%) and higher AFFO; the Gordon perpetuity (r−g = 4%) amplifies it. Treat NAV ($146 bull) as the firmer bull anchor. Bear DCF ($71) reflects the opposite stack (8.5% discount, 1.5% g, weaker AFFO).

Sheet Summary
A1: PROLOGIS, INC. (NYSE: PLD) - INVESTMENT SUMMARY
A2: Institutional valuation summary · all figures link to the NAV, DCF, Comps, Football Field and Scenarios tabs. Reference state = Base (Assumptions!B5 = 1). $ in thousands except per-share.
A4: 1 · INVESTMENT THESIS
A5: Key positives
A6: + Premium global logistics platform | B6: ~95% occupancy with embedded below-market rents; base same-store NOI growth ~5%/yr from escalators + mark-to-market on rollover.
A7: + Multiple growth engines | B7: Development (logistics + data centers) creates value at cost-plus-margin; the strategic-capital platform scales fee income (~$87B third-party AUM by FY2030).
A8: + Balance-sheet strength | B8: Net debt/EBITDA ~5.0x under a disciplined leverage policy, funding the development pipeline while preserving capacity.
A9: Key risks
A10: − Valuation premium / downside | B10: Trades ~17% above NAV base and above DCF & comps -priced toward the bull case; vulnerable to multiple compression if growth slows.
A11: − Development & capital intensity | B11: Heavy starts require external funding (ATM equity + debt); value-creation margins compress sharply in the bear case (logistics 5%, DC 10%).
A12: − Macro / rate sensitivity | B12: Cap & discount rates are the dominant value levers; the bear case (5.8% cap, 8.5% WACC, falling rents) implies ~30–50% downside.
A13: Key valuation drivers
A14: • Cap rate & discount rate | B14: The single largest lever -~$6–7/share per 25 bps on both NAV (cap rate) and DCF (WACC).
A15: • Stabilized NOI growth | B15: Same-store rent growth, occupancy and MTM realization set the cash-flow base across all three methods.
A16: • Development margins & strategic-capital value | B16: Logistics/DC value-creation margins and the FRE platform multiple drive the premium above the operating portfolio.
A18: 2 · VALUATION SUMMARY ($/share)
A19: Methodology | B19: Low / Bear | C19: Base | D19: High / Bull | E19: Source
A20: NAV (sum-of-parts) | B20: =NAV!D54 -> 98.954963 | C20: =NAV!B54 -> 124.42681 | D20: =NAV!C54 -> 145.55968 | E20: NAV tab Bear/Base/Bull
A21: DCF (AFFO equity) | C21: =DCF!B33 -> 123.77367 | E21: DCF base; scenario DCF on Scenarios tab
A22: Trading comps | B22: =Comps!D23 -> 92.526686 | C22: =(Comps!D22+Comps!D23)/2 -> 99.678233 | D22: =Comps!D22 -> 106.82978 | E22: Comps P/AFFO–P/Core FFO implied
A23: Football Field (blended) | B23: =Football_Field!B17 -> 92.526686 | C23: =Football_Field!B19 -> 114.06008 | D23: =Football_Field!B18 -> 145.55968 | E23: Football Field low/mid/high
A24: Current share price | C24: =NAV!B79 -> 145 | E24: Linked to model current-price input (NAV!B79).
A26: 3 · RECOMMENDATION FRAMEWORK — probability-weighted target
A27: Case | B27: Valuation ($/sh) | C27: Probability | D27: Weighted ($/sh) | E27: Basis
A28: Bear | B28: =Scenarios!D17 -> 88.150919 | C28: 0.25 | D28: =B28*C28 -> 22.03773 | E28: Blended Football Field midpoint, bear
A29: Base | B29: =Scenarios!B17 -> 115.95957 | C29: 0.5 | D29: =B29*C29 -> 57.979785 | E29: Blended Football Field midpoint, base
A30: Bull | B30: =Scenarios!C17 -> 149.84903 | C30: 0.25 | D30: =B30*C30 -> 37.462258 | E30: Blended Football Field midpoint, bull
A31: Probability-weighted target | C31: =SUM(C28:C30) -> 1 | D31: =SUM(D28:D30) -> 117.47977
A32: Memo: NAV-based weighted target (cross-check) | D32: =Scenarios!D14*C28+Scenarios!B14*C29+Scenarios!C14*C30 -> 123.34207
A33: Target vs current price | D33: =D31/C24-1 -> -0.18979467 | E33: Probabilities are institutional judgment (Base 50%, Bull/Bear 25% each — symmetric; quality anchors Base, the premium valuation tempers an upward tilt). Adjustable (blue).
A35: 4 · KEY MODEL OUTPUTS — FY2030E
A36: Metric | B36: Base | C36: Bull | D36: Bear | E36: Source
A37: Revenue ($000s) | B37: =Scenarios!B6 -> 13522501 | C37: =Scenarios!C6 -> 17092091 | D37: =Scenarios!D6 -> 10999577 | E37: Scenarios FY2030
A38: Total property NOI ($000s) | B38: =Scenarios!B7 -> 10209488 | C38: =Scenarios!C7 -> 12989989 | D38: =Scenarios!D7 -> 8194685.2 | E38: Scenarios FY2030
A39: Core FFO / share ($) | B39: =Scenarios!B10 -> 8.3924009 | C39: =Scenarios!C10 -> 10.799107 | D39: =Scenarios!D10 -> 6.6679195 | E39: Scenarios FY2030
A40: AFFO / share ($) | B40: =Scenarios!B11 -> 6.5418926 | C40: =Scenarios!C11 -> 8.4179242 | D40: =Scenarios!D11 -> 5.197656 | E40: Scenarios FY2030
A41: Net debt / EBITDA (x) | B41: =Model!G65 -> 4.9695157 | C41: =Assumptions!D46 -> 4.5 | D41: =Assumptions!E46 -> 5.5 | E41: Model FY2030 (base); leverage policy bull/bear
A43: 5 · FINAL INVESTMENT CONCLUSION
A44: What the model says | B44: Intrinsic value clusters near $124/share (NAV base ≈ DCF base); the blended Football Field midpoint is ~$114 and the probability-weighted target ~$117 -all below the current ~$145 price. Independent asset-, cash-flow- and peer-based methods triangulate tightly.
A45: Why PLD trades at a premium | B45: Scale, a global platform, the strategic-capital franchise and development / data-center optionality command a premium that asset-, cash-flow- and peer-multiple methods only partly capture -PLD is the sector bellwether and consistently trades richer than pure-play peers.
A46: What the price implies | B46: At ~$145 the market is pricing the BULL case: only under bull do NAV (~$146) and the blended midpoint (~$150) reach today's price. Base and bear sit ~15% and ~40% lower. The premium is the thesis -and the risk.
A47: What could change the valuation | B47: Cap-rate / interest-rate moves (the dominant lever); the pace and margins of development, especially data centers; strategic-capital AUM growth and promotes; and the direction of the logistics rent cycle.
